Workbook

Sheet COVER
B10: Venture Wolf — SaaS & Software Financial Model (India) Dynamic 60-Month Forecast
B18: Confidential - Generated for internal venture analysis.

Sheet ASSUMPTIONS
B2: ACTIVE SCENARIO: | C2: Base
B4: Particulars | C4: Worst | D4: Base | E4: Best
B5: 1. MACRO-ECONOMIC & TAX (INDIA)
B6: Corporate Tax Rate (%) | C6: 0.25 | D6: 0.25 | E6: 0.25
B7: DPIIT Tax Holiday Active (1=Yes, 0=No) | C7: 0 | D7: 0 | E7: 0
B8: Employer PF Burden (%) | C8: 0.16 | D8: 0.12 | E8: 0.095
B9: 0.045
B10: Initial Customer Count | C10: 500 | D10: 1000 | E10: 2000
B11: Avg. Monthly Revenue Per User (₹) | C11: 50000 | D11: 50000 | E11: 50000
B12: MoM Growth Rate (%) | C12: 0.02 | D12: 0.1 | E12: 0.25
B13: Monthly Churn Rate (%) | C13: 0.14 | D13: 0.06 | E13: 0.02
B14: 3. COST & OPEX DRIVERS
B15: Direct COGS Margin (%) | C15: 0.3 | D15: 0.2 | E15: 0.15
B16: Annual Payroll Inflation (%) | C16: 0.12 | D16: 0.1 | E16: 0.08
B17: Marketing Spend (% of Revenue) | C17: 0.15 | D17: 0.12 | E17: 0.1
B18: 0.15
B19: Accounts Receivable (Days) | C19: 45 | D19: 30 | E19: 15
B20: Inventory Days (if applicable) | C20: 60 | D20: 45 | E20: 30
B21: Accounts Payable (Days) | C21: 0 | D21: 0 | E21: 0
C22: 30 | D22: 45 | E22: 60

Sheet FUNDING_REQUIREMENT
B2: Funding Requirement (Tranche Breakdown)
B4: Use of Funds | C4: Amount (₹)
B5: CapEx & Hardware | C5: 5000000
B6: Working Capital Buffer | C6: 3000000
B7: Marketing Launch | C7: 1500000
B8: Contingency | C8: 500000
B9: Total Funding Required | C9: =SUM(C5:C8) -> 10000000

Sheet SUBSCRIBER_FUNNEL
B2: Subscriber Funnel & Growth
B4: Particulars | C4: Month 1 | D4: Month 2 | E4: Month 3 | F4: Month 4 | G4: Month 5 | H4: Month 6 | I4: Month 7 | J4: Month 8 | K4: Month 9 | L4: Month 10 | M4: Month 11 | N4: Month 12 | O4: Month 13 | P4: Month 14 | Q4: Month 15 | R4: Month 16 | S4: Month 17 | T4: Month 18 | U4: Month 19 | V4: Month 20 | W4: Month 21 | X4: Month 22 | Y4: Month 23 | Z4: Month 24 | AA4: Month 25 | AB4: Month 26 | AC4: Month 27 | AD4: Month 28 | AE4: Month 29 | AF4: Month 30 | AG4: Month 31 | AH4: Month 32 | AI4: Month 33 | AJ4: Month 34 | AK4: Month 35 | AL4: Month 36 | AM4: Month 37 | AN4: Month 38 | AO4: Month 39 | AP4: Month 40 | AQ4: Month 41 | AR4: Month 42 | AS4: Month 43 | AT4: Month 44 | AU4: Month 45 | AV4: Month 46 | AW4: Month 47 | AX4: Month 48 | AY4: Month 49 | AZ4: Month 50 | BA4: Month 51 | BB4: Month 52 | BC4: Month 53 | BD4: Month 54 | BE4: Month 55 | BF4: Month 56 | BG4: Month 57 | BH4: Month 58 | BI4: Month 59 | BJ4: Month 60
B5: Starting Subscribers | C5: 0 | D5: =C8 -> 0.4 | E5: =D8 -> 0.816 | F5: =E8 -> 1.25104 | G5: =F8 -> 1.7083776 | H5: =G8 -> 2.1915149 | I5: =H8 -> 2.704228 | J5: =I8 -> 3.2505988 | K5: =J8 -> 3.8350497 | ... BJ5: =BI8 -> 691.93879
B6: New Subscribers | C6: =INDEX(ASSUMPTIONS!$C$10:$E$10, 1, MATCH(ASSUMPTIONS!$C$2, ASSUMPTIONS!$C$4:$E$4, 0)) / 2500 -> 0.4 | D6: =C6 * (1 + INDEX(ASSUMPTIONS!$C$12:$E$12, 1, MATCH(ASSUMPTIONS!$C$2, ASSUMPTIONS!$C$4:$E$4, 0))) -> 0.44 | E6: =D6 * (1 + INDEX(ASSUMPTIONS!$C$12:$E$12, 1, MATCH(ASSUMPTIONS!$C$2, ASSUMPTIONS!$C$4:$E$4, 0))) -> 0.484 | F6: =E6 * (1 + INDEX(ASSUMPTIONS!$C$12:$E$12, 1, MATCH(ASSUMPTIONS!$C$2, ASSUMPTIONS!$C$4:$E$4, 0))) -> 0.5324 | G6: =F6 * (1 + INDEX(ASSUMPTIONS!$C$12:$E$12, 1, MATCH(ASSUMPTIONS!$C$2, ASSUMPTIONS!$C$4:$E$4, 0))) -> 0.58564 | H6: =G6 * (1 + INDEX(ASSUMPTIONS!$C$12:$E$12, 1, MATCH(ASSUMPTIONS!$C$2, ASSUMPTIONS!$C$4:$E$4, 0))) -> 0.644204 | I6: =H6 * (1 + INDEX(ASSUMPTIONS!$C$12:$E$12, 1, MATCH(ASSUMPTIONS!$C$2, ASSUMPTIONS!$C$4:$E$4, 0))) -> 0.7086244 | J6: =I6 * (1 + INDEX(ASSUMPTIONS!$C$12:$E$12, 1, MATCH(ASSUMPTIONS!$C$2, ASSUMPTIONS!$C$4:$E$4, 0))) -> 0.77948684 | K6: =J6 * (1 + INDEX(ASSUMPTIONS!$C$12:$E$12, 1, MATCH(ASSUMPTIONS!$C$2, ASSUMPTIONS!$C$4:$E$4, 0))) -> 0.85743552 | ... BJ6: =BI6 * (1 + INDEX(ASSUMPTIONS!$C$12:$E$12, 1, MATCH(ASSUMPTIONS!$C$2, ASSUMPTIONS!$C$4:$E$4, 0))) -> 110.7206
B7: Churned Subscribers | C7: =C5 * INDEX(ASSUMPTIONS!$C$13:$E$13, 1, MATCH(ASSUMPTIONS!$C$2, ASSUMPTIONS!$C$4:$E$4, 0)) -> 0 | D7: =D5 * INDEX(ASSUMPTIONS!$C$13:$E$13, 1, MATCH(ASSUMPTIONS!$C$2, ASSUMPTIONS!$C$4:$E$4, 0)) -> 0.024 | E7: =E5 * INDEX(ASSUMPTIONS!$C$13:$E$13, 1, MATCH(ASSUMPTIONS!$C$2, ASSUMPTIONS!$C$4:$E$4, 0)) -> 0.04896 | F7: =F5 * INDEX(ASSUMPTIONS!$C$13:$E$13, 1, MATCH(ASSUMPTIONS!$C$2, ASSUMPTIONS!$C$4:$E$4, 0)) -> 0.0750624 | G7: =G5 * INDEX(ASSUMPTIONS!$C$13:$E$13, 1, MATCH(ASSUMPTIONS!$C$2, ASSUMPTIONS!$C$4:$E$4, 0)) -> 0.10250266 | H7: =H5 * INDEX(ASSUMPTIONS!$C$13:$E$13, 1, MATCH(ASSUMPTIONS!$C$2, ASSUMPTIONS!$C$4:$E$4, 0)) -> 0.1314909 | I7: =I5 * INDEX(ASSUMPTIONS!$C$13:$E$13, 1, MATCH(ASSUMPTIONS!$C$2, ASSUMPTIONS!$C$4:$E$4, 0)) -> 0.16225368 | J7: =J5 * INDEX(ASSUMPTIONS!$C$13:$E$13, 1, MATCH(ASSUMPTIONS!$C$2, ASSUMPTIONS!$C$4:$E$4, 0)) -> 0.19503593 | ... BJ7: =BJ5 * INDEX(ASSUMPTIONS!$C$13:$E$13, 1, MATCH(ASSUMPTIONS!$C$2, ASSUMPTIONS!$C$4:$E$4, 0)) -> 41.516327
B8: Ending Subscribers | C8: =C5 + C6 - C7 -> 0.4 | D8: =D5 + D6 - D7 -> 0.816 | E8: =E5 + E6 - E7 -> 1.25104 | F8: =F5 + F6 - F7 -> 1.7083776 | G8: =G5 + G6 - G7 -> 2.1915149 | H8: =H5 + H6 - H7 -> 2.704228 | I8: =I5 + I6 - I7 -> 3.2505988 | J8: =J5 + J6 - J7 -> 3.8350497 | ... BJ8: =BJ5 + BJ6 - BJ7 -> 761.14306

Sheet REVENUE_ENGINE
B2: MRR & Revenue Engine
B4: Particulars | C4: Month 1 | D4: Month 2 | E4: Month 3 | F4: Month 4 | G4: Month 5 | H4: Month 6 | I4: Month 7 | J4: Month 8 | K4: Month 9 | L4: Month 10 | M4: Month 11 | N4: Month 12 | O4: Month 13 | P4: Month 14 | Q4: Month 15 | R4: Month 16 | S4: Month 17 | T4: Month 18 | U4: Month 19 | V4: Month 20 | W4: Month 21 | X4: Month 22 | Y4: Month 23 | Z4: Month 24 | AA4: Month 25 | AB4: Month 26 | AC4: Month 27 | AD4: Month 28 | AE4: Month 29 | AF4: Month 30 | AG4: Month 31 | AH4: Month 32 | AI4: Month 33 | AJ4: Month 34 | AK4: Month 35 | AL4: Month 36 | AM4: Month 37 | AN4: Month 38 | AO4: Month 39 | AP4: Month 40 | AQ4: Month 41 | AR4: Month 42 | AS4: Month 43 | AT4: Month 44 | AU4: Month 45 | AV4: Month 46 | AW4: Month 47 | AX4: Month 48 | AY4: Month 49 | AZ4: Month 50 | BA4: Month 51 | BB4: Month 52 | BC4: Month 53 | BD4: Month 54 | BE4: Month 55 | BF4: Month 56 | BG4: Month 57 | BH4: Month 58 | BI4: Month 59 | BJ4: Month 60
B5: ARPU (Average Revenue Per User) (₹) | C5: 2500 | D5: 2500 | E5: 2500 | F5: 2500 | G5: 2500 | H5: 2500 | I5: 2500 | J5: 2500 | K5: 2500 | L5: 2500 | M5: 2500 | N5: 2500 | O5: 2500 | P5: 2500 | Q5: 2500 | R5: 2500 | S5: 2500 | T5: 2500 | U5: 2500 | V5: 2500 | W5: 2500 | X5: 2500 | Y5: 2500 | Z5: 2500 | AA5: 2500 | AB5: 2500 | AC5: 2500 | AD5: 2500 | AE5: 2500 | AF5: 2500 | AG5: 2500 | AH5: 2500 | AI5: 2500 | AJ5: 2500 | AK5: 2500 | AL5: 2500 | AM5: 2500 | AN5: 2500 | AO5: 2500 | AP5: 2500 | AQ5: 2500 | AR5: 2500 | AS5: 2500 | AT5: 2500 | AU5: 2500 | AV5: 2500 | AW5: 2500 | AX5: 2500 | AY5: 2500 | AZ5: 2500 | BA5: 2500 | BB5: 2500 | BC5: 2500 | BD5: 2500 | BE5: 2500 | BF5: 2500 | BG5: 2500 | BH5: 2500 | BI5: 2500 | BJ5: 2500
B6: Total MRR (Total Revenue) (₹) | C6: =SUBSCRIBER_FUNNEL!C8 * C5 -> 1000 | D6: =SUBSCRIBER_FUNNEL!D8 * D5 -> 2040 | E6: =SUBSCRIBER_FUNNEL!E8 * E5 -> 3127.6 | F6: =SUBSCRIBER_FUNNEL!F8 * F5 -> 4270.944 | G6: =SUBSCRIBER_FUNNEL!G8 * G5 -> 5478.7874 | H6: =SUBSCRIBER_FUNNEL!H8 * H5 -> 6760.5701 | I6: =SUBSCRIBER_FUNNEL!I8 * I5 -> 8126.4969 | J6: =SUBSCRIBER_FUNNEL!J8 * J5 -> 9587.6242 | ... BJ6: =SUBSCRIBER_FUNNEL!BJ8 * BJ5 -> 1902857.6

Sheet COGS_ENGINE
B2: Cloud Infrastructure & Variable COGS
B4: Particulars | C4: Month 1 | D4: Month 2 | E4: Month 3 | F4: Month 4 | G4: Month 5 | H4: Month 6 | I4: Month 7 | J4: Month 8 | K4: Month 9 | L4: Month 10 | M4: Month 11 | N4: Month 12 | O4: Month 13 | P4: Month 14 | Q4: Month 15 | R4: Month 16 | S4: Month 17 | T4: Month 18 | U4: Month 19 | V4: Month 20 | W4: Month 21 | X4: Month 22 | Y4: Month 23 | Z4: Month 24 | AA4: Month 25 | AB4: Month 26 | AC4: Month 27 | AD4: Month 28 | AE4: Month 29 | AF4: Month 30 | AG4: Month 31 | AH4: Month 32 | AI4: Month 33 | AJ4: Month 34 | AK4: Month 35 | AL4: Month 36 | AM4: Month 37 | AN4: Month 38 | AO4: Month 39 | AP4: Month 40 | AQ4: Month 41 | AR4: Month 42 | AS4: Month 43 | AT4: Month 44 | AU4: Month 45 | AV4: Month 46 | AW4: Month 47 | AX4: Month 48 | AY4: Month 49 | AZ4: Month 50 | BA4: Month 51 | BB4: Month 52 | BC4: Month 53 | BD4: Month 54 | BE4: Month 55 | BF4: Month 56 | BG4: Month 57 | BH4: Month 58 | BI4: Month 59 | BJ4: Month 60
B5: Cloud & Server Hosting (₹) | C5: =10000 + (50 * SUBSCRIBER_FUNNEL!C8) -> 10020 | D5: =10000 + (50 * SUBSCRIBER_FUNNEL!D8) -> 10040.8 | E5: =10000 + (50 * SUBSCRIBER_FUNNEL!E8) -> 10062.552 | F5: =10000 + (50 * SUBSCRIBER_FUNNEL!F8) -> 10085.419 | G5: =10000 + (50 * SUBSCRIBER_FUNNEL!G8) -> 10109.576 | H5: =10000 + (50 * SUBSCRIBER_FUNNEL!H8) -> 10135.211 | I5: =10000 + (50 * SUBSCRIBER_FUNNEL!I8) -> 10162.53 | J5: =10000 + (50 * SUBSCRIBER_FUNNEL!J8) -> 10191.752 | ... BJ5: =10000 + (50 * SUBSCRIBER_FUNNEL!BJ8) -> 48057.153
B6: Payment Gateway Fees (2%) (₹) | C6: =0.02 * REVENUE_ENGINE!C6 -> 20 | D6: =0.02 * REVENUE_ENGINE!D6 -> 40.8 | E6: =0.02 * REVENUE_ENGINE!E6 -> 62.552 | F6: =0.02 * REVENUE_ENGINE!F6 -> 85.41888 | G6: =0.02 * REVENUE_ENGINE!G6 -> 109.57575 | H6: =0.02 * REVENUE_ENGINE!H6 -> 135.2114 | I6: =0.02 * REVENUE_ENGINE!I6 -> 162.52994 | J6: =0.02 * REVENUE_ENGINE!J6 -> 191.75248 | ... BJ6: =0.02 * REVENUE_ENGINE!BJ6 -> 38057.153
B7: Total COGS (₹) | C7: =C5 + C6 -> 10040 | D7: =D5 + D6 -> 10081.6 | E7: =E5 + E6 -> 10125.104 | F7: =F5 + F6 -> 10170.838 | G7: =G5 + G6 -> 10219.151 | H7: =H5 + H6 -> 10270.423 | I7: =I5 + I6 -> 10325.06 | J7: =J5 + J6 -> 10383.505 | ... BJ7: =BJ5 + BJ6 -> 86114.306

Sheet HR_AND_OPEX
B2: HR & Operating Expenses (OpEx)
B4: Particulars | C4: Month 1 | D4: Month 2 | E4: Month 3 | F4: Month 4 | G4: Month 5 | H4: Month 6 | I4: Month 7 | J4: Month 8 | K4: Month 9 | L4: Month 10 | M4: Month 11 | N4: Month 12 | O4: Month 13 | P4: Month 14 | Q4: Month 15 | R4: Month 16 | S4: Month 17 | T4: Month 18 | U4: Month 19 | V4: Month 20 | W4: Month 21 | X4: Month 22 | Y4: Month 23 | Z4: Month 24 | AA4: Month 25 | AB4: Month 26 | AC4: Month 27 | AD4: Month 28 | AE4: Month 29 | AF4: Month 30 | AG4: Month 31 | AH4: Month 32 | AI4: Month 33 | AJ4: Month 34 | AK4: Month 35 | AL4: Month 36 | AM4: Month 37 | AN4: Month 38 | AO4: Month 39 | AP4: Month 40 | AQ4: Month 41 | AR4: Month 42 | AS4: Month 43 | AT4: Month 44 | AU4: Month 45 | AV4: Month 46 | AW4: Month 47 | AX4: Month 48 | AY4: Month 49 | AZ4: Month 50 | BA4: Month 51 | BB4: Month 52 | BC4: Month 53 | BD4: Month 54 | BE4: Month 55 | BF4: Month 56 | BG4: Month 57 | BH4: Month 58 | BI4: Month 59 | BJ4: Month 60
B5: Engineering & Product (₹) | C5: =300000 * ((1 + INDEX(ASSUMPTIONS!$C$16:$E$16, 1, MATCH(ASSUMPTIONS!$C$2, ASSUMPTIONS!$C$4:$E$4, 0))) ^ 0) -> 300000 | D5: =300000 * ((1 + INDEX(ASSUMPTIONS!$C$16:$E$16, 1, MATCH(ASSUMPTIONS!$C$2, ASSUMPTIONS!$C$4:$E$4, 0))) ^ 0) -> 300000 | E5: =300000 * ((1 + INDEX(ASSUMPTIONS!$C$16:$E$16, 1, MATCH(ASSUMPTIONS!$C$2, ASSUMPTIONS!$C$4:$E$4, 0))) ^ 0) -> 300000 | F5: =300000 * ((1 + INDEX(ASSUMPTIONS!$C$16:$E$16, 1, MATCH(ASSUMPTIONS!$C$2, ASSUMPTIONS!$C$4:$E$4, 0))) ^ 0) -> 300000 | G5: =300000 * ((1 + INDEX(ASSUMPTIONS!$C$16:$E$16, 1, MATCH(ASSUMPTIONS!$C$2, ASSUMPTIONS!$C$4:$E$4, 0))) ^ 0) -> 300000 | H5: =300000 * ((1 + INDEX(ASSUMPTIONS!$C$16:$E$16, 1, MATCH(ASSUMPTIONS!$C$2, ASSUMPTIONS!$C$4:$E$4, 0))) ^ 0) -> 300000 | I5: =300000 * ((1 + INDEX(ASSUMPTIONS!$C$16:$E$16, 1, MATCH(ASSUMPTIONS!$C$2, ASSUMPTIONS!$C$4:$E$4, 0))) ^ 0) -> 300000 | J5: =300000 * ((1 + INDEX(ASSUMPTIONS!$C$16:$E$16, 1, MATCH(ASSUMPTIONS!$C$2, ASSUMPTIONS!$C$4:$E$4, 0))) ^ 0) -> 300000 | ... N5: =300000 * ((1 + INDEX(ASSUMPTIONS!$C$16:$E$16, 1, MATCH(ASSUMPTIONS!$C$2, ASSUMPTIONS!$C$4:$E$4, 0))) ^ 0) -> 300000 | O5: =300000 * ((1 + INDEX(ASSUMPTIONS!$C$16:$E$16, 1, MATCH(ASSUMPTIONS!$C$2, ASSUMPTIONS!$C$4:$E$4, 0))) ^ 1) -> 330000 | P5: =300000 * ((1 + INDEX(ASSUMPTIONS!$C$16:$E$16, 1, MATCH(ASSUMPTIONS!$C$2, ASSUMPTIONS!$C$4:$E$4, 0))) ^ 1) -> 330000 | Q5: =300000 * ((1 + INDEX(ASSUMPTIONS!$C$16:$E$16, 1, MATCH(ASSUMPTIONS!$C$2, ASSUMPTIONS!$C$4:$E$4, 0))) ^ 1) -> 330000 | R5: =300000 * ((1 + INDEX(ASSUMPTIONS!$C$16:$E$16, 1, MATCH(ASSUMPTIONS!$C$2, ASSUMPTIONS!$C$4:$E$4, 0))) ^ 1) -> 330000 | S5: =300000 * ((1 + INDEX(ASSUMPTIONS!$C$16:$E$16, 1, MATCH(ASSUMPTIONS!$C$2, ASSUMPTIONS!$C$4:$E$4, 0))) ^ 1) -> 330000 | T5: =300000 * ((1 + INDEX(ASSUMPTIONS!$C$16:$E$16, 1, MATCH(ASSUMPTIONS!$C$2, ASSUMPTIONS!$C$4:$E$4, 0))) ^ 1) -> 330000 | U5: =300000 * ((1 + INDEX(ASSUMPTIONS!$C$16:$E$16, 1, MATCH(ASSUMPTIONS!$C$2, ASSUMPTIONS!$C$4:$E$4, 0))) ^ 1) -> 330000 | V5: =300000 * ((1 + INDEX(ASSUMPTIONS!$C$16:$E$16, 1, MATCH(ASSUMPTIONS!$C$2, ASSUMPTIONS!$C$4:$E$4, 0))) ^ 1) -> 330000 | ... Z5: =300000 * ((1 + INDEX(ASSUMPTIONS!$C$16:$E$16, 1, MATCH(ASSUMPTIONS!$C$2, ASSUMPTIONS!$C$4:$E$4, 0))) ^ 1) -> 330000 | AA5: =300000 * ((1 + INDEX(ASSUMPTIONS!$C$16:$E$16, 1, MATCH(ASSUMPTIONS!$C$2, ASSUMPTIONS!$C$4:$E$4, 0))) ^ 2) -> 363000 | AB5: =300000 * ((1 + INDEX(ASSUMPTIONS!$C$16:$E$16, 1, MATCH(ASSUMPTIONS!$C$2, ASSUMPTIONS!$C$4:$E$4, 0))) ^ 2) -> 363000 | AC5: =300000 * ((1 + INDEX(ASSUMPTIONS!$C$16:$E$16, 1, MATCH(ASSUMPTIONS!$C$2, ASSUMPTIONS!$C$4:$E$4, 0))) ^ 2) -> 363000 | AD5: =300000 * ((1 + INDEX(ASSUMPTIONS!$C$16:$E$16, 1, MATCH(ASSUMPTIONS!$C$2, ASSUMPTIONS!$C$4:$E$4, 0))) ^ 2) -> 363000 | AE5: =300000 * ((1 + INDEX(ASSUMPTIONS!$C$16:$E$16, 1, MATCH(ASSUMPTIONS!$C$2, ASSUMPTIONS!$C$4:$E$4, 0))) ^ 2) -> 363000 | AF5: =300000 * ((1 + INDEX(ASSUMPTIONS!$C$16:$E$16, 1, MATCH(ASSUMPTIONS!$C$2, ASSUMPTIONS!$C$4:$E$4, 0))) ^ 2) -> 363000 | AG5: =300000 * ((1 + INDEX(ASSUMPTIONS!$C$16:$E$16, 1, MATCH(ASSUMPTIONS!$C$2, ASSUMPTIONS!$C$4:$E$4, 0))) ^ 2) -> 363000 | AH5: =300000 * ((1 + INDEX(ASSUMPTIONS!$C$16:$E$16, 1, MATCH(ASSUMPTIONS!$C$2, ASSUMPTIONS!$C$4:$E$4, 0))) ^ 2) -> 363000 | ... AL5: =300000 * ((1 + INDEX(ASSUMPTIONS!$C$16:$E$16, 1, MATCH(ASSUMPTIONS!$C$2, ASSUMPTIONS!$C$4:$E$4, 0))) ^ 2) -> 363000 | AM5: =300000 * ((1 + INDEX(ASSUMPTIONS!$C$16:$E$16, 1, MATCH(ASSUMPTIONS!$C$2, ASSUMPTIONS!$C$4:$E$4, 0))) ^ 3) -> 399300 | AN5: =300000 * ((1 + INDEX(ASSUMPTIONS!$C$16:$E$16, 1, MATCH(ASSUMPTIONS!$C$2, ASSUMPTIONS!$C$4:$E$4, 0))) ^ 3) -> 399300 | AO5: =300000 * ((1 + INDEX(ASSUMPTIONS!$C$16:$E$16, 1, MATCH(ASSUMPTIONS!$C$2, ASSUMPTIONS!$C$4:$E$4, 0))) ^ 3) -> 399300 | AP5: =300000 * ((1 + INDEX(ASSUMPTIONS!$C$16:$E$16, 1, MATCH(ASSUMPTIONS!$C$2, ASSUMPTIONS!$C$4:$E$4, 0))) ^ 3) -> 399300 | AQ5: =300000 * ((1 + INDEX(ASSUMPTIONS!$C$16:$E$16, 1, MATCH(ASSUMPTIONS!$C$2, ASSUMPTIONS!$C$4:$E$4, 0))) ^ 3) -> 399300 | AR5: =300000 * ((1 + INDEX(ASSUMPTIONS!$C$16:$E$16, 1, MATCH(ASSUMPTIONS!$C$2, ASSUMPTIONS!$C$4:$E$4, 0))) ^ 3) -> 399300 | AS5: =300000 * ((1 + INDEX(ASSUMPTIONS!$C$16:$E$16, 1, MATCH(ASSUMPTIONS!$C$2, ASSUMPTIONS!$C$4:$E$4, 0))) ^ 3) -> 399300 | AT5: =300000 * ((1 + INDEX(ASSUMPTIONS!$C$16:$E$16, 1, MATCH(ASSUMPTIONS!$C$2, ASSUMPTIONS!$C$4:$E$4, 0))) ^ 3) -> 399300 | ... AX5: =300000 * ((1 + INDEX(ASSUMPTIONS!$C$16:$E$16, 1, MATCH(ASSUMPTIONS!$C$2, ASSUMPTIONS!$C$4:$E$4, 0))) ^ 3) -> 399300 | AY5: =300000 * ((1 + INDEX(ASSUMPTIONS!$C$16:$E$16, 1, MATCH(ASSUMPTIONS!$C$2, ASSUMPTIONS!$C$4:$E$4, 0))) ^ 4) -> 439230 | AZ5: =300000 * ((1 + INDEX(ASSUMPTIONS!$C$16:$E$16, 1, MATCH(ASSUMPTIONS!$C$2, ASSUMPTIONS!$C$4:$E$4, 0))) ^ 4) -> 439230 | BA5: =300000 * ((1 + INDEX(ASSUMPTIONS!$C$16:$E$16, 1, MATCH(ASSUMPTIONS!$C$2, ASSUMPTIONS!$C$4:$E$4, 0))) ^ 4) -> 439230 | BB5: =300000 * ((1 + INDEX(ASSUMPTIONS!$C$16:$E$16, 1, MATCH(ASSUMPTIONS!$C$2, ASSUMPTIONS!$C$4:$E$4, 0))) ^ 4) -> 439230 | BC5: =300000 * ((1 + INDEX(ASSUMPTIONS!$C$16:$E$16, 1, MATCH(ASSUMPTIONS!$C$2, ASSUMPTIONS!$C$4:$E$4, 0))) ^ 4) -> 439230 | BD5: =300000 * ((1 + INDEX(ASSUMPTIONS!$C$16:$E$16, 1, MATCH(ASSUMPTIONS!$C$2, ASSUMPTIONS!$C$4:$E$4, 0))) ^ 4) -> 439230 | BE5: =300000 * ((1 + INDEX(ASSUMPTIONS!$C$16:$E$16, 1, MATCH(ASSUMPTIONS!$C$2, ASSUMPTIONS!$C$4:$E$4, 0))) ^ 4) -> 439230 | BF5: =300000 * ((1 + INDEX(ASSUMPTIONS!$C$16:$E$16, 1, MATCH(ASSUMPTIONS!$C$2, ASSUMPTIONS!$C$4:$E$4, 0))) ^ 4) -> 439230 | ... BJ5: =300000 * ((1 + INDEX(ASSUMPTIONS!$C$16:$E$16, 1, MATCH(ASSUMPTIONS!$C$2, ASSUMPTIONS!$C$4:$E$4, 0))) ^ 4) -> 439230
B6: Sales & Marketing (CAC) (₹) | C6: =REVENUE_ENGINE!C6 * INDEX(ASSUMPTIONS!$C$17:$E$17, 1, MATCH(ASSUMPTIONS!$C$2, ASSUMPTIONS!$C$4:$E$4, 0)) -> 120 | D6: =REVENUE_ENGINE!D6 * INDEX(ASSUMPTIONS!$C$17:$E$17, 1, MATCH(ASSUMPTIONS!$C$2, ASSUMPTIONS!$C$4:$E$4, 0)) -> 244.8 | E6: =REVENUE_ENGINE!E6 * INDEX(ASSUMPTIONS!$C$17:$E$17, 1, MATCH(ASSUMPTIONS!$C$2, ASSUMPTIONS!$C$4:$E$4, 0)) -> 375.312 | F6: =REVENUE_ENGINE!F6 * INDEX(ASSUMPTIONS!$C$17:$E$17, 1, MATCH(ASSUMPTIONS!$C$2, ASSUMPTIONS!$C$4:$E$4, 0)) -> 512.51328 | G6: =REVENUE_ENGINE!G6 * INDEX(ASSUMPTIONS!$C$17:$E$17, 1, MATCH(ASSUMPTIONS!$C$2, ASSUMPTIONS!$C$4:$E$4, 0)) -> 657.45448 | H6: =REVENUE_ENGINE!H6 * INDEX(ASSUMPTIONS!$C$17:$E$17, 1, MATCH(ASSUMPTIONS!$C$2, ASSUMPTIONS!$C$4:$E$4, 0)) -> 811.26841 | I6: =REVENUE_ENGINE!I6 * INDEX(ASSUMPTIONS!$C$17:$E$17, 1, MATCH(ASSUMPTIONS!$C$2, ASSUMPTIONS!$C$4:$E$4, 0)) -> 975.17963 | J6: =REVENUE_ENGINE!J6 * INDEX(ASSUMPTIONS!$C$17:$E$17, 1, MATCH(ASSUMPTIONS!$C$2, ASSUMPTIONS!$C$4:$E$4, 0)) -> 1150.5149 | ... BJ6: =REVENUE_ENGINE!BJ6 * INDEX(ASSUMPTIONS!$C$17:$E$17, 1, MATCH(ASSUMPTIONS!$C$2, ASSUMPTIONS!$C$4:$E$4, 0)) -> 228342.92
B7: Customer Success (₹) | C7: =100000 * ((1 + INDEX(ASSUMPTIONS!$C$16:$E$16, 1, MATCH(ASSUMPTIONS!$C$2, ASSUMPTIONS!$C$4:$E$4, 0))) ^ 0) -> 100000 | D7: =100000 * ((1 + INDEX(ASSUMPTIONS!$C$16:$E$16, 1, MATCH(ASSUMPTIONS!$C$2, ASSUMPTIONS!$C$4:$E$4, 0))) ^ 0) -> 100000 | E7: =100000 * ((1 + INDEX(ASSUMPTIONS!$C$16:$E$16, 1, MATCH(ASSUMPTIONS!$C$2, ASSUMPTIONS!$C$4:$E$4, 0))) ^ 0) -> 100000 | F7: =100000 * ((1 + INDEX(ASSUMPTIONS!$C$16:$E$16, 1, MATCH(ASSUMPTIONS!$C$2, ASSUMPTIONS!$C$4:$E$4, 0))) ^ 0) -> 100000 | G7: =100000 * ((1 + INDEX(ASSUMPTIONS!$C$16:$E$16, 1, MATCH(ASSUMPTIONS!$C$2, ASSUMPTIONS!$C$4:$E$4, 0))) ^ 0) -> 100000 | H7: =100000 * ((1 + INDEX(ASSUMPTIONS!$C$16:$E$16, 1, MATCH(ASSUMPTIONS!$C$2, ASSUMPTIONS!$C$4:$E$4, 0))) ^ 0) -> 100000 | I7: =100000 * ((1 + INDEX(ASSUMPTIONS!$C$16:$E$16, 1, MATCH(ASSUMPTIONS!$C$2, ASSUMPTIONS!$C$4:$E$4, 0))) ^ 0) -> 100000 | J7: =100000 * ((1 + INDEX(ASSUMPTIONS!$C$16:$E$16, 1, MATCH(ASSUMPTIONS!$C$2, ASSUMPTIONS!$C$4:$E$4, 0))) ^ 0) -> 100000 | ... N7: =100000 * ((1 + INDEX(ASSUMPTIONS!$C$16:$E$16, 1, MATCH(ASSUMPTIONS!$C$2, ASSUMPTIONS!$C$4:$E$4, 0))) ^ 0) -> 100000 | O7: =100000 * ((1 + INDEX(ASSUMPTIONS!$C$16:$E$16, 1, MATCH(ASSUMPTIONS!$C$2, ASSUMPTIONS!$C$4:$E$4, 0))) ^ 1) -> 110000 | P7: =100000 * ((1 + INDEX(ASSUMPTIONS!$C$16:$E$16, 1, MATCH(ASSUMPTIONS!$C$2, ASSUMPTIONS!$C$4:$E$4, 0))) ^ 1) -> 110000 | Q7: =100000 * ((1 + INDEX(ASSUMPTIONS!$C$16:$E$16, 1, MATCH(ASSUMPTIONS!$C$2, ASSUMPTIONS!$C$4:$E$4, 0))) ^ 1) -> 110000 | R7: =100000 * ((1 + INDEX(ASSUMPTIONS!$C$16:$E$16, 1, MATCH(ASSUMPTIONS!$C$2, ASSUMPTIONS!$C$4:$E$4, 0))) ^ 1) -> 110000 | S7: =100000 * ((1 + INDEX(ASSUMPTIONS!$C$16:$E$16, 1, MATCH(ASSUMPTIONS!$C$2, ASSUMPTIONS!$C$4:$E$4, 0))) ^ 1) -> 110000 | T7: =100000 * ((1 + INDEX(ASSUMPTIONS!$C$16:$E$16, 1, MATCH(ASSUMPTIONS!$C$2, ASSUMPTIONS!$C$4:$E$4, 0))) ^ 1) -> 110000 | U7: =100000 * ((1 + INDEX(ASSUMPTIONS!$C$16:$E$16, 1, MATCH(ASSUMPTIONS!$C$2, ASSUMPTIONS!$C$4:$E$4, 0))) ^ 1) -> 110000 | V7: =100000 * ((1 + INDEX(ASSUMPTIONS!$C$16:$E$16, 1, MATCH(ASSUMPTIONS!$C$2, ASSUMPTIONS!$C$4:$E$4, 0))) ^ 1) -> 110000 | ... Z7: =100000 * ((1 + INDEX(ASSUMPTIONS!$C$16:$E$16, 1, MATCH(ASSUMPTIONS!$C$2, ASSUMPTIONS!$C$4:$E$4, 0))) ^ 1) -> 110000 | AA7: =100000 * ((1 + INDEX(ASSUMPTIONS!$C$16:$E$16, 1, MATCH(ASSUMPTIONS!$C$2, ASSUMPTIONS!$C$4:$E$4, 0))) ^ 2) -> 121000 | AB7: =100000 * ((1 + INDEX(ASSUMPTIONS!$C$16:$E$16, 1, MATCH(ASSUMPTIONS!$C$2, ASSUMPTIONS!$C$4:$E$4, 0))) ^ 2) -> 121000 | AC7: =100000 * ((1 + INDEX(ASSUMPTIONS!$C$16:$E$16, 1, MATCH(ASSUMPTIONS!$C$2, ASSUMPTIONS!$C$4:$E$4, 0))) ^ 2) -> 121000 | AD7: =100000 * ((1 + INDEX(ASSUMPTIONS!$C$16:$E$16, 1, MATCH(ASSUMPTIONS!$C$2, ASSUMPTIONS!$C$4:$E$4, 0))) ^ 2) -> 121000 | AE7: =100000 * ((1 + INDEX(ASSUMPTIONS!$C$16:$E$16, 1, MATCH(ASSUMPTIONS!$C$2, ASSUMPTIONS!$C$4:$E$4, 0))) ^ 2) -> 121000 | AF7: =100000 * ((1 + INDEX(ASSUMPTIONS!$C$16:$E$16, 1, MATCH(ASSUMPTIONS!$C$2, ASSUMPTIONS!$C$4:$E$4, 0))) ^ 2) -> 121000 | AG7: =100000 * ((1 + INDEX(ASSUMPTIONS!$C$16:$E$16, 1, MATCH(ASSUMPTIONS!$C$2, ASSUMPTIONS!$C$4:$E$4, 0))) ^ 2) -> 121000 | AH7: =100000 * ((1 + INDEX(ASSUMPTIONS!$C$16:$E$16, 1, MATCH(ASSUMPTIONS!$C$2, ASSUMPTIONS!$C$4:$E$4, 0))) ^ 2) -> 121000 | ... AL7: =100000 * ((1 + INDEX(ASSUMPTIONS!$C$16:$E$16, 1, MATCH(ASSUMPTIONS!$C$2, ASSUMPTIONS!$C$4:$E$4, 0))) ^ 2) -> 121000 | AM7: =100000 * ((1 + INDEX(ASSUMPTIONS!$C$16:$E$16, 1, MATCH(ASSUMPTIONS!$C$2, ASSUMPTIONS!$C$4:$E$4, 0))) ^ 3) -> 133100 | AN7: =100000 * ((1 + INDEX(ASSUMPTIONS!$C$16:$E$16, 1, MATCH(ASSUMPTIONS!$C$2, ASSUMPTIONS!$C$4:$E$4, 0))) ^ 3) -> 133100 | AO7: =100000 * ((1 + INDEX(ASSUMPTIONS!$C$16:$E$16, 1, MATCH(ASSUMPTIONS!$C$2, ASSUMPTIONS!$C$4:$E$4, 0))) ^ 3) -> 133100 | AP7: =100000 * ((1 + INDEX(ASSUMPTIONS!$C$16:$E$16, 1, MATCH(ASSUMPTIONS!$C$2, ASSUMPTIONS!$C$4:$E$4, 0))) ^ 3) -> 133100 | AQ7: =100000 * ((1 + INDEX(ASSUMPTIONS!$C$16:$E$16, 1, MATCH(ASSUMPTIONS!$C$2, ASSUMPTIONS!$C$4:$E$4, 0))) ^ 3) -> 133100 | AR7: =100000 * ((1 + INDEX(ASSUMPTIONS!$C$16:$E$16, 1, MATCH(ASSUMPTIONS!$C$2, ASSUMPTIONS!$C$4:$E$4, 0))) ^ 3) -> 133100 | AS7: =100000 * ((1 + INDEX(ASSUMPTIONS!$C$16:$E$16, 1, MATCH(ASSUMPTIONS!$C$2, ASSUMPTIONS!$C$4:$E$4, 0))) ^ 3) -> 133100 | AT7: =100000 * ((1 + INDEX(ASSUMPTIONS!$C$16:$E$16, 1, MATCH(ASSUMPTIONS!$C$2, ASSUMPTIONS!$C$4:$E$4, 0))) ^ 3) -> 133100 | ... AX7: =100000 * ((1 + INDEX(ASSUMPTIONS!$C$16:$E$16, 1, MATCH(ASSUMPTIONS!$C$2, ASSUMPTIONS!$C$4:$E$4, 0))) ^ 3) -> 133100 | AY7: =100000 * ((1 + INDEX(ASSUMPTIONS!$C$16:$E$16, 1, MATCH(ASSUMPTIONS!$C$2, ASSUMPTIONS!$C$4:$E$4, 0))) ^ 4) -> 146410 | AZ7: =100000 * ((1 + INDEX(ASSUMPTIONS!$C$16:$E$16, 1, MATCH(ASSUMPTIONS!$C$2, ASSUMPTIONS!$C$4:$E$4, 0))) ^ 4) -> 146410 | BA7: =100000 * ((1 + INDEX(ASSUMPTIONS!$C$16:$E$16, 1, MATCH(ASSUMPTIONS!$C$2, ASSUMPTIONS!$C$4:$E$4, 0))) ^ 4) -> 146410 | BB7: =100000 * ((1 + INDEX(ASSUMPTIONS!$C$16:$E$16, 1, MATCH(ASSUMPTIONS!$C$2, ASSUMPTIONS!$C$4:$E$4, 0))) ^ 4) -> 146410 | BC7: =100000 * ((1 + INDEX(ASSUMPTIONS!$C$16:$E$16, 1, MATCH(ASSUMPTIONS!$C$2, ASSUMPTIONS!$C$4:$E$4, 0))) ^ 4) -> 146410 | BD7: =100000 * ((1 + INDEX(ASSUMPTIONS!$C$16:$E$16, 1, MATCH(ASSUMPTIONS!$C$2, ASSUMPTIONS!$C$4:$E$4, 0))) ^ 4) -> 146410 | BE7: =100000 * ((1 + INDEX(ASSUMPTIONS!$C$16:$E$16, 1, MATCH(ASSUMPTIONS!$C$2, ASSUMPTIONS!$C$4:$E$4, 0))) ^ 4) -> 146410 | BF7: =100000 * ((1 + INDEX(ASSUMPTIONS!$C$16:$E$16, 1, MATCH(ASSUMPTIONS!$C$2, ASSUMPTIONS!$C$4:$E$4, 0))) ^ 4) -> 146410 | ... BJ7: =100000 * ((1 + INDEX(ASSUMPTIONS!$C$16:$E$16, 1, MATCH(ASSUMPTIONS!$C$2, ASSUMPTIONS!$C$4:$E$4, 0))) ^ 4) -> 146410
B8: Founders (₹) | C8: =150000 * ((1 + INDEX(ASSUMPTIONS!$C$16:$E$16, 1, MATCH(ASSUMPTIONS!$C$2, ASSUMPTIONS!$C$4:$E$4, 0))) ^ 0) -> 150000 | D8: =150000 * ((1 + INDEX(ASSUMPTIONS!$C$16:$E$16, 1, MATCH(ASSUMPTIONS!$C$2, ASSUMPTIONS!$C$4:$E$4, 0))) ^ 0) -> 150000 | E8: =150000 * ((1 + INDEX(ASSUMPTIONS!$C$16:$E$16, 1, MATCH(ASSUMPTIONS!$C$2, ASSUMPTIONS!$C$4:$E$4, 0))) ^ 0) -> 150000 | F8: =150000 * ((1 + INDEX(ASSUMPTIONS!$C$16:$E$16, 1, MATCH(ASSUMPTIONS!$C$2, ASSUMPTIONS!$C$4:$E$4, 0))) ^ 0) -> 150000 | G8: =150000 * ((1 + INDEX(ASSUMPTIONS!$C$16:$E$16, 1, MATCH(ASSUMPTIONS!$C$2, ASSUMPTIONS!$C$4:$E$4, 0))) ^ 0) -> 150000 | H8: =150000 * ((1 + INDEX(ASSUMPTIONS!$C$16:$E$16, 1, MATCH(ASSUMPTIONS!$C$2, ASSUMPTIONS!$C$4:$E$4, 0))) ^ 0) -> 150000 | I8: =150000 * ((1 + INDEX(ASSUMPTIONS!$C$16:$E$16, 1, MATCH(ASSUMPTIONS!$C$2, ASSUMPTIONS!$C$4:$E$4, 0))) ^ 0) -> 150000 | J8: =150000 * ((1 + INDEX(ASSUMPTIONS!$C$16:$E$16, 1, MATCH(ASSUMPTIONS!$C$2, ASSUMPTIONS!$C$4:$E$4, 0))) ^ 0) -> 150000 | ... N8: =150000 * ((1 + INDEX(ASSUMPTIONS!$C$16:$E$16, 1, MATCH(ASSUMPTIONS!$C$2, ASSUMPTIONS!$C$4:$E$4, 0))) ^ 0) -> 150000 | O8: =150000 * ((1 + INDEX(ASSUMPTIONS!$C$16:$E$16, 1, MATCH(ASSUMPTIONS!$C$2, ASSUMPTIONS!$C$4:$E$4, 0))) ^ 1) -> 165000 | P8: =150000 * ((1 + INDEX(ASSUMPTIONS!$C$16:$E$16, 1, MATCH(ASSUMPTIONS!$C$2, ASSUMPTIONS!$C$4:$E$4, 0))) ^ 1) -> 165000 | Q8: =150000 * ((1 + INDEX(ASSUMPTIONS!$C$16:$E$16, 1, MATCH(ASSUMPTIONS!$C$2, ASSUMPTIONS!$C$4:$E$4, 0))) ^ 1) -> 165000 | R8: =150000 * ((1 + INDEX(ASSUMPTIONS!$C$16:$E$16, 1, MATCH(ASSUMPTIONS!$C$2, ASSUMPTIONS!$C$4:$E$4, 0))) ^ 1) -> 165000 | S8: =150000 * ((1 + INDEX(ASSUMPTIONS!$C$16:$E$16, 1, MATCH(ASSUMPTIONS!$C$2, ASSUMPTIONS!$C$4:$E$4, 0))) ^ 1) -> 165000 | T8: =150000 * ((1 + INDEX(ASSUMPTIONS!$C$16:$E$16, 1, MATCH(ASSUMPTIONS!$C$2, ASSUMPTIONS!$C$4:$E$4, 0))) ^ 1) -> 165000 | U8: =150000 * ((1 + INDEX(ASSUMPTIONS!$C$16:$E$16, 1, MATCH(ASSUMPTIONS!$C$2, ASSUMPTIONS!$C$4:$E$4, 0))) ^ 1) -> 165000 | V8: =150000 * ((1 + INDEX(ASSUMPTIONS!$C$16:$E$16, 1, MATCH(ASSUMPTIONS!$C$2, ASSUMPTIONS!$C$4:$E$4, 0))) ^ 1) -> 165000 | ... Z8: =150000 * ((1 + INDEX(ASSUMPTIONS!$C$16:$E$16, 1, MATCH(ASSUMPTIONS!$C$2, ASSUMPTIONS!$C$4:$E$4, 0))) ^ 1) -> 165000 | AA8: =150000 * ((1 + INDEX(ASSUMPTIONS!$C$16:$E$16, 1, MATCH(ASSUMPTIONS!$C$2, ASSUMPTIONS!$C$4:$E$4, 0))) ^ 2) -> 181500 | AB8: =150000 * ((1 + INDEX(ASSUMPTIONS!$C$16:$E$16, 1, MATCH(ASSUMPTIONS!$C$2, ASSUMPTIONS!$C$4:$E$4, 0))) ^ 2) -> 181500 | AC8: =150000 * ((1 + INDEX(ASSUMPTIONS!$C$16:$E$16, 1, MATCH(ASSUMPTIONS!$C$2, ASSUMPTIONS!$C$4:$E$4, 0))) ^ 2) -> 181500 | AD8: =150000 * ((1 + INDEX(ASSUMPTIONS!$C$16:$E$16, 1, MATCH(ASSUMPTIONS!$C$2, ASSUMPTIONS!$C$4:$E$4, 0))) ^ 2) -> 181500 | AE8: =150000 * ((1 + INDEX(ASSUMPTIONS!$C$16:$E$16, 1, MATCH(ASSUMPTIONS!$C$2, ASSUMPTIONS!$C$4:$E$4, 0))) ^ 2) -> 181500 | AF8: =150000 * ((1 + INDEX(ASSUMPTIONS!$C$16:$E$16, 1, MATCH(ASSUMPTIONS!$C$2, ASSUMPTIONS!$C$4:$E$4, 0))) ^ 2) -> 181500 | AG8: =150000 * ((1 + INDEX(ASSUMPTIONS!$C$16:$E$16, 1, MATCH(ASSUMPTIONS!$C$2, ASSUMPTIONS!$C$4:$E$4, 0))) ^ 2) -> 181500 | AH8: =150000 * ((1 + INDEX(ASSUMPTIONS!$C$16:$E$16, 1, MATCH(ASSUMPTIONS!$C$2, ASSUMPTIONS!$C$4:$E$4, 0))) ^ 2) -> 181500 | ... AL8: =150000 * ((1 + INDEX(ASSUMPTIONS!$C$16:$E$16, 1, MATCH(ASSUMPTIONS!$C$2, ASSUMPTIONS!$C$4:$E$4, 0))) ^ 2) -> 181500 | AM8: =150000 * ((1 + INDEX(ASSUMPTIONS!$C$16:$E$16, 1, MATCH(ASSUMPTIONS!$C$2, ASSUMPTIONS!$C$4:$E$4, 0))) ^ 3) -> 199650 | AN8: =150000 * ((1 + INDEX(ASSUMPTIONS!$C$16:$E$16, 1, MATCH(ASSUMPTIONS!$C$2, ASSUMPTIONS!$C$4:$E$4, 0))) ^ 3) -> 199650 | AO8: =150000 * ((1 + INDEX(ASSUMPTIONS!$C$16:$E$16, 1, MATCH(ASSUMPTIONS!$C$2, ASSUMPTIONS!$C$4:$E$4, 0))) ^ 3) -> 199650 | AP8: =150000 * ((1 + INDEX(ASSUMPTIONS!$C$16:$E$16, 1, MATCH(ASSUMPTIONS!$C$2, ASSUMPTIONS!$C$4:$E$4, 0))) ^ 3) -> 199650 | AQ8: =150000 * ((1 + INDEX(ASSUMPTIONS!$C$16:$E$16, 1, MATCH(ASSUMPTIONS!$C$2, ASSUMPTIONS!$C$4:$E$4, 0))) ^ 3) -> 199650 | AR8: =150000 * ((1 + INDEX(ASSUMPTIONS!$C$16:$E$16, 1, MATCH(ASSUMPTIONS!$C$2, ASSUMPTIONS!$C$4:$E$4, 0))) ^ 3) -> 199650 | AS8: =150000 * ((1 + INDEX(ASSUMPTIONS!$C$16:$E$16, 1, MATCH(ASSUMPTIONS!$C$2, ASSUMPTIONS!$C$4:$E$4, 0))) ^ 3) -> 199650 | AT8: =150000 * ((1 + INDEX(ASSUMPTIONS!$C$16:$E$16, 1, MATCH(ASSUMPTIONS!$C$2, ASSUMPTIONS!$C$4:$E$4, 0))) ^ 3) -> 199650 | ... AX8: =150000 * ((1 + INDEX(ASSUMPTIONS!$C$16:$E$16, 1, MATCH(ASSUMPTIONS!$C$2, ASSUMPTIONS!$C$4:$E$4, 0))) ^ 3) -> 199650 | AY8: =150000 * ((1 + INDEX(ASSUMPTIONS!$C$16:$E$16, 1, MATCH(ASSUMPTIONS!$C$2, ASSUMPTIONS!$C$4:$E$4, 0))) ^ 4) -> 219615 | AZ8: =150000 * ((1 + INDEX(ASSUMPTIONS!$C$16:$E$16, 1, MATCH(ASSUMPTIONS!$C$2, ASSUMPTIONS!$C$4:$E$4, 0))) ^ 4) -> 219615 | BA8: =150000 * ((1 + INDEX(ASSUMPTIONS!$C$16:$E$16, 1, MATCH(ASSUMPTIONS!$C$2, ASSUMPTIONS!$C$4:$E$4, 0))) ^ 4) -> 219615 | BB8: =150000 * ((1 + INDEX(ASSUMPTIONS!$C$16:$E$16, 1, MATCH(ASSUMPTIONS!$C$2, ASSUMPTIONS!$C$4:$E$4, 0))) ^ 4) -> 219615 | BC8: =150000 * ((1 + INDEX(ASSUMPTIONS!$C$16:$E$16, 1, MATCH(ASSUMPTIONS!$C$2, ASSUMPTIONS!$C$4:$E$4, 0))) ^ 4) -> 219615 | BD8: =150000 * ((1 + INDEX(ASSUMPTIONS!$C$16:$E$16, 1, MATCH(ASSUMPTIONS!$C$2, ASSUMPTIONS!$C$4:$E$4, 0))) ^ 4) -> 219615 | BE8: =150000 * ((1 + INDEX(ASSUMPTIONS!$C$16:$E$16, 1, MATCH(ASSUMPTIONS!$C$2, ASSUMPTIONS!$C$4:$E$4, 0))) ^ 4) -> 219615 | BF8: =150000 * ((1 + INDEX(ASSUMPTIONS!$C$16:$E$16, 1, MATCH(ASSUMPTIONS!$C$2, ASSUMPTIONS!$C$4:$E$4, 0))) ^ 4) -> 219615 | ... BJ8: =150000 * ((1 + INDEX(ASSUMPTIONS!$C$16:$E$16, 1, MATCH(ASSUMPTIONS!$C$2, ASSUMPTIONS!$C$4:$E$4, 0))) ^ 4) -> 219615
B9: Admin & Legal (₹) | C9: =50000 * ((1 + INDEX(ASSUMPTIONS!$C$16:$E$16, 1, MATCH(ASSUMPTIONS!$C$2, ASSUMPTIONS!$C$4:$E$4, 0))) ^ 0) -> 50000 | D9: =50000 * ((1 + INDEX(ASSUMPTIONS!$C$16:$E$16, 1, MATCH(ASSUMPTIONS!$C$2, ASSUMPTIONS!$C$4:$E$4, 0))) ^ 0) -> 50000 | E9: =50000 * ((1 + INDEX(ASSUMPTIONS!$C$16:$E$16, 1, MATCH(ASSUMPTIONS!$C$2, ASSUMPTIONS!$C$4:$E$4, 0))) ^ 0) -> 50000 | F9: =50000 * ((1 + INDEX(ASSUMPTIONS!$C$16:$E$16, 1, MATCH(ASSUMPTIONS!$C$2, ASSUMPTIONS!$C$4:$E$4, 0))) ^ 0) -> 50000 | G9: =50000 * ((1 + INDEX(ASSUMPTIONS!$C$16:$E$16, 1, MATCH(ASSUMPTIONS!$C$2, ASSUMPTIONS!$C$4:$E$4, 0))) ^ 0) -> 50000 | H9: =50000 * ((1 + INDEX(ASSUMPTIONS!$C$16:$E$16, 1, MATCH(ASSUMPTIONS!$C$2, ASSUMPTIONS!$C$4:$E$4, 0))) ^ 0) -> 50000 | I9: =50000 * ((1 + INDEX(ASSUMPTIONS!$C$16:$E$16, 1, MATCH(ASSUMPTIONS!$C$2, ASSUMPTIONS!$C$4:$E$4, 0))) ^ 0) -> 50000 | J9: =50000 * ((1 + INDEX(ASSUMPTIONS!$C$16:$E$16, 1, MATCH(ASSUMPTIONS!$C$2, ASSUMPTIONS!$C$4:$E$4, 0))) ^ 0) -> 50000 | ... N9: =50000 * ((1 + INDEX(ASSUMPTIONS!$C$16:$E$16, 1, MATCH(ASSUMPTIONS!$C$2, ASSUMPTIONS!$C$4:$E$4, 0))) ^ 0) -> 50000 | O9: =50000 * ((1 + INDEX(ASSUMPTIONS!$C$16:$E$16, 1, MATCH(ASSUMPTIONS!$C$2, ASSUMPTIONS!$C$4:$E$4, 0))) ^ 1) -> 55000 | P9: =50000 * ((1 + INDEX(ASSUMPTIONS!$C$16:$E$16, 1, MATCH(ASSUMPTIONS!$C$2, ASSUMPTIONS!$C$4:$E$4, 0))) ^ 1) -> 55000 | Q9: =50000 * ((1 + INDEX(ASSUMPTIONS!$C$16:$E$16, 1, MATCH(ASSUMPTIONS!$C$2, ASSUMPTIONS!$C$4:$E$4, 0))) ^ 1) -> 55000 | R9: =50000 * ((1 + INDEX(ASSUMPTIONS!$C$16:$E$16, 1, MATCH(ASSUMPTIONS!$C$2, ASSUMPTIONS!$C$4:$E$4, 0))) ^ 1) -> 55000 | S9: =50000 * ((1 + INDEX(ASSUMPTIONS!$C$16:$E$16, 1, MATCH(ASSUMPTIONS!$C$2, ASSUMPTIONS!$C$4:$E$4, 0))) ^ 1) -> 55000 | T9: =50000 * ((1 + INDEX(ASSUMPTIONS!$C$16:$E$16, 1, MATCH(ASSUMPTIONS!$C$2, ASSUMPTIONS!$C$4:$E$4, 0))) ^ 1) -> 55000 | U9: =50000 * ((1 + INDEX(ASSUMPTIONS!$C$16:$E$16, 1, MATCH(ASSUMPTIONS!$C$2, ASSUMPTIONS!$C$4:$E$4, 0))) ^ 1) -> 55000 | V9: =50000 * ((1 + INDEX(ASSUMPTIONS!$C$16:$E$16, 1, MATCH(ASSUMPTIONS!$C$2, ASSUMPTIONS!$C$4:$E$4, 0))) ^ 1) -> 55000 | ... Z9: =50000 * ((1 + INDEX(ASSUMPTIONS!$C$16:$E$16, 1, MATCH(ASSUMPTIONS!$C$2, ASSUMPTIONS!$C$4:$E$4, 0))) ^ 1) -> 55000 | AA9: =50000 * ((1 + INDEX(ASSUMPTIONS!$C$16:$E$16, 1, MATCH(ASSUMPTIONS!$C$2, ASSUMPTIONS!$C$4:$E$4, 0))) ^ 2) -> 60500 | AB9: =50000 * ((1 + INDEX(ASSUMPTIONS!$C$16:$E$16, 1, MATCH(ASSUMPTIONS!$C$2, ASSUMPTIONS!$C$4:$E$4, 0))) ^ 2) -> 60500 | AC9: =50000 * ((1 + INDEX(ASSUMPTIONS!$C$16:$E$16, 1, MATCH(ASSUMPTIONS!$C$2, ASSUMPTIONS!$C$4:$E$4, 0))) ^ 2) -> 60500 | AD9: =50000 * ((1 + INDEX(ASSUMPTIONS!$C$16:$E$16, 1, MATCH(ASSUMPTIONS!$C$2, ASSUMPTIONS!$C$4:$E$4, 0))) ^ 2) -> 60500 | AE9: =50000 * ((1 + INDEX(ASSUMPTIONS!$C$16:$E$16, 1, MATCH(ASSUMPTIONS!$C$2, ASSUMPTIONS!$C$4:$E$4, 0))) ^ 2) -> 60500 | AF9: =50000 * ((1 + INDEX(ASSUMPTIONS!$C$16:$E$16, 1, MATCH(ASSUMPTIONS!$C$2, ASSUMPTIONS!$C$4:$E$4, 0))) ^ 2) -> 60500 | AG9: =50000 * ((1 + INDEX(ASSUMPTIONS!$C$16:$E$16, 1, MATCH(ASSUMPTIONS!$C$2, ASSUMPTIONS!$C$4:$E$4, 0))) ^ 2) -> 60500 | AH9: =50000 * ((1 + INDEX(ASSUMPTIONS!$C$16:$E$16, 1, MATCH(ASSUMPTIONS!$C$2, ASSUMPTIONS!$C$4:$E$4, 0))) ^ 2) -> 60500 | ... AL9: =50000 * ((1 + INDEX(ASSUMPTIONS!$C$16:$E$16, 1, MATCH(ASSUMPTIONS!$C$2, ASSUMPTIONS!$C$4:$E$4, 0))) ^ 2) -> 60500 | AM9: =50000 * ((1 + INDEX(ASSUMPTIONS!$C$16:$E$16, 1, MATCH(ASSUMPTIONS!$C$2, ASSUMPTIONS!$C$4:$E$4, 0))) ^ 3) -> 66550 | AN9: =50000 * ((1 + INDEX(ASSUMPTIONS!$C$16:$E$16, 1, MATCH(ASSUMPTIONS!$C$2, ASSUMPTIONS!$C$4:$E$4, 0))) ^ 3) -> 66550 | AO9: =50000 * ((1 + INDEX(ASSUMPTIONS!$C$16:$E$16, 1, MATCH(ASSUMPTIONS!$C$2, ASSUMPTIONS!$C$4:$E$4, 0))) ^ 3) -> 66550 | AP9: =50000 * ((1 + INDEX(ASSUMPTIONS!$C$16:$E$16, 1, MATCH(ASSUMPTIONS!$C$2, ASSUMPTIONS!$C$4:$E$4, 0))) ^ 3) -> 66550 | AQ9: =50000 * ((1 + INDEX(ASSUMPTIONS!$C$16:$E$16, 1, MATCH(ASSUMPTIONS!$C$2, ASSUMPTIONS!$C$4:$E$4, 0))) ^ 3) -> 66550 | AR9: =50000 * ((1 + INDEX(ASSUMPTIONS!$C$16:$E$16, 1, MATCH(ASSUMPTIONS!$C$2, ASSUMPTIONS!$C$4:$E$4, 0))) ^ 3) -> 66550 | AS9: =50000 * ((1 + INDEX(ASSUMPTIONS!$C$16:$E$16, 1, MATCH(ASSUMPTIONS!$C$2, ASSUMPTIONS!$C$4:$E$4, 0))) ^ 3) -> 66550 | AT9: =50000 * ((1 + INDEX(ASSUMPTIONS!$C$16:$E$16, 1, MATCH(ASSUMPTIONS!$C$2, ASSUMPTIONS!$C$4:$E$4, 0))) ^ 3) -> 66550 | ... AX9: =50000 * ((1 + INDEX(ASSUMPTIONS!$C$16:$E$16, 1, MATCH(ASSUMPTIONS!$C$2, ASSUMPTIONS!$C$4:$E$4, 0))) ^ 3) -> 66550 | AY9: =50000 * ((1 + INDEX(ASSUMPTIONS!$C$16:$E$16, 1, MATCH(ASSUMPTIONS!$C$2, ASSUMPTIONS!$C$4:$E$4, 0))) ^ 4) -> 73205 | AZ9: =50000 * ((1 + INDEX(ASSUMPTIONS!$C$16:$E$16, 1, MATCH(ASSUMPTIONS!$C$2, ASSUMPTIONS!$C$4:$E$4, 0))) ^ 4) -> 73205 | BA9: =50000 * ((1 + INDEX(ASSUMPTIONS!$C$16:$E$16, 1, MATCH(ASSUMPTIONS!$C$2, ASSUMPTIONS!$C$4:$E$4, 0))) ^ 4) -> 73205 | BB9: =50000 * ((1 + INDEX(ASSUMPTIONS!$C$16:$E$16, 1, MATCH(ASSUMPTIONS!$C$2, ASSUMPTIONS!$C$4:$E$4, 0))) ^ 4) -> 73205 | BC9: =50000 * ((1 + INDEX(ASSUMPTIONS!$C$16:$E$16, 1, MATCH(ASSUMPTIONS!$C$2, ASSUMPTIONS!$C$4:$E$4, 0))) ^ 4) -> 73205 | BD9: =50000 * ((1 + INDEX(ASSUMPTIONS!$C$16:$E$16, 1, MATCH(ASSUMPTIONS!$C$2, ASSUMPTIONS!$C$4:$E$4, 0))) ^ 4) -> 73205 | BE9: =50000 * ((1 + INDEX(ASSUMPTIONS!$C$16:$E$16, 1, MATCH(ASSUMPTIONS!$C$2, ASSUMPTIONS!$C$4:$E$4, 0))) ^ 4) -> 73205 | BF9: =50000 * ((1 + INDEX(ASSUMPTIONS!$C$16:$E$16, 1, MATCH(ASSUMPTIONS!$C$2, ASSUMPTIONS!$C$4:$E$4, 0))) ^ 4) -> 73205 | ... BJ9: =50000 * ((1 + INDEX(ASSUMPTIONS!$C$16:$E$16, 1, MATCH(ASSUMPTIONS!$C$2, ASSUMPTIONS!$C$4:$E$4, 0))) ^ 4) -> 73205
B10: Total OpEx (Incl. PF Burden) (₹) | C10: =((C5 + C6 + C7 + C8 + C9) * (1 + INDEX(ASSUMPTIONS!$C$8:$E$8, 1, MATCH(ASSUMPTIONS!$C$2, ASSUMPTIONS!$C$4:$E$4, 0)))) -> 672134.4 | D10: =((D5 + D6 + D7 + D8 + D9) * (1 + INDEX(ASSUMPTIONS!$C$8:$E$8, 1, MATCH(ASSUMPTIONS!$C$2, ASSUMPTIONS!$C$4:$E$4, 0)))) -> 672274.18 | E10: =((E5 + E6 + E7 + E8 + E9) * (1 + INDEX(ASSUMPTIONS!$C$8:$E$8, 1, MATCH(ASSUMPTIONS!$C$2, ASSUMPTIONS!$C$4:$E$4, 0)))) -> 672420.35 | F10: =((F5 + F6 + F7 + F8 + F9) * (1 + INDEX(ASSUMPTIONS!$C$8:$E$8, 1, MATCH(ASSUMPTIONS!$C$2, ASSUMPTIONS!$C$4:$E$4, 0)))) -> 672574.01 | G10: =((G5 + G6 + G7 + G8 + G9) * (1 + INDEX(ASSUMPTIONS!$C$8:$E$8, 1, MATCH(ASSUMPTIONS!$C$2, ASSUMPTIONS!$C$4:$E$4, 0)))) -> 672736.35 | H10: =((H5 + H6 + H7 + H8 + H9) * (1 + INDEX(ASSUMPTIONS!$C$8:$E$8, 1, MATCH(ASSUMPTIONS!$C$2, ASSUMPTIONS!$C$4:$E$4, 0)))) -> 672908.62 | I10: =((I5 + I6 + I7 + I8 + I9) * (1 + INDEX(ASSUMPTIONS!$C$8:$E$8, 1, MATCH(ASSUMPTIONS!$C$2, ASSUMPTIONS!$C$4:$E$4, 0)))) -> 673092.2 | J10: =((J5 + J6 + J7 + J8 + J9) * (1 + INDEX(ASSUMPTIONS!$C$8:$E$8, 1, MATCH(ASSUMPTIONS!$C$2, ASSUMPTIONS!$C$4:$E$4, 0)))) -> 673288.58 | ... BJ10: =((BJ5 + BJ6 + BJ7 + BJ8 + BJ9) * (1 + INDEX(ASSUMPTIONS!$C$8:$E$8, 1, MATCH(ASSUMPTIONS!$C$2, ASSUMPTIONS!$C$4:$E$4, 0)))) -> 1239619.3

Sheet CAPEX_AND_DEPRECIATION
B2: CapEx & Depreciation Schedule
B4: Particulars | C4: Month 1 | D4: Month 2 | E4: Month 3 | F4: Month 4 | G4: Month 5 | H4: Month 6 | I4: Month 7 | J4: Month 8 | K4: Month 9 | L4: Month 10 | M4: Month 11 | N4: Month 12 | O4: Month 13 | P4: Month 14 | Q4: Month 15 | R4: Month 16 | S4: Month 17 | T4: Month 18 | U4: Month 19 | V4: Month 20 | W4: Month 21 | X4: Month 22 | Y4: Month 23 | Z4: Month 24 | AA4: Month 25 | AB4: Month 26 | AC4: Month 27 | AD4: Month 28 | AE4: Month 29 | AF4: Month 30 | AG4: Month 31 | AH4: Month 32 | AI4: Month 33 | AJ4: Month 34 | AK4: Month 35 | AL4: Month 36 | AM4: Month 37 | AN4: Month 38 | AO4: Month 39 | AP4: Month 40 | AQ4: Month 41 | AR4: Month 42 | AS4: Month 43 | AT4: Month 44 | AU4: Month 45 | AV4: Month 46 | AW4: Month 47 | AX4: Month 48 | AY4: Month 49 | AZ4: Month 50 | BA4: Month 51 | BB4: Month 52 | BC4: Month 53 | BD4: Month 54 | BE4: Month 55 | BF4: Month 56 | BG4: Month 57 | BH4: Month 58 | BI4: Month 59 | BJ4: Month 60
B5: Opening Asset Balance (₹) | C5: 0 | D5: =C8 -> 4916666.7 | E5: =D8 -> 4834722.2 | F5: =E8 -> 4754143.5 | G5: =F8 -> 4674907.8 | H5: =G8 -> 4596992.7 | I5: =H8 -> 4520376.1 | J5: =I8 -> 4445036.5 | K5: =J8 -> 4370952.6 | ... BJ5: =BI8 -> 1854876.2
B6: New CapEx Additions (₹) | C6: =FUNDING_REQUIREMENT!$C$5 -> 5000000 | D6: 0 | E6: 0 | F6: 0 | G6: 0 | H6: 0 | I6: 0 | J6: 0 | K6: 0 | L6: 0 | M6: 0 | N6: 0 | O6: 0 | P6: 0 | Q6: 0 | R6: 0 | S6: 0 | T6: 0 | U6: 0 | V6: 0 | W6: 0 | X6: 0 | Y6: 0 | Z6: 0 | AA6: 0 | AB6: 0 | AC6: 0 | AD6: 0 | AE6: 0 | AF6: 0 | AG6: 0 | AH6: 0 | AI6: 0 | AJ6: 0 | AK6: 0 | AL6: 0 | AM6: 0 | AN6: 0 | AO6: 0 | AP6: 0 | AQ6: 0 | AR6: 0 | AS6: 0 | AT6: 0 | AU6: 0 | AV6: 0 | AW6: 0 | AX6: 0 | AY6: 0 | AZ6: 0 | BA6: 0 | BB6: 0 | BC6: 0 | BD6: 0 | BE6: 0 | BF6: 0 | BG6: 0 | BH6: 0 | BI6: 0 | BJ6: 0
B7: Depreciation Expense (₹) | C7: =(C5 + C6) / 60 -> 83333.333 | D7: =(D5 + D6) / 60 -> 81944.444 | E7: =(E5 + E6) / 60 -> 80578.704 | F7: =(F5 + F6) / 60 -> 79235.725 | G7: =(G5 + G6) / 60 -> 77915.13 | H7: =(H5 + H6) / 60 -> 76616.544 | I7: =(I5 + I6) / 60 -> 75339.602 | J7: =(J5 + J6) / 60 -> 74083.942 | ... BJ7: =(BJ5 + BJ6) / 60 -> 30914.603
B8: Closing Asset Balance (₹) | C8: =C5 + C6 - C7 -> 4916666.7 | D8: =D5 + D6 - D7 -> 4834722.2 | E8: =E5 + E6 - E7 -> 4754143.5 | F8: =F5 + F6 - F7 -> 4674907.8 | G8: =G5 + G6 - G7 -> 4596992.7 | H8: =H5 + H6 - H7 -> 4520376.1 | I8: =I5 + I6 - I7 -> 4445036.5 | J8: =J5 + J6 - J7 -> 4370952.6 | ... BJ8: =BJ5 + BJ6 - BJ7 -> 1823961.6

Sheet WORKING_CAPITAL
B2: Working Capital Schedule
B4: Particulars | C4: Month 1 | D4: Month 2 | E4: Month 3 | F4: Month 4 | G4: Month 5 | H4: Month 6 | I4: Month 7 | J4: Month 8 | K4: Month 9 | L4: Month 10 | M4: Month 11 | N4: Month 12 | O4: Month 13 | P4: Month 14 | Q4: Month 15 | R4: Month 16 | S4: Month 17 | T4: Month 18 | U4: Month 19 | V4: Month 20 | W4: Month 21 | X4: Month 22 | Y4: Month 23 | Z4: Month 24 | AA4: Month 25 | AB4: Month 26 | AC4: Month 27 | AD4: Month 28 | AE4: Month 29 | AF4: Month 30 | AG4: Month 31 | AH4: Month 32 | AI4: Month 33 | AJ4: Month 34 | AK4: Month 35 | AL4: Month 36 | AM4: Month 37 | AN4: Month 38 | AO4: Month 39 | AP4: Month 40 | AQ4: Month 41 | AR4: Month 42 | AS4: Month 43 | AT4: Month 44 | AU4: Month 45 | AV4: Month 46 | AW4: Month 47 | AX4: Month 48 | AY4: Month 49 | AZ4: Month 50 | BA4: Month 51 | BB4: Month 52 | BC4: Month 53 | BD4: Month 54 | BE4: Month 55 | BF4: Month 56 | BG4: Month 57 | BH4: Month 58 | BI4: Month 59 | BJ4: Month 60
B5: Accounts Receivable (₹) | C5: =MONTHLY_P_AND_L!C5 * (30/365) -> 82.191781 | D5: =MONTHLY_P_AND_L!D5 * (30/365) -> 167.67123 | E5: =MONTHLY_P_AND_L!E5 * (30/365) -> 257.06301 | F5: =MONTHLY_P_AND_L!F5 * (30/365) -> 351.03649 | G5: =MONTHLY_P_AND_L!G5 * (30/365) -> 450.31129 | H5: =MONTHLY_P_AND_L!H5 * (30/365) -> 555.6633 | I5: =MONTHLY_P_AND_L!I5 * (30/365) -> 667.93125 | J5: =MONTHLY_P_AND_L!J5 * (30/365) -> 788.02391 | ... BJ5: =MONTHLY_P_AND_L!BJ5 * (30/365) -> 156399.26
B6: Accounts Payable (₹) | C6: =MONTHLY_P_AND_L!C8 * (15/365) -> 27621.962 | D6: =MONTHLY_P_AND_L!D8 * (15/365) -> 27627.706 | E6: =MONTHLY_P_AND_L!E8 * (15/365) -> 27633.713 | F6: =MONTHLY_P_AND_L!F8 * (15/365) -> 27640.028 | G6: =MONTHLY_P_AND_L!G8 * (15/365) -> 27646.699 | H6: =MONTHLY_P_AND_L!H8 * (15/365) -> 27653.779 | I6: =MONTHLY_P_AND_L!I8 * (15/365) -> 27661.323 | J6: =MONTHLY_P_AND_L!J8 * (15/365) -> 27669.394 | ... BJ6: =MONTHLY_P_AND_L!BJ8 * (15/365) -> 50943.258
B7: Net Working Capital (₹) | C7: =C5 - C6 -> -27539.77 | D7: =D5 - D6 -> -27460.035 | E7: =E5 - E6 -> -27376.65 | F7: =F5 - F6 -> -27288.992 | G7: =G5 - G6 -> -27196.388 | H7: =H5 - H6 -> -27098.116 | I7: =I5 - I6 -> -26993.392 | J7: =J5 - J6 -> -26881.37 | ... BJ7: =BJ5 - BJ6 -> 105456
B8: Change in Working Capital (₹) | C8: =C7 -> -27539.77 | D8: =D7 - C7 -> 79.735233 | E8: =E7 - D7 -> 83.384653 | F8: =F7 - E7 -> 87.658462 | G8: =G7 - F7 -> 92.60353 | H8: =H7 - G7 -> 98.272353 | I8: =I7 - H7 -> 104.72355 | J8: =J7 - I7 -> 112.02243 | K8: =K7 - J7 -> 120.2416 | ... BJ8: =BJ7 - BI7 -> 13264.468

Sheet MONTHLY_P_AND_L
B2: Monthly Profit & Loss
B4: Particulars | C4: Month 1 | D4: Month 2 | E4: Month 3 | F4: Month 4 | G4: Month 5 | H4: Month 6 | I4: Month 7 | J4: Month 8 | K4: Month 9 | L4: Month 10 | M4: Month 11 | N4: Month 12 | O4: Month 13 | P4: Month 14 | Q4: Month 15 | R4: Month 16 | S4: Month 17 | T4: Month 18 | U4: Month 19 | V4: Month 20 | W4: Month 21 | X4: Month 22 | Y4: Month 23 | Z4: Month 24 | AA4: Month 25 | AB4: Month 26 | AC4: Month 27 | AD4: Month 28 | AE4: Month 29 | AF4: Month 30 | AG4: Month 31 | AH4: Month 32 | AI4: Month 33 | AJ4: Month 34 | AK4: Month 35 | AL4: Month 36 | AM4: Month 37 | AN4: Month 38 | AO4: Month 39 | AP4: Month 40 | AQ4: Month 41 | AR4: Month 42 | AS4: Month 43 | AT4: Month 44 | AU4: Month 45 | AV4: Month 46 | AW4: Month 47 | AX4: Month 48 | AY4: Month 49 | AZ4: Month 50 | BA4: Month 51 | BB4: Month 52 | BC4: Month 53 | BD4: Month 54 | BE4: Month 55 | BF4: Month 56 | BG4: Month 57 | BH4: Month 58 | BI4: Month 59 | BJ4: Month 60
B5: Total Revenue | C5: =REVENUE_ENGINE!C6 -> 1000 | D5: =REVENUE_ENGINE!D6 -> 2040 | E5: =REVENUE_ENGINE!E6 -> 3127.6 | F5: =REVENUE_ENGINE!F6 -> 4270.944 | G5: =REVENUE_ENGINE!G6 -> 5478.7874 | H5: =REVENUE_ENGINE!H6 -> 6760.5701 | I5: =REVENUE_ENGINE!I6 -> 8126.4969 | J5: =REVENUE_ENGINE!J6 -> 9587.6242 | ... BJ5: =REVENUE_ENGINE!BJ6 -> 1902857.6
B6: Total COGS | C6: =COGS_ENGINE!C7 -> 10040 | D6: =COGS_ENGINE!D7 -> 10081.6 | E6: =COGS_ENGINE!E7 -> 10125.104 | F6: =COGS_ENGINE!F7 -> 10170.838 | G6: =COGS_ENGINE!G7 -> 10219.151 | H6: =COGS_ENGINE!H7 -> 10270.423 | I6: =COGS_ENGINE!I7 -> 10325.06 | J6: =COGS_ENGINE!J7 -> 10383.505 | ... BJ6: =COGS_ENGINE!BJ7 -> 86114.306
B7: Gross Profit | C7: =C5 - C6 -> -9040 | D7: =D5 - D6 -> -8041.6 | E7: =E5 - E6 -> -6997.504 | F7: =F5 - F6 -> -5899.8938 | G7: =G5 - G6 -> -4740.3641 | H7: =H5 - H6 -> -3509.8527 | I7: =I5 - I6 -> -2198.563 | J7: =J5 - J6 -> -795.88077 | ... BJ7: =BJ5 - BJ6 -> 1816743.3
B8: Total OpEx | C8: =HR_AND_OPEX!C10 -> 672134.4 | D8: =HR_AND_OPEX!D10 -> 672274.18 | E8: =HR_AND_OPEX!E10 -> 672420.35 | F8: =HR_AND_OPEX!F10 -> 672574.01 | G8: =HR_AND_OPEX!G10 -> 672736.35 | H8: =HR_AND_OPEX!H10 -> 672908.62 | I8: =HR_AND_OPEX!I10 -> 673092.2 | J8: =HR_AND_OPEX!J10 -> 673288.58 | ... BJ8: =HR_AND_OPEX!BJ10 -> 1239619.3
B9: EBITDA | C9: =C7 - C8 -> -681174.4 | D9: =D7 - D8 -> -680315.78 | E9: =E7 - E8 -> -679417.85 | F9: =F7 - F8 -> -678473.91 | G9: =G7 - G8 -> -677476.71 | H9: =H7 - H8 -> -676418.47 | I9: =I7 - I8 -> -675290.76 | J9: =J7 - J8 -> -674084.46 | ... BJ9: =BJ7 - BJ8 -> 577124.07
B10: Depreciation & Amortization | C10: =CAPEX_AND_DEPRECIATION!C7 -> 83333.333 | D10: =CAPEX_AND_DEPRECIATION!D7 -> 81944.444 | E10: =CAPEX_AND_DEPRECIATION!E7 -> 80578.704 | F10: =CAPEX_AND_DEPRECIATION!F7 -> 79235.725 | G10: =CAPEX_AND_DEPRECIATION!G7 -> 77915.13 | H10: =CAPEX_AND_DEPRECIATION!H7 -> 76616.544 | I10: =CAPEX_AND_DEPRECIATION!I7 -> 75339.602 | J10: =CAPEX_AND_DEPRECIATION!J7 -> 74083.942 | ... BJ10: =CAPEX_AND_DEPRECIATION!BJ7 -> 30914.603
B11: EBIT | C11: =C9 - C10 -> -764507.73 | D11: =D9 - D10 -> -762260.22 | E11: =E9 - E10 -> -759996.56 | F11: =F9 - F10 -> -757709.63 | G11: =G9 - G10 -> -755391.84 | H11: =H9 - H10 -> -753035.02 | I11: =I9 - I10 -> -750630.37 | J11: =J9 - J10 -> -748168.4 | ... BJ11: =BJ9 - BJ10 -> 546209.47
B12: Interest Expense | C12: =(5000000 * 0.12) / 12 -> 50000 | D12: =(5000000 * 0.12) / 12 -> 50000 | E12: =(5000000 * 0.12) / 12 -> 50000 | F12: =(5000000 * 0.12) / 12 -> 50000 | G12: =(5000000 * 0.12) / 12 -> 50000 | H12: =(5000000 * 0.12) / 12 -> 50000 | I12: =(5000000 * 0.12) / 12 -> 50000 | J12: =(5000000 * 0.12) / 12 -> 50000 | ... BJ12: =(5000000 * 0.12) / 12 -> 50000
B13: Profit Before Tax (PBT) | C13: =C11 - C12 -> -814507.73 | D13: =D11 - D12 -> -812260.22 | E13: =E11 - E12 -> -809996.56 | F13: =F11 - F12 -> -807709.63 | G13: =G11 - G12 -> -805391.84 | H13: =H11 - H12 -> -803035.02 | I13: =I11 - I12 -> -800630.37 | J13: =J11 - J12 -> -798168.4 | ... BJ13: =BJ11 - BJ12 -> 496209.47
B14: Corporate Tax | C14: =IF(INDEX(ASSUMPTIONS!$C$7:$E$7, 1, MATCH(ASSUMPTIONS!$C$2, ASSUMPTIONS!$C$4:$E$4, 0))=1, 0, MAX(0, C13 * INDEX(ASSUMPTIONS!$C$6:$E$6, 1, MATCH(ASSUMPTIONS!$C$2, ASSUMPTIONS!$C$4:$E$4, 0)))) -> 0 | D14: =IF(INDEX(ASSUMPTIONS!$C$7:$E$7, 1, MATCH(ASSUMPTIONS!$C$2, ASSUMPTIONS!$C$4:$E$4, 0))=1, 0, MAX(0, D13 * INDEX(ASSUMPTIONS!$C$6:$E$6, 1, MATCH(ASSUMPTIONS!$C$2, ASSUMPTIONS!$C$4:$E$4, 0)))) -> 0 | E14: =IF(INDEX(ASSUMPTIONS!$C$7:$E$7, 1, MATCH(ASSUMPTIONS!$C$2, ASSUMPTIONS!$C$4:$E$4, 0))=1, 0, MAX(0, E13 * INDEX(ASSUMPTIONS!$C$6:$E$6, 1, MATCH(ASSUMPTIONS!$C$2, ASSUMPTIONS!$C$4:$E$4, 0)))) -> 0 | F14: =IF(INDEX(ASSUMPTIONS!$C$7:$E$7, 1, MATCH(ASSUMPTIONS!$C$2, ASSUMPTIONS!$C$4:$E$4, 0))=1, 0, MAX(0, F13 * INDEX(ASSUMPTIONS!$C$6:$E$6, 1, MATCH(ASSUMPTIONS!$C$2, ASSUMPTIONS!$C$4:$E$4, 0)))) -> 0 | G14: =IF(INDEX(ASSUMPTIONS!$C$7:$E$7, 1, MATCH(ASSUMPTIONS!$C$2, ASSUMPTIONS!$C$4:$E$4, 0))=1, 0, MAX(0, G13 * INDEX(ASSUMPTIONS!$C$6:$E$6, 1, MATCH(ASSUMPTIONS!$C$2, ASSUMPTIONS!$C$4:$E$4, 0)))) -> 0 | H14: =IF(INDEX(ASSUMPTIONS!$C$7:$E$7, 1, MATCH(ASSUMPTIONS!$C$2, ASSUMPTIONS!$C$4:$E$4, 0))=1, 0, MAX(0, H13 * INDEX(ASSUMPTIONS!$C$6:$E$6, 1, MATCH(ASSUMPTIONS!$C$2, ASSUMPTIONS!$C$4:$E$4, 0)))) -> 0 | I14: =IF(INDEX(ASSUMPTIONS!$C$7:$E$7, 1, MATCH(ASSUMPTIONS!$C$2, ASSUMPTIONS!$C$4:$E$4, 0))=1, 0, MAX(0, I13 * INDEX(ASSUMPTIONS!$C$6:$E$6, 1, MATCH(ASSUMPTIONS!$C$2, ASSUMPTIONS!$C$4:$E$4, 0)))) -> 0 | J14: =IF(INDEX(ASSUMPTIONS!$C$7:$E$7, 1, MATCH(ASSUMPTIONS!$C$2, ASSUMPTIONS!$C$4:$E$4, 0))=1, 0, MAX(0, J13 * INDEX(ASSUMPTIONS!$C$6:$E$6, 1, MATCH(ASSUMPTIONS!$C$2, ASSUMPTIONS!$C$4:$E$4, 0)))) -> 0 | ... AL14: =IF(INDEX(ASSUMPTIONS!$C$7:$E$7, 1, MATCH(ASSUMPTIONS!$C$2, ASSUMPTIONS!$C$4:$E$4, 0))=1, 0, MAX(0, AL13 * INDEX(ASSUMPTIONS!$C$6:$E$6, 1, MATCH(ASSUMPTIONS!$C$2, ASSUMPTIONS!$C$4:$E$4, 0)))) -> 0 | AM14: =MAX(0, AM13 * INDEX(ASSUMPTIONS!$C$6:$E$6, 1, MATCH(ASSUMPTIONS!$C$2, ASSUMPTIONS!$C$4:$E$4, 0))) -> 0 | AN14: =MAX(0, AN13 * INDEX(ASSUMPTIONS!$C$6:$E$6, 1, MATCH(ASSUMPTIONS!$C$2, ASSUMPTIONS!$C$4:$E$4, 0))) -> 0 | AO14: =MAX(0, AO13 * INDEX(ASSUMPTIONS!$C$6:$E$6, 1, MATCH(ASSUMPTIONS!$C$2, ASSUMPTIONS!$C$4:$E$4, 0))) -> 0 | AP14: =MAX(0, AP13 * INDEX(ASSUMPTIONS!$C$6:$E$6, 1, MATCH(ASSUMPTIONS!$C$2, ASSUMPTIONS!$C$4:$E$4, 0))) -> 0 | AQ14: =MAX(0, AQ13 * INDEX(ASSUMPTIONS!$C$6:$E$6, 1, MATCH(ASSUMPTIONS!$C$2, ASSUMPTIONS!$C$4:$E$4, 0))) -> 0 | AR14: =MAX(0, AR13 * INDEX(ASSUMPTIONS!$C$6:$E$6, 1, MATCH(ASSUMPTIONS!$C$2, ASSUMPTIONS!$C$4:$E$4, 0))) -> 0 | AS14: =MAX(0, AS13 * INDEX(ASSUMPTIONS!$C$6:$E$6, 1, MATCH(ASSUMPTIONS!$C$2, ASSUMPTIONS!$C$4:$E$4, 0))) -> 0 | AT14: =MAX(0, AT13 * INDEX(ASSUMPTIONS!$C$6:$E$6, 1, MATCH(ASSUMPTIONS!$C$2, ASSUMPTIONS!$C$4:$E$4, 0))) -> 0 | ... BJ14: =MAX(0, BJ13 * INDEX(ASSUMPTIONS!$C$6:$E$6, 1, MATCH(ASSUMPTIONS!$C$2, ASSUMPTIONS!$C$4:$E$4, 0))) -> 124052.37
B15: Net Income (PAT) | C15: =C13 - C14 -> -814507.73 | D15: =D13 - D14 -> -812260.22 | E15: =E13 - E14 -> -809996.56 | F15: =F13 - F14 -> -807709.63 | G15: =G13 - G14 -> -805391.84 | H15: =H13 - H14 -> -803035.02 | I15: =I13 - I14 -> -800630.37 | J15: =J13 - J14 -> -798168.4 | ... BJ15: =BJ13 - BJ14 -> 372157.1

Sheet MONTHLY_CASH_FLOW
B2: Monthly Cash Flow Statement
B4: Particulars | C4: Month 1 | D4: Month 2 | E4: Month 3 | F4: Month 4 | G4: Month 5 | H4: Month 6 | I4: Month 7 | J4: Month 8 | K4: Month 9 | L4: Month 10 | M4: Month 11 | N4: Month 12 | O4: Month 13 | P4: Month 14 | Q4: Month 15 | R4: Month 16 | S4: Month 17 | T4: Month 18 | U4: Month 19 | V4: Month 20 | W4: Month 21 | X4: Month 22 | Y4: Month 23 | Z4: Month 24 | AA4: Month 25 | AB4: Month 26 | AC4: Month 27 | AD4: Month 28 | AE4: Month 29 | AF4: Month 30 | AG4: Month 31 | AH4: Month 32 | AI4: Month 33 | AJ4: Month 34 | AK4: Month 35 | AL4: Month 36 | AM4: Month 37 | AN4: Month 38 | AO4: Month 39 | AP4: Month 40 | AQ4: Month 41 | AR4: Month 42 | AS4: Month 43 | AT4: Month 44 | AU4: Month 45 | AV4: Month 46 | AW4: Month 47 | AX4: Month 48 | AY4: Month 49 | AZ4: Month 50 | BA4: Month 51 | BB4: Month 52 | BC4: Month 53 | BD4: Month 54 | BE4: Month 55 | BF4: Month 56 | BG4: Month 57 | BH4: Month 58 | BI4: Month 59 | BJ4: Month 60
B5: Net Income (₹) | C5: =MONTHLY_P_AND_L!C15 -> -814507.73 | D5: =MONTHLY_P_AND_L!D15 -> -812260.22 | E5: =MONTHLY_P_AND_L!E15 -> -809996.56 | F5: =MONTHLY_P_AND_L!F15 -> -807709.63 | G5: =MONTHLY_P_AND_L!G15 -> -805391.84 | H5: =MONTHLY_P_AND_L!H15 -> -803035.02 | I5: =MONTHLY_P_AND_L!I15 -> -800630.37 | J5: =MONTHLY_P_AND_L!J15 -> -798168.4 | ... BJ5: =MONTHLY_P_AND_L!BJ15 -> 372157.1
B6: Add Back: Depreciation (₹) | C6: =CAPEX_AND_DEPRECIATION!C7 -> 83333.333 | D6: =CAPEX_AND_DEPRECIATION!D7 -> 81944.444 | E6: =CAPEX_AND_DEPRECIATION!E7 -> 80578.704 | F6: =CAPEX_AND_DEPRECIATION!F7 -> 79235.725 | G6: =CAPEX_AND_DEPRECIATION!G7 -> 77915.13 | H6: =CAPEX_AND_DEPRECIATION!H7 -> 76616.544 | I6: =CAPEX_AND_DEPRECIATION!I7 -> 75339.602 | J6: =CAPEX_AND_DEPRECIATION!J7 -> 74083.942 | ... BJ6: =CAPEX_AND_DEPRECIATION!BJ7 -> 30914.603
B7: Less: Change in Working Capital (₹) | C7: =WORKING_CAPITAL!C8 -> -27539.77 | D7: =WORKING_CAPITAL!D8 -> 79.735233 | E7: =WORKING_CAPITAL!E8 -> 83.384653 | F7: =WORKING_CAPITAL!F8 -> 87.658462 | G7: =WORKING_CAPITAL!G8 -> 92.60353 | H7: =WORKING_CAPITAL!H8 -> 98.272353 | I7: =WORKING_CAPITAL!I8 -> 104.72355 | J7: =WORKING_CAPITAL!J8 -> 112.02243 | ... BJ7: =WORKING_CAPITAL!BJ8 -> 13264.468
B8: Operating Cash Flow (₹) | C8: =C5 + C6 - C7 -> -703634.63 | D8: =D5 + D6 - D7 -> -730395.51 | E8: =E5 + E6 - E7 -> -729501.24 | F8: =F5 + F6 - F7 -> -728561.57 | G8: =G5 + G6 - G7 -> -727569.32 | H8: =H5 + H6 - H7 -> -726516.75 | I8: =I5 + I6 - I7 -> -725395.49 | J8: =J5 + J6 - J7 -> -724196.48 | ... BJ8: =BJ5 + BJ6 - BJ7 -> 389807.24
B9: Less: CapEx Additions (₹) | C9: =CAPEX_AND_DEPRECIATION!C6 -> 5000000 | D9: =CAPEX_AND_DEPRECIATION!D6 -> 0 | E9: =CAPEX_AND_DEPRECIATION!E6 -> 0 | F9: =CAPEX_AND_DEPRECIATION!F6 -> 0 | G9: =CAPEX_AND_DEPRECIATION!G6 -> 0 | H9: =CAPEX_AND_DEPRECIATION!H6 -> 0 | I9: =CAPEX_AND_DEPRECIATION!I6 -> 0 | J9: =CAPEX_AND_DEPRECIATION!J6 -> 0 | ... BJ9: =CAPEX_AND_DEPRECIATION!BJ6 -> 0
B10: Investing Cash Flow (₹) | C10: =-C9 -> -5000000 | D10: =-D9 -> 0 | E10: =-E9 -> 0 | F10: =-F9 -> 0 | G10: =-G9 -> 0 | H10: =-H9 -> 0 | I10: =-I9 -> 0 | J10: =-J9 -> 0 | ... BJ10: =-BJ9 -> 0
B11: Add: Equity Funding (₹) | C11: =FUNDING_REQUIREMENT!$C$9 -> 10000000 | D11: 0 | E11: 0 | F11: 0 | G11: 0 | H11: 0 | I11: 0 | J11: 0 | K11: 0 | L11: 0 | M11: 0 | N11: 0 | O11: 0 | P11: 0 | Q11: 0 | R11: 0 | S11: 0 | T11: 0 | U11: 0 | V11: 0 | W11: 0 | X11: 0 | Y11: 0 | Z11: 0 | AA11: 0 | AB11: 0 | AC11: 0 | AD11: 0 | AE11: 0 | AF11: 0 | AG11: 0 | AH11: 0 | AI11: 0 | AJ11: 0 | AK11: 0 | AL11: 0 | AM11: 0 | AN11: 0 | AO11: 0 | AP11: 0 | AQ11: 0 | AR11: 0 | AS11: 0 | AT11: 0 | AU11: 0 | AV11: 0 | AW11: 0 | AX11: 0 | AY11: 0 | AZ11: 0 | BA11: 0 | BB11: 0 | BC11: 0 | BD11: 0 | BE11: 0 | BF11: 0 | BG11: 0 | BH11: 0 | BI11: 0 | BJ11: 0
B12: Financing Cash Flow (₹) | C12: =C11 -> 10000000 | D12: =D11 -> 0 | E12: =E11 -> 0 | F12: =F11 -> 0 | G12: =G11 -> 0 | H12: =H11 -> 0 | I12: =I11 -> 0 | J12: =J11 -> 0 | ... BJ12: =BJ11 -> 0
B13: Net Cash Flow for Month (₹) | C13: =C8 + C10 + C12 -> 4296365.4 | D13: =D8 + D10 + D12 -> -730395.51 | E13: =E8 + E10 + E12 -> -729501.24 | F13: =F8 + F10 + F12 -> -728561.57 | G13: =G8 + G10 + G12 -> -727569.32 | H13: =H8 + H10 + H12 -> -726516.75 | I13: =I8 + I10 + I12 -> -725395.49 | J13: =J8 + J10 + J12 -> -724196.48 | ... BJ13: =BJ8 + BJ10 + BJ12 -> 389807.24
B14: Closing Cash Balance (₹) | C14: =C13 -> 4296365.4 | D14: =C14 + D13 -> 3565969.9 | E14: =D14 + E13 -> 2836468.6 | F14: =E14 + F13 -> 2107907.1 | G14: =F14 + G13 -> 1380337.7 | H14: =G14 + H13 -> 653820.99 | I14: =H14 + I13 -> -71574.497 | J14: =I14 + J13 -> -795770.98 | K14: =J14 + K13 -> -1518680.9 | ... BJ14: =BI14 + BJ13 -> -31084078

Sheet QUARTERLY_SUMMARY
B2: Venture Wolf India — Master Quarterly Dashboard (Full Metrics)
B4: BASE CASE
B5: Particulars | C5: Q1 | D5: Q2 | E5: Q3 | F5: Q4 | G5: Q5 | H5: Q6 | I5: Q7 | J5: Q8 | K5: Q9 | L5: Q10 | M5: Q11 | N5: Q12 | O5: Q13 | P5: Q14 | Q5: Q15 | R5: Q16 | S5: Q17 | T5: Q18 | U5: Q19 | V5: Q20
B6: 1. Total Revenue | C6: 262500 | D6: 275625 | E6: 289406.25 | F6: 303876.56 | G6: 319070.39 | H6: 335023.91 | I6: 351775.11 | J6: 369363.86 | K6: 387832.05 | L6: 407223.66 | M6: 427584.84 | N6: 448964.08 | O6: 471412.29 | P6: 494982.9 | Q6: 519732.04 | R6: 545718.65 | S6: 573004.58 | T6: 601654.81 | U6: 631737.55 | V6: 663324.43
B7: 2. Total COGS | C7: 78750 | D7: 82687.5 | E7: 86821.875 | F7: 91162.969 | G7: 95721.117 | H7: 100507.17 | I7: 105532.53 | J7: 110809.16 | K7: 116349.62 | L7: 122167.1 | M7: 128275.45 | N7: 134689.22 | O7: 141423.69 | P7: 148494.87 | Q7: 155919.61 | R7: 163715.59 | S7: 171901.37 | T7: 180496.44 | U7: 189521.26 | V7: 198997.33
B8: 3. Gross Profit | C8: =C6-C7 -> 183750 | D8: =D6-D7 -> 192937.5 | E8: =E6-E7 -> 202584.38 | F8: =F6-F7 -> 212713.59 | G8: =G6-G7 -> 223349.27 | H8: =H6-H7 -> 234516.74 | I8: =I6-I7 -> 246242.57 | J8: =J6-J7 -> 258554.7 | ... V8: =V6-V7 -> 464327.1
B9: A. Gross Margin % | C9: =IF(C6>0, C8/C6, 0) -> 0.7 | D9: =IF(D6>0, D8/D6, 0) -> 0.7 | E9: =IF(E6>0, E8/E6, 0) -> 0.7 | F9: =IF(F6>0, F8/F6, 0) -> 0.7 | G9: =IF(G6>0, G8/G6, 0) -> 0.7 | H9: =IF(H6>0, H8/H6, 0) -> 0.7 | I9: =IF(I6>0, I8/I6, 0) -> 0.7 | J9: =IF(J6>0, J8/J6, 0) -> 0.7 | ... V9: =IF(V6>0, V8/V6, 0) -> 0.7
B10: 4. Total Operating Expenses | C10: 26250 | D10: 27562.5 | E10: 28940.625 | F10: 30387.656 | G10: 31907.039 | H10: 33502.391 | I10: 35177.511 | J10: 36936.386 | K10: 38783.205 | L10: 40722.366 | M10: 42758.484 | N10: 44896.408 | O10: 47141.229 | P10: 49498.29 | Q10: 51973.204 | R10: 54571.865 | S10: 57300.458 | T10: 60165.481 | U10: 63173.755 | V10: 66332.443
B11: 5. EBITDA | C11: =C8-C10 -> 157500 | D11: =D8-D10 -> 165375 | E11: =E8-E10 -> 173643.75 | F11: =F8-F10 -> 182325.94 | G11: =G8-G10 -> 191442.23 | H11: =H8-H10 -> 201014.35 | I11: =I8-I10 -> 211065.06 | J11: =J8-J10 -> 221618.32 | ... V11: =V8-V10 -> 397994.66
B12: B. EBITDA % | C12: =IF(C6>0, C11/C6, 0) -> 0.6 | D12: =IF(D6>0, D11/D6, 0) -> 0.6 | E12: =IF(E6>0, E11/E6, 0) -> 0.6 | F12: =IF(F6>0, F11/F6, 0) -> 0.6 | G12: =IF(G6>0, G11/G6, 0) -> 0.6 | H12: =IF(H6>0, H11/H6, 0) -> 0.6 | I12: =IF(I6>0, I11/I6, 0) -> 0.6 | J12: =IF(J6>0, J11/J6, 0) -> 0.6 | ... V12: =IF(V6>0, V11/V6, 0) -> 0.6
B13: 6. Depreciation & Amortisation | C13: 125000 | D13: 125000 | E13: 125000 | F13: 125000 | G13: 125000 | H13: 125000 | I13: 125000 | J13: 125000 | K13: 125000 | L13: 125000 | M13: 125000 | N13: 125000 | O13: 125000 | P13: 125000 | Q13: 125000 | R13: 125000 | S13: 125000 | T13: 125000 | U13: 125000 | V13: 125000
B14: 7. EBIT | C14: =C11-C13 -> 32500 | D14: =D11-D13 -> 40375 | E14: =E11-E13 -> 48643.75 | F14: =F11-F13 -> 57325.938 | G14: =G11-G13 -> 66442.234 | H14: =H11-H13 -> 76014.346 | I14: =I11-I13 -> 86065.063 | J14: =J11-J13 -> 96618.317 | ... V14: =V11-V13 -> 272994.66
B15: 8. Interest | C15: 15000 | D15: 15000 | E15: 15000 | F15: 15000 | G15: 15000 | H15: 15000 | I15: 15000 | J15: 15000 | K15: 15000 | L15: 15000 | M15: 15000 | N15: 15000 | O15: 15000 | P15: 15000 | Q15: 15000 | R15: 15000 | S15: 15000 | T15: 15000 | U15: 15000 | V15: 15000
B16: 9. PBT | C16: =C14-C15 -> 17500 | D16: =D14-D15 -> 25375 | E16: =E14-E15 -> 33643.75 | F16: =F14-F15 -> 42325.938 | G16: =G14-G15 -> 51442.234 | H16: =H14-H15 -> 61014.346 | I16: =I14-I15 -> 71065.063 | J16: =J14-J15 -> 81618.317 | ... V16: =V14-V15 -> 257994.66
B17: 10. Taxes | C17: =IF(INDEX(ASSUMPTIONS!$C$7:$E$7, 1, MATCH(ASSUMPTIONS!$C$2, ASSUMPTIONS!$C$4:$E$4, 0))=1, 0, MAX(0, C16 * INDEX(ASSUMPTIONS!$C$6:$E$6, 1, MATCH(ASSUMPTIONS!$C$2, ASSUMPTIONS!$C$4:$E$4, 0)))) -> 4375 | D17: =IF(INDEX(ASSUMPTIONS!$C$7:$E$7, 1, MATCH(ASSUMPTIONS!$C$2, ASSUMPTIONS!$C$4:$E$4, 0))=1, 0, MAX(0, D16 * INDEX(ASSUMPTIONS!$C$6:$E$6, 1, MATCH(ASSUMPTIONS!$C$2, ASSUMPTIONS!$C$4:$E$4, 0)))) -> 6343.75 | E17: =IF(INDEX(ASSUMPTIONS!$C$7:$E$7, 1, MATCH(ASSUMPTIONS!$C$2, ASSUMPTIONS!$C$4:$E$4, 0))=1, 0, MAX(0, E16 * INDEX(ASSUMPTIONS!$C$6:$E$6, 1, MATCH(ASSUMPTIONS!$C$2, ASSUMPTIONS!$C$4:$E$4, 0)))) -> 8410.9375 | F17: =IF(INDEX(ASSUMPTIONS!$C$7:$E$7, 1, MATCH(ASSUMPTIONS!$C$2, ASSUMPTIONS!$C$4:$E$4, 0))=1, 0, MAX(0, F16 * INDEX(ASSUMPTIONS!$C$6:$E$6, 1, MATCH(ASSUMPTIONS!$C$2, ASSUMPTIONS!$C$4:$E$4, 0)))) -> 10581.484 | G17: =IF(INDEX(ASSUMPTIONS!$C$7:$E$7, 1, MATCH(ASSUMPTIONS!$C$2, ASSUMPTIONS!$C$4:$E$4, 0))=1, 0, MAX(0, G16 * INDEX(ASSUMPTIONS!$C$6:$E$6, 1, MATCH(ASSUMPTIONS!$C$2, ASSUMPTIONS!$C$4:$E$4, 0)))) -> 12860.559 | H17: =IF(INDEX(ASSUMPTIONS!$C$7:$E$7, 1, MATCH(ASSUMPTIONS!$C$2, ASSUMPTIONS!$C$4:$E$4, 0))=1, 0, MAX(0, H16 * INDEX(ASSUMPTIONS!$C$6:$E$6, 1, MATCH(ASSUMPTIONS!$C$2, ASSUMPTIONS!$C$4:$E$4, 0)))) -> 15253.587 | I17: =IF(INDEX(ASSUMPTIONS!$C$7:$E$7, 1, MATCH(ASSUMPTIONS!$C$2, ASSUMPTIONS!$C$4:$E$4, 0))=1, 0, MAX(0, I16 * INDEX(ASSUMPTIONS!$C$6:$E$6, 1, MATCH(ASSUMPTIONS!$C$2, ASSUMPTIONS!$C$4:$E$4, 0)))) -> 17766.266 | J17: =IF(INDEX(ASSUMPTIONS!$C$7:$E$7, 1, MATCH(ASSUMPTIONS!$C$2, ASSUMPTIONS!$C$4:$E$4, 0))=1, 0, MAX(0, J16 * INDEX(ASSUMPTIONS!$C$6:$E$6, 1, MATCH(ASSUMPTIONS!$C$2, ASSUMPTIONS!$C$4:$E$4, 0)))) -> 20404.579 | ... N17: =IF(INDEX(ASSUMPTIONS!$C$7:$E$7, 1, MATCH(ASSUMPTIONS!$C$2, ASSUMPTIONS!$C$4:$E$4, 0))=1, 0, MAX(0, N16 * INDEX(ASSUMPTIONS!$C$6:$E$6, 1, MATCH(ASSUMPTIONS!$C$2, ASSUMPTIONS!$C$4:$E$4, 0)))) -> 32344.612 | O17: =MAX(0, O16 * INDEX(ASSUMPTIONS!$C$6:$E$6, 1, MATCH(ASSUMPTIONS!$C$2, ASSUMPTIONS!$C$4:$E$4, 0))) -> 35711.843 | P17: =MAX(0, P16 * INDEX(ASSUMPTIONS!$C$6:$E$6, 1, MATCH(ASSUMPTIONS!$C$2, ASSUMPTIONS!$C$4:$E$4, 0))) -> 39247.435 | Q17: =MAX(0, Q16 * INDEX(ASSUMPTIONS!$C$6:$E$6, 1, MATCH(ASSUMPTIONS!$C$2, ASSUMPTIONS!$C$4:$E$4, 0))) -> 42959.807 | R17: =MAX(0, R16 * INDEX(ASSUMPTIONS!$C$6:$E$6, 1, MATCH(ASSUMPTIONS!$C$2, ASSUMPTIONS!$C$4:$E$4, 0))) -> 46857.797 | S17: =MAX(0, S16 * INDEX(ASSUMPTIONS!$C$6:$E$6, 1, MATCH(ASSUMPTIONS!$C$2, ASSUMPTIONS!$C$4:$E$4, 0))) -> 50950.687 | T17: =MAX(0, T16 * INDEX(ASSUMPTIONS!$C$6:$E$6, 1, MATCH(ASSUMPTIONS!$C$2, ASSUMPTIONS!$C$4:$E$4, 0))) -> 55248.221 | U17: =MAX(0, U16 * INDEX(ASSUMPTIONS!$C$6:$E$6, 1, MATCH(ASSUMPTIONS!$C$2, ASSUMPTIONS!$C$4:$E$4, 0))) -> 59760.632 | V17: =MAX(0, V16 * INDEX(ASSUMPTIONS!$C$6:$E$6, 1, MATCH(ASSUMPTIONS!$C$2, ASSUMPTIONS!$C$4:$E$4, 0))) -> 64498.664
B18: 11. PAT | C18: =C16-C17 -> 13125 | D18: =D16-D17 -> 19031.25 | E18: =E16-E17 -> 25232.813 | F18: =F16-F17 -> 31744.453 | G18: =G16-G17 -> 38581.676 | H18: =H16-H17 -> 45760.76 | I18: =I16-I17 -> 53298.798 | J18: =J16-J17 -> 61213.737 | ... V18: =V16-V17 -> 193495.99
B19: C. PAT % | C19: =IF(C6>0, C18/C6, 0) -> 0.05 | D19: =IF(D6>0, D18/D6, 0) -> 0.069047619 | E19: =IF(E6>0, E18/E6, 0) -> 0.087188209 | F19: =IF(F6>0, F18/F6, 0) -> 0.10446496 | G19: =IF(G6>0, G18/G6, 0) -> 0.12091901 | H19: =IF(H6>0, H18/H6, 0) -> 0.13658953 | I19: =IF(I6>0, I18/I6, 0) -> 0.15151384 | J19: =IF(J6>0, J18/J6, 0) -> 0.16572747 | ... V19: =IF(V6>0, V18/V6, 0) -> 0.29170642
B21: BEST CASE
B22: Particulars | C22: Q1 | D22: Q2 | E22: Q3 | F22: Q4 | G22: Q5 | H22: Q6 | I22: Q7 | J22: Q8 | K22: Q9 | L22: Q10 | M22: Q11 | N22: Q12 | O22: Q13 | P22: Q14 | Q22: Q15 | R22: Q16 | S22: Q17 | T22: Q18 | U22: Q19 | V22: Q20
B23: 1. Total Revenue | C23: 393750 | D23: 413437.5 | E23: 434109.38 | F23: 455814.84 | G23: 478605.59 | H23: 502535.87 | I23: 527662.66 | J23: 554045.79 | K23: 581748.08 | L23: 610835.49 | M23: 641377.26 | N23: 673446.12 | O23: 707118.43 | P23: 742474.35 | Q23: 779598.07 | R23: 818577.97 | S23: 859506.87 | T23: 902482.21 | U23: 947606.32 | V23: 994986.64
B24: 2. Total COGS | C24: 118125 | D24: 124031.25 | E24: 130232.81 | F24: 136744.45 | G24: 143581.68 | H24: 150760.76 | I24: 158298.8 | J24: 166213.74 | K24: 174524.42 | L24: 183250.65 | M24: 192413.18 | N24: 202033.84 | O24: 212135.53 | P24: 222742.3 | Q24: 233879.42 | R24: 245573.39 | S24: 257852.06 | T24: 270744.66 | U24: 284281.9 | V24: 298495.99
B25: 3. Gross Profit | C25: =C23-C24 -> 275625 | D25: =D23-D24 -> 289406.25 | E25: =E23-E24 -> 303876.56 | F25: =F23-F24 -> 319070.39 | G25: =G23-G24 -> 335023.91 | H25: =H23-H24 -> 351775.11 | I25: =I23-I24 -> 369363.86 | J25: =J23-J24 -> 387832.05 | ... V25: =V23-V24 -> 696490.65
B26: A. Gross Margin % | C26: =IF(C23>0, C25/C23, 0) -> 0.7 | D26: =IF(D23>0, D25/D23, 0) -> 0.7 | E26: =IF(E23>0, E25/E23, 0) -> 0.7 | F26: =IF(F23>0, F25/F23, 0) -> 0.7 | G26: =IF(G23>0, G25/G23, 0) -> 0.7 | H26: =IF(H23>0, H25/H23, 0) -> 0.7 | I26: =IF(I23>0, I25/I23, 0) -> 0.7 | J26: =IF(J23>0, J25/J23, 0) -> 0.7 | ... V26: =IF(V23>0, V25/V23, 0) -> 0.7
B27: 4. Total Operating Expenses | C27: 39375 | D27: 41343.75 | E27: 43410.938 | F27: 45581.484 | G27: 47860.559 | H27: 50253.587 | I27: 52766.266 | J27: 55404.579 | K27: 58174.808 | L27: 61083.549 | M27: 64137.726 | N27: 67344.612 | O27: 70711.843 | P27: 74247.435 | Q27: 77959.807 | R27: 81857.797 | S27: 85950.687 | T27: 90248.221 | U27: 94760.632 | V27: 99498.664
B28: 5. EBITDA | C28: =C25-C27 -> 236250 | D28: =D25-D27 -> 248062.5 | E28: =E25-E27 -> 260465.63 | F28: =F25-F27 -> 273488.91 | G28: =G25-G27 -> 287163.35 | H28: =H25-H27 -> 301521.52 | I28: =I25-I27 -> 316597.6 | J28: =J25-J27 -> 332427.47 | ... V28: =V25-V27 -> 596991.98
B29: B. EBITDA % | C29: =IF(C23>0, C28/C23, 0) -> 0.6 | D29: =IF(D23>0, D28/D23, 0) -> 0.6 | E29: =IF(E23>0, E28/E23, 0) -> 0.6 | F29: =IF(F23>0, F28/F23, 0) -> 0.6 | G29: =IF(G23>0, G28/G23, 0) -> 0.6 | H29: =IF(H23>0, H28/H23, 0) -> 0.6 | I29: =IF(I23>0, I28/I23, 0) -> 0.6 | J29: =IF(J23>0, J28/J23, 0) -> 0.6 | ... V29: =IF(V23>0, V28/V23, 0) -> 0.6
B30: 6. Depreciation & Amortisation | C30: 125000 | D30: 125000 | E30: 125000 | F30: 125000 | G30: 125000 | H30: 125000 | I30: 125000 | J30: 125000 | K30: 125000 | L30: 125000 | M30: 125000 | N30: 125000 | O30: 125000 | P30: 125000 | Q30: 125000 | R30: 125000 | S30: 125000 | T30: 125000 | U30: 125000 | V30: 125000
B31: 7. EBIT | C31: =C28-C30 -> 111250 | D31: =D28-D30 -> 123062.5 | E31: =E28-E30 -> 135465.63 | F31: =F28-F30 -> 148488.91 | G31: =G28-G30 -> 162163.35 | H31: =H28-H30 -> 176521.52 | I31: =I28-I30 -> 191597.6 | J31: =J28-J30 -> 207427.47 | ... V31: =V28-V30 -> 471991.98
B32: 8. Interest | C32: 15000 | D32: 15000 | E32: 15000 | F32: 15000 | G32: 15000 | H32: 15000 | I32: 15000 | J32: 15000 | K32: 15000 | L32: 15000 | M32: 15000 | N32: 15000 | O32: 15000 | P32: 15000 | Q32: 15000 | R32: 15000 | S32: 15000 | T32: 15000 | U32: 15000 | V32: 15000
B33: 9. PBT | C33: =C31-C32 -> 96250 | D33: =D31-D32 -> 108062.5 | E33: =E31-E32 -> 120465.63 | F33: =F31-F32 -> 133488.91 | G33: =G31-G32 -> 147163.35 | H33: =H31-H32 -> 161521.52 | I33: =I31-I32 -> 176597.6 | J33: =J31-J32 -> 192427.47 | ... V33: =V31-V32 -> 456991.98
B34: 10. Taxes | C34: =IF(INDEX(ASSUMPTIONS!$C$7:$E$7, 1, MATCH(ASSUMPTIONS!$C$2, ASSUMPTIONS!$C$4:$E$4, 0))=1, 0, MAX(0, C33 * INDEX(ASSUMPTIONS!$C$6:$E$6, 1, MATCH(ASSUMPTIONS!$C$2, ASSUMPTIONS!$C$4:$E$4, 0)))) -> 24062.5 | D34: =IF(INDEX(ASSUMPTIONS!$C$7:$E$7, 1, MATCH(ASSUMPTIONS!$C$2, ASSUMPTIONS!$C$4:$E$4, 0))=1, 0, MAX(0, D33 * INDEX(ASSUMPTIONS!$C$6:$E$6, 1, MATCH(ASSUMPTIONS!$C$2, ASSUMPTIONS!$C$4:$E$4, 0)))) -> 27015.625 | E34: =IF(INDEX(ASSUMPTIONS!$C$7:$E$7, 1, MATCH(ASSUMPTIONS!$C$2, ASSUMPTIONS!$C$4:$E$4, 0))=1, 0, MAX(0, E33 * INDEX(ASSUMPTIONS!$C$6:$E$6, 1, MATCH(ASSUMPTIONS!$C$2, ASSUMPTIONS!$C$4:$E$4, 0)))) -> 30116.406 | F34: =IF(INDEX(ASSUMPTIONS!$C$7:$E$7, 1, MATCH(ASSUMPTIONS!$C$2, ASSUMPTIONS!$C$4:$E$4, 0))=1, 0, MAX(0, F33 * INDEX(ASSUMPTIONS!$C$6:$E$6, 1, MATCH(ASSUMPTIONS!$C$2, ASSUMPTIONS!$C$4:$E$4, 0)))) -> 33372.227 | G34: =IF(INDEX(ASSUMPTIONS!$C$7:$E$7, 1, MATCH(ASSUMPTIONS!$C$2, ASSUMPTIONS!$C$4:$E$4, 0))=1, 0, MAX(0, G33 * INDEX(ASSUMPTIONS!$C$6:$E$6, 1, MATCH(ASSUMPTIONS!$C$2, ASSUMPTIONS!$C$4:$E$4, 0)))) -> 36790.838 | H34: =IF(INDEX(ASSUMPTIONS!$C$7:$E$7, 1, MATCH(ASSUMPTIONS!$C$2, ASSUMPTIONS!$C$4:$E$4, 0))=1, 0, MAX(0, H33 * INDEX(ASSUMPTIONS!$C$6:$E$6, 1, MATCH(ASSUMPTIONS!$C$2, ASSUMPTIONS!$C$4:$E$4, 0)))) -> 40380.38 | I34: =IF(INDEX(ASSUMPTIONS!$C$7:$E$7, 1, MATCH(ASSUMPTIONS!$C$2, ASSUMPTIONS!$C$4:$E$4, 0))=1, 0, MAX(0, I33 * INDEX(ASSUMPTIONS!$C$6:$E$6, 1, MATCH(ASSUMPTIONS!$C$2, ASSUMPTIONS!$C$4:$E$4, 0)))) -> 44149.399 | J34: =IF(INDEX(ASSUMPTIONS!$C$7:$E$7, 1, MATCH(ASSUMPTIONS!$C$2, ASSUMPTIONS!$C$4:$E$4, 0))=1, 0, MAX(0, J33 * INDEX(ASSUMPTIONS!$C$6:$E$6, 1, MATCH(ASSUMPTIONS!$C$2, ASSUMPTIONS!$C$4:$E$4, 0)))) -> 48106.869 | ... N34: =IF(INDEX(ASSUMPTIONS!$C$7:$E$7, 1, MATCH(ASSUMPTIONS!$C$2, ASSUMPTIONS!$C$4:$E$4, 0))=1, 0, MAX(0, N33 * INDEX(ASSUMPTIONS!$C$6:$E$6, 1, MATCH(ASSUMPTIONS!$C$2, ASSUMPTIONS!$C$4:$E$4, 0)))) -> 66016.918 | O34: =MAX(0, O33 * INDEX(ASSUMPTIONS!$C$6:$E$6, 1, MATCH(ASSUMPTIONS!$C$2, ASSUMPTIONS!$C$4:$E$4, 0))) -> 71067.764 | P34: =MAX(0, P33 * INDEX(ASSUMPTIONS!$C$6:$E$6, 1, MATCH(ASSUMPTIONS!$C$2, ASSUMPTIONS!$C$4:$E$4, 0))) -> 76371.152 | Q34: =MAX(0, Q33 * INDEX(ASSUMPTIONS!$C$6:$E$6, 1, MATCH(ASSUMPTIONS!$C$2, ASSUMPTIONS!$C$4:$E$4, 0))) -> 81939.71 | R34: =MAX(0, R33 * INDEX(ASSUMPTIONS!$C$6:$E$6, 1, MATCH(ASSUMPTIONS!$C$2, ASSUMPTIONS!$C$4:$E$4, 0))) -> 87786.696 | S34: =MAX(0, S33 * INDEX(ASSUMPTIONS!$C$6:$E$6, 1, MATCH(ASSUMPTIONS!$C$2, ASSUMPTIONS!$C$4:$E$4, 0))) -> 93926.03 | T34: =MAX(0, T33 * INDEX(ASSUMPTIONS!$C$6:$E$6, 1, MATCH(ASSUMPTIONS!$C$2, ASSUMPTIONS!$C$4:$E$4, 0))) -> 100372.33 | U34: =MAX(0, U33 * INDEX(ASSUMPTIONS!$C$6:$E$6, 1, MATCH(ASSUMPTIONS!$C$2, ASSUMPTIONS!$C$4:$E$4, 0))) -> 107140.95 | V34: =MAX(0, V33 * INDEX(ASSUMPTIONS!$C$6:$E$6, 1, MATCH(ASSUMPTIONS!$C$2, ASSUMPTIONS!$C$4:$E$4, 0))) -> 114248
B35: 11. PAT | C35: =C33-C34 -> 72187.5 | D35: =D33-D34 -> 81046.875 | E35: =E33-E34 -> 90349.219 | F35: =F33-F34 -> 100116.68 | G35: =G33-G34 -> 110372.51 | H35: =H33-H34 -> 121141.14 | I35: =I33-I34 -> 132448.2 | J35: =J33-J34 -> 144320.61 | ... V35: =V33-V34 -> 342743.99
B36: C. PAT % | C36: =IF(C23>0, C35/C23, 0) -> 0.18333333 | D36: =IF(D23>0, D35/D23, 0) -> 0.19603175 | E36: =IF(E23>0, E35/E23, 0) -> 0.20812547 | F36: =IF(F23>0, F35/F23, 0) -> 0.21964331 | G36: =IF(G23>0, G35/G23, 0) -> 0.23061267 | H36: =IF(H23>0, H35/H23, 0) -> 0.24105969 | I36: =IF(I23>0, I35/I23, 0) -> 0.25100923 | J36: =IF(J23>0, J35/J23, 0) -> 0.26048498 | ... V36: =IF(V23>0, V35/V23, 0) -> 0.34447094
B38: WORST CASE
B39: Particulars | C39: Q1 | D39: Q2 | E39: Q3 | F39: Q4 | G39: Q5 | H39: Q6 | I39: Q7 | J39: Q8 | K39: Q9 | L39: Q10 | M39: Q11 | N39: Q12 | O39: Q13 | P39: Q14 | Q39: Q15 | R39: Q16 | S39: Q17 | T39: Q18 | U39: Q19 | V39: Q20
B40: 1. Total Revenue | C40: 157500 | D40: 165375 | E40: 173643.75 | F40: 182325.94 | G40: 191442.23 | H40: 201014.35 | I40: 211065.06 | J40: 221618.32 | K40: 232699.23 | L40: 244334.19 | M40: 256550.9 | N40: 269378.45 | O40: 282847.37 | P40: 296989.74 | Q40: 311839.23 | R40: 327431.19 | S40: 343802.75 | T40: 360992.89 | U40: 379042.53 | V40: 397994.66
B41: 2. Total COGS | C41: 47250 | D41: 49612.5 | E41: 52093.125 | F41: 54697.781 | G41: 57432.67 | H41: 60304.304 | I41: 63319.519 | J41: 66485.495 | K41: 69809.77 | L41: 73300.258 | M41: 76965.271 | N41: 80813.535 | O41: 84854.211 | P41: 89096.922 | Q41: 93551.768 | R41: 98229.356 | S41: 103140.82 | T41: 108297.87 | U41: 113712.76 | V41: 119398.4
B42: 3. Gross Profit | C42: =C40-C41 -> 110250 | D42: =D40-D41 -> 115762.5 | E42: =E40-E41 -> 121550.63 | F42: =F40-F41 -> 127628.16 | G42: =G40-G41 -> 134009.56 | H42: =H40-H41 -> 140710.04 | I42: =I40-I41 -> 147745.54 | J42: =J40-J41 -> 155132.82 | ... V42: =V40-V41 -> 278596.26
B43: A. Gross Margin % | C43: =IF(C40>0, C42/C40, 0) -> 0.7 | D43: =IF(D40>0, D42/D40, 0) -> 0.7 | E43: =IF(E40>0, E42/E40, 0) -> 0.7 | F43: =IF(F40>0, F42/F40, 0) -> 0.7 | G43: =IF(G40>0, G42/G40, 0) -> 0.7 | H43: =IF(H40>0, H42/H40, 0) -> 0.7 | I43: =IF(I40>0, I42/I40, 0) -> 0.7 | J43: =IF(J40>0, J42/J40, 0) -> 0.7 | ... V43: =IF(V40>0, V42/V40, 0) -> 0.7
B44: 4. Total Operating Expenses | C44: 15750 | D44: 16537.5 | E44: 17364.375 | F44: 18232.594 | G44: 19144.223 | H44: 20101.435 | I44: 21106.506 | J44: 22161.832 | K44: 23269.923 | L44: 24433.419 | M44: 25655.09 | N44: 26937.845 | O44: 28284.737 | P44: 29698.974 | Q44: 31183.923 | R44: 32743.119 | S44: 34380.275 | T44: 36099.289 | U44: 37904.253 | V44: 39799.466
B45: 5. EBITDA | C45: =C42-C44 -> 94500 | D45: =D42-D44 -> 99225 | E45: =E42-E44 -> 104186.25 | F45: =F42-F44 -> 109395.56 | G45: =G42-G44 -> 114865.34 | H45: =H42-H44 -> 120608.61 | I45: =I42-I44 -> 126639.04 | J45: =J42-J44 -> 132970.99 | ... V45: =V42-V44 -> 238796.79
B46: B. EBITDA % | C46: =IF(C40>0, C45/C40, 0) -> 0.6 | D46: =IF(D40>0, D45/D40, 0) -> 0.6 | E46: =IF(E40>0, E45/E40, 0) -> 0.6 | F46: =IF(F40>0, F45/F40, 0) -> 0.6 | G46: =IF(G40>0, G45/G40, 0) -> 0.6 | H46: =IF(H40>0, H45/H40, 0) -> 0.6 | I46: =IF(I40>0, I45/I40, 0) -> 0.6 | J46: =IF(J40>0, J45/J40, 0) -> 0.6 | ... V46: =IF(V40>0, V45/V40, 0) -> 0.6
B47: 6. Depreciation & Amortisation | C47: 125000 | D47: 125000 | E47: 125000 | F47: 125000 | G47: 125000 | H47: 125000 | I47: 125000 | J47: 125000 | K47: 125000 | L47: 125000 | M47: 125000 | N47: 125000 | O47: 125000 | P47: 125000 | Q47: 125000 | R47: 125000 | S47: 125000 | T47: 125000 | U47: 125000 | V47: 125000
B48: 7. EBIT | C48: =C45-C47 -> -30500 | D48: =D45-D47 -> -25775 | E48: =E45-E47 -> -20813.75 | F48: =F45-F47 -> -15604.437 | G48: =G45-G47 -> -10134.659 | H48: =H45-H47 -> -4391.3923 | I48: =I45-I47 -> 1639.038 | J48: =J45-J47 -> 7970.9899 | ... V48: =V45-V47 -> 113796.79
B49: 8. Interest | C49: 15000 | D49: 15000 | E49: 15000 | F49: 15000 | G49: 15000 | H49: 15000 | I49: 15000 | J49: 15000 | K49: 15000 | L49: 15000 | M49: 15000 | N49: 15000 | O49: 15000 | P49: 15000 | Q49: 15000 | R49: 15000 | S49: 15000 | T49: 15000 | U49: 15000 | V49: 15000
B50: 9. PBT | C50: =C48-C49 -> -45500 | D50: =D48-D49 -> -40775 | E50: =E48-E49 -> -35813.75 | F50: =F48-F49 -> -30604.437 | G50: =G48-G49 -> -25134.659 | H50: =H48-H49 -> -19391.392 | I50: =I48-I49 -> -13360.962 | J50: =J48-J49 -> -7029.0101 | ... V50: =V48-V49 -> 98796.793
B51: 10. Taxes | C51: =IF(INDEX(ASSUMPTIONS!$C$7:$E$7, 1, MATCH(ASSUMPTIONS!$C$2, ASSUMPTIONS!$C$4:$E$4, 0))=1, 0, MAX(0, C50 * INDEX(ASSUMPTIONS!$C$6:$E$6, 1, MATCH(ASSUMPTIONS!$C$2, ASSUMPTIONS!$C$4:$E$4, 0)))) -> 0 | D51: =IF(INDEX(ASSUMPTIONS!$C$7:$E$7, 1, MATCH(ASSUMPTIONS!$C$2, ASSUMPTIONS!$C$4:$E$4, 0))=1, 0, MAX(0, D50 * INDEX(ASSUMPTIONS!$C$6:$E$6, 1, MATCH(ASSUMPTIONS!$C$2, ASSUMPTIONS!$C$4:$E$4, 0)))) -> 0 | E51: =IF(INDEX(ASSUMPTIONS!$C$7:$E$7, 1, MATCH(ASSUMPTIONS!$C$2, ASSUMPTIONS!$C$4:$E$4, 0))=1, 0, MAX(0, E50 * INDEX(ASSUMPTIONS!$C$6:$E$6, 1, MATCH(ASSUMPTIONS!$C$2, ASSUMPTIONS!$C$4:$E$4, 0)))) -> 0 | F51: =IF(INDEX(ASSUMPTIONS!$C$7:$E$7, 1, MATCH(ASSUMPTIONS!$C$2, ASSUMPTIONS!$C$4:$E$4, 0))=1, 0, MAX(0, F50 * INDEX(ASSUMPTIONS!$C$6:$E$6, 1, MATCH(ASSUMPTIONS!$C$2, ASSUMPTIONS!$C$4:$E$4, 0)))) -> 0 | G51: =IF(INDEX(ASSUMPTIONS!$C$7:$E$7, 1, MATCH(ASSUMPTIONS!$C$2, ASSUMPTIONS!$C$4:$E$4, 0))=1, 0, MAX(0, G50 * INDEX(ASSUMPTIONS!$C$6:$E$6, 1, MATCH(ASSUMPTIONS!$C$2, ASSUMPTIONS!$C$4:$E$4, 0)))) -> 0 | H51: =IF(INDEX(ASSUMPTIONS!$C$7:$E$7, 1, MATCH(ASSUMPTIONS!$C$2, ASSUMPTIONS!$C$4:$E$4, 0))=1, 0, MAX(0, H50 * INDEX(ASSUMPTIONS!$C$6:$E$6, 1, MATCH(ASSUMPTIONS!$C$2, ASSUMPTIONS!$C$4:$E$4, 0)))) -> 0 | I51: =IF(INDEX(ASSUMPTIONS!$C$7:$E$7, 1, MATCH(ASSUMPTIONS!$C$2, ASSUMPTIONS!$C$4:$E$4, 0))=1, 0, MAX(0, I50 * INDEX(ASSUMPTIONS!$C$6:$E$6, 1, MATCH(ASSUMPTIONS!$C$2, ASSUMPTIONS!$C$4:$E$4, 0)))) -> 0 | J51: =IF(INDEX(ASSUMPTIONS!$C$7:$E$7, 1, MATCH(ASSUMPTIONS!$C$2, ASSUMPTIONS!$C$4:$E$4, 0))=1, 0, MAX(0, J50 * INDEX(ASSUMPTIONS!$C$6:$E$6, 1, MATCH(ASSUMPTIONS!$C$2, ASSUMPTIONS!$C$4:$E$4, 0)))) -> 0 | ... N51: =IF(INDEX(ASSUMPTIONS!$C$7:$E$7, 1, MATCH(ASSUMPTIONS!$C$2, ASSUMPTIONS!$C$4:$E$4, 0))=1, 0, MAX(0, N50 * INDEX(ASSUMPTIONS!$C$6:$E$6, 1, MATCH(ASSUMPTIONS!$C$2, ASSUMPTIONS!$C$4:$E$4, 0)))) -> 5406.7673 | O51: =MAX(0, O50 * INDEX(ASSUMPTIONS!$C$6:$E$6, 1, MATCH(ASSUMPTIONS!$C$2, ASSUMPTIONS!$C$4:$E$4, 0))) -> 7427.1057 | P51: =MAX(0, P50 * INDEX(ASSUMPTIONS!$C$6:$E$6, 1, MATCH(ASSUMPTIONS!$C$2, ASSUMPTIONS!$C$4:$E$4, 0))) -> 9548.461 | Q51: =MAX(0, Q50 * INDEX(ASSUMPTIONS!$C$6:$E$6, 1, MATCH(ASSUMPTIONS!$C$2, ASSUMPTIONS!$C$4:$E$4, 0))) -> 11775.884 | R51: =MAX(0, R50 * INDEX(ASSUMPTIONS!$C$6:$E$6, 1, MATCH(ASSUMPTIONS!$C$2, ASSUMPTIONS!$C$4:$E$4, 0))) -> 14114.678 | S51: =MAX(0, S50 * INDEX(ASSUMPTIONS!$C$6:$E$6, 1, MATCH(ASSUMPTIONS!$C$2, ASSUMPTIONS!$C$4:$E$4, 0))) -> 16570.412 | T51: =MAX(0, T50 * INDEX(ASSUMPTIONS!$C$6:$E$6, 1, MATCH(ASSUMPTIONS!$C$2, ASSUMPTIONS!$C$4:$E$4, 0))) -> 19148.933 | U51: =MAX(0, U50 * INDEX(ASSUMPTIONS!$C$6:$E$6, 1, MATCH(ASSUMPTIONS!$C$2, ASSUMPTIONS!$C$4:$E$4, 0))) -> 21856.379 | V51: =MAX(0, V50 * INDEX(ASSUMPTIONS!$C$6:$E$6, 1, MATCH(ASSUMPTIONS!$C$2, ASSUMPTIONS!$C$4:$E$4, 0))) -> 24699.198
B52: 11. PAT | C52: =C50-C51 -> -45500 | D52: =D50-D51 -> -40775 | E52: =E50-E51 -> -35813.75 | F52: =F50-F51 -> -30604.437 | G52: =G50-G51 -> -25134.659 | H52: =H50-H51 -> -19391.392 | I52: =I50-I51 -> -13360.962 | J52: =J50-J51 -> -7029.0101 | ... V52: =V50-V51 -> 74097.595
B53: C. PAT % | C53: =IF(C40>0, C52/C40, 0) -> -0.28888889 | D53: =IF(D40>0, D52/D40, 0) -> -0.24656085 | E53: =IF(E40>0, E52/E40, 0) -> -0.20624843 | F53: =IF(F40>0, F52/F40, 0) -> -0.16785564 | G53: =IF(G40>0, G52/G40, 0) -> -0.13129109 | H53: =IF(H40>0, H52/H40, 0) -> -0.096467704 | I53: =IF(I40>0, I52/I40, 0) -> -0.063302575 | J53: =IF(J40>0, J52/J40, 0) -> -0.031716738 | ... V53: =IF(V40>0, V52/V40, 0) -> 0.18617736

Sheet YEARLY_SUMMARY
B2: Venture Wolf India — Master Summary Dashboard (Full Metrics)
B4: BASE CASE
B5: Particulars | C5: Year 1 | D5: Year 2 | E5: Year 3 | F5: Year 4 | G5: Year 5
B6: 1. Total Revenue | C6: 750626 | D6: 1121166 | E6: 1674621 | F6: 2501284 | G6: 3736022
B7: 2. Total COGS | C7: 150125 | D7: 224233 | E7: 334924 | F7: 500257 | G7: 747204
B8: 3. Gross Profit | C8: 600501 | D8: 896933 | E8: 1339697 | F8: 2001027 | G8: 2988818
B9: A. Gross Margin % | C9: 0.8 | D9: 0.8 | E9: 0.8 | F9: 0.8 | G9: 0.8
B10: 4. Total Operating Expenses | C10: 2614125 | D10: 2934633 | E10: 3316364 | F10: 3779841 | G10: 4354747
B11: 5. EBITDA | C11: -2013624 | D11: -2037700 | E11: -1976667 | F11: -1778814 | G11: -1365929
B12: B. EBITDA % | C12: -2.6826 | D12: -1.8175 | E12: -1.1804 | F12: -0.7112 | G12: -0.3656
B13: 6. Depreciation & Amortisation | C13: 37531 | D13: 56058 | E13: 83731 | F13: 125064 | G13: 186801
B14: 7. EBIT | C14: -2051155 | D14: -2093758 | E14: -2060398 | F14: -1903878 | G14: -1552730
B15: 8. Interest | C15: 216000 | D15: 237600 | E15: 261360 | F15: 287496 | G15: 316246
B16: 9. PBT | C16: -2267155 | D16: -2331358 | E16: -2321758 | F16: -2191374 | G16: -1868976
B17: 10. Taxes | C17: 0 | D17: 0 | E17: 0 | F17: 0 | G17: 0
... B19: C. PAT % | C19: -3.0204 | D19: -2.0794 | E19: -1.3864 | F19: -0.8761 | G19: -0.5003
B21: BEST CASE
B22: Particulars | C22: Year 1 | D22: Year 2 | E22: Year 3 | F22: Year 4 | G22: Year 5
B23: 1. Total Revenue | C23: 2836319 | D23: 32388300 | E23: 369846244 | F23: 4223322797 | G23: 48226677297
B24: 2. Total COGS | C24: 425448 | D24: 4858245 | E24: 55476937 | F24: 633498420 | G24: 7234001595
B25: 3. Gross Profit | C25: 2410871 | D25: 27530055 | E25: 314369307 | F25: 3589824377 | G25: 40992675702
B26: A. Gross Margin % | C26: 0.85 | D26: 0.85 | E26: 0.85 | F26: 0.85 | G26: 0.85
B27: 4. Total Operating Expenses | C27: 2801448 | D27: 7424325 | E27: 58248303 | F27: 636491495 | G27: 7237234116
B28: 5. EBITDA | C28: -390577 | D28: 20105730 | E28: 256121004 | F28: 2953332882 | G28: 33755441586
B29: B. EBITDA % | C29: -0.1377 | D29: 0.6208 | E29: 0.6925 | F29: 0.6993 | G29: 0.6999
B30: 6. Depreciation & Amortisation | C30: 141816 | D30: 1619415 | E30: 18492312 | F30: 211166140 | G30: 2411333865
B31: 7. EBIT | C31: -532393 | D31: 18486315 | E31: 237628692 | F31: 2742166742 | G31: 31344107721
B32: 8. Interest | C32: 171000 | D32: 188100 | E32: 169290 | F32: 152361 | G32: 137125
B33: 9. PBT | C33: -703393 | D33: 18298215 | E33: 237459402 | F33: 2742014381 | G33: 31343970596
B34: 10. Taxes | C34: 0 | D34: 4574554 | E34: 59364851 | F34: 685503595 | G34: 7835992649
... B36: C. PAT % | C36: -0.248 | D36: 0.4237 | E36: 0.4815 | F36: 0.4869 | G36: 0.4874
B38: WORST CASE
B39: Particulars | C39: Year 1 | D39: Year 2 | E39: Year 3 | F39: Year 4 | G39: Year 5
B40: 1. Total Revenue | C40: 283026 | D40: 58750 | E40: 12195 | F40: 2531 | G40: 525
B41: 2. Total COGS | C41: 84908 | D41: 17625 | E41: 3659 | F41: 759 | G41: 158
B42: 3. Gross Profit | C42: 198118 | D42: 41125 | E42: 8536 | F42: 1772 | G42: 367
B43: A. Gross Margin % | C43: 0.7 | D43: 0.7 | E43: 0.6999 | F43: 0.7 | G43: 0.6984
B44: 4. Total Operating Expenses | C44: 2646756 | D44: 2899808 | E44: 3234383 | F44: 3619727 | G44: 4053517
B45: 5. EBITDA | C45: -2448638 | D45: -2858683 | E45: -3225847 | F45: -3617955 | G45: -4053150
B46: B. EBITDA % | C46: -8.6516 | D46: -48.6582 | E46: -264.5152 | F46: -1429.1786 | G46: -7713.1637
B47: 6. Depreciation & Amortisation | C47: 14151 | D47: 2938 | E47: 610 | F47: 127 | G47: 26
B48: 7. EBIT | C48: -2462789 | D48: -2861621 | E48: -3226457 | F48: -3618082 | G48: -4053176
B49: 8. Interest | C49: 288000 | D49: 316800 | E49: 348480 | F49: 383328 | G49: 421661
B50: 9. PBT | C50: -2750789 | D50: -3178421 | E50: -3574937 | F50: -4001410 | G50: -4474837
B51: 10. Taxes | C51: 0 | D51: 0 | E51: 0 | F51: 0 | G51: 0
... B53: C. PAT % | C53: -9.7192 | D53: -54.1006 | E53: -293.1401 | F53: -1580.6525 | G53: -8515.6361
