Workbook

Sheet COVER
B12: Narayan Dairy Project
B13: =TODAY()-5 -> 46208
B24: Financial Model Worksheet
B25: FY2026 – FY 2030

Sheet ASSUMPTIONS
A1: =COVER!$B$12 -> Narayan Dairy Project
A2: Assumptions
D4: Particular | E4: Worst | F4: Base | G4: Best | H4: Active | J4: Product | K4: Product Category | L4: Milk Allocation | N4: Scenario
D7: Scenario Control | J7: Fresh Milk Category | K7: Whole Milk | L7: 1 | N7: Best
D8: Capacity Ramp | E8: 0.8 | F8: 1 | G8: 1.2 | H8: =IF($N$7="Worst",E8,IF($N$7="Base",F8,G8)) -> 1.2 | J8: Procured Milk Category
D9: Revenue Realisation | E9: 0.95 | F9: 1 | G9: 1.08 | H9: =IF($N$7="Worst",E9,IF($N$7="Base",F9,G9)) -> 1.08 | J9: Yogurt | K9: Value-added dairy | L9: 0.1
D10: Installed Capacity | H10: =IF($N$7="Worst",E10,IF($N$7="Base",F10,G10)) | J10: Thandai | K10: Value-added dairy | L10: 0.2
D11: Installed Capacity | E11: 120000 | F11: 120000 | G11: 120000 | H11: =IF($N$7="Worst",E11,IF($N$7="Base",F11,G11)) -> 120000 | J11: A2 Powder & Ghee | K11: Premium products | L11: 0.2
D12: Effective Usable Capacity | E12: 90000 | F12: 100000 | G12: 110000 | H12: =IF($N$7="Worst",E12,IF($N$7="Base",F12,G12)) -> 110000 | J12: SMP & Butter | K12: Value-added dairy | L12: 0.1
D13: Downtime % | E13: 0.12 | F13: 0.08 | G13: 0.05 | H13: =IF($N$7="Worst",E13,IF($N$7="Base",F13,G13)) -> 0.05 | J13: Curd | K13: Value-added dairy | L13: 0.2
D14: Spoilage % | E14: 0.03 | F14: 0.02 | G14: 0.01 | H14: =IF($N$7="Worst",E14,IF($N$7="Base",F14,G14)) -> 0.01 | J14: Peda | K14: Premium products | L14: 0.2
D15: Utilisation Ramp
D16: M1 | E16: 10000 | F16: 15000 | G16: 20000 | H16: =IF($N$7="Worst",E16,IF($N$7="Base",F16,G16)) -> 20000 | J16: Product | K16: Conversion Ratios | L16: Packaging Cost
D17: M3 | E17: 22000 | F17: 30000 | G17: 40000 | H17: =IF($N$7="Worst",E17,IF($N$7="Base",F17,G17)) -> 40000 | J17: Fresh Milk Category | K17: 1 | L17: 0.04
D18: M6 | E18: 40000 | F18: 50000 | G18: 65000 | H18: =IF($N$7="Worst",E18,IF($N$7="Base",F18,G18)) -> 65000 | J18: Procured Milk Category
D19: M9 | E19: 55000 | F19: 65000 | G19: 80000 | H19: =IF($N$7="Worst",E19,IF($N$7="Base",F19,G19)) -> 80000 | J19: Yogurt | K19: 0.96 | L19: 0.06
D20: M12 | E20: 65000 | F20: 80000 | G20: 95000 | H20: =IF($N$7="Worst",E20,IF($N$7="Base",F20,G20)) -> 95000 | J20: Thandai | K20: 0.9 | L20: 0.08
D21: Procured Milk | J21: SMP | K21: 0.125 | L21: 0.03
D22: Procurement Inflation | E22: 0.08 | F22: 0.06 | G22: 0.04 | H22: =IF($N$7="Worst",E22,IF($N$7="Base",F22,G22)) -> 0.04 | J22: Butter | K22: 0.06 | L22: 0.04
D23: Milk Sourcing | H23: =IF($N$7="Worst",E23,IF($N$7="Base",F23,G23)) | J23: A2 Powder | K23: 0.0825 | L23: 0.05
D24: Own Milk | H24: =IF($N$7="Worst",E25,IF($N$7="Base",F24,G24)) | J24: Ghee | K24: 0.04 | L24: 0.05
D25: Volume litre per day per cow | E25: 18 | F25: 22 | G25: 32 | H25: =IF($N$7="Worst",E25,IF($N$7="Base",F25,G25)) -> 32 | J25: Curd | K25: 0.96 | L25: 0.05
D26: Cost per litre | E26: 24 | F26: 23 | G26: 22 | H26: =IF($N$7="Worst",E26,IF($N$7="Base",F26,G26)) -> 22 | J26: Peda | K26: 0.18 | L26: 0.07
D27: Feed Cost per Cow per Month | E27: 9000 | F27: 10000 | G27: 11000 | H27: =IF($N$7="Worst",E27,IF($N$7="Base",F27,G27)) -> 11000
D28: Pricing | H28: =IF($N$7="Worst",E28,IF($N$7="Base",F28,G28))
D29: MRP per litre | E29: 60 | F29: 63 | G29: 65 | H29: =IF($N$7="Worst",E29,IF($N$7="Base",F29,G29)) -> 65
D30: Distributor Margin | E30: 0.06 | F30: 0.08 | G30: 0.1 | H30: =IF($N$7="Worst",E30,IF($N$7="Base",F30,G30)) -> 0.1
D31: Retail Margin | E31: 0.12 | F31: 0.16 | G31: 0.2 | H31: =IF($N$7="Worst",E31,IF($N$7="Base",F31,G31)) -> 0.2
D32: Sales Returns / Wastage | E32: 0.02 | F32: 0.015 | G32: 0.01 | H32: =IF($N$7="Worst",E32,IF($N$7="Base",F32,G32)) -> 0.01
D33: Freight & Distribution of Revenue | E33: 0.03 | F33: 0.04 | G33: 0.07 | H33: =IF($N$7="Worst",E33,IF($N$7="Base",F33,G33)) -> 0.07
D34: Processing Cost | E34: 4 | F34: 3 | G34: 2.5 | H34: =IF($N$7="Worst",E34,IF($N$7="Base",F34,G34)) -> 2.5
D35: Cost Inflation
D36: Milk Procurement | E36: 0.08 | F36: 0.06 | G36: 0.04 | H36: =IF($N$7="Worst",E36,IF($N$7="Base",F36,G36)) -> 0.04
D37: Packaging | E37: 0.07 | F37: 0.05 | G37: 0.03 | H37: =IF($N$7="Worst",E37,IF($N$7="Base",F37,G37)) -> 0.03
D38: Feed | E38: 0.1 | F38: 0.08 | G38: 0.06 | H38: =IF($N$7="Worst",E38,IF($N$7="Base",F38,G38)) -> 0.06
D39: Salaries | E39: 0.12 | F39: 0.1 | G39: 0.08 | H39: =IF($N$7="Worst",E39,IF($N$7="Base",F39,G39)) -> 0.08
D40: Freight | E40: 0.09 | F40: 0.07 | G40: 0.05 | H40: =IF($N$7="Worst",E40,IF($N$7="Base",F40,G40)) -> 0.05
D41: Distribution | E41: Y1 | F41: Y2 | G41: Y3
D42: Distributors | E42: 15 | F42: 40 | G42: 75 | H42: =IF($N$7="Worst",E42,IF($N$7="Base",F42,G42)) -> 75
D43: Retail Outlets | E43: 500 | F43: 2000 | G43: 5000 | H43: =IF($N$7="Worst",E43,IF($N$7="Base",F43,G43)) -> 5000
D44: Throughput/Outlet | E44: 120000 | F44: 150000 | G44: 180000 | H44: =IF($N$7="Worst",E44,IF($N$7="Base",F44,G44)) -> 180000
D45: Working Capital
D46: Receivable Days | E46: 5 | F46: 2 | G46: 1 | H46: =IF($N$7="Worst",E46,IF($N$7="Base",F46,G46)) -> 1
D47: Inventory Days | E47: 12 | F47: 8 | G47: 5 | H47: =IF($N$7="Worst",E47,IF($N$7="Base",F47,G47)) -> 5
D48: Payable Days | E48: 7 | F48: 3 | G48: 2 | H48: =IF($N$7="Worst",E48,IF($N$7="Base",F48,G48)) -> 2
D50: Livestock Engine | G50: Procured Milk
D51: Investor-funded Livestock | E51: 500 | G51: Procurement Volume litre per month - M7 to M24 | H51: =5000 * 30 -> 150000
D52: Initial Accrual Expansion | E52: 500 | G52: Procurement Volume litre per month - M25 to M36 | H52: =H51 * 2 -> 300000
D53: Expansion timeline | E53: 24 months | G53: Procurement Volume litre per month - M37 to M60 | H53: =H52 * 3 -> 900000
D54: Total Target Livestock | E54: 1000 | G54: Cost per litre | H54: 50
D55: Annual Price Increase | G55: Miscellaneous
D56: Milk | E56: 0.03 | G56: Processing Loss | H56: 0.05
D57: Value-added dairy | E57: 0.05 | G57: Utilities | H57: 0.01
D58: Premium products | E58: 0.06 | G58: Tax | H58: 0.25
D60: Channel Mix / Year | E60: 1 | F60: 2 | G60: 3 | H60: 4 | I60: 5
D63: Distributor Retail | E63: 1 | F63: 0.95 | G63: 0.85 | H63: 0.75 | I63: 0.5
D64: D2C | E64: =100% - E63 -> 0 | F64: =100% - F63 -> 0.05 | G64: =100% - G63 -> 0.15 | H64: =100% - H63 -> 0.25 | I64: =100% - I63 -> 0.5
D66: Funding Assumptions | E66: Value | F66: Value (₹)
D69: Total funding raised | F69: 300000000
D70: Part 1 - First 2 months | E70: =F70 / $F$69 -> 0.31421333 | F70: ='FUNDING REQUIREMENT'!$E$15 -> 94264000
D71: Part 2 - Next 1 month | E71: =F71 / $F$69 -> 0.35912 | F71: ='FUNDING REQUIREMENT'!$E$25 -> 107736000
D72: Part 3 - Next 3 months | E72: =F72 / $F$69 -> 0.32666667 | F72: ='FUNDING REQUIREMENT'!$E$31 -> 98000000

Sheet FUNDING REQUIREMENT
A1: =COVER!$B$12 -> Narayan Dairy Project
A2: Funding Requirement
D4: Name | E4: Amount (₹)
D7: Part 1
D8: Land | E8: 50000000
D9: Baundary wall - 400/ Sqft* 28160 sqft | E9: 11264000
D10: Borwell & Water Testing | E10: 500000
D11: Shed Construction - 400/ Sqft* 28160 sqft | E11: 20000000
D12: Stamp Duty Advocate Fees & Pollution NOC | E12: 5000000
D13: Bank Deposit | E13: 2500000
D14: Leveling & Compressing | E14: 5000000
D15: Part 1 Total | E15: =SUM(E8:E14) -> 94264000
D16: Part 2
D17: Plant & Building (Civil Work) | E17: 28736000
D18: Machinery Advnace | E18: 30000000
D19: Cow Mat | E19: 2500000
D20: Livestock Purchase | E20: 22500000
D21: Solar System | E21: 13000000
D22: Trasportation Vechile | E22: 5000000
D23: Salary | E23: 1500000
D24: Feed | E24: 4500000
D25: Part 2 Total | E25: =SUM(E17:E24) -> 107736000
D26: Part 3
D27: Plant & Machinery Dileviring & Erection | E27: 70000000
D28: Appartment Cart | E28: 500000
D29: Livestock | E29: 22500000
D30: Trasportation Vechile | E30: 5000000
D31: Part 3 Total | E31: =SUM(E27:E30) -> 98000000
D32: Total | E32: =SUM(E15,E25,E31) -> 300000000

Sheet MILK FLOW ENGINE
A1: =COVER!$B$12 -> Narayan Dairy Project
A2: Milk Flow Engine
D4: Particulars / Month | E4: 1 | F4: =E4+1 -> 2 | G4: =F4+1 -> 3 | H4: =G4+1 -> 4 | I4: =H4+1 -> 5 | J4: =I4+1 -> 6 | K4: =J4+1 -> 7 | L4: =K4+1 -> 8 | M4: =L4+1 -> 9 | ... BL4: =BK4+1 -> 60
D7: Section A – Milk Input
D8: Own Livestock (units) | E8: =MIN(IF(E4 < 5, 0, IF(E4 = 5, 50, IF(E4 <=36, (D$8 + 50), (D$8 + 150)))), 2800) -> 0 | F8: =MIN(IF(F4 < 5, 0, IF(F4 = 5, 50, IF(F4 <=36, (E$8 + 50), (E$8 + 150)))), 2800) -> 0 | G8: =MIN(IF(G4 < 5, 0, IF(G4 = 5, 50, IF(G4 <=36, (F$8 + 50), (F$8 + 150)))), 2800) -> 0 | H8: =MIN(IF(H4 < 5, 0, IF(H4 = 5, 50, IF(H4 <=36, (G$8 + 50), (G$8 + 150)))), 2800) -> 0 | I8: =MIN(IF(I4 < 5, 0, IF(I4 = 5, 50, IF(I4 <=36, (H$8 + 50), (H$8 + 150)))), 2800) -> 50 | J8: =MIN(IF(J4 < 5, 0, IF(J4 = 5, 50, IF(J4 <=36, (I$8 + 50), (I$8 + 150)))), 2800) -> 100 | K8: =MIN(IF(K4 < 5, 0, IF(K4 = 5, 50, IF(K4 <=36, (J$8 + 50), (J$8 + 150)))), 2800) -> 150 | L8: =MIN(IF(L4 < 5, 0, IF(L4 = 5, 50, IF(L4 <=36, (K$8 + 50), (K$8 + 150)))), 2800) -> 200 | ... BL8: =MIN(IF(BL4 < 5, 0, IF(BL4 = 5, 50, IF(BL4 <=36, (BK$8 + 50), (BK$8 + 150)))), 2800) -> 2800
D9: Avg Yield per Cow per Day (litre) | E9: =ASSUMPTIONS!$H$25 -> 32 | F9: =ASSUMPTIONS!$H$25 -> 32 | G9: =ASSUMPTIONS!$H$25 -> 32 | H9: =ASSUMPTIONS!$H$25 -> 32 | I9: =ASSUMPTIONS!$H$25 -> 32 | J9: =ASSUMPTIONS!$H$25 -> 32 | K9: =ASSUMPTIONS!$H$25 -> 32 | L9: =ASSUMPTIONS!$H$25 -> 32 | ... BL9: =ASSUMPTIONS!$H$25 -> 32
D10: Own Milk Production (litre) | E10: =E8 * E9 * 30 -> 0 | F10: =F8 * F9 * 30 -> 0 | G10: =G8 * G9 * 30 -> 0 | H10: =H8 * H9 * 30 -> 0 | I10: =I8 * I9 * 30 -> 48000 | J10: =J8 * J9 * 30 -> 96000 | K10: =K8 * K9 * 30 -> 144000 | L10: =L8 * L9 * 30 -> 192000 | ... BL10: =BL8 * BL9 * 30 -> 2688000
D11: Procured Milk (litre) | E11: =IF( E$4 <= 6, 0, IF( E$4 <= 24, ASSUMPTIONS!$H$51, IF(E$4 <=36, ASSUMPTIONS!$H$52, ASSUMPTIONS!$H$53))) -> 0 | F11: =IF( F$4 <= 6, 0, IF( F$4 <= 24, ASSUMPTIONS!$H$51, IF(F$4 <=36, ASSUMPTIONS!$H$52, ASSUMPTIONS!$H$53))) -> 0 | G11: =IF( G$4 <= 6, 0, IF( G$4 <= 24, ASSUMPTIONS!$H$51, IF(G$4 <=36, ASSUMPTIONS!$H$52, ASSUMPTIONS!$H$53))) -> 0 | H11: =IF( H$4 <= 6, 0, IF( H$4 <= 24, ASSUMPTIONS!$H$51, IF(H$4 <=36, ASSUMPTIONS!$H$52, ASSUMPTIONS!$H$53))) -> 0 | I11: =IF( I$4 <= 6, 0, IF( I$4 <= 24, ASSUMPTIONS!$H$51, IF(I$4 <=36, ASSUMPTIONS!$H$52, ASSUMPTIONS!$H$53))) -> 0 | J11: =IF( J$4 <= 6, 0, IF( J$4 <= 24, ASSUMPTIONS!$H$51, IF(J$4 <=36, ASSUMPTIONS!$H$52, ASSUMPTIONS!$H$53))) -> 0 | K11: =IF( K$4 <= 6, 0, IF( K$4 <= 24, ASSUMPTIONS!$H$51, IF(K$4 <=36, ASSUMPTIONS!$H$52, ASSUMPTIONS!$H$53))) -> 150000 | L11: =IF( L$4 <= 6, 0, IF( L$4 <= 24, ASSUMPTIONS!$H$51, IF(L$4 <=36, ASSUMPTIONS!$H$52, ASSUMPTIONS!$H$53))) -> 150000 | ... BL11: =IF( BL$4 <= 6, 0, IF( BL$4 <= 24, ASSUMPTIONS!$H$51, IF(BL$4 <=36, ASSUMPTIONS!$H$52, ASSUMPTIONS!$H$53))) -> 900000
D12: Section B – Operational Losses
D13: Spoilage - Own Milk Production (litre) | E13: =E10 * ASSUMPTIONS!$H$14 -> 0 | F13: =F10 * ASSUMPTIONS!$H$14 -> 0 | G13: =G10 * ASSUMPTIONS!$H$14 -> 0 | H13: =H10 * ASSUMPTIONS!$H$14 -> 0 | I13: =I10 * ASSUMPTIONS!$H$14 -> 480 | J13: =J10 * ASSUMPTIONS!$H$14 -> 960 | K13: =K10 * ASSUMPTIONS!$H$14 -> 1440 | L13: =L10 * ASSUMPTIONS!$H$14 -> 1920 | ... BL13: =BL10 * ASSUMPTIONS!$H$14 -> 26880
D14: Total Own Milk Available (litre) | E14: =E10 - E13 -> 0 | F14: =F10 - F13 -> 0 | G14: =G10 - G13 -> 0 | H14: =H10 - H13 -> 0 | I14: =I10 - I13 -> 47520 | J14: =J10 - J13 -> 95040 | K14: =K10 - K13 -> 142560 | L14: =L10 - L13 -> 190080 | ... BL14: =BL10 - BL13 -> 2661120
D15: Processing Loss - Procured Milk (litre) | E15: =E11 * ASSUMPTIONS!$H$56 -> 0 | F15: =F11 * ASSUMPTIONS!$H$56 -> 0 | G15: =G11 * ASSUMPTIONS!$H$56 -> 0 | H15: =H11 * ASSUMPTIONS!$H$56 -> 0 | I15: =I11 * ASSUMPTIONS!$H$56 -> 0 | J15: =J11 * ASSUMPTIONS!$H$56 -> 0 | K15: =K11 * ASSUMPTIONS!$H$56 -> 7500 | L15: =L11 * ASSUMPTIONS!$H$56 -> 7500 | ... BL15: =BL11 * ASSUMPTIONS!$H$56 -> 45000
D16: Spoilage - Procured Milk (litre) | E16: =E11 * ASSUMPTIONS!$H$14 -> 0 | F16: =F11 * ASSUMPTIONS!$H$14 -> 0 | G16: =G11 * ASSUMPTIONS!$H$14 -> 0 | H16: =H11 * ASSUMPTIONS!$H$14 -> 0 | I16: =I11 * ASSUMPTIONS!$H$14 -> 0 | J16: =J11 * ASSUMPTIONS!$H$14 -> 0 | K16: =K11 * ASSUMPTIONS!$H$14 -> 1500 | L16: =L11 * ASSUMPTIONS!$H$14 -> 1500 | ... BL16: =BL11 * ASSUMPTIONS!$H$14 -> 9000
D17: Total Procured Milk Available (litre) | E17: =E11 - E15 - E16 -> 0 | F17: =F11 - F15 - F16 -> 0 | G17: =G11 - G15 - G16 -> 0 | H17: =H11 - H15 - H16 -> 0 | I17: =I11 - I15 - I16 -> 0 | J17: =J11 - J15 - J16 -> 0 | K17: =K11 - K15 - K16 -> 141000 | L17: =L11 - L15 - L16 -> 141000 | ... BL17: =BL11 - BL15 - BL16 -> 846000
D18: Section C – Product Allocation
D19: Fresh Milk | E19: =IF(E$4 <= 6, E$14, E$14) -> 0 | F19: =IF(F$4 <= 6, F$14, F$14) -> 0 | G19: =IF(G$4 <= 6, G$14, G$14) -> 0 | H19: =IF(H$4 <= 6, H$14, H$14) -> 0 | I19: =IF(I$4 <= 6, I$14, I$14) -> 47520 | J19: =IF(J$4 <= 6, J$14, J$14) -> 95040 | K19: =IF(K$4 <= 6, K$14, K$14) -> 142560 | L19: =IF(L$4 <= 6, L$14, L$14) -> 190080 | ... BL19: =IF(BL$4 <= 6, BL$14, BL$14) -> 2661120
D20: Yogurt | E20: =IF( E$4 <= 6, 0, E$17 * ASSUMPTIONS!$L$9) -> 0 | F20: =IF( F$4 <= 6, 0, F$17 * ASSUMPTIONS!$L$9) -> 0 | G20: =IF( G$4 <= 6, 0, G$17 * ASSUMPTIONS!$L$9) -> 0 | H20: =IF( H$4 <= 6, 0, H$17 * ASSUMPTIONS!$L$9) -> 0 | I20: =IF( I$4 <= 6, 0, I$17 * ASSUMPTIONS!$L$9) -> 0 | J20: =IF( J$4 <= 6, 0, J$17 * ASSUMPTIONS!$L$9) -> 0 | K20: =IF( K$4 <= 6, 0, K$17 * ASSUMPTIONS!$L$9) -> 14100 | L20: =IF( L$4 <= 6, 0, L$17 * ASSUMPTIONS!$L$9) -> 14100 | ... BL20: =IF( BL$4 <= 6, 0, BL$17 * ASSUMPTIONS!$L$9) -> 84600
D21: Thandai | E21: =IF( E$4 <= 6, 0, E$17 * ASSUMPTIONS!$L$10) -> 0 | F21: =IF( F$4 <= 6, 0, F$17 * ASSUMPTIONS!$L$10) -> 0 | G21: =IF( G$4 <= 6, 0, G$17 * ASSUMPTIONS!$L$10) -> 0 | H21: =IF( H$4 <= 6, 0, H$17 * ASSUMPTIONS!$L$10) -> 0 | I21: =IF( I$4 <= 6, 0, I$17 * ASSUMPTIONS!$L$10) -> 0 | J21: =IF( J$4 <= 6, 0, J$17 * ASSUMPTIONS!$L$10) -> 0 | K21: =IF( K$4 <= 6, 0, K$17 * ASSUMPTIONS!$L$10) -> 28200 | L21: =IF( L$4 <= 6, 0, L$17 * ASSUMPTIONS!$L$10) -> 28200 | ... BL21: =IF( BL$4 <= 6, 0, BL$17 * ASSUMPTIONS!$L$10) -> 169200
D22: SMP | E22: =IF( E$4 <= 6, 0, E$17 * ASSUMPTIONS!$L$12) -> 0 | F22: =IF( F$4 <= 6, 0, F$17 * ASSUMPTIONS!$L$12) -> 0 | G22: =IF( G$4 <= 6, 0, G$17 * ASSUMPTIONS!$L$12) -> 0 | H22: =IF( H$4 <= 6, 0, H$17 * ASSUMPTIONS!$L$12) -> 0 | I22: =IF( I$4 <= 6, 0, I$17 * ASSUMPTIONS!$L$12) -> 0 | J22: =IF( J$4 <= 6, 0, J$17 * ASSUMPTIONS!$L$12) -> 0 | K22: =IF( K$4 <= 6, 0, K$17 * ASSUMPTIONS!$L$12) -> 14100 | L22: =IF( L$4 <= 6, 0, L$17 * ASSUMPTIONS!$L$12) -> 14100 | ... BL22: =IF( BL$4 <= 6, 0, BL$17 * ASSUMPTIONS!$L$12) -> 84600
D23: Butter | E23: =IF( E$4 <= 6, 0, E$17 * ASSUMPTIONS!$L$12) -> 0 | F23: =IF( F$4 <= 6, 0, F$17 * ASSUMPTIONS!$L$12) -> 0 | G23: =IF( G$4 <= 6, 0, G$17 * ASSUMPTIONS!$L$12) -> 0 | H23: =IF( H$4 <= 6, 0, H$17 * ASSUMPTIONS!$L$12) -> 0 | I23: =IF( I$4 <= 6, 0, I$17 * ASSUMPTIONS!$L$12) -> 0 | J23: =IF( J$4 <= 6, 0, J$17 * ASSUMPTIONS!$L$12) -> 0 | K23: =IF( K$4 <= 6, 0, K$17 * ASSUMPTIONS!$L$12) -> 14100 | L23: =IF( L$4 <= 6, 0, L$17 * ASSUMPTIONS!$L$12) -> 14100 | ... BL23: =IF( BL$4 <= 6, 0, BL$17 * ASSUMPTIONS!$L$12) -> 84600
D24: A2 | E24: =IF( E$4 <= 6, 0, E$17 * ASSUMPTIONS!$L$11) -> 0 | F24: =IF( F$4 <= 6, 0, F$17 * ASSUMPTIONS!$L$11) -> 0 | G24: =IF( G$4 <= 6, 0, G$17 * ASSUMPTIONS!$L$11) -> 0 | H24: =IF( H$4 <= 6, 0, H$17 * ASSUMPTIONS!$L$11) -> 0 | I24: =IF( I$4 <= 6, 0, I$17 * ASSUMPTIONS!$L$11) -> 0 | J24: =IF( J$4 <= 6, 0, J$17 * ASSUMPTIONS!$L$11) -> 0 | K24: =IF( K$4 <= 6, 0, K$17 * ASSUMPTIONS!$L$11) -> 28200 | L24: =IF( L$4 <= 6, 0, L$17 * ASSUMPTIONS!$L$11) -> 28200 | ... BL24: =IF( BL$4 <= 6, 0, BL$17 * ASSUMPTIONS!$L$11) -> 169200
D25: Ghee | E25: =IF( E$4 <= 6, 0, E$17 * ASSUMPTIONS!$L$11) -> 0 | F25: =IF( F$4 <= 6, 0, F$17 * ASSUMPTIONS!$L$11) -> 0 | G25: =IF( G$4 <= 6, 0, G$17 * ASSUMPTIONS!$L$11) -> 0 | H25: =IF( H$4 <= 6, 0, H$17 * ASSUMPTIONS!$L$11) -> 0 | I25: =IF( I$4 <= 6, 0, I$17 * ASSUMPTIONS!$L$11) -> 0 | J25: =IF( J$4 <= 6, 0, J$17 * ASSUMPTIONS!$L$11) -> 0 | K25: =IF( K$4 <= 6, 0, K$17 * ASSUMPTIONS!$L$11) -> 28200 | L25: =IF( L$4 <= 6, 0, L$17 * ASSUMPTIONS!$L$11) -> 28200 | ... BL25: =IF( BL$4 <= 6, 0, BL$17 * ASSUMPTIONS!$L$11) -> 169200
D26: Curd | E26: =IF( E$4 <= 6, 0, E$17 * ASSUMPTIONS!$L$13) -> 0 | F26: =IF( F$4 <= 6, 0, F$17 * ASSUMPTIONS!$L$13) -> 0 | G26: =IF( G$4 <= 6, 0, G$17 * ASSUMPTIONS!$L$13) -> 0 | H26: =IF( H$4 <= 6, 0, H$17 * ASSUMPTIONS!$L$13) -> 0 | I26: =IF( I$4 <= 6, 0, I$17 * ASSUMPTIONS!$L$13) -> 0 | J26: =IF( J$4 <= 6, 0, J$17 * ASSUMPTIONS!$L$13) -> 0 | K26: =IF( K$4 <= 6, 0, K$17 * ASSUMPTIONS!$L$13) -> 28200 | L26: =IF( L$4 <= 6, 0, L$17 * ASSUMPTIONS!$L$13) -> 28200 | ... BL26: =IF( BL$4 <= 6, 0, BL$17 * ASSUMPTIONS!$L$13) -> 169200
D27: Peda | E27: =IF( E$4 <= 6, 0, E$17 * ASSUMPTIONS!$L$14) -> 0 | F27: =IF( F$4 <= 6, 0, F$17 * ASSUMPTIONS!$L$14) -> 0 | G27: =IF( G$4 <= 6, 0, G$17 * ASSUMPTIONS!$L$14) -> 0 | H27: =IF( H$4 <= 6, 0, H$17 * ASSUMPTIONS!$L$14) -> 0 | I27: =IF( I$4 <= 6, 0, I$17 * ASSUMPTIONS!$L$14) -> 0 | J27: =IF( J$4 <= 6, 0, J$17 * ASSUMPTIONS!$L$14) -> 0 | K27: =IF( K$4 <= 6, 0, K$17 * ASSUMPTIONS!$L$14) -> 28200 | L27: =IF( L$4 <= 6, 0, L$17 * ASSUMPTIONS!$L$14) -> 28200 | ... BL27: =IF( BL$4 <= 6, 0, BL$17 * ASSUMPTIONS!$L$14) -> 169200
D28: Section C – Conversion Engine
D29: Fresh Milk | E29: =E19 * ASSUMPTIONS!$K$17 -> 0 | F29: =F19 * ASSUMPTIONS!$K$17 -> 0 | G29: =G19 * ASSUMPTIONS!$K$17 -> 0 | H29: =H19 * ASSUMPTIONS!$K$17 -> 0 | I29: =I19 * ASSUMPTIONS!$K$17 -> 47520 | J29: =J19 * ASSUMPTIONS!$K$17 -> 95040 | K29: =K19 * ASSUMPTIONS!$K$17 -> 142560 | L29: =L19 * ASSUMPTIONS!$K$17 -> 190080 | ... BL29: =BL19 * ASSUMPTIONS!$K$17 -> 2661120
D30: Yogurt | E30: =E20 * ASSUMPTIONS!$K$19 -> 0 | F30: =F20 * ASSUMPTIONS!$K$19 -> 0 | G30: =G20 * ASSUMPTIONS!$K$19 -> 0 | H30: =H20 * ASSUMPTIONS!$K$19 -> 0 | I30: =I20 * ASSUMPTIONS!$K$19 -> 0 | J30: =J20 * ASSUMPTIONS!$K$19 -> 0 | K30: =K20 * ASSUMPTIONS!$K$19 -> 13536 | L30: =L20 * ASSUMPTIONS!$K$19 -> 13536 | ... BL30: =BL20 * ASSUMPTIONS!$K$19 -> 81216
D31: Thandai | E31: =E21 * ASSUMPTIONS!$K$20 -> 0 | F31: =F21 * ASSUMPTIONS!$K$20 -> 0 | G31: =G21 * ASSUMPTIONS!$K$20 -> 0 | H31: =H21 * ASSUMPTIONS!$K$20 -> 0 | I31: =I21 * ASSUMPTIONS!$K$20 -> 0 | J31: =J21 * ASSUMPTIONS!$K$20 -> 0 | K31: =K21 * ASSUMPTIONS!$K$20 -> 25380 | L31: =L21 * ASSUMPTIONS!$K$20 -> 25380 | ... BL31: =BL21 * ASSUMPTIONS!$K$20 -> 152280
D32: SMP | E32: =E22 * ASSUMPTIONS!$K$21 -> 0 | F32: =F22 * ASSUMPTIONS!$K$21 -> 0 | G32: =G22 * ASSUMPTIONS!$K$21 -> 0 | H32: =H22 * ASSUMPTIONS!$K$21 -> 0 | I32: =I22 * ASSUMPTIONS!$K$21 -> 0 | J32: =J22 * ASSUMPTIONS!$K$21 -> 0 | K32: =K22 * ASSUMPTIONS!$K$21 -> 1762.5 | L32: =L22 * ASSUMPTIONS!$K$21 -> 1762.5 | ... BL32: =BL22 * ASSUMPTIONS!$K$21 -> 10575
D33: Butter | E33: =E23 * ASSUMPTIONS!$K$22 -> 0 | F33: =F23 * ASSUMPTIONS!$K$22 -> 0 | G33: =G23 * ASSUMPTIONS!$K$22 -> 0 | H33: =H23 * ASSUMPTIONS!$K$22 -> 0 | I33: =I23 * ASSUMPTIONS!$K$22 -> 0 | J33: =J23 * ASSUMPTIONS!$K$22 -> 0 | K33: =K23 * ASSUMPTIONS!$K$22 -> 846 | L33: =L23 * ASSUMPTIONS!$K$22 -> 846 | ... BL33: =BL23 * ASSUMPTIONS!$K$22 -> 5076
D34: A2 | E34: =E24 * ASSUMPTIONS!$K$23 -> 0 | F34: =F24 * ASSUMPTIONS!$K$23 -> 0 | G34: =G24 * ASSUMPTIONS!$K$23 -> 0 | H34: =H24 * ASSUMPTIONS!$K$23 -> 0 | I34: =I24 * ASSUMPTIONS!$K$23 -> 0 | J34: =J24 * ASSUMPTIONS!$K$23 -> 0 | K34: =K24 * ASSUMPTIONS!$K$23 -> 2326.5 | L34: =L24 * ASSUMPTIONS!$K$23 -> 2326.5 | ... BL34: =BL24 * ASSUMPTIONS!$K$23 -> 13959
D35: Ghee | E35: =E25 * ASSUMPTIONS!$K$24 -> 0 | F35: =F25 * ASSUMPTIONS!$K$24 -> 0 | G35: =G25 * ASSUMPTIONS!$K$24 -> 0 | H35: =H25 * ASSUMPTIONS!$K$24 -> 0 | I35: =I25 * ASSUMPTIONS!$K$24 -> 0 | J35: =J25 * ASSUMPTIONS!$K$24 -> 0 | K35: =K25 * ASSUMPTIONS!$K$24 -> 1128 | L35: =L25 * ASSUMPTIONS!$K$24 -> 1128 | ... BL35: =BL25 * ASSUMPTIONS!$K$24 -> 6768
D36: Curd | E36: =E26 * ASSUMPTIONS!$K$25 -> 0 | F36: =F26 * ASSUMPTIONS!$K$25 -> 0 | G36: =G26 * ASSUMPTIONS!$K$25 -> 0 | H36: =H26 * ASSUMPTIONS!$K$25 -> 0 | I36: =I26 * ASSUMPTIONS!$K$25 -> 0 | J36: =J26 * ASSUMPTIONS!$K$25 -> 0 | K36: =K26 * ASSUMPTIONS!$K$25 -> 27072 | L36: =L26 * ASSUMPTIONS!$K$25 -> 27072 | ... BL36: =BL26 * ASSUMPTIONS!$K$25 -> 162432
D37: Peda | E37: =E27 * ASSUMPTIONS!$K$26 -> 0 | F37: =F27 * ASSUMPTIONS!$K$26 -> 0 | G37: =G27 * ASSUMPTIONS!$K$26 -> 0 | H37: =H27 * ASSUMPTIONS!$K$26 -> 0 | I37: =I27 * ASSUMPTIONS!$K$26 -> 0 | J37: =J27 * ASSUMPTIONS!$K$26 -> 0 | K37: =K27 * ASSUMPTIONS!$K$26 -> 5076 | L37: =L27 * ASSUMPTIONS!$K$26 -> 5076 | ... BL37: =BL27 * ASSUMPTIONS!$K$26 -> 30456

Sheet PRODUCT PRICING & REVENUE ENGIN
A1: =COVER!$B$12 -> Narayan Dairy Project
A2: Product Pricing & Revenue Engine
D4: Product | E4: Unit | F4: MRP | G4: Distributor Margin | H4: Retail Margin | I4: Wholesale Rate
D7: Section A – Product Master
D8: Fresh Milk | E8: Per Litre | F8: 65 | G8: 0.08 | H8: 0.16 | I8: =F8 * (1 - G8) * (1 - H8) -> 50.232
D9: Yogurt | E9: Per Kg | F9: 150 | G9: 0.1 | H9: 0.2 | I9: =F9 * (1 - G9) * (1 - H9) -> 108
D10: Thandai | E10: Per Litre | F10: 160 | G10: 0.1 | H10: 0.2 | I10: =F10 * (1 - G10) * (1 - H10) -> 115.2
D11: SMP | E11: Per Kg | F11: 320 | G11: 0.05 | H11: 0.1 | I11: =F11 * (1 - G11) * (1 - H11) -> 273.6
D12: Butter | E12: Per Kg | F12: 600 | G12: 0.06 | H12: 0.14 | I12: =F12 * (1 - G12) * (1 - H12) -> 485.04
D13: A2 Powder | E13: Per Kg | F13: 1200 | G13: 0.08 | H13: 0.18 | I13: =F13 * (1 - G13) * (1 - H13) -> 905.28
D14: Ghee | E14: Per Litre | F14: 900 | G14: 0.08 | H14: 0.18 | I14: =F14 * (1 - G14) * (1 - H14) -> 678.96
D15: Curd | E15: Per Kg | F15: 100 | G15: 0.08 | H15: 0.18 | I15: =F15 * (1 - G15) * (1 - H15) -> 75.44
D16: Peda | E16: Per Kg | F16: 600 | G16: 0.1 | H16: 0.2 | I16: =F16 * (1 - G16) * (1 - H16) -> 432
D18: Product / Year | E18: 1 | F18: 2 | G18: 3 | H18: 4 | I18: 5
D21: Section A – Price Escalation Factor Schedule
D22: Fresh Milk | E22: =1 -> 1 | F22: =E22 * (1 + ASSUMPTIONS!$E$56) -> 1.03 | G22: =F22 * (1 + ASSUMPTIONS!$E$56) -> 1.0609 | H22: =G22 * (1 + ASSUMPTIONS!$E$56) -> 1.092727 | I22: =H22 * (1 + ASSUMPTIONS!$E$56) -> 1.1255088
D23: Yogurt | E23: =1 -> 1 | F23: =E23 * ( 1 + ASSUMPTIONS!$E$57) -> 1.05 | G23: =F23 * ( 1 + ASSUMPTIONS!$E$57) -> 1.1025 | H23: =G23 * ( 1 + ASSUMPTIONS!$E$57) -> 1.157625 | I23: =H23 * ( 1 + ASSUMPTIONS!$E$57) -> 1.2155063
D24: Thandai | E24: =1 -> 1 | F24: =E24 * ( 1 + ASSUMPTIONS!$E$57) -> 1.05 | G24: =F24 * ( 1 + ASSUMPTIONS!$E$57) -> 1.1025 | H24: =G24 * ( 1 + ASSUMPTIONS!$E$57) -> 1.157625 | I24: =H24 * ( 1 + ASSUMPTIONS!$E$57) -> 1.2155063
D25: SMP | E25: =1 -> 1 | F25: =E25 * ( 1 + ASSUMPTIONS!$E$58) -> 1.06 | G25: =F25 * ( 1 + ASSUMPTIONS!$E$58) -> 1.1236 | H25: =G25 * ( 1 + ASSUMPTIONS!$E$58) -> 1.191016 | I25: =H25 * ( 1 + ASSUMPTIONS!$E$58) -> 1.262477
D26: Butter | E26: =1 -> 1 | F26: =E26 * ( 1 + ASSUMPTIONS!$E$57) -> 1.05 | G26: =F26 * ( 1 + ASSUMPTIONS!$E$57) -> 1.1025 | H26: =G26 * ( 1 + ASSUMPTIONS!$E$57) -> 1.157625 | I26: =H26 * ( 1 + ASSUMPTIONS!$E$57) -> 1.2155063
D27: A2 Powder | E27: =1 -> 1 | F27: =E27 * ( 1 + ASSUMPTIONS!$E$58) -> 1.06 | G27: =F27 * ( 1 + ASSUMPTIONS!$E$58) -> 1.1236 | H27: =G27 * ( 1 + ASSUMPTIONS!$E$58) -> 1.191016 | I27: =H27 * ( 1 + ASSUMPTIONS!$E$58) -> 1.262477
D28: Ghee | E28: =1 -> 1 | F28: =E28 * ( 1 + ASSUMPTIONS!$E$57) -> 1.05 | G28: =F28 * ( 1 + ASSUMPTIONS!$E$57) -> 1.1025 | H28: =G28 * ( 1 + ASSUMPTIONS!$E$57) -> 1.157625 | I28: =H28 * ( 1 + ASSUMPTIONS!$E$57) -> 1.2155063
D29: Curd | E29: =1 -> 1 | F29: =E29 * ( 1 + ASSUMPTIONS!$E$57) -> 1.05 | G29: =F29 * ( 1 + ASSUMPTIONS!$E$57) -> 1.1025 | H29: =G29 * ( 1 + ASSUMPTIONS!$E$57) -> 1.157625 | I29: =H29 * ( 1 + ASSUMPTIONS!$E$57) -> 1.2155063
D30: Peda | E30: =1 -> 1 | F30: =E30 * ( 1 + ASSUMPTIONS!$E$58) -> 1.06 | G30: =F30 * ( 1 + ASSUMPTIONS!$E$58) -> 1.1236 | H30: =G30 * ( 1 + ASSUMPTIONS!$E$58) -> 1.191016 | I30: =H30 * ( 1 + ASSUMPTIONS!$E$58) -> 1.262477
D33: Product / Month / Year | E33: 1 | F33: =E33+1 -> 2 | G33: =F33+1 -> 3 | H33: =G33+1 -> 4 | I33: =H33+1 -> 5 | J33: =I33+1 -> 6 | K33: =J33+1 -> 7 | L33: =K33+1 -> 8 | M33: =L33+1 -> 9 | ... BL33: =BK33+1 -> 60
E36: =INT((E33-1)/12)+1 -> 1 | F36: =INT((F33-1)/12)+1 -> 1 | G36: =INT((G33-1)/12)+1 -> 1 | H36: =INT((H33-1)/12)+1 -> 1 | I36: =INT((I33-1)/12)+1 -> 1 | J36: =INT((J33-1)/12)+1 -> 1 | K36: =INT((K33-1)/12)+1 -> 1 | L36: =INT((L33-1)/12)+1 -> 1 | ... BL36: =INT((BL33-1)/12)+1 -> 5
D38: Section B – Sellable Quantity
D39: Fresh Milk | E39: ='MILK FLOW ENGINE'!E29 -> 0 | F39: ='MILK FLOW ENGINE'!F29 -> 0 | G39: ='MILK FLOW ENGINE'!G29 -> 0 | H39: ='MILK FLOW ENGINE'!H29 -> 0 | I39: ='MILK FLOW ENGINE'!I29 -> 47520 | J39: ='MILK FLOW ENGINE'!J29 -> 95040 | K39: ='MILK FLOW ENGINE'!K29 -> 142560 | L39: ='MILK FLOW ENGINE'!L29 -> 190080 | ... BL39: ='MILK FLOW ENGINE'!BL29 -> 2661120
D40: Yogurt | E40: ='MILK FLOW ENGINE'!E30 -> 0 | F40: ='MILK FLOW ENGINE'!F30 -> 0 | G40: ='MILK FLOW ENGINE'!G30 -> 0 | H40: ='MILK FLOW ENGINE'!H30 -> 0 | I40: ='MILK FLOW ENGINE'!I30 -> 0 | J40: ='MILK FLOW ENGINE'!J30 -> 0 | K40: ='MILK FLOW ENGINE'!K30 -> 13536 | L40: ='MILK FLOW ENGINE'!L30 -> 13536 | ... BL40: ='MILK FLOW ENGINE'!BL30 -> 81216
D41: Thandai | E41: ='MILK FLOW ENGINE'!E31 -> 0 | F41: ='MILK FLOW ENGINE'!F31 -> 0 | G41: ='MILK FLOW ENGINE'!G31 -> 0 | H41: ='MILK FLOW ENGINE'!H31 -> 0 | I41: ='MILK FLOW ENGINE'!I31 -> 0 | J41: ='MILK FLOW ENGINE'!J31 -> 0 | K41: ='MILK FLOW ENGINE'!K31 -> 25380 | L41: ='MILK FLOW ENGINE'!L31 -> 25380 | ... BL41: ='MILK FLOW ENGINE'!BL31 -> 152280
D42: SMP | E42: ='MILK FLOW ENGINE'!E32 -> 0 | F42: ='MILK FLOW ENGINE'!F32 -> 0 | G42: ='MILK FLOW ENGINE'!G32 -> 0 | H42: ='MILK FLOW ENGINE'!H32 -> 0 | I42: ='MILK FLOW ENGINE'!I32 -> 0 | J42: ='MILK FLOW ENGINE'!J32 -> 0 | K42: ='MILK FLOW ENGINE'!K32 -> 1762.5 | L42: ='MILK FLOW ENGINE'!L32 -> 1762.5 | ... BL42: ='MILK FLOW ENGINE'!BL32 -> 10575
D43: Butter | E43: ='MILK FLOW ENGINE'!E33 -> 0 | F43: ='MILK FLOW ENGINE'!F33 -> 0 | G43: ='MILK FLOW ENGINE'!G33 -> 0 | H43: ='MILK FLOW ENGINE'!H33 -> 0 | I43: ='MILK FLOW ENGINE'!I33 -> 0 | J43: ='MILK FLOW ENGINE'!J33 -> 0 | K43: ='MILK FLOW ENGINE'!K33 -> 846 | L43: ='MILK FLOW ENGINE'!L33 -> 846 | ... BL43: ='MILK FLOW ENGINE'!BL33 -> 5076
D44: A2 Powder | E44: ='MILK FLOW ENGINE'!E34 -> 0 | F44: ='MILK FLOW ENGINE'!F34 -> 0 | G44: ='MILK FLOW ENGINE'!G34 -> 0 | H44: ='MILK FLOW ENGINE'!H34 -> 0 | I44: ='MILK FLOW ENGINE'!I34 -> 0 | J44: ='MILK FLOW ENGINE'!J34 -> 0 | K44: ='MILK FLOW ENGINE'!K34 -> 2326.5 | L44: ='MILK FLOW ENGINE'!L34 -> 2326.5 | ... BL44: ='MILK FLOW ENGINE'!BL34 -> 13959
D45: Ghee | E45: ='MILK FLOW ENGINE'!E35 -> 0 | F45: ='MILK FLOW ENGINE'!F35 -> 0 | G45: ='MILK FLOW ENGINE'!G35 -> 0 | H45: ='MILK FLOW ENGINE'!H35 -> 0 | I45: ='MILK FLOW ENGINE'!I35 -> 0 | J45: ='MILK FLOW ENGINE'!J35 -> 0 | K45: ='MILK FLOW ENGINE'!K35 -> 1128 | L45: ='MILK FLOW ENGINE'!L35 -> 1128 | ... BL45: ='MILK FLOW ENGINE'!BL35 -> 6768
D46: Curd | E46: ='MILK FLOW ENGINE'!E36 -> 0 | F46: ='MILK FLOW ENGINE'!F36 -> 0 | G46: ='MILK FLOW ENGINE'!G36 -> 0 | H46: ='MILK FLOW ENGINE'!H36 -> 0 | I46: ='MILK FLOW ENGINE'!I36 -> 0 | J46: ='MILK FLOW ENGINE'!J36 -> 0 | K46: ='MILK FLOW ENGINE'!K36 -> 27072 | L46: ='MILK FLOW ENGINE'!L36 -> 27072 | ... BL46: ='MILK FLOW ENGINE'!BL36 -> 162432
D47: Peda | E47: ='MILK FLOW ENGINE'!E37 -> 0 | F47: ='MILK FLOW ENGINE'!F37 -> 0 | G47: ='MILK FLOW ENGINE'!G37 -> 0 | H47: ='MILK FLOW ENGINE'!H37 -> 0 | I47: ='MILK FLOW ENGINE'!I37 -> 0 | J47: ='MILK FLOW ENGINE'!J37 -> 0 | K47: ='MILK FLOW ENGINE'!K37 -> 5076 | L47: ='MILK FLOW ENGINE'!L37 -> 5076 | ... BL47: ='MILK FLOW ENGINE'!BL37 -> 30456
D48: Section C – Revenue
D49: Fresh Milk | E49: {=IFS(AND(E$36 = $E$18, E$36 =ASSUMPTIONS!$E$60), $E22 * E39 * ((ASSUMPTIONS!$E$63 * $I8) + (ASSUMPTIONS!$E$64 * $F8)), AND(E$36 = $F$18, E$36 =ASSUMPTIONS!$F$60), $F22 * E39 * ((ASSUMPTIONS!$F$63 * $I8) + (ASSUMPTIONS!$F$64 * $F8)), AND(E$36 = $G$18, E$36 =ASSUMPTIONS!$G$60), $G22 * E39 * ((ASSUMPTIONS!$G$63 * $I8) + (ASSUMPTIONS!$G$64 * $F8)), AND(E$36 = $H$18, E$36 =ASSUMPTIONS!$H$60), $H22 * E39 * ((ASSUMPTIONS!$H$63 * $I8) + (ASSUMPTIONS!$H$64 * $F8)), TRUE, $I22 *E39 * ((ASSUMPTIONS!$I$63 * $I8) + (ASSUMPTIONS!$I$64 * $F8)) )} -> 0 | F49: {=IFS(AND(F$36 = $E$18, F$36 =ASSUMPTIONS!$E$60), $E22 * F39 * ((ASSUMPTIONS!$E$63 * $I8) + (ASSUMPTIONS!$E$64 * $F8)), AND(F$36 = $F$18, F$36 =ASSUMPTIONS!$F$60), $F22 * F39 * ((ASSUMPTIONS!$F$63 * $I8) + (ASSUMPTIONS!$F$64 * $F8)), AND(F$36 = $G$18, F$36 =ASSUMPTIONS!$G$60), $G22 * F39 * ((ASSUMPTIONS!$G$63 * $I8) + (ASSUMPTIONS!$G$64 * $F8)), AND(F$36 = $H$18, F$36 =ASSUMPTIONS!$H$60), $H22 * F39 * ((ASSUMPTIONS!$H$63 * $I8) + (ASSUMPTIONS!$H$64 * $F8)), TRUE, $I22 *F39 * ((ASSUMPTIONS!$I$63 * $I8) + (ASSUMPTIONS!$I$64 * $F8)) )} -> 0 | G49: {=IFS(AND(G$36 = $E$18, G$36 =ASSUMPTIONS!$E$60), $E22 * G39 * ((ASSUMPTIONS!$E$63 * $I8) + (ASSUMPTIONS!$E$64 * $F8)), AND(G$36 = $F$18, G$36 =ASSUMPTIONS!$F$60), $F22 * G39 * ((ASSUMPTIONS!$F$63 * $I8) + (ASSUMPTIONS!$F$64 * $F8)), AND(G$36 = $G$18, G$36 =ASSUMPTIONS!$G$60), $G22 * G39 * ((ASSUMPTIONS!$G$63 * $I8) + (ASSUMPTIONS!$G$64 * $F8)), AND(G$36 = $H$18, G$36 =ASSUMPTIONS!$H$60), $H22 * G39 * ((ASSUMPTIONS!$H$63 * $I8) + (ASSUMPTIONS!$H$64 * $F8)), TRUE, $I22 *G39 * ((ASSUMPTIONS!$I$63 * $I8) + (ASSUMPTIONS!$I$64 * $F8)) )} -> 0 | H49: {=IFS(AND(H$36 = $E$18, H$36 =ASSUMPTIONS!$E$60), $E22 * H39 * ((ASSUMPTIONS!$E$63 * $I8) + (ASSUMPTIONS!$E$64 * $F8)), AND(H$36 = $F$18, H$36 =ASSUMPTIONS!$F$60), $F22 * H39 * ((ASSUMPTIONS!$F$63 * $I8) + (ASSUMPTIONS!$F$64 * $F8)), AND(H$36 = $G$18, H$36 =ASSUMPTIONS!$G$60), $G22 * H39 * ((ASSUMPTIONS!$G$63 * $I8) + (ASSUMPTIONS!$G$64 * $F8)), AND(H$36 = $H$18, H$36 =ASSUMPTIONS!$H$60), $H22 * H39 * ((ASSUMPTIONS!$H$63 * $I8) + (ASSUMPTIONS!$H$64 * $F8)), TRUE, $I22 *H39 * ((ASSUMPTIONS!$I$63 * $I8) + (ASSUMPTIONS!$I$64 * $F8)) )} -> 0 | I49: {=IFS(AND(I$36 = $E$18, I$36 =ASSUMPTIONS!$E$60), $E22 * I39 * ((ASSUMPTIONS!$E$63 * $I8) + (ASSUMPTIONS!$E$64 * $F8)), AND(I$36 = $F$18, I$36 =ASSUMPTIONS!$F$60), $F22 * I39 * ((ASSUMPTIONS!$F$63 * $I8) + (ASSUMPTIONS!$F$64 * $F8)), AND(I$36 = $G$18, I$36 =ASSUMPTIONS!$G$60), $G22 * I39 * ((ASSUMPTIONS!$G$63 * $I8) + (ASSUMPTIONS!$G$64 * $F8)), AND(I$36 = $H$18, I$36 =ASSUMPTIONS!$H$60), $H22 * I39 * ((ASSUMPTIONS!$H$63 * $I8) + (ASSUMPTIONS!$H$64 * $F8)), TRUE, $I22 *I39 * ((ASSUMPTIONS!$I$63 * $I8) + (ASSUMPTIONS!$I$64 * $F8)) )} -> 2387024.6 | J49: {=IFS(AND(J$36 = $E$18, J$36 =ASSUMPTIONS!$E$60), $E22 * J39 * ((ASSUMPTIONS!$E$63 * $I8) + (ASSUMPTIONS!$E$64 * $F8)), AND(J$36 = $F$18, J$36 =ASSUMPTIONS!$F$60), $F22 * J39 * ((ASSUMPTIONS!$F$63 * $I8) + (ASSUMPTIONS!$F$64 * $F8)), AND(J$36 = $G$18, J$36 =ASSUMPTIONS!$G$60), $G22 * J39 * ((ASSUMPTIONS!$G$63 * $I8) + (ASSUMPTIONS!$G$64 * $F8)), AND(J$36 = $H$18, J$36 =ASSUMPTIONS!$H$60), $H22 * J39 * ((ASSUMPTIONS!$H$63 * $I8) + (ASSUMPTIONS!$H$64 * $F8)), TRUE, $I22 *J39 * ((ASSUMPTIONS!$I$63 * $I8) + (ASSUMPTIONS!$I$64 * $F8)) )} -> 4774049.3 | K49: {=IFS(AND(K$36 = $E$18, K$36 =ASSUMPTIONS!$E$60), $E22 * K39 * ((ASSUMPTIONS!$E$63 * $I8) + (ASSUMPTIONS!$E$64 * $F8)), AND(K$36 = $F$18, K$36 =ASSUMPTIONS!$F$60), $F22 * K39 * ((ASSUMPTIONS!$F$63 * $I8) + (ASSUMPTIONS!$F$64 * $F8)), AND(K$36 = $G$18, K$36 =ASSUMPTIONS!$G$60), $G22 * K39 * ((ASSUMPTIONS!$G$63 * $I8) + (ASSUMPTIONS!$G$64 * $F8)), AND(K$36 = $H$18, K$36 =ASSUMPTIONS!$H$60), $H22 * K39 * ((ASSUMPTIONS!$H$63 * $I8) + (ASSUMPTIONS!$H$64 * $F8)), TRUE, $I22 *K39 * ((ASSUMPTIONS!$I$63 * $I8) + (ASSUMPTIONS!$I$64 * $F8)) )} -> 7161073.9 | L49: {=IFS(AND(L$36 = $E$18, L$36 =ASSUMPTIONS!$E$60), $E22 * L39 * ((ASSUMPTIONS!$E$63 * $I8) + (ASSUMPTIONS!$E$64 * $F8)), AND(L$36 = $F$18, L$36 =ASSUMPTIONS!$F$60), $F22 * L39 * ((ASSUMPTIONS!$F$63 * $I8) + (ASSUMPTIONS!$F$64 * $F8)), AND(L$36 = $G$18, L$36 =ASSUMPTIONS!$G$60), $G22 * L39 * ((ASSUMPTIONS!$G$63 * $I8) + (ASSUMPTIONS!$G$64 * $F8)), AND(L$36 = $H$18, L$36 =ASSUMPTIONS!$H$60), $H22 * L39 * ((ASSUMPTIONS!$H$63 * $I8) + (ASSUMPTIONS!$H$64 * $F8)), TRUE, $I22 *L39 * ((ASSUMPTIONS!$I$63 * $I8) + (ASSUMPTIONS!$I$64 * $F8)) )} -> 9548098.6 | ... BL49: {=IFS(AND(BL$36 = $E$18, BL$36 =ASSUMPTIONS!$E$60), $E22 * BL39 * ((ASSUMPTIONS!$E$63 * $I8) + (ASSUMPTIONS!$E$64 * $F8)), AND(BL$36 = $F$18, BL$36 =ASSUMPTIONS!$F$60), $F22 * BL39 * ((ASSUMPTIONS!$F$63 * $I8) + (ASSUMPTIONS!$F$64 * $F8)), AND(BL$36 = $G$18, BL$36 =ASSUMPTIONS!$G$60), $G22 * BL39 * ((ASSUMPTIONS!$G$63 * $I8) + (ASSUMPTIONS!$G$64 * $F8)), AND(BL$36 = $H$18, BL$36 =ASSUMPTIONS!$H$60), $H22 * BL39 * ((ASSUMPTIONS!$H$63 * $I8) + (ASSUMPTIONS!$H$64 * $F8)), TRUE, $I22 *BL39 * ((ASSUMPTIONS!$I$63 * $I8) + (ASSUMPTIONS!$I$64 * $F8)) )} -> 1.7256649e+08
D50: Yogurt | E50: {=IFS(AND(E$36 = $E$18, E$36 =ASSUMPTIONS!$E$60), $E23 * E40 * ((ASSUMPTIONS!$E$63 * $I9) + (ASSUMPTIONS!$E$64 * $F9)), AND(E$36 = $F$18, E$36 =ASSUMPTIONS!$F$60), $F23 * E40 * ((ASSUMPTIONS!$F$63 * $I9) + (ASSUMPTIONS!$F$64 * $F9)), AND(E$36 = $G$18, E$36 =ASSUMPTIONS!$G$60), $G23 * E40 * ((ASSUMPTIONS!$G$63 * $I9) + (ASSUMPTIONS!$G$64 * $F9)), AND(E$36 = $H$18, E$36 =ASSUMPTIONS!$H$60), $H23 * E40 * ((ASSUMPTIONS!$H$63 * $I9) + (ASSUMPTIONS!$H$64 * $F9)), TRUE, $I23 *E40 * ((ASSUMPTIONS!$I$63 * $I9) + (ASSUMPTIONS!$I$64 * $F9)) )} -> 0 | F50: {=IFS(AND(F$36 = $E$18, F$36 =ASSUMPTIONS!$E$60), $E23 * F40 * ((ASSUMPTIONS!$E$63 * $I9) + (ASSUMPTIONS!$E$64 * $F9)), AND(F$36 = $F$18, F$36 =ASSUMPTIONS!$F$60), $F23 * F40 * ((ASSUMPTIONS!$F$63 * $I9) + (ASSUMPTIONS!$F$64 * $F9)), AND(F$36 = $G$18, F$36 =ASSUMPTIONS!$G$60), $G23 * F40 * ((ASSUMPTIONS!$G$63 * $I9) + (ASSUMPTIONS!$G$64 * $F9)), AND(F$36 = $H$18, F$36 =ASSUMPTIONS!$H$60), $H23 * F40 * ((ASSUMPTIONS!$H$63 * $I9) + (ASSUMPTIONS!$H$64 * $F9)), TRUE, $I23 *F40 * ((ASSUMPTIONS!$I$63 * $I9) + (ASSUMPTIONS!$I$64 * $F9)) )} -> 0 | G50: {=IFS(AND(G$36 = $E$18, G$36 =ASSUMPTIONS!$E$60), $E23 * G40 * ((ASSUMPTIONS!$E$63 * $I9) + (ASSUMPTIONS!$E$64 * $F9)), AND(G$36 = $F$18, G$36 =ASSUMPTIONS!$F$60), $F23 * G40 * ((ASSUMPTIONS!$F$63 * $I9) + (ASSUMPTIONS!$F$64 * $F9)), AND(G$36 = $G$18, G$36 =ASSUMPTIONS!$G$60), $G23 * G40 * ((ASSUMPTIONS!$G$63 * $I9) + (ASSUMPTIONS!$G$64 * $F9)), AND(G$36 = $H$18, G$36 =ASSUMPTIONS!$H$60), $H23 * G40 * ((ASSUMPTIONS!$H$63 * $I9) + (ASSUMPTIONS!$H$64 * $F9)), TRUE, $I23 *G40 * ((ASSUMPTIONS!$I$63 * $I9) + (ASSUMPTIONS!$I$64 * $F9)) )} -> 0 | H50: {=IFS(AND(H$36 = $E$18, H$36 =ASSUMPTIONS!$E$60), $E23 * H40 * ((ASSUMPTIONS!$E$63 * $I9) + (ASSUMPTIONS!$E$64 * $F9)), AND(H$36 = $F$18, H$36 =ASSUMPTIONS!$F$60), $F23 * H40 * ((ASSUMPTIONS!$F$63 * $I9) + (ASSUMPTIONS!$F$64 * $F9)), AND(H$36 = $G$18, H$36 =ASSUMPTIONS!$G$60), $G23 * H40 * ((ASSUMPTIONS!$G$63 * $I9) + (ASSUMPTIONS!$G$64 * $F9)), AND(H$36 = $H$18, H$36 =ASSUMPTIONS!$H$60), $H23 * H40 * ((ASSUMPTIONS!$H$63 * $I9) + (ASSUMPTIONS!$H$64 * $F9)), TRUE, $I23 *H40 * ((ASSUMPTIONS!$I$63 * $I9) + (ASSUMPTIONS!$I$64 * $F9)) )} -> 0 | I50: {=IFS(AND(I$36 = $E$18, I$36 =ASSUMPTIONS!$E$60), $E23 * I40 * ((ASSUMPTIONS!$E$63 * $I9) + (ASSUMPTIONS!$E$64 * $F9)), AND(I$36 = $F$18, I$36 =ASSUMPTIONS!$F$60), $F23 * I40 * ((ASSUMPTIONS!$F$63 * $I9) + (ASSUMPTIONS!$F$64 * $F9)), AND(I$36 = $G$18, I$36 =ASSUMPTIONS!$G$60), $G23 * I40 * ((ASSUMPTIONS!$G$63 * $I9) + (ASSUMPTIONS!$G$64 * $F9)), AND(I$36 = $H$18, I$36 =ASSUMPTIONS!$H$60), $H23 * I40 * ((ASSUMPTIONS!$H$63 * $I9) + (ASSUMPTIONS!$H$64 * $F9)), TRUE, $I23 *I40 * ((ASSUMPTIONS!$I$63 * $I9) + (ASSUMPTIONS!$I$64 * $F9)) )} -> 0 | J50: {=IFS(AND(J$36 = $E$18, J$36 =ASSUMPTIONS!$E$60), $E23 * J40 * ((ASSUMPTIONS!$E$63 * $I9) + (ASSUMPTIONS!$E$64 * $F9)), AND(J$36 = $F$18, J$36 =ASSUMPTIONS!$F$60), $F23 * J40 * ((ASSUMPTIONS!$F$63 * $I9) + (ASSUMPTIONS!$F$64 * $F9)), AND(J$36 = $G$18, J$36 =ASSUMPTIONS!$G$60), $G23 * J40 * ((ASSUMPTIONS!$G$63 * $I9) + (ASSUMPTIONS!$G$64 * $F9)), AND(J$36 = $H$18, J$36 =ASSUMPTIONS!$H$60), $H23 * J40 * ((ASSUMPTIONS!$H$63 * $I9) + (ASSUMPTIONS!$H$64 * $F9)), TRUE, $I23 *J40 * ((ASSUMPTIONS!$I$63 * $I9) + (ASSUMPTIONS!$I$64 * $F9)) )} -> 0 | K50: {=IFS(AND(K$36 = $E$18, K$36 =ASSUMPTIONS!$E$60), $E23 * K40 * ((ASSUMPTIONS!$E$63 * $I9) + (ASSUMPTIONS!$E$64 * $F9)), AND(K$36 = $F$18, K$36 =ASSUMPTIONS!$F$60), $F23 * K40 * ((ASSUMPTIONS!$F$63 * $I9) + (ASSUMPTIONS!$F$64 * $F9)), AND(K$36 = $G$18, K$36 =ASSUMPTIONS!$G$60), $G23 * K40 * ((ASSUMPTIONS!$G$63 * $I9) + (ASSUMPTIONS!$G$64 * $F9)), AND(K$36 = $H$18, K$36 =ASSUMPTIONS!$H$60), $H23 * K40 * ((ASSUMPTIONS!$H$63 * $I9) + (ASSUMPTIONS!$H$64 * $F9)), TRUE, $I23 *K40 * ((ASSUMPTIONS!$I$63 * $I9) + (ASSUMPTIONS!$I$64 * $F9)) )} -> 1461888 | L50: {=IFS(AND(L$36 = $E$18, L$36 =ASSUMPTIONS!$E$60), $E23 * L40 * ((ASSUMPTIONS!$E$63 * $I9) + (ASSUMPTIONS!$E$64 * $F9)), AND(L$36 = $F$18, L$36 =ASSUMPTIONS!$F$60), $F23 * L40 * ((ASSUMPTIONS!$F$63 * $I9) + (ASSUMPTIONS!$F$64 * $F9)), AND(L$36 = $G$18, L$36 =ASSUMPTIONS!$G$60), $G23 * L40 * ((ASSUMPTIONS!$G$63 * $I9) + (ASSUMPTIONS!$G$64 * $F9)), AND(L$36 = $H$18, L$36 =ASSUMPTIONS!$H$60), $H23 * L40 * ((ASSUMPTIONS!$H$63 * $I9) + (ASSUMPTIONS!$H$64 * $F9)), TRUE, $I23 *L40 * ((ASSUMPTIONS!$I$63 * $I9) + (ASSUMPTIONS!$I$64 * $F9)) )} -> 1461888 | ... BL50: {=IFS(AND(BL$36 = $E$18, BL$36 =ASSUMPTIONS!$E$60), $E23 * BL40 * ((ASSUMPTIONS!$E$63 * $I9) + (ASSUMPTIONS!$E$64 * $F9)), AND(BL$36 = $F$18, BL$36 =ASSUMPTIONS!$F$60), $F23 * BL40 * ((ASSUMPTIONS!$F$63 * $I9) + (ASSUMPTIONS!$F$64 * $F9)), AND(BL$36 = $G$18, BL$36 =ASSUMPTIONS!$G$60), $G23 * BL40 * ((ASSUMPTIONS!$G$63 * $I9) + (ASSUMPTIONS!$G$64 * $F9)), AND(BL$36 = $H$18, BL$36 =ASSUMPTIONS!$H$60), $H23 * BL40 * ((ASSUMPTIONS!$H$63 * $I9) + (ASSUMPTIONS!$H$64 * $F9)), TRUE, $I23 *BL40 * ((ASSUMPTIONS!$I$63 * $I9) + (ASSUMPTIONS!$I$64 * $F9)) )} -> 12734694
D51: Thandai | E51: {=IFS(AND(E$36 = $E$18, E$36 =ASSUMPTIONS!$E$60), $E24 * E41 * ((ASSUMPTIONS!$E$63 * $I10) + (ASSUMPTIONS!$E$64 * $F10)), AND(E$36 = $F$18, E$36 =ASSUMPTIONS!$F$60), $F24 * E41 * ((ASSUMPTIONS!$F$63 * $I10) + (ASSUMPTIONS!$F$64 * $F10)), AND(E$36 = $G$18, E$36 =ASSUMPTIONS!$G$60), $G24 * E41 * ((ASSUMPTIONS!$G$63 * $I10) + (ASSUMPTIONS!$G$64 * $F10)), AND(E$36 = $H$18, E$36 =ASSUMPTIONS!$H$60), $H24 * E41 * ((ASSUMPTIONS!$H$63 * $I10) + (ASSUMPTIONS!$H$64 * $F10)), TRUE, $I24 *E41 * ((ASSUMPTIONS!$I$63 * $I10) + (ASSUMPTIONS!$I$64 * $F10)) )} -> 0 | F51: {=IFS(AND(F$36 = $E$18, F$36 =ASSUMPTIONS!$E$60), $E24 * F41 * ((ASSUMPTIONS!$E$63 * $I10) + (ASSUMPTIONS!$E$64 * $F10)), AND(F$36 = $F$18, F$36 =ASSUMPTIONS!$F$60), $F24 * F41 * ((ASSUMPTIONS!$F$63 * $I10) + (ASSUMPTIONS!$F$64 * $F10)), AND(F$36 = $G$18, F$36 =ASSUMPTIONS!$G$60), $G24 * F41 * ((ASSUMPTIONS!$G$63 * $I10) + (ASSUMPTIONS!$G$64 * $F10)), AND(F$36 = $H$18, F$36 =ASSUMPTIONS!$H$60), $H24 * F41 * ((ASSUMPTIONS!$H$63 * $I10) + (ASSUMPTIONS!$H$64 * $F10)), TRUE, $I24 *F41 * ((ASSUMPTIONS!$I$63 * $I10) + (ASSUMPTIONS!$I$64 * $F10)) )} -> 0 | G51: {=IFS(AND(G$36 = $E$18, G$36 =ASSUMPTIONS!$E$60), $E24 * G41 * ((ASSUMPTIONS!$E$63 * $I10) + (ASSUMPTIONS!$E$64 * $F10)), AND(G$36 = $F$18, G$36 =ASSUMPTIONS!$F$60), $F24 * G41 * ((ASSUMPTIONS!$F$63 * $I10) + (ASSUMPTIONS!$F$64 * $F10)), AND(G$36 = $G$18, G$36 =ASSUMPTIONS!$G$60), $G24 * G41 * ((ASSUMPTIONS!$G$63 * $I10) + (ASSUMPTIONS!$G$64 * $F10)), AND(G$36 = $H$18, G$36 =ASSUMPTIONS!$H$60), $H24 * G41 * ((ASSUMPTIONS!$H$63 * $I10) + (ASSUMPTIONS!$H$64 * $F10)), TRUE, $I24 *G41 * ((ASSUMPTIONS!$I$63 * $I10) + (ASSUMPTIONS!$I$64 * $F10)) )} -> 0 | H51: {=IFS(AND(H$36 = $E$18, H$36 =ASSUMPTIONS!$E$60), $E24 * H41 * ((ASSUMPTIONS!$E$63 * $I10) + (ASSUMPTIONS!$E$64 * $F10)), AND(H$36 = $F$18, H$36 =ASSUMPTIONS!$F$60), $F24 * H41 * ((ASSUMPTIONS!$F$63 * $I10) + (ASSUMPTIONS!$F$64 * $F10)), AND(H$36 = $G$18, H$36 =ASSUMPTIONS!$G$60), $G24 * H41 * ((ASSUMPTIONS!$G$63 * $I10) + (ASSUMPTIONS!$G$64 * $F10)), AND(H$36 = $H$18, H$36 =ASSUMPTIONS!$H$60), $H24 * H41 * ((ASSUMPTIONS!$H$63 * $I10) + (ASSUMPTIONS!$H$64 * $F10)), TRUE, $I24 *H41 * ((ASSUMPTIONS!$I$63 * $I10) + (ASSUMPTIONS!$I$64 * $F10)) )} -> 0 | I51: {=IFS(AND(I$36 = $E$18, I$36 =ASSUMPTIONS!$E$60), $E24 * I41 * ((ASSUMPTIONS!$E$63 * $I10) + (ASSUMPTIONS!$E$64 * $F10)), AND(I$36 = $F$18, I$36 =ASSUMPTIONS!$F$60), $F24 * I41 * ((ASSUMPTIONS!$F$63 * $I10) + (ASSUMPTIONS!$F$64 * $F10)), AND(I$36 = $G$18, I$36 =ASSUMPTIONS!$G$60), $G24 * I41 * ((ASSUMPTIONS!$G$63 * $I10) + (ASSUMPTIONS!$G$64 * $F10)), AND(I$36 = $H$18, I$36 =ASSUMPTIONS!$H$60), $H24 * I41 * ((ASSUMPTIONS!$H$63 * $I10) + (ASSUMPTIONS!$H$64 * $F10)), TRUE, $I24 *I41 * ((ASSUMPTIONS!$I$63 * $I10) + (ASSUMPTIONS!$I$64 * $F10)) )} -> 0 | J51: {=IFS(AND(J$36 = $E$18, J$36 =ASSUMPTIONS!$E$60), $E24 * J41 * ((ASSUMPTIONS!$E$63 * $I10) + (ASSUMPTIONS!$E$64 * $F10)), AND(J$36 = $F$18, J$36 =ASSUMPTIONS!$F$60), $F24 * J41 * ((ASSUMPTIONS!$F$63 * $I10) + (ASSUMPTIONS!$F$64 * $F10)), AND(J$36 = $G$18, J$36 =ASSUMPTIONS!$G$60), $G24 * J41 * ((ASSUMPTIONS!$G$63 * $I10) + (ASSUMPTIONS!$G$64 * $F10)), AND(J$36 = $H$18, J$36 =ASSUMPTIONS!$H$60), $H24 * J41 * ((ASSUMPTIONS!$H$63 * $I10) + (ASSUMPTIONS!$H$64 * $F10)), TRUE, $I24 *J41 * ((ASSUMPTIONS!$I$63 * $I10) + (ASSUMPTIONS!$I$64 * $F10)) )} -> 0 | K51: {=IFS(AND(K$36 = $E$18, K$36 =ASSUMPTIONS!$E$60), $E24 * K41 * ((ASSUMPTIONS!$E$63 * $I10) + (ASSUMPTIONS!$E$64 * $F10)), AND(K$36 = $F$18, K$36 =ASSUMPTIONS!$F$60), $F24 * K41 * ((ASSUMPTIONS!$F$63 * $I10) + (ASSUMPTIONS!$F$64 * $F10)), AND(K$36 = $G$18, K$36 =ASSUMPTIONS!$G$60), $G24 * K41 * ((ASSUMPTIONS!$G$63 * $I10) + (ASSUMPTIONS!$G$64 * $F10)), AND(K$36 = $H$18, K$36 =ASSUMPTIONS!$H$60), $H24 * K41 * ((ASSUMPTIONS!$H$63 * $I10) + (ASSUMPTIONS!$H$64 * $F10)), TRUE, $I24 *K41 * ((ASSUMPTIONS!$I$63 * $I10) + (ASSUMPTIONS!$I$64 * $F10)) )} -> 2923776 | L51: {=IFS(AND(L$36 = $E$18, L$36 =ASSUMPTIONS!$E$60), $E24 * L41 * ((ASSUMPTIONS!$E$63 * $I10) + (ASSUMPTIONS!$E$64 * $F10)), AND(L$36 = $F$18, L$36 =ASSUMPTIONS!$F$60), $F24 * L41 * ((ASSUMPTIONS!$F$63 * $I10) + (ASSUMPTIONS!$F$64 * $F10)), AND(L$36 = $G$18, L$36 =ASSUMPTIONS!$G$60), $G24 * L41 * ((ASSUMPTIONS!$G$63 * $I10) + (ASSUMPTIONS!$G$64 * $F10)), AND(L$36 = $H$18, L$36 =ASSUMPTIONS!$H$60), $H24 * L41 * ((ASSUMPTIONS!$H$63 * $I10) + (ASSUMPTIONS!$H$64 * $F10)), TRUE, $I24 *L41 * ((ASSUMPTIONS!$I$63 * $I10) + (ASSUMPTIONS!$I$64 * $F10)) )} -> 2923776 | ... BL51: {=IFS(AND(BL$36 = $E$18, BL$36 =ASSUMPTIONS!$E$60), $E24 * BL41 * ((ASSUMPTIONS!$E$63 * $I10) + (ASSUMPTIONS!$E$64 * $F10)), AND(BL$36 = $F$18, BL$36 =ASSUMPTIONS!$F$60), $F24 * BL41 * ((ASSUMPTIONS!$F$63 * $I10) + (ASSUMPTIONS!$F$64 * $F10)), AND(BL$36 = $G$18, BL$36 =ASSUMPTIONS!$G$60), $G24 * BL41 * ((ASSUMPTIONS!$G$63 * $I10) + (ASSUMPTIONS!$G$64 * $F10)), AND(BL$36 = $H$18, BL$36 =ASSUMPTIONS!$H$60), $H24 * BL41 * ((ASSUMPTIONS!$H$63 * $I10) + (ASSUMPTIONS!$H$64 * $F10)), TRUE, $I24 *BL41 * ((ASSUMPTIONS!$I$63 * $I10) + (ASSUMPTIONS!$I$64 * $F10)) )} -> 25469387
D52: SMP | E52: {=IFS(AND(E$36 = $E$18, E$36 =ASSUMPTIONS!$E$60), $E25 * E42 * ((ASSUMPTIONS!$E$63 * $I11) + (ASSUMPTIONS!$E$64 * $F11)), AND(E$36 = $F$18, E$36 =ASSUMPTIONS!$F$60), $F25 * E42 * ((ASSUMPTIONS!$F$63 * $I11) + (ASSUMPTIONS!$F$64 * $F11)), AND(E$36 = $G$18, E$36 =ASSUMPTIONS!$G$60), $G25 * E42 * ((ASSUMPTIONS!$G$63 * $I11) + (ASSUMPTIONS!$G$64 * $F11)), AND(E$36 = $H$18, E$36 =ASSUMPTIONS!$H$60), $H25 * E42 * ((ASSUMPTIONS!$H$63 * $I11) + (ASSUMPTIONS!$H$64 * $F11)), TRUE, $I25 *E42 * ((ASSUMPTIONS!$I$63 * $I11) + (ASSUMPTIONS!$I$64 * $F11)) )} -> 0 | F52: {=IFS(AND(F$36 = $E$18, F$36 =ASSUMPTIONS!$E$60), $E25 * F42 * ((ASSUMPTIONS!$E$63 * $I11) + (ASSUMPTIONS!$E$64 * $F11)), AND(F$36 = $F$18, F$36 =ASSUMPTIONS!$F$60), $F25 * F42 * ((ASSUMPTIONS!$F$63 * $I11) + (ASSUMPTIONS!$F$64 * $F11)), AND(F$36 = $G$18, F$36 =ASSUMPTIONS!$G$60), $G25 * F42 * ((ASSUMPTIONS!$G$63 * $I11) + (ASSUMPTIONS!$G$64 * $F11)), AND(F$36 = $H$18, F$36 =ASSUMPTIONS!$H$60), $H25 * F42 * ((ASSUMPTIONS!$H$63 * $I11) + (ASSUMPTIONS!$H$64 * $F11)), TRUE, $I25 *F42 * ((ASSUMPTIONS!$I$63 * $I11) + (ASSUMPTIONS!$I$64 * $F11)) )} -> 0 | G52: {=IFS(AND(G$36 = $E$18, G$36 =ASSUMPTIONS!$E$60), $E25 * G42 * ((ASSUMPTIONS!$E$63 * $I11) + (ASSUMPTIONS!$E$64 * $F11)), AND(G$36 = $F$18, G$36 =ASSUMPTIONS!$F$60), $F25 * G42 * ((ASSUMPTIONS!$F$63 * $I11) + (ASSUMPTIONS!$F$64 * $F11)), AND(G$36 = $G$18, G$36 =ASSUMPTIONS!$G$60), $G25 * G42 * ((ASSUMPTIONS!$G$63 * $I11) + (ASSUMPTIONS!$G$64 * $F11)), AND(G$36 = $H$18, G$36 =ASSUMPTIONS!$H$60), $H25 * G42 * ((ASSUMPTIONS!$H$63 * $I11) + (ASSUMPTIONS!$H$64 * $F11)), TRUE, $I25 *G42 * ((ASSUMPTIONS!$I$63 * $I11) + (ASSUMPTIONS!$I$64 * $F11)) )} -> 0 | H52: {=IFS(AND(H$36 = $E$18, H$36 =ASSUMPTIONS!$E$60), $E25 * H42 * ((ASSUMPTIONS!$E$63 * $I11) + (ASSUMPTIONS!$E$64 * $F11)), AND(H$36 = $F$18, H$36 =ASSUMPTIONS!$F$60), $F25 * H42 * ((ASSUMPTIONS!$F$63 * $I11) + (ASSUMPTIONS!$F$64 * $F11)), AND(H$36 = $G$18, H$36 =ASSUMPTIONS!$G$60), $G25 * H42 * ((ASSUMPTIONS!$G$63 * $I11) + (ASSUMPTIONS!$G$64 * $F11)), AND(H$36 = $H$18, H$36 =ASSUMPTIONS!$H$60), $H25 * H42 * ((ASSUMPTIONS!$H$63 * $I11) + (ASSUMPTIONS!$H$64 * $F11)), TRUE, $I25 *H42 * ((ASSUMPTIONS!$I$63 * $I11) + (ASSUMPTIONS!$I$64 * $F11)) )} -> 0 | I52: {=IFS(AND(I$36 = $E$18, I$36 =ASSUMPTIONS!$E$60), $E25 * I42 * ((ASSUMPTIONS!$E$63 * $I11) + (ASSUMPTIONS!$E$64 * $F11)), AND(I$36 = $F$18, I$36 =ASSUMPTIONS!$F$60), $F25 * I42 * ((ASSUMPTIONS!$F$63 * $I11) + (ASSUMPTIONS!$F$64 * $F11)), AND(I$36 = $G$18, I$36 =ASSUMPTIONS!$G$60), $G25 * I42 * ((ASSUMPTIONS!$G$63 * $I11) + (ASSUMPTIONS!$G$64 * $F11)), AND(I$36 = $H$18, I$36 =ASSUMPTIONS!$H$60), $H25 * I42 * ((ASSUMPTIONS!$H$63 * $I11) + (ASSUMPTIONS!$H$64 * $F11)), TRUE, $I25 *I42 * ((ASSUMPTIONS!$I$63 * $I11) + (ASSUMPTIONS!$I$64 * $F11)) )} -> 0 | J52: {=IFS(AND(J$36 = $E$18, J$36 =ASSUMPTIONS!$E$60), $E25 * J42 * ((ASSUMPTIONS!$E$63 * $I11) + (ASSUMPTIONS!$E$64 * $F11)), AND(J$36 = $F$18, J$36 =ASSUMPTIONS!$F$60), $F25 * J42 * ((ASSUMPTIONS!$F$63 * $I11) + (ASSUMPTIONS!$F$64 * $F11)), AND(J$36 = $G$18, J$36 =ASSUMPTIONS!$G$60), $G25 * J42 * ((ASSUMPTIONS!$G$63 * $I11) + (ASSUMPTIONS!$G$64 * $F11)), AND(J$36 = $H$18, J$36 =ASSUMPTIONS!$H$60), $H25 * J42 * ((ASSUMPTIONS!$H$63 * $I11) + (ASSUMPTIONS!$H$64 * $F11)), TRUE, $I25 *J42 * ((ASSUMPTIONS!$I$63 * $I11) + (ASSUMPTIONS!$I$64 * $F11)) )} -> 0 | K52: {=IFS(AND(K$36 = $E$18, K$36 =ASSUMPTIONS!$E$60), $E25 * K42 * ((ASSUMPTIONS!$E$63 * $I11) + (ASSUMPTIONS!$E$64 * $F11)), AND(K$36 = $F$18, K$36 =ASSUMPTIONS!$F$60), $F25 * K42 * ((ASSUMPTIONS!$F$63 * $I11) + (ASSUMPTIONS!$F$64 * $F11)), AND(K$36 = $G$18, K$36 =ASSUMPTIONS!$G$60), $G25 * K42 * ((ASSUMPTIONS!$G$63 * $I11) + (ASSUMPTIONS!$G$64 * $F11)), AND(K$36 = $H$18, K$36 =ASSUMPTIONS!$H$60), $H25 * K42 * ((ASSUMPTIONS!$H$63 * $I11) + (ASSUMPTIONS!$H$64 * $F11)), TRUE, $I25 *K42 * ((ASSUMPTIONS!$I$63 * $I11) + (ASSUMPTIONS!$I$64 * $F11)) )} -> 482220 | L52: {=IFS(AND(L$36 = $E$18, L$36 =ASSUMPTIONS!$E$60), $E25 * L42 * ((ASSUMPTIONS!$E$63 * $I11) + (ASSUMPTIONS!$E$64 * $F11)), AND(L$36 = $F$18, L$36 =ASSUMPTIONS!$F$60), $F25 * L42 * ((ASSUMPTIONS!$F$63 * $I11) + (ASSUMPTIONS!$F$64 * $F11)), AND(L$36 = $G$18, L$36 =ASSUMPTIONS!$G$60), $G25 * L42 * ((ASSUMPTIONS!$G$63 * $I11) + (ASSUMPTIONS!$G$64 * $F11)), AND(L$36 = $H$18, L$36 =ASSUMPTIONS!$H$60), $H25 * L42 * ((ASSUMPTIONS!$H$63 * $I11) + (ASSUMPTIONS!$H$64 * $F11)), TRUE, $I25 *L42 * ((ASSUMPTIONS!$I$63 * $I11) + (ASSUMPTIONS!$I$64 * $F11)) )} -> 482220 | ... BL52: {=IFS(AND(BL$36 = $E$18, BL$36 =ASSUMPTIONS!$E$60), $E25 * BL42 * ((ASSUMPTIONS!$E$63 * $I11) + (ASSUMPTIONS!$E$64 * $F11)), AND(BL$36 = $F$18, BL$36 =ASSUMPTIONS!$F$60), $F25 * BL42 * ((ASSUMPTIONS!$F$63 * $I11) + (ASSUMPTIONS!$F$64 * $F11)), AND(BL$36 = $G$18, BL$36 =ASSUMPTIONS!$G$60), $G25 * BL42 * ((ASSUMPTIONS!$G$63 * $I11) + (ASSUMPTIONS!$G$64 * $F11)), AND(BL$36 = $H$18, BL$36 =ASSUMPTIONS!$H$60), $H25 * BL42 * ((ASSUMPTIONS!$H$63 * $I11) + (ASSUMPTIONS!$H$64 * $F11)), TRUE, $I25 *BL42 * ((ASSUMPTIONS!$I$63 * $I11) + (ASSUMPTIONS!$I$64 * $F11)) )} -> 3962485.9
D53: Butter | E53: {=IFS(AND(E$36 = $E$18, E$36 =ASSUMPTIONS!$E$60), $E26 * E43 * ((ASSUMPTIONS!$E$63 * $I12) + (ASSUMPTIONS!$E$64 * $F12)), AND(E$36 = $F$18, E$36 =ASSUMPTIONS!$F$60), $F26 * E43 * ((ASSUMPTIONS!$F$63 * $I12) + (ASSUMPTIONS!$F$64 * $F12)), AND(E$36 = $G$18, E$36 =ASSUMPTIONS!$G$60), $G26 * E43 * ((ASSUMPTIONS!$G$63 * $I12) + (ASSUMPTIONS!$G$64 * $F12)), AND(E$36 = $H$18, E$36 =ASSUMPTIONS!$H$60), $H26 * E43 * ((ASSUMPTIONS!$H$63 * $I12) + (ASSUMPTIONS!$H$64 * $F12)), TRUE, $I26 *E43 * ((ASSUMPTIONS!$I$63 * $I12) + (ASSUMPTIONS!$I$64 * $F12)) )} -> 0 | F53: {=IFS(AND(F$36 = $E$18, F$36 =ASSUMPTIONS!$E$60), $E26 * F43 * ((ASSUMPTIONS!$E$63 * $I12) + (ASSUMPTIONS!$E$64 * $F12)), AND(F$36 = $F$18, F$36 =ASSUMPTIONS!$F$60), $F26 * F43 * ((ASSUMPTIONS!$F$63 * $I12) + (ASSUMPTIONS!$F$64 * $F12)), AND(F$36 = $G$18, F$36 =ASSUMPTIONS!$G$60), $G26 * F43 * ((ASSUMPTIONS!$G$63 * $I12) + (ASSUMPTIONS!$G$64 * $F12)), AND(F$36 = $H$18, F$36 =ASSUMPTIONS!$H$60), $H26 * F43 * ((ASSUMPTIONS!$H$63 * $I12) + (ASSUMPTIONS!$H$64 * $F12)), TRUE, $I26 *F43 * ((ASSUMPTIONS!$I$63 * $I12) + (ASSUMPTIONS!$I$64 * $F12)) )} -> 0 | G53: {=IFS(AND(G$36 = $E$18, G$36 =ASSUMPTIONS!$E$60), $E26 * G43 * ((ASSUMPTIONS!$E$63 * $I12) + (ASSUMPTIONS!$E$64 * $F12)), AND(G$36 = $F$18, G$36 =ASSUMPTIONS!$F$60), $F26 * G43 * ((ASSUMPTIONS!$F$63 * $I12) + (ASSUMPTIONS!$F$64 * $F12)), AND(G$36 = $G$18, G$36 =ASSUMPTIONS!$G$60), $G26 * G43 * ((ASSUMPTIONS!$G$63 * $I12) + (ASSUMPTIONS!$G$64 * $F12)), AND(G$36 = $H$18, G$36 =ASSUMPTIONS!$H$60), $H26 * G43 * ((ASSUMPTIONS!$H$63 * $I12) + (ASSUMPTIONS!$H$64 * $F12)), TRUE, $I26 *G43 * ((ASSUMPTIONS!$I$63 * $I12) + (ASSUMPTIONS!$I$64 * $F12)) )} -> 0 | H53: {=IFS(AND(H$36 = $E$18, H$36 =ASSUMPTIONS!$E$60), $E26 * H43 * ((ASSUMPTIONS!$E$63 * $I12) + (ASSUMPTIONS!$E$64 * $F12)), AND(H$36 = $F$18, H$36 =ASSUMPTIONS!$F$60), $F26 * H43 * ((ASSUMPTIONS!$F$63 * $I12) + (ASSUMPTIONS!$F$64 * $F12)), AND(H$36 = $G$18, H$36 =ASSUMPTIONS!$G$60), $G26 * H43 * ((ASSUMPTIONS!$G$63 * $I12) + (ASSUMPTIONS!$G$64 * $F12)), AND(H$36 = $H$18, H$36 =ASSUMPTIONS!$H$60), $H26 * H43 * ((ASSUMPTIONS!$H$63 * $I12) + (ASSUMPTIONS!$H$64 * $F12)), TRUE, $I26 *H43 * ((ASSUMPTIONS!$I$63 * $I12) + (ASSUMPTIONS!$I$64 * $F12)) )} -> 0 | I53: {=IFS(AND(I$36 = $E$18, I$36 =ASSUMPTIONS!$E$60), $E26 * I43 * ((ASSUMPTIONS!$E$63 * $I12) + (ASSUMPTIONS!$E$64 * $F12)), AND(I$36 = $F$18, I$36 =ASSUMPTIONS!$F$60), $F26 * I43 * ((ASSUMPTIONS!$F$63 * $I12) + (ASSUMPTIONS!$F$64 * $F12)), AND(I$36 = $G$18, I$36 =ASSUMPTIONS!$G$60), $G26 * I43 * ((ASSUMPTIONS!$G$63 * $I12) + (ASSUMPTIONS!$G$64 * $F12)), AND(I$36 = $H$18, I$36 =ASSUMPTIONS!$H$60), $H26 * I43 * ((ASSUMPTIONS!$H$63 * $I12) + (ASSUMPTIONS!$H$64 * $F12)), TRUE, $I26 *I43 * ((ASSUMPTIONS!$I$63 * $I12) + (ASSUMPTIONS!$I$64 * $F12)) )} -> 0 | J53: {=IFS(AND(J$36 = $E$18, J$36 =ASSUMPTIONS!$E$60), $E26 * J43 * ((ASSUMPTIONS!$E$63 * $I12) + (ASSUMPTIONS!$E$64 * $F12)), AND(J$36 = $F$18, J$36 =ASSUMPTIONS!$F$60), $F26 * J43 * ((ASSUMPTIONS!$F$63 * $I12) + (ASSUMPTIONS!$F$64 * $F12)), AND(J$36 = $G$18, J$36 =ASSUMPTIONS!$G$60), $G26 * J43 * ((ASSUMPTIONS!$G$63 * $I12) + (ASSUMPTIONS!$G$64 * $F12)), AND(J$36 = $H$18, J$36 =ASSUMPTIONS!$H$60), $H26 * J43 * ((ASSUMPTIONS!$H$63 * $I12) + (ASSUMPTIONS!$H$64 * $F12)), TRUE, $I26 *J43 * ((ASSUMPTIONS!$I$63 * $I12) + (ASSUMPTIONS!$I$64 * $F12)) )} -> 0 | K53: {=IFS(AND(K$36 = $E$18, K$36 =ASSUMPTIONS!$E$60), $E26 * K43 * ((ASSUMPTIONS!$E$63 * $I12) + (ASSUMPTIONS!$E$64 * $F12)), AND(K$36 = $F$18, K$36 =ASSUMPTIONS!$F$60), $F26 * K43 * ((ASSUMPTIONS!$F$63 * $I12) + (ASSUMPTIONS!$F$64 * $F12)), AND(K$36 = $G$18, K$36 =ASSUMPTIONS!$G$60), $G26 * K43 * ((ASSUMPTIONS!$G$63 * $I12) + (ASSUMPTIONS!$G$64 * $F12)), AND(K$36 = $H$18, K$36 =ASSUMPTIONS!$H$60), $H26 * K43 * ((ASSUMPTIONS!$H$63 * $I12) + (ASSUMPTIONS!$H$64 * $F12)), TRUE, $I26 *K43 * ((ASSUMPTIONS!$I$63 * $I12) + (ASSUMPTIONS!$I$64 * $F12)) )} -> 410343.84 | L53: {=IFS(AND(L$36 = $E$18, L$36 =ASSUMPTIONS!$E$60), $E26 * L43 * ((ASSUMPTIONS!$E$63 * $I12) + (ASSUMPTIONS!$E$64 * $F12)), AND(L$36 = $F$18, L$36 =ASSUMPTIONS!$F$60), $F26 * L43 * ((ASSUMPTIONS!$F$63 * $I12) + (ASSUMPTIONS!$F$64 * $F12)), AND(L$36 = $G$18, L$36 =ASSUMPTIONS!$G$60), $G26 * L43 * ((ASSUMPTIONS!$G$63 * $I12) + (ASSUMPTIONS!$G$64 * $F12)), AND(L$36 = $H$18, L$36 =ASSUMPTIONS!$H$60), $H26 * L43 * ((ASSUMPTIONS!$H$63 * $I12) + (ASSUMPTIONS!$H$64 * $F12)), TRUE, $I26 *L43 * ((ASSUMPTIONS!$I$63 * $I12) + (ASSUMPTIONS!$I$64 * $F12)) )} -> 410343.84 | ... BL53: {=IFS(AND(BL$36 = $E$18, BL$36 =ASSUMPTIONS!$E$60), $E26 * BL43 * ((ASSUMPTIONS!$E$63 * $I12) + (ASSUMPTIONS!$E$64 * $F12)), AND(BL$36 = $F$18, BL$36 =ASSUMPTIONS!$F$60), $F26 * BL43 * ((ASSUMPTIONS!$F$63 * $I12) + (ASSUMPTIONS!$F$64 * $F12)), AND(BL$36 = $G$18, BL$36 =ASSUMPTIONS!$G$60), $G26 * BL43 * ((ASSUMPTIONS!$G$63 * $I12) + (ASSUMPTIONS!$G$64 * $F12)), AND(BL$36 = $H$18, BL$36 =ASSUMPTIONS!$H$60), $H26 * BL43 * ((ASSUMPTIONS!$H$63 * $I12) + (ASSUMPTIONS!$H$64 * $F12)), TRUE, $I26 *BL43 * ((ASSUMPTIONS!$I$63 * $I12) + (ASSUMPTIONS!$I$64 * $F12)) )} -> 3347299.4
D54: A2 Powder | E54: {=IFS(AND(E$36 = $E$18, E$36 =ASSUMPTIONS!$E$60), $E27 * E44 * ((ASSUMPTIONS!$E$63 * $I13) + (ASSUMPTIONS!$E$64 * $F13)), AND(E$36 = $F$18, E$36 =ASSUMPTIONS!$F$60), $F27 * E44 * ((ASSUMPTIONS!$F$63 * $I13) + (ASSUMPTIONS!$F$64 * $F13)), AND(E$36 = $G$18, E$36 =ASSUMPTIONS!$G$60), $G27 * E44 * ((ASSUMPTIONS!$G$63 * $I13) + (ASSUMPTIONS!$G$64 * $F13)), AND(E$36 = $H$18, E$36 =ASSUMPTIONS!$H$60), $H27 * E44 * ((ASSUMPTIONS!$H$63 * $I13) + (ASSUMPTIONS!$H$64 * $F13)), TRUE, $I27 *E44 * ((ASSUMPTIONS!$I$63 * $I13) + (ASSUMPTIONS!$I$64 * $F13)) )} -> 0 | F54: {=IFS(AND(F$36 = $E$18, F$36 =ASSUMPTIONS!$E$60), $E27 * F44 * ((ASSUMPTIONS!$E$63 * $I13) + (ASSUMPTIONS!$E$64 * $F13)), AND(F$36 = $F$18, F$36 =ASSUMPTIONS!$F$60), $F27 * F44 * ((ASSUMPTIONS!$F$63 * $I13) + (ASSUMPTIONS!$F$64 * $F13)), AND(F$36 = $G$18, F$36 =ASSUMPTIONS!$G$60), $G27 * F44 * ((ASSUMPTIONS!$G$63 * $I13) + (ASSUMPTIONS!$G$64 * $F13)), AND(F$36 = $H$18, F$36 =ASSUMPTIONS!$H$60), $H27 * F44 * ((ASSUMPTIONS!$H$63 * $I13) + (ASSUMPTIONS!$H$64 * $F13)), TRUE, $I27 *F44 * ((ASSUMPTIONS!$I$63 * $I13) + (ASSUMPTIONS!$I$64 * $F13)) )} -> 0 | G54: {=IFS(AND(G$36 = $E$18, G$36 =ASSUMPTIONS!$E$60), $E27 * G44 * ((ASSUMPTIONS!$E$63 * $I13) + (ASSUMPTIONS!$E$64 * $F13)), AND(G$36 = $F$18, G$36 =ASSUMPTIONS!$F$60), $F27 * G44 * ((ASSUMPTIONS!$F$63 * $I13) + (ASSUMPTIONS!$F$64 * $F13)), AND(G$36 = $G$18, G$36 =ASSUMPTIONS!$G$60), $G27 * G44 * ((ASSUMPTIONS!$G$63 * $I13) + (ASSUMPTIONS!$G$64 * $F13)), AND(G$36 = $H$18, G$36 =ASSUMPTIONS!$H$60), $H27 * G44 * ((ASSUMPTIONS!$H$63 * $I13) + (ASSUMPTIONS!$H$64 * $F13)), TRUE, $I27 *G44 * ((ASSUMPTIONS!$I$63 * $I13) + (ASSUMPTIONS!$I$64 * $F13)) )} -> 0 | H54: {=IFS(AND(H$36 = $E$18, H$36 =ASSUMPTIONS!$E$60), $E27 * H44 * ((ASSUMPTIONS!$E$63 * $I13) + (ASSUMPTIONS!$E$64 * $F13)), AND(H$36 = $F$18, H$36 =ASSUMPTIONS!$F$60), $F27 * H44 * ((ASSUMPTIONS!$F$63 * $I13) + (ASSUMPTIONS!$F$64 * $F13)), AND(H$36 = $G$18, H$36 =ASSUMPTIONS!$G$60), $G27 * H44 * ((ASSUMPTIONS!$G$63 * $I13) + (ASSUMPTIONS!$G$64 * $F13)), AND(H$36 = $H$18, H$36 =ASSUMPTIONS!$H$60), $H27 * H44 * ((ASSUMPTIONS!$H$63 * $I13) + (ASSUMPTIONS!$H$64 * $F13)), TRUE, $I27 *H44 * ((ASSUMPTIONS!$I$63 * $I13) + (ASSUMPTIONS!$I$64 * $F13)) )} -> 0 | I54: {=IFS(AND(I$36 = $E$18, I$36 =ASSUMPTIONS!$E$60), $E27 * I44 * ((ASSUMPTIONS!$E$63 * $I13) + (ASSUMPTIONS!$E$64 * $F13)), AND(I$36 = $F$18, I$36 =ASSUMPTIONS!$F$60), $F27 * I44 * ((ASSUMPTIONS!$F$63 * $I13) + (ASSUMPTIONS!$F$64 * $F13)), AND(I$36 = $G$18, I$36 =ASSUMPTIONS!$G$60), $G27 * I44 * ((ASSUMPTIONS!$G$63 * $I13) + (ASSUMPTIONS!$G$64 * $F13)), AND(I$36 = $H$18, I$36 =ASSUMPTIONS!$H$60), $H27 * I44 * ((ASSUMPTIONS!$H$63 * $I13) + (ASSUMPTIONS!$H$64 * $F13)), TRUE, $I27 *I44 * ((ASSUMPTIONS!$I$63 * $I13) + (ASSUMPTIONS!$I$64 * $F13)) )} -> 0 | J54: {=IFS(AND(J$36 = $E$18, J$36 =ASSUMPTIONS!$E$60), $E27 * J44 * ((ASSUMPTIONS!$E$63 * $I13) + (ASSUMPTIONS!$E$64 * $F13)), AND(J$36 = $F$18, J$36 =ASSUMPTIONS!$F$60), $F27 * J44 * ((ASSUMPTIONS!$F$63 * $I13) + (ASSUMPTIONS!$F$64 * $F13)), AND(J$36 = $G$18, J$36 =ASSUMPTIONS!$G$60), $G27 * J44 * ((ASSUMPTIONS!$G$63 * $I13) + (ASSUMPTIONS!$G$64 * $F13)), AND(J$36 = $H$18, J$36 =ASSUMPTIONS!$H$60), $H27 * J44 * ((ASSUMPTIONS!$H$63 * $I13) + (ASSUMPTIONS!$H$64 * $F13)), TRUE, $I27 *J44 * ((ASSUMPTIONS!$I$63 * $I13) + (ASSUMPTIONS!$I$64 * $F13)) )} -> 0 | K54: {=IFS(AND(K$36 = $E$18, K$36 =ASSUMPTIONS!$E$60), $E27 * K44 * ((ASSUMPTIONS!$E$63 * $I13) + (ASSUMPTIONS!$E$64 * $F13)), AND(K$36 = $F$18, K$36 =ASSUMPTIONS!$F$60), $F27 * K44 * ((ASSUMPTIONS!$F$63 * $I13) + (ASSUMPTIONS!$F$64 * $F13)), AND(K$36 = $G$18, K$36 =ASSUMPTIONS!$G$60), $G27 * K44 * ((ASSUMPTIONS!$G$63 * $I13) + (ASSUMPTIONS!$G$64 * $F13)), AND(K$36 = $H$18, K$36 =ASSUMPTIONS!$H$60), $H27 * K44 * ((ASSUMPTIONS!$H$63 * $I13) + (ASSUMPTIONS!$H$64 * $F13)), TRUE, $I27 *K44 * ((ASSUMPTIONS!$I$63 * $I13) + (ASSUMPTIONS!$I$64 * $F13)) )} -> 2106133.9 | L54: {=IFS(AND(L$36 = $E$18, L$36 =ASSUMPTIONS!$E$60), $E27 * L44 * ((ASSUMPTIONS!$E$63 * $I13) + (ASSUMPTIONS!$E$64 * $F13)), AND(L$36 = $F$18, L$36 =ASSUMPTIONS!$F$60), $F27 * L44 * ((ASSUMPTIONS!$F$63 * $I13) + (ASSUMPTIONS!$F$64 * $F13)), AND(L$36 = $G$18, L$36 =ASSUMPTIONS!$G$60), $G27 * L44 * ((ASSUMPTIONS!$G$63 * $I13) + (ASSUMPTIONS!$G$64 * $F13)), AND(L$36 = $H$18, L$36 =ASSUMPTIONS!$H$60), $H27 * L44 * ((ASSUMPTIONS!$H$63 * $I13) + (ASSUMPTIONS!$H$64 * $F13)), TRUE, $I27 *L44 * ((ASSUMPTIONS!$I$63 * $I13) + (ASSUMPTIONS!$I$64 * $F13)) )} -> 2106133.9 | ... BL54: {=IFS(AND(BL$36 = $E$18, BL$36 =ASSUMPTIONS!$E$60), $E27 * BL44 * ((ASSUMPTIONS!$E$63 * $I13) + (ASSUMPTIONS!$E$64 * $F13)), AND(BL$36 = $F$18, BL$36 =ASSUMPTIONS!$F$60), $F27 * BL44 * ((ASSUMPTIONS!$F$63 * $I13) + (ASSUMPTIONS!$F$64 * $F13)), AND(BL$36 = $G$18, BL$36 =ASSUMPTIONS!$G$60), $G27 * BL44 * ((ASSUMPTIONS!$G$63 * $I13) + (ASSUMPTIONS!$G$64 * $F13)), AND(BL$36 = $H$18, BL$36 =ASSUMPTIONS!$H$60), $H27 * BL44 * ((ASSUMPTIONS!$H$63 * $I13) + (ASSUMPTIONS!$H$64 * $F13)), TRUE, $I27 *BL44 * ((ASSUMPTIONS!$I$63 * $I13) + (ASSUMPTIONS!$I$64 * $F13)) )} -> 18550586
D55: Ghee | E55: {=IFS(AND(E$36 = $E$18, E$36 =ASSUMPTIONS!$E$60), $E28 * E45 * ((ASSUMPTIONS!$E$63 * $I14) + (ASSUMPTIONS!$E$64 * $F14)), AND(E$36 = $F$18, E$36 =ASSUMPTIONS!$F$60), $F28 * E45 * ((ASSUMPTIONS!$F$63 * $I14) + (ASSUMPTIONS!$F$64 * $F14)), AND(E$36 = $G$18, E$36 =ASSUMPTIONS!$G$60), $G28 * E45 * ((ASSUMPTIONS!$G$63 * $I14) + (ASSUMPTIONS!$G$64 * $F14)), AND(E$36 = $H$18, E$36 =ASSUMPTIONS!$H$60), $H28 * E45 * ((ASSUMPTIONS!$H$63 * $I14) + (ASSUMPTIONS!$H$64 * $F14)), TRUE, $I28 *E45 * ((ASSUMPTIONS!$I$63 * $I14) + (ASSUMPTIONS!$I$64 * $F14)) )} -> 0 | F55: {=IFS(AND(F$36 = $E$18, F$36 =ASSUMPTIONS!$E$60), $E28 * F45 * ((ASSUMPTIONS!$E$63 * $I14) + (ASSUMPTIONS!$E$64 * $F14)), AND(F$36 = $F$18, F$36 =ASSUMPTIONS!$F$60), $F28 * F45 * ((ASSUMPTIONS!$F$63 * $I14) + (ASSUMPTIONS!$F$64 * $F14)), AND(F$36 = $G$18, F$36 =ASSUMPTIONS!$G$60), $G28 * F45 * ((ASSUMPTIONS!$G$63 * $I14) + (ASSUMPTIONS!$G$64 * $F14)), AND(F$36 = $H$18, F$36 =ASSUMPTIONS!$H$60), $H28 * F45 * ((ASSUMPTIONS!$H$63 * $I14) + (ASSUMPTIONS!$H$64 * $F14)), TRUE, $I28 *F45 * ((ASSUMPTIONS!$I$63 * $I14) + (ASSUMPTIONS!$I$64 * $F14)) )} -> 0 | G55: {=IFS(AND(G$36 = $E$18, G$36 =ASSUMPTIONS!$E$60), $E28 * G45 * ((ASSUMPTIONS!$E$63 * $I14) + (ASSUMPTIONS!$E$64 * $F14)), AND(G$36 = $F$18, G$36 =ASSUMPTIONS!$F$60), $F28 * G45 * ((ASSUMPTIONS!$F$63 * $I14) + (ASSUMPTIONS!$F$64 * $F14)), AND(G$36 = $G$18, G$36 =ASSUMPTIONS!$G$60), $G28 * G45 * ((ASSUMPTIONS!$G$63 * $I14) + (ASSUMPTIONS!$G$64 * $F14)), AND(G$36 = $H$18, G$36 =ASSUMPTIONS!$H$60), $H28 * G45 * ((ASSUMPTIONS!$H$63 * $I14) + (ASSUMPTIONS!$H$64 * $F14)), TRUE, $I28 *G45 * ((ASSUMPTIONS!$I$63 * $I14) + (ASSUMPTIONS!$I$64 * $F14)) )} -> 0 | H55: {=IFS(AND(H$36 = $E$18, H$36 =ASSUMPTIONS!$E$60), $E28 * H45 * ((ASSUMPTIONS!$E$63 * $I14) + (ASSUMPTIONS!$E$64 * $F14)), AND(H$36 = $F$18, H$36 =ASSUMPTIONS!$F$60), $F28 * H45 * ((ASSUMPTIONS!$F$63 * $I14) + (ASSUMPTIONS!$F$64 * $F14)), AND(H$36 = $G$18, H$36 =ASSUMPTIONS!$G$60), $G28 * H45 * ((ASSUMPTIONS!$G$63 * $I14) + (ASSUMPTIONS!$G$64 * $F14)), AND(H$36 = $H$18, H$36 =ASSUMPTIONS!$H$60), $H28 * H45 * ((ASSUMPTIONS!$H$63 * $I14) + (ASSUMPTIONS!$H$64 * $F14)), TRUE, $I28 *H45 * ((ASSUMPTIONS!$I$63 * $I14) + (ASSUMPTIONS!$I$64 * $F14)) )} -> 0 | I55: {=IFS(AND(I$36 = $E$18, I$36 =ASSUMPTIONS!$E$60), $E28 * I45 * ((ASSUMPTIONS!$E$63 * $I14) + (ASSUMPTIONS!$E$64 * $F14)), AND(I$36 = $F$18, I$36 =ASSUMPTIONS!$F$60), $F28 * I45 * ((ASSUMPTIONS!$F$63 * $I14) + (ASSUMPTIONS!$F$64 * $F14)), AND(I$36 = $G$18, I$36 =ASSUMPTIONS!$G$60), $G28 * I45 * ((ASSUMPTIONS!$G$63 * $I14) + (ASSUMPTIONS!$G$64 * $F14)), AND(I$36 = $H$18, I$36 =ASSUMPTIONS!$H$60), $H28 * I45 * ((ASSUMPTIONS!$H$63 * $I14) + (ASSUMPTIONS!$H$64 * $F14)), TRUE, $I28 *I45 * ((ASSUMPTIONS!$I$63 * $I14) + (ASSUMPTIONS!$I$64 * $F14)) )} -> 0 | J55: {=IFS(AND(J$36 = $E$18, J$36 =ASSUMPTIONS!$E$60), $E28 * J45 * ((ASSUMPTIONS!$E$63 * $I14) + (ASSUMPTIONS!$E$64 * $F14)), AND(J$36 = $F$18, J$36 =ASSUMPTIONS!$F$60), $F28 * J45 * ((ASSUMPTIONS!$F$63 * $I14) + (ASSUMPTIONS!$F$64 * $F14)), AND(J$36 = $G$18, J$36 =ASSUMPTIONS!$G$60), $G28 * J45 * ((ASSUMPTIONS!$G$63 * $I14) + (ASSUMPTIONS!$G$64 * $F14)), AND(J$36 = $H$18, J$36 =ASSUMPTIONS!$H$60), $H28 * J45 * ((ASSUMPTIONS!$H$63 * $I14) + (ASSUMPTIONS!$H$64 * $F14)), TRUE, $I28 *J45 * ((ASSUMPTIONS!$I$63 * $I14) + (ASSUMPTIONS!$I$64 * $F14)) )} -> 0 | K55: {=IFS(AND(K$36 = $E$18, K$36 =ASSUMPTIONS!$E$60), $E28 * K45 * ((ASSUMPTIONS!$E$63 * $I14) + (ASSUMPTIONS!$E$64 * $F14)), AND(K$36 = $F$18, K$36 =ASSUMPTIONS!$F$60), $F28 * K45 * ((ASSUMPTIONS!$F$63 * $I14) + (ASSUMPTIONS!$F$64 * $F14)), AND(K$36 = $G$18, K$36 =ASSUMPTIONS!$G$60), $G28 * K45 * ((ASSUMPTIONS!$G$63 * $I14) + (ASSUMPTIONS!$G$64 * $F14)), AND(K$36 = $H$18, K$36 =ASSUMPTIONS!$H$60), $H28 * K45 * ((ASSUMPTIONS!$H$63 * $I14) + (ASSUMPTIONS!$H$64 * $F14)), TRUE, $I28 *K45 * ((ASSUMPTIONS!$I$63 * $I14) + (ASSUMPTIONS!$I$64 * $F14)) )} -> 765866.88 | L55: {=IFS(AND(L$36 = $E$18, L$36 =ASSUMPTIONS!$E$60), $E28 * L45 * ((ASSUMPTIONS!$E$63 * $I14) + (ASSUMPTIONS!$E$64 * $F14)), AND(L$36 = $F$18, L$36 =ASSUMPTIONS!$F$60), $F28 * L45 * ((ASSUMPTIONS!$F$63 * $I14) + (ASSUMPTIONS!$F$64 * $F14)), AND(L$36 = $G$18, L$36 =ASSUMPTIONS!$G$60), $G28 * L45 * ((ASSUMPTIONS!$G$63 * $I14) + (ASSUMPTIONS!$G$64 * $F14)), AND(L$36 = $H$18, L$36 =ASSUMPTIONS!$H$60), $H28 * L45 * ((ASSUMPTIONS!$H$63 * $I14) + (ASSUMPTIONS!$H$64 * $F14)), TRUE, $I28 *L45 * ((ASSUMPTIONS!$I$63 * $I14) + (ASSUMPTIONS!$I$64 * $F14)) )} -> 765866.88 | ... BL55: {=IFS(AND(BL$36 = $E$18, BL$36 =ASSUMPTIONS!$E$60), $E28 * BL45 * ((ASSUMPTIONS!$E$63 * $I14) + (ASSUMPTIONS!$E$64 * $F14)), AND(BL$36 = $F$18, BL$36 =ASSUMPTIONS!$F$60), $F28 * BL45 * ((ASSUMPTIONS!$F$63 * $I14) + (ASSUMPTIONS!$F$64 * $F14)), AND(BL$36 = $G$18, BL$36 =ASSUMPTIONS!$G$60), $G28 * BL45 * ((ASSUMPTIONS!$G$63 * $I14) + (ASSUMPTIONS!$G$64 * $F14)), AND(BL$36 = $H$18, BL$36 =ASSUMPTIONS!$H$60), $H28 * BL45 * ((ASSUMPTIONS!$H$63 * $I14) + (ASSUMPTIONS!$H$64 * $F14)), TRUE, $I28 *BL45 * ((ASSUMPTIONS!$I$63 * $I14) + (ASSUMPTIONS!$I$64 * $F14)) )} -> 6494693.8
D56: Curd | E56: {=IFS(AND(E$36 = $E$18, E$36 =ASSUMPTIONS!$E$60), $E29 * E46 * ((ASSUMPTIONS!$E$63 * $I15) + (ASSUMPTIONS!$E$64 * $F15)), AND(E$36 = $F$18, E$36 =ASSUMPTIONS!$F$60), $F29 * E46 * ((ASSUMPTIONS!$F$63 * $I15) + (ASSUMPTIONS!$F$64 * $F15)), AND(E$36 = $G$18, E$36 =ASSUMPTIONS!$G$60), $G29 * E46 * ((ASSUMPTIONS!$G$63 * $I15) + (ASSUMPTIONS!$G$64 * $F15)), AND(E$36 = $H$18, E$36 =ASSUMPTIONS!$H$60), $H29 * E46 * ((ASSUMPTIONS!$H$63 * $I15) + (ASSUMPTIONS!$H$64 * $F15)), TRUE, $I29 *E46 * ((ASSUMPTIONS!$I$63 * $I15) + (ASSUMPTIONS!$I$64 * $F15)) )} -> 0 | F56: {=IFS(AND(F$36 = $E$18, F$36 =ASSUMPTIONS!$E$60), $E29 * F46 * ((ASSUMPTIONS!$E$63 * $I15) + (ASSUMPTIONS!$E$64 * $F15)), AND(F$36 = $F$18, F$36 =ASSUMPTIONS!$F$60), $F29 * F46 * ((ASSUMPTIONS!$F$63 * $I15) + (ASSUMPTIONS!$F$64 * $F15)), AND(F$36 = $G$18, F$36 =ASSUMPTIONS!$G$60), $G29 * F46 * ((ASSUMPTIONS!$G$63 * $I15) + (ASSUMPTIONS!$G$64 * $F15)), AND(F$36 = $H$18, F$36 =ASSUMPTIONS!$H$60), $H29 * F46 * ((ASSUMPTIONS!$H$63 * $I15) + (ASSUMPTIONS!$H$64 * $F15)), TRUE, $I29 *F46 * ((ASSUMPTIONS!$I$63 * $I15) + (ASSUMPTIONS!$I$64 * $F15)) )} -> 0 | G56: {=IFS(AND(G$36 = $E$18, G$36 =ASSUMPTIONS!$E$60), $E29 * G46 * ((ASSUMPTIONS!$E$63 * $I15) + (ASSUMPTIONS!$E$64 * $F15)), AND(G$36 = $F$18, G$36 =ASSUMPTIONS!$F$60), $F29 * G46 * ((ASSUMPTIONS!$F$63 * $I15) + (ASSUMPTIONS!$F$64 * $F15)), AND(G$36 = $G$18, G$36 =ASSUMPTIONS!$G$60), $G29 * G46 * ((ASSUMPTIONS!$G$63 * $I15) + (ASSUMPTIONS!$G$64 * $F15)), AND(G$36 = $H$18, G$36 =ASSUMPTIONS!$H$60), $H29 * G46 * ((ASSUMPTIONS!$H$63 * $I15) + (ASSUMPTIONS!$H$64 * $F15)), TRUE, $I29 *G46 * ((ASSUMPTIONS!$I$63 * $I15) + (ASSUMPTIONS!$I$64 * $F15)) )} -> 0 | H56: {=IFS(AND(H$36 = $E$18, H$36 =ASSUMPTIONS!$E$60), $E29 * H46 * ((ASSUMPTIONS!$E$63 * $I15) + (ASSUMPTIONS!$E$64 * $F15)), AND(H$36 = $F$18, H$36 =ASSUMPTIONS!$F$60), $F29 * H46 * ((ASSUMPTIONS!$F$63 * $I15) + (ASSUMPTIONS!$F$64 * $F15)), AND(H$36 = $G$18, H$36 =ASSUMPTIONS!$G$60), $G29 * H46 * ((ASSUMPTIONS!$G$63 * $I15) + (ASSUMPTIONS!$G$64 * $F15)), AND(H$36 = $H$18, H$36 =ASSUMPTIONS!$H$60), $H29 * H46 * ((ASSUMPTIONS!$H$63 * $I15) + (ASSUMPTIONS!$H$64 * $F15)), TRUE, $I29 *H46 * ((ASSUMPTIONS!$I$63 * $I15) + (ASSUMPTIONS!$I$64 * $F15)) )} -> 0 | I56: {=IFS(AND(I$36 = $E$18, I$36 =ASSUMPTIONS!$E$60), $E29 * I46 * ((ASSUMPTIONS!$E$63 * $I15) + (ASSUMPTIONS!$E$64 * $F15)), AND(I$36 = $F$18, I$36 =ASSUMPTIONS!$F$60), $F29 * I46 * ((ASSUMPTIONS!$F$63 * $I15) + (ASSUMPTIONS!$F$64 * $F15)), AND(I$36 = $G$18, I$36 =ASSUMPTIONS!$G$60), $G29 * I46 * ((ASSUMPTIONS!$G$63 * $I15) + (ASSUMPTIONS!$G$64 * $F15)), AND(I$36 = $H$18, I$36 =ASSUMPTIONS!$H$60), $H29 * I46 * ((ASSUMPTIONS!$H$63 * $I15) + (ASSUMPTIONS!$H$64 * $F15)), TRUE, $I29 *I46 * ((ASSUMPTIONS!$I$63 * $I15) + (ASSUMPTIONS!$I$64 * $F15)) )} -> 0 | J56: {=IFS(AND(J$36 = $E$18, J$36 =ASSUMPTIONS!$E$60), $E29 * J46 * ((ASSUMPTIONS!$E$63 * $I15) + (ASSUMPTIONS!$E$64 * $F15)), AND(J$36 = $F$18, J$36 =ASSUMPTIONS!$F$60), $F29 * J46 * ((ASSUMPTIONS!$F$63 * $I15) + (ASSUMPTIONS!$F$64 * $F15)), AND(J$36 = $G$18, J$36 =ASSUMPTIONS!$G$60), $G29 * J46 * ((ASSUMPTIONS!$G$63 * $I15) + (ASSUMPTIONS!$G$64 * $F15)), AND(J$36 = $H$18, J$36 =ASSUMPTIONS!$H$60), $H29 * J46 * ((ASSUMPTIONS!$H$63 * $I15) + (ASSUMPTIONS!$H$64 * $F15)), TRUE, $I29 *J46 * ((ASSUMPTIONS!$I$63 * $I15) + (ASSUMPTIONS!$I$64 * $F15)) )} -> 0 | K56: {=IFS(AND(K$36 = $E$18, K$36 =ASSUMPTIONS!$E$60), $E29 * K46 * ((ASSUMPTIONS!$E$63 * $I15) + (ASSUMPTIONS!$E$64 * $F15)), AND(K$36 = $F$18, K$36 =ASSUMPTIONS!$F$60), $F29 * K46 * ((ASSUMPTIONS!$F$63 * $I15) + (ASSUMPTIONS!$F$64 * $F15)), AND(K$36 = $G$18, K$36 =ASSUMPTIONS!$G$60), $G29 * K46 * ((ASSUMPTIONS!$G$63 * $I15) + (ASSUMPTIONS!$G$64 * $F15)), AND(K$36 = $H$18, K$36 =ASSUMPTIONS!$H$60), $H29 * K46 * ((ASSUMPTIONS!$H$63 * $I15) + (ASSUMPTIONS!$H$64 * $F15)), TRUE, $I29 *K46 * ((ASSUMPTIONS!$I$63 * $I15) + (ASSUMPTIONS!$I$64 * $F15)) )} -> 2042311.7 | L56: {=IFS(AND(L$36 = $E$18, L$36 =ASSUMPTIONS!$E$60), $E29 * L46 * ((ASSUMPTIONS!$E$63 * $I15) + (ASSUMPTIONS!$E$64 * $F15)), AND(L$36 = $F$18, L$36 =ASSUMPTIONS!$F$60), $F29 * L46 * ((ASSUMPTIONS!$F$63 * $I15) + (ASSUMPTIONS!$F$64 * $F15)), AND(L$36 = $G$18, L$36 =ASSUMPTIONS!$G$60), $G29 * L46 * ((ASSUMPTIONS!$G$63 * $I15) + (ASSUMPTIONS!$G$64 * $F15)), AND(L$36 = $H$18, L$36 =ASSUMPTIONS!$H$60), $H29 * L46 * ((ASSUMPTIONS!$H$63 * $I15) + (ASSUMPTIONS!$H$64 * $F15)), TRUE, $I29 *L46 * ((ASSUMPTIONS!$I$63 * $I15) + (ASSUMPTIONS!$I$64 * $F15)) )} -> 2042311.7 | ... BL56: {=IFS(AND(BL$36 = $E$18, BL$36 =ASSUMPTIONS!$E$60), $E29 * BL46 * ((ASSUMPTIONS!$E$63 * $I15) + (ASSUMPTIONS!$E$64 * $F15)), AND(BL$36 = $F$18, BL$36 =ASSUMPTIONS!$F$60), $F29 * BL46 * ((ASSUMPTIONS!$F$63 * $I15) + (ASSUMPTIONS!$F$64 * $F15)), AND(BL$36 = $G$18, BL$36 =ASSUMPTIONS!$G$60), $G29 * BL46 * ((ASSUMPTIONS!$G$63 * $I15) + (ASSUMPTIONS!$G$64 * $F15)), AND(BL$36 = $H$18, BL$36 =ASSUMPTIONS!$H$60), $H29 * BL46 * ((ASSUMPTIONS!$H$63 * $I15) + (ASSUMPTIONS!$H$64 * $F15)), TRUE, $I29 *BL46 * ((ASSUMPTIONS!$I$63 * $I15) + (ASSUMPTIONS!$I$64 * $F15)) )} -> 17319183
D57: Peda | E57: {=IFS(AND(E$36 = $E$18, E$36 =ASSUMPTIONS!$E$60), $E30 * E47 * ((ASSUMPTIONS!$E$63 * $I16) + (ASSUMPTIONS!$E$64 * $F16)), AND(E$36 = $F$18, E$36 =ASSUMPTIONS!$F$60), $F30 * E47 * ((ASSUMPTIONS!$F$63 * $I16) + (ASSUMPTIONS!$F$64 * $F16)), AND(E$36 = $G$18, E$36 =ASSUMPTIONS!$G$60), $G30 * E47 * ((ASSUMPTIONS!$G$63 * $I16) + (ASSUMPTIONS!$G$64 * $F16)), AND(E$36 = $H$18, E$36 =ASSUMPTIONS!$H$60), $H30 * E47 * ((ASSUMPTIONS!$H$63 * $I16) + (ASSUMPTIONS!$H$64 * $F16)), TRUE, $I30 *E47 * ((ASSUMPTIONS!$I$63 * $I16) + (ASSUMPTIONS!$I$64 * $F16)) )} -> 0 | F57: {=IFS(AND(F$36 = $E$18, F$36 =ASSUMPTIONS!$E$60), $E30 * F47 * ((ASSUMPTIONS!$E$63 * $I16) + (ASSUMPTIONS!$E$64 * $F16)), AND(F$36 = $F$18, F$36 =ASSUMPTIONS!$F$60), $F30 * F47 * ((ASSUMPTIONS!$F$63 * $I16) + (ASSUMPTIONS!$F$64 * $F16)), AND(F$36 = $G$18, F$36 =ASSUMPTIONS!$G$60), $G30 * F47 * ((ASSUMPTIONS!$G$63 * $I16) + (ASSUMPTIONS!$G$64 * $F16)), AND(F$36 = $H$18, F$36 =ASSUMPTIONS!$H$60), $H30 * F47 * ((ASSUMPTIONS!$H$63 * $I16) + (ASSUMPTIONS!$H$64 * $F16)), TRUE, $I30 *F47 * ((ASSUMPTIONS!$I$63 * $I16) + (ASSUMPTIONS!$I$64 * $F16)) )} -> 0 | G57: {=IFS(AND(G$36 = $E$18, G$36 =ASSUMPTIONS!$E$60), $E30 * G47 * ((ASSUMPTIONS!$E$63 * $I16) + (ASSUMPTIONS!$E$64 * $F16)), AND(G$36 = $F$18, G$36 =ASSUMPTIONS!$F$60), $F30 * G47 * ((ASSUMPTIONS!$F$63 * $I16) + (ASSUMPTIONS!$F$64 * $F16)), AND(G$36 = $G$18, G$36 =ASSUMPTIONS!$G$60), $G30 * G47 * ((ASSUMPTIONS!$G$63 * $I16) + (ASSUMPTIONS!$G$64 * $F16)), AND(G$36 = $H$18, G$36 =ASSUMPTIONS!$H$60), $H30 * G47 * ((ASSUMPTIONS!$H$63 * $I16) + (ASSUMPTIONS!$H$64 * $F16)), TRUE, $I30 *G47 * ((ASSUMPTIONS!$I$63 * $I16) + (ASSUMPTIONS!$I$64 * $F16)) )} -> 0 | H57: {=IFS(AND(H$36 = $E$18, H$36 =ASSUMPTIONS!$E$60), $E30 * H47 * ((ASSUMPTIONS!$E$63 * $I16) + (ASSUMPTIONS!$E$64 * $F16)), AND(H$36 = $F$18, H$36 =ASSUMPTIONS!$F$60), $F30 * H47 * ((ASSUMPTIONS!$F$63 * $I16) + (ASSUMPTIONS!$F$64 * $F16)), AND(H$36 = $G$18, H$36 =ASSUMPTIONS!$G$60), $G30 * H47 * ((ASSUMPTIONS!$G$63 * $I16) + (ASSUMPTIONS!$G$64 * $F16)), AND(H$36 = $H$18, H$36 =ASSUMPTIONS!$H$60), $H30 * H47 * ((ASSUMPTIONS!$H$63 * $I16) + (ASSUMPTIONS!$H$64 * $F16)), TRUE, $I30 *H47 * ((ASSUMPTIONS!$I$63 * $I16) + (ASSUMPTIONS!$I$64 * $F16)) )} -> 0 | I57: {=IFS(AND(I$36 = $E$18, I$36 =ASSUMPTIONS!$E$60), $E30 * I47 * ((ASSUMPTIONS!$E$63 * $I16) + (ASSUMPTIONS!$E$64 * $F16)), AND(I$36 = $F$18, I$36 =ASSUMPTIONS!$F$60), $F30 * I47 * ((ASSUMPTIONS!$F$63 * $I16) + (ASSUMPTIONS!$F$64 * $F16)), AND(I$36 = $G$18, I$36 =ASSUMPTIONS!$G$60), $G30 * I47 * ((ASSUMPTIONS!$G$63 * $I16) + (ASSUMPTIONS!$G$64 * $F16)), AND(I$36 = $H$18, I$36 =ASSUMPTIONS!$H$60), $H30 * I47 * ((ASSUMPTIONS!$H$63 * $I16) + (ASSUMPTIONS!$H$64 * $F16)), TRUE, $I30 *I47 * ((ASSUMPTIONS!$I$63 * $I16) + (ASSUMPTIONS!$I$64 * $F16)) )} -> 0 | J57: {=IFS(AND(J$36 = $E$18, J$36 =ASSUMPTIONS!$E$60), $E30 * J47 * ((ASSUMPTIONS!$E$63 * $I16) + (ASSUMPTIONS!$E$64 * $F16)), AND(J$36 = $F$18, J$36 =ASSUMPTIONS!$F$60), $F30 * J47 * ((ASSUMPTIONS!$F$63 * $I16) + (ASSUMPTIONS!$F$64 * $F16)), AND(J$36 = $G$18, J$36 =ASSUMPTIONS!$G$60), $G30 * J47 * ((ASSUMPTIONS!$G$63 * $I16) + (ASSUMPTIONS!$G$64 * $F16)), AND(J$36 = $H$18, J$36 =ASSUMPTIONS!$H$60), $H30 * J47 * ((ASSUMPTIONS!$H$63 * $I16) + (ASSUMPTIONS!$H$64 * $F16)), TRUE, $I30 *J47 * ((ASSUMPTIONS!$I$63 * $I16) + (ASSUMPTIONS!$I$64 * $F16)) )} -> 0 | K57: {=IFS(AND(K$36 = $E$18, K$36 =ASSUMPTIONS!$E$60), $E30 * K47 * ((ASSUMPTIONS!$E$63 * $I16) + (ASSUMPTIONS!$E$64 * $F16)), AND(K$36 = $F$18, K$36 =ASSUMPTIONS!$F$60), $F30 * K47 * ((ASSUMPTIONS!$F$63 * $I16) + (ASSUMPTIONS!$F$64 * $F16)), AND(K$36 = $G$18, K$36 =ASSUMPTIONS!$G$60), $G30 * K47 * ((ASSUMPTIONS!$G$63 * $I16) + (ASSUMPTIONS!$G$64 * $F16)), AND(K$36 = $H$18, K$36 =ASSUMPTIONS!$H$60), $H30 * K47 * ((ASSUMPTIONS!$H$63 * $I16) + (ASSUMPTIONS!$H$64 * $F16)), TRUE, $I30 *K47 * ((ASSUMPTIONS!$I$63 * $I16) + (ASSUMPTIONS!$I$64 * $F16)) )} -> 2192832 | L57: {=IFS(AND(L$36 = $E$18, L$36 =ASSUMPTIONS!$E$60), $E30 * L47 * ((ASSUMPTIONS!$E$63 * $I16) + (ASSUMPTIONS!$E$64 * $F16)), AND(L$36 = $F$18, L$36 =ASSUMPTIONS!$F$60), $F30 * L47 * ((ASSUMPTIONS!$F$63 * $I16) + (ASSUMPTIONS!$F$64 * $F16)), AND(L$36 = $G$18, L$36 =ASSUMPTIONS!$G$60), $G30 * L47 * ((ASSUMPTIONS!$G$63 * $I16) + (ASSUMPTIONS!$G$64 * $F16)), AND(L$36 = $H$18, L$36 =ASSUMPTIONS!$H$60), $H30 * L47 * ((ASSUMPTIONS!$H$63 * $I16) + (ASSUMPTIONS!$H$64 * $F16)), TRUE, $I30 *L47 * ((ASSUMPTIONS!$I$63 * $I16) + (ASSUMPTIONS!$I$64 * $F16)) )} -> 2192832 | ... BL57: {=IFS(AND(BL$36 = $E$18, BL$36 =ASSUMPTIONS!$E$60), $E30 * BL47 * ((ASSUMPTIONS!$E$63 * $I16) + (ASSUMPTIONS!$E$64 * $F16)), AND(BL$36 = $F$18, BL$36 =ASSUMPTIONS!$F$60), $F30 * BL47 * ((ASSUMPTIONS!$F$63 * $I16) + (ASSUMPTIONS!$F$64 * $F16)), AND(BL$36 = $G$18, BL$36 =ASSUMPTIONS!$G$60), $G30 * BL47 * ((ASSUMPTIONS!$G$63 * $I16) + (ASSUMPTIONS!$G$64 * $F16)), AND(BL$36 = $H$18, BL$36 =ASSUMPTIONS!$H$60), $H30 * BL47 * ((ASSUMPTIONS!$H$63 * $I16) + (ASSUMPTIONS!$H$64 * $F16)), TRUE, $I30 *BL47 * ((ASSUMPTIONS!$I$63 * $I16) + (ASSUMPTIONS!$I$64 * $F16)) )} -> 19840199
D58: Section E – Total Revenue | E58: =SUM(E49:E57) -> 0 | F58: =SUM(F49:F57) -> 0 | G58: =SUM(G49:G57) -> 0 | H58: =SUM(H49:H57) -> 0 | I58: =SUM(I49:I57) -> 2387024.6 | J58: =SUM(J49:J57) -> 4774049.3 | K58: =SUM(K49:K57) -> 19546446 | L58: =SUM(L49:L57) -> 21933471 | ... BL58: =SUM(BL49:BL57) -> 2.8028502e+08

Sheet COGS ENGINE
A1: =COVER!$B$12 -> Narayan Dairy Project
A2: COGS Engine
D4: Product / Year | E4: 1 | F4: 2 | G4: 3 | H4: 4 | I4: 5
D7: Section B – Salary Escalation Factor Schedule
D8: Milk Procurement | E8: =1 -> 1 | F8: =E8 * (1 + ASSUMPTIONS!$H$36) -> 1.04 | G8: =F8 * (1 + ASSUMPTIONS!$H$36) -> 1.0816 | H8: =G8 * (1 + ASSUMPTIONS!$H$36) -> 1.124864 | I8: =H8 * (1 + ASSUMPTIONS!$H$36) -> 1.1698586
D9: Feed | E9: =1 -> 1 | F9: =E9 * (1 + ASSUMPTIONS!$H$38) -> 1.06 | G9: =F9 * (1 + ASSUMPTIONS!$H$38) -> 1.1236 | H9: =G9 * (1 + ASSUMPTIONS!$H$38) -> 1.191016 | I9: =H9 * (1 + ASSUMPTIONS!$H$38) -> 1.262477
D10: Freight | E10: =1 -> 1 | F10: =E10 * (1 + ASSUMPTIONS!$H$40) -> 1.05 | G10: =F10 * (1 + ASSUMPTIONS!$H$40) -> 1.1025 | H10: =G10 * (1 + ASSUMPTIONS!$H$40) -> 1.157625 | I10: =H10 * (1 + ASSUMPTIONS!$H$40) -> 1.2155063
D12: Product / Month / Year | E12: 1 | F12: =E12+1 -> 2 | G12: =F12+1 -> 3 | H12: =G12+1 -> 4 | I12: =H12+1 -> 5 | J12: =I12+1 -> 6 | K12: =J12+1 -> 7 | L12: =K12+1 -> 8 | M12: =L12+1 -> 9 | ... BL12: =BK12+1 -> 60
E15: =INT((E12 - 1) / 12) +1 -> 1 | F15: =INT((F12 - 1) / 12) +1 -> 1 | G15: =INT((G12 - 1) / 12) +1 -> 1 | H15: =INT((H12 - 1) / 12) +1 -> 1 | I15: =INT((I12 - 1) / 12) +1 -> 1 | J15: =INT((J12 - 1) / 12) +1 -> 1 | K15: =INT((K12 - 1) / 12) +1 -> 1 | L15: =INT((L12 - 1) / 12) +1 -> 1 | ... BL15: =INT((BL12 - 1) / 12) +1 -> 5
D17: Section A – Raw Milk Cost
D18: Own Livestock | E18: ='MILK FLOW ENGINE'!E$8 -> 0 | F18: ='MILK FLOW ENGINE'!F$8 -> 0 | G18: ='MILK FLOW ENGINE'!G$8 -> 0 | H18: ='MILK FLOW ENGINE'!H$8 -> 0 | I18: ='MILK FLOW ENGINE'!I$8 -> 50 | J18: ='MILK FLOW ENGINE'!J$8 -> 100 | K18: ='MILK FLOW ENGINE'!K$8 -> 150 | L18: ='MILK FLOW ENGINE'!L$8 -> 200 | ... BL18: ='MILK FLOW ENGINE'!BL$8 -> 2800
D19: Own Milk Volume | E19: ='MILK FLOW ENGINE'!E10 -> 0 | F19: ='MILK FLOW ENGINE'!F10 -> 0 | G19: ='MILK FLOW ENGINE'!G10 -> 0 | H19: ='MILK FLOW ENGINE'!H10 -> 0 | I19: ='MILK FLOW ENGINE'!I10 -> 48000 | J19: ='MILK FLOW ENGINE'!J10 -> 96000 | K19: ='MILK FLOW ENGINE'!K10 -> 144000 | L19: ='MILK FLOW ENGINE'!L10 -> 192000 | ... BL19: ='MILK FLOW ENGINE'!BL10 -> 2688000
D20: Own Milk Cost per Litre | E20: =IF(E$15=$E$4, ASSUMPTIONS!$H$26 * $E$9, IF(E$15=$F$4, ASSUMPTIONS!$H$26 * $F$9, IF(E$15=$G$4, ASSUMPTIONS!$H$26 * $G$9, IF(E$15=$H$4, ASSUMPTIONS!$H$26 * $H$9, IF(E$15=$I$4, ASSUMPTIONS!$H$26 * $I$9, 0 ))))) -> 22 | F20: =IF(F$15=$E$4, ASSUMPTIONS!$H$26 * $E$9, IF(F$15=$F$4, ASSUMPTIONS!$H$26 * $F$9, IF(F$15=$G$4, ASSUMPTIONS!$H$26 * $G$9, IF(F$15=$H$4, ASSUMPTIONS!$H$26 * $H$9, IF(F$15=$I$4, ASSUMPTIONS!$H$26 * $I$9, 0 ))))) -> 22 | G20: =IF(G$15=$E$4, ASSUMPTIONS!$H$26 * $E$9, IF(G$15=$F$4, ASSUMPTIONS!$H$26 * $F$9, IF(G$15=$G$4, ASSUMPTIONS!$H$26 * $G$9, IF(G$15=$H$4, ASSUMPTIONS!$H$26 * $H$9, IF(G$15=$I$4, ASSUMPTIONS!$H$26 * $I$9, 0 ))))) -> 22 | H20: =IF(H$15=$E$4, ASSUMPTIONS!$H$26 * $E$9, IF(H$15=$F$4, ASSUMPTIONS!$H$26 * $F$9, IF(H$15=$G$4, ASSUMPTIONS!$H$26 * $G$9, IF(H$15=$H$4, ASSUMPTIONS!$H$26 * $H$9, IF(H$15=$I$4, ASSUMPTIONS!$H$26 * $I$9, 0 ))))) -> 22 | I20: =IF(I$15=$E$4, ASSUMPTIONS!$H$26 * $E$9, IF(I$15=$F$4, ASSUMPTIONS!$H$26 * $F$9, IF(I$15=$G$4, ASSUMPTIONS!$H$26 * $G$9, IF(I$15=$H$4, ASSUMPTIONS!$H$26 * $H$9, IF(I$15=$I$4, ASSUMPTIONS!$H$26 * $I$9, 0 ))))) -> 22 | J20: =IF(J$15=$E$4, ASSUMPTIONS!$H$26 * $E$9, IF(J$15=$F$4, ASSUMPTIONS!$H$26 * $F$9, IF(J$15=$G$4, ASSUMPTIONS!$H$26 * $G$9, IF(J$15=$H$4, ASSUMPTIONS!$H$26 * $H$9, IF(J$15=$I$4, ASSUMPTIONS!$H$26 * $I$9, 0 ))))) -> 22 | K20: =IF(K$15=$E$4, ASSUMPTIONS!$H$26 * $E$9, IF(K$15=$F$4, ASSUMPTIONS!$H$26 * $F$9, IF(K$15=$G$4, ASSUMPTIONS!$H$26 * $G$9, IF(K$15=$H$4, ASSUMPTIONS!$H$26 * $H$9, IF(K$15=$I$4, ASSUMPTIONS!$H$26 * $I$9, 0 ))))) -> 22 | L20: =IF(L$15=$E$4, ASSUMPTIONS!$H$26 * $E$9, IF(L$15=$F$4, ASSUMPTIONS!$H$26 * $F$9, IF(L$15=$G$4, ASSUMPTIONS!$H$26 * $G$9, IF(L$15=$H$4, ASSUMPTIONS!$H$26 * $H$9, IF(L$15=$I$4, ASSUMPTIONS!$H$26 * $I$9, 0 ))))) -> 22 | ... BL20: =IF(BL$15=$E$4, ASSUMPTIONS!$H$26 * $E$9, IF(BL$15=$F$4, ASSUMPTIONS!$H$26 * $F$9, IF(BL$15=$G$4, ASSUMPTIONS!$H$26 * $G$9, IF(BL$15=$H$4, ASSUMPTIONS!$H$26 * $H$9, IF(BL$15=$I$4, ASSUMPTIONS!$H$26 * $I$9, 0 ))))) -> 27.774493
D21: Own Milk Total Cost | E21: =E19 * E20 -> 0 | F21: =F19 * F20 -> 0 | G21: =G19 * G20 -> 0 | H21: =H19 * H20 -> 0 | I21: =I19 * I20 -> 1056000 | J21: =J19 * J20 -> 2112000 | K21: =K19 * K20 -> 3168000 | L21: =L19 * L20 -> 4224000 | ... BL21: =BL19 * BL20 -> 74657838
D22: Procured Milk Volume | E22: ='MILK FLOW ENGINE'!E11 -> 0 | F22: ='MILK FLOW ENGINE'!F11 -> 0 | G22: ='MILK FLOW ENGINE'!G11 -> 0 | H22: ='MILK FLOW ENGINE'!H11 -> 0 | I22: ='MILK FLOW ENGINE'!I11 -> 0 | J22: ='MILK FLOW ENGINE'!J11 -> 0 | K22: ='MILK FLOW ENGINE'!K11 -> 150000 | L22: ='MILK FLOW ENGINE'!L11 -> 150000 | ... BL22: ='MILK FLOW ENGINE'!BL11 -> 900000
D23: Procured Milk Cost per Litre | E23: =IF(E$15=$E$4, ASSUMPTIONS!$H$54 * $E$8, IF(E$15=$F$4, ASSUMPTIONS!$H$54 * $F$8, IF(E$15=$G$4, ASSUMPTIONS!$H$54 * $G$8, IF(E$15=$H$4, ASSUMPTIONS!$H$54 * $H$8, IF(E$15=$I$4, ASSUMPTIONS!$H$54 * $I$8, 0 ))))) -> 50 | F23: =IF(F$15=$E$4, ASSUMPTIONS!$H$54 * $E$8, IF(F$15=$F$4, ASSUMPTIONS!$H$54 * $F$8, IF(F$15=$G$4, ASSUMPTIONS!$H$54 * $G$8, IF(F$15=$H$4, ASSUMPTIONS!$H$54 * $H$8, IF(F$15=$I$4, ASSUMPTIONS!$H$54 * $I$8, 0 ))))) -> 50 | G23: =IF(G$15=$E$4, ASSUMPTIONS!$H$54 * $E$8, IF(G$15=$F$4, ASSUMPTIONS!$H$54 * $F$8, IF(G$15=$G$4, ASSUMPTIONS!$H$54 * $G$8, IF(G$15=$H$4, ASSUMPTIONS!$H$54 * $H$8, IF(G$15=$I$4, ASSUMPTIONS!$H$54 * $I$8, 0 ))))) -> 50 | H23: =IF(H$15=$E$4, ASSUMPTIONS!$H$54 * $E$8, IF(H$15=$F$4, ASSUMPTIONS!$H$54 * $F$8, IF(H$15=$G$4, ASSUMPTIONS!$H$54 * $G$8, IF(H$15=$H$4, ASSUMPTIONS!$H$54 * $H$8, IF(H$15=$I$4, ASSUMPTIONS!$H$54 * $I$8, 0 ))))) -> 50 | I23: =IF(I$15=$E$4, ASSUMPTIONS!$H$54 * $E$8, IF(I$15=$F$4, ASSUMPTIONS!$H$54 * $F$8, IF(I$15=$G$4, ASSUMPTIONS!$H$54 * $G$8, IF(I$15=$H$4, ASSUMPTIONS!$H$54 * $H$8, IF(I$15=$I$4, ASSUMPTIONS!$H$54 * $I$8, 0 ))))) -> 50 | J23: =IF(J$15=$E$4, ASSUMPTIONS!$H$54 * $E$8, IF(J$15=$F$4, ASSUMPTIONS!$H$54 * $F$8, IF(J$15=$G$4, ASSUMPTIONS!$H$54 * $G$8, IF(J$15=$H$4, ASSUMPTIONS!$H$54 * $H$8, IF(J$15=$I$4, ASSUMPTIONS!$H$54 * $I$8, 0 ))))) -> 50 | K23: =IF(K$15=$E$4, ASSUMPTIONS!$H$54 * $E$8, IF(K$15=$F$4, ASSUMPTIONS!$H$54 * $F$8, IF(K$15=$G$4, ASSUMPTIONS!$H$54 * $G$8, IF(K$15=$H$4, ASSUMPTIONS!$H$54 * $H$8, IF(K$15=$I$4, ASSUMPTIONS!$H$54 * $I$8, 0 ))))) -> 50 | L23: =IF(L$15=$E$4, ASSUMPTIONS!$H$54 * $E$8, IF(L$15=$F$4, ASSUMPTIONS!$H$54 * $F$8, IF(L$15=$G$4, ASSUMPTIONS!$H$54 * $G$8, IF(L$15=$H$4, ASSUMPTIONS!$H$54 * $H$8, IF(L$15=$I$4, ASSUMPTIONS!$H$54 * $I$8, 0 ))))) -> 50 | ... BL23: =IF(BL$15=$E$4, ASSUMPTIONS!$H$54 * $E$8, IF(BL$15=$F$4, ASSUMPTIONS!$H$54 * $F$8, IF(BL$15=$G$4, ASSUMPTIONS!$H$54 * $G$8, IF(BL$15=$H$4, ASSUMPTIONS!$H$54 * $H$8, IF(BL$15=$I$4, ASSUMPTIONS!$H$54 * $I$8, 0 ))))) -> 58.492928
D24: Procured Milk Total Cost | E24: =E22 * E23 -> 0 | F24: =F22 * F23 -> 0 | G24: =G22 * G23 -> 0 | H24: =H22 * H23 -> 0 | I24: =I22 * I23 -> 0 | J24: =J22 * J23 -> 0 | K24: =K22 * K23 -> 7500000 | L24: =L22 * L23 -> 7500000 | ... BL24: =BL22 * BL23 -> 52643635
D25: Section B – Packaging Cost
D26: Fresh Milk | E26: ='PRODUCT PRICING & REVENUE ENGIN'!E49 * ASSUMPTIONS!$L$17 -> 0 | F26: ='PRODUCT PRICING & REVENUE ENGIN'!F49 * ASSUMPTIONS!$L$17 -> 0 | G26: ='PRODUCT PRICING & REVENUE ENGIN'!G49 * ASSUMPTIONS!$L$17 -> 0 | H26: ='PRODUCT PRICING & REVENUE ENGIN'!H49 * ASSUMPTIONS!$L$17 -> 0 | I26: ='PRODUCT PRICING & REVENUE ENGIN'!I49 * ASSUMPTIONS!$L$17 -> 95480.986 | J26: ='PRODUCT PRICING & REVENUE ENGIN'!J49 * ASSUMPTIONS!$L$17 -> 190961.97 | K26: ='PRODUCT PRICING & REVENUE ENGIN'!K49 * ASSUMPTIONS!$L$17 -> 286442.96 | L26: ='PRODUCT PRICING & REVENUE ENGIN'!L49 * ASSUMPTIONS!$L$17 -> 381923.94 | ... BL26: ='PRODUCT PRICING & REVENUE ENGIN'!BL49 * ASSUMPTIONS!$L$17 -> 6902659.5
D27: Yogurt | E27: ='PRODUCT PRICING & REVENUE ENGIN'!E50 * ASSUMPTIONS!$L$19 -> 0 | F27: ='PRODUCT PRICING & REVENUE ENGIN'!F50 * ASSUMPTIONS!$L$19 -> 0 | G27: ='PRODUCT PRICING & REVENUE ENGIN'!G50 * ASSUMPTIONS!$L$19 -> 0 | H27: ='PRODUCT PRICING & REVENUE ENGIN'!H50 * ASSUMPTIONS!$L$19 -> 0 | I27: ='PRODUCT PRICING & REVENUE ENGIN'!I50 * ASSUMPTIONS!$L$19 -> 0 | J27: ='PRODUCT PRICING & REVENUE ENGIN'!J50 * ASSUMPTIONS!$L$19 -> 0 | K27: ='PRODUCT PRICING & REVENUE ENGIN'!K50 * ASSUMPTIONS!$L$19 -> 87713.28 | L27: ='PRODUCT PRICING & REVENUE ENGIN'!L50 * ASSUMPTIONS!$L$19 -> 87713.28 | ... BL27: ='PRODUCT PRICING & REVENUE ENGIN'!BL50 * ASSUMPTIONS!$L$19 -> 764081.62
D28: Thandai | E28: ='PRODUCT PRICING & REVENUE ENGIN'!E51 * ASSUMPTIONS!$L$20 -> 0 | F28: ='PRODUCT PRICING & REVENUE ENGIN'!F51 * ASSUMPTIONS!$L$20 -> 0 | G28: ='PRODUCT PRICING & REVENUE ENGIN'!G51 * ASSUMPTIONS!$L$20 -> 0 | H28: ='PRODUCT PRICING & REVENUE ENGIN'!H51 * ASSUMPTIONS!$L$20 -> 0 | I28: ='PRODUCT PRICING & REVENUE ENGIN'!I51 * ASSUMPTIONS!$L$20 -> 0 | J28: ='PRODUCT PRICING & REVENUE ENGIN'!J51 * ASSUMPTIONS!$L$20 -> 0 | K28: ='PRODUCT PRICING & REVENUE ENGIN'!K51 * ASSUMPTIONS!$L$20 -> 233902.08 | L28: ='PRODUCT PRICING & REVENUE ENGIN'!L51 * ASSUMPTIONS!$L$20 -> 233902.08 | ... BL28: ='PRODUCT PRICING & REVENUE ENGIN'!BL51 * ASSUMPTIONS!$L$20 -> 2037551
D29: SMP | E29: ='PRODUCT PRICING & REVENUE ENGIN'!E52 * ASSUMPTIONS!$L$21 -> 0 | F29: ='PRODUCT PRICING & REVENUE ENGIN'!F52 * ASSUMPTIONS!$L$21 -> 0 | G29: ='PRODUCT PRICING & REVENUE ENGIN'!G52 * ASSUMPTIONS!$L$21 -> 0 | H29: ='PRODUCT PRICING & REVENUE ENGIN'!H52 * ASSUMPTIONS!$L$21 -> 0 | I29: ='PRODUCT PRICING & REVENUE ENGIN'!I52 * ASSUMPTIONS!$L$21 -> 0 | J29: ='PRODUCT PRICING & REVENUE ENGIN'!J52 * ASSUMPTIONS!$L$21 -> 0 | K29: ='PRODUCT PRICING & REVENUE ENGIN'!K52 * ASSUMPTIONS!$L$21 -> 14466.6 | L29: ='PRODUCT PRICING & REVENUE ENGIN'!L52 * ASSUMPTIONS!$L$21 -> 14466.6 | ... BL29: ='PRODUCT PRICING & REVENUE ENGIN'!BL52 * ASSUMPTIONS!$L$21 -> 118874.58
D30: Butter | E30: ='PRODUCT PRICING & REVENUE ENGIN'!E53 * ASSUMPTIONS!$L$22 -> 0 | F30: ='PRODUCT PRICING & REVENUE ENGIN'!F53 * ASSUMPTIONS!$L$22 -> 0 | G30: ='PRODUCT PRICING & REVENUE ENGIN'!G53 * ASSUMPTIONS!$L$22 -> 0 | H30: ='PRODUCT PRICING & REVENUE ENGIN'!H53 * ASSUMPTIONS!$L$22 -> 0 | I30: ='PRODUCT PRICING & REVENUE ENGIN'!I53 * ASSUMPTIONS!$L$22 -> 0 | J30: ='PRODUCT PRICING & REVENUE ENGIN'!J53 * ASSUMPTIONS!$L$22 -> 0 | K30: ='PRODUCT PRICING & REVENUE ENGIN'!K53 * ASSUMPTIONS!$L$22 -> 16413.754 | L30: ='PRODUCT PRICING & REVENUE ENGIN'!L53 * ASSUMPTIONS!$L$22 -> 16413.754 | ... BL30: ='PRODUCT PRICING & REVENUE ENGIN'!BL53 * ASSUMPTIONS!$L$22 -> 133891.98
D31: A2 Powder | E31: ='PRODUCT PRICING & REVENUE ENGIN'!E54 * ASSUMPTIONS!$L$23 -> 0 | F31: ='PRODUCT PRICING & REVENUE ENGIN'!F54 * ASSUMPTIONS!$L$23 -> 0 | G31: ='PRODUCT PRICING & REVENUE ENGIN'!G54 * ASSUMPTIONS!$L$23 -> 0 | H31: ='PRODUCT PRICING & REVENUE ENGIN'!H54 * ASSUMPTIONS!$L$23 -> 0 | I31: ='PRODUCT PRICING & REVENUE ENGIN'!I54 * ASSUMPTIONS!$L$23 -> 0 | J31: ='PRODUCT PRICING & REVENUE ENGIN'!J54 * ASSUMPTIONS!$L$23 -> 0 | K31: ='PRODUCT PRICING & REVENUE ENGIN'!K54 * ASSUMPTIONS!$L$23 -> 105306.7 | L31: ='PRODUCT PRICING & REVENUE ENGIN'!L54 * ASSUMPTIONS!$L$23 -> 105306.7 | ... BL31: ='PRODUCT PRICING & REVENUE ENGIN'!BL54 * ASSUMPTIONS!$L$23 -> 927529.31
D32: Ghee | E32: ='PRODUCT PRICING & REVENUE ENGIN'!E55 * ASSUMPTIONS!$L$24 -> 0 | F32: ='PRODUCT PRICING & REVENUE ENGIN'!F55 * ASSUMPTIONS!$L$24 -> 0 | G32: ='PRODUCT PRICING & REVENUE ENGIN'!G55 * ASSUMPTIONS!$L$24 -> 0 | H32: ='PRODUCT PRICING & REVENUE ENGIN'!H55 * ASSUMPTIONS!$L$24 -> 0 | I32: ='PRODUCT PRICING & REVENUE ENGIN'!I55 * ASSUMPTIONS!$L$24 -> 0 | J32: ='PRODUCT PRICING & REVENUE ENGIN'!J55 * ASSUMPTIONS!$L$24 -> 0 | K32: ='PRODUCT PRICING & REVENUE ENGIN'!K55 * ASSUMPTIONS!$L$24 -> 38293.344 | L32: ='PRODUCT PRICING & REVENUE ENGIN'!L55 * ASSUMPTIONS!$L$24 -> 38293.344 | ... BL32: ='PRODUCT PRICING & REVENUE ENGIN'!BL55 * ASSUMPTIONS!$L$24 -> 324734.69
D33: Curd | E33: ='PRODUCT PRICING & REVENUE ENGIN'!E56 * ASSUMPTIONS!$L$25 -> 0 | F33: ='PRODUCT PRICING & REVENUE ENGIN'!F56 * ASSUMPTIONS!$L$25 -> 0 | G33: ='PRODUCT PRICING & REVENUE ENGIN'!G56 * ASSUMPTIONS!$L$25 -> 0 | H33: ='PRODUCT PRICING & REVENUE ENGIN'!H56 * ASSUMPTIONS!$L$25 -> 0 | I33: ='PRODUCT PRICING & REVENUE ENGIN'!I56 * ASSUMPTIONS!$L$25 -> 0 | J33: ='PRODUCT PRICING & REVENUE ENGIN'!J56 * ASSUMPTIONS!$L$25 -> 0 | K33: ='PRODUCT PRICING & REVENUE ENGIN'!K56 * ASSUMPTIONS!$L$25 -> 102115.58 | L33: ='PRODUCT PRICING & REVENUE ENGIN'!L56 * ASSUMPTIONS!$L$25 -> 102115.58 | ... BL33: ='PRODUCT PRICING & REVENUE ENGIN'!BL56 * ASSUMPTIONS!$L$25 -> 865959.17
D34: Peda | E34: ='PRODUCT PRICING & REVENUE ENGIN'!E57 * ASSUMPTIONS!$L$26 -> 0 | F34: ='PRODUCT PRICING & REVENUE ENGIN'!F57 * ASSUMPTIONS!$L$26 -> 0 | G34: ='PRODUCT PRICING & REVENUE ENGIN'!G57 * ASSUMPTIONS!$L$26 -> 0 | H34: ='PRODUCT PRICING & REVENUE ENGIN'!H57 * ASSUMPTIONS!$L$26 -> 0 | I34: ='PRODUCT PRICING & REVENUE ENGIN'!I57 * ASSUMPTIONS!$L$26 -> 0 | J34: ='PRODUCT PRICING & REVENUE ENGIN'!J57 * ASSUMPTIONS!$L$26 -> 0 | K34: ='PRODUCT PRICING & REVENUE ENGIN'!K57 * ASSUMPTIONS!$L$26 -> 153498.24 | L34: ='PRODUCT PRICING & REVENUE ENGIN'!L57 * ASSUMPTIONS!$L$26 -> 153498.24 | ... BL34: ='PRODUCT PRICING & REVENUE ENGIN'!BL57 * ASSUMPTIONS!$L$26 -> 1388813.9
D35: Section C – Feed Cost | E35: =IF(E$15=$E$4, E18 * ASSUMPTIONS!$H$27 * $E$9, IF(E$15=$F$4, E18 * ASSUMPTIONS!$H$27 * $F$9, IF(E$15=$G$4, E18 * ASSUMPTIONS!$H$27 * $G$9, IF(E$15=$H$4, E18 * ASSUMPTIONS!$H$27 * $H$9, IF(E$15=$I$4, E18 * ASSUMPTIONS!$H$27 * $I$9, 0 ))))) -> 0 | F35: =IF(F$15=$E$4, F18 * ASSUMPTIONS!$H$27 * $E$9, IF(F$15=$F$4, F18 * ASSUMPTIONS!$H$27 * $F$9, IF(F$15=$G$4, F18 * ASSUMPTIONS!$H$27 * $G$9, IF(F$15=$H$4, F18 * ASSUMPTIONS!$H$27 * $H$9, IF(F$15=$I$4, F18 * ASSUMPTIONS!$H$27 * $I$9, 0 ))))) -> 0 | G35: =IF(G$15=$E$4, G18 * ASSUMPTIONS!$H$27 * $E$9, IF(G$15=$F$4, G18 * ASSUMPTIONS!$H$27 * $F$9, IF(G$15=$G$4, G18 * ASSUMPTIONS!$H$27 * $G$9, IF(G$15=$H$4, G18 * ASSUMPTIONS!$H$27 * $H$9, IF(G$15=$I$4, G18 * ASSUMPTIONS!$H$27 * $I$9, 0 ))))) -> 0 | H35: =IF(H$15=$E$4, H18 * ASSUMPTIONS!$H$27 * $E$9, IF(H$15=$F$4, H18 * ASSUMPTIONS!$H$27 * $F$9, IF(H$15=$G$4, H18 * ASSUMPTIONS!$H$27 * $G$9, IF(H$15=$H$4, H18 * ASSUMPTIONS!$H$27 * $H$9, IF(H$15=$I$4, H18 * ASSUMPTIONS!$H$27 * $I$9, 0 ))))) -> 0 | I35: =IF(I$15=$E$4, I18 * ASSUMPTIONS!$H$27 * $E$9, IF(I$15=$F$4, I18 * ASSUMPTIONS!$H$27 * $F$9, IF(I$15=$G$4, I18 * ASSUMPTIONS!$H$27 * $G$9, IF(I$15=$H$4, I18 * ASSUMPTIONS!$H$27 * $H$9, IF(I$15=$I$4, I18 * ASSUMPTIONS!$H$27 * $I$9, 0 ))))) -> 550000 | J35: =IF(J$15=$E$4, J18 * ASSUMPTIONS!$H$27 * $E$9, IF(J$15=$F$4, J18 * ASSUMPTIONS!$H$27 * $F$9, IF(J$15=$G$4, J18 * ASSUMPTIONS!$H$27 * $G$9, IF(J$15=$H$4, J18 * ASSUMPTIONS!$H$27 * $H$9, IF(J$15=$I$4, J18 * ASSUMPTIONS!$H$27 * $I$9, 0 ))))) -> 1100000 | K35: =IF(K$15=$E$4, K18 * ASSUMPTIONS!$H$27 * $E$9, IF(K$15=$F$4, K18 * ASSUMPTIONS!$H$27 * $F$9, IF(K$15=$G$4, K18 * ASSUMPTIONS!$H$27 * $G$9, IF(K$15=$H$4, K18 * ASSUMPTIONS!$H$27 * $H$9, IF(K$15=$I$4, K18 * ASSUMPTIONS!$H$27 * $I$9, 0 ))))) -> 1650000 | L35: =IF(L$15=$E$4, L18 * ASSUMPTIONS!$H$27 * $E$9, IF(L$15=$F$4, L18 * ASSUMPTIONS!$H$27 * $F$9, IF(L$15=$G$4, L18 * ASSUMPTIONS!$H$27 * $G$9, IF(L$15=$H$4, L18 * ASSUMPTIONS!$H$27 * $H$9, IF(L$15=$I$4, L18 * ASSUMPTIONS!$H$27 * $I$9, 0 ))))) -> 2200000 | ... BL35: =IF(BL$15=$E$4, BL18 * ASSUMPTIONS!$H$27 * $E$9, IF(BL$15=$F$4, BL18 * ASSUMPTIONS!$H$27 * $F$9, IF(BL$15=$G$4, BL18 * ASSUMPTIONS!$H$27 * $G$9, IF(BL$15=$H$4, BL18 * ASSUMPTIONS!$H$27 * $H$9, IF(BL$15=$I$4, BL18 * ASSUMPTIONS!$H$27 * $I$9, 0 ))))) -> 38884290
D36: Section D – Freight & Distribution | E36: =IF(E$15=$E$4, 'PRODUCT PRICING & REVENUE ENGIN'!E58 * ASSUMPTIONS!$H$33 * $E$10, IF(E$15=$F$4, 'PRODUCT PRICING & REVENUE ENGIN'!E58 * ASSUMPTIONS!$H$33 * $F$10, IF(E$15=$G$4, 'PRODUCT PRICING & REVENUE ENGIN'!E58 * ASSUMPTIONS!$H$33 * $G$10, IF(E$15=$H$4, 'PRODUCT PRICING & REVENUE ENGIN'!E58 * ASSUMPTIONS!$H$33 * $H$10, IF(E$15=$I$4, 'PRODUCT PRICING & REVENUE ENGIN'!E58 * ASSUMPTIONS!$H$33 * $I$10, 0 ))))) -> 0 | F36: =IF(F$15=$E$4, 'PRODUCT PRICING & REVENUE ENGIN'!F58 * ASSUMPTIONS!$H$33 * $E$10, IF(F$15=$F$4, 'PRODUCT PRICING & REVENUE ENGIN'!F58 * ASSUMPTIONS!$H$33 * $F$10, IF(F$15=$G$4, 'PRODUCT PRICING & REVENUE ENGIN'!F58 * ASSUMPTIONS!$H$33 * $G$10, IF(F$15=$H$4, 'PRODUCT PRICING & REVENUE ENGIN'!F58 * ASSUMPTIONS!$H$33 * $H$10, IF(F$15=$I$4, 'PRODUCT PRICING & REVENUE ENGIN'!F58 * ASSUMPTIONS!$H$33 * $I$10, 0 ))))) -> 0 | G36: =IF(G$15=$E$4, 'PRODUCT PRICING & REVENUE ENGIN'!G58 * ASSUMPTIONS!$H$33 * $E$10, IF(G$15=$F$4, 'PRODUCT PRICING & REVENUE ENGIN'!G58 * ASSUMPTIONS!$H$33 * $F$10, IF(G$15=$G$4, 'PRODUCT PRICING & REVENUE ENGIN'!G58 * ASSUMPTIONS!$H$33 * $G$10, IF(G$15=$H$4, 'PRODUCT PRICING & REVENUE ENGIN'!G58 * ASSUMPTIONS!$H$33 * $H$10, IF(G$15=$I$4, 'PRODUCT PRICING & REVENUE ENGIN'!G58 * ASSUMPTIONS!$H$33 * $I$10, 0 ))))) -> 0 | H36: =IF(H$15=$E$4, 'PRODUCT PRICING & REVENUE ENGIN'!H58 * ASSUMPTIONS!$H$33 * $E$10, IF(H$15=$F$4, 'PRODUCT PRICING & REVENUE ENGIN'!H58 * ASSUMPTIONS!$H$33 * $F$10, IF(H$15=$G$4, 'PRODUCT PRICING & REVENUE ENGIN'!H58 * ASSUMPTIONS!$H$33 * $G$10, IF(H$15=$H$4, 'PRODUCT PRICING & REVENUE ENGIN'!H58 * ASSUMPTIONS!$H$33 * $H$10, IF(H$15=$I$4, 'PRODUCT PRICING & REVENUE ENGIN'!H58 * ASSUMPTIONS!$H$33 * $I$10, 0 ))))) -> 0 | I36: =IF(I$15=$E$4, 'PRODUCT PRICING & REVENUE ENGIN'!I58 * ASSUMPTIONS!$H$33 * $E$10, IF(I$15=$F$4, 'PRODUCT PRICING & REVENUE ENGIN'!I58 * ASSUMPTIONS!$H$33 * $F$10, IF(I$15=$G$4, 'PRODUCT PRICING & REVENUE ENGIN'!I58 * ASSUMPTIONS!$H$33 * $G$10, IF(I$15=$H$4, 'PRODUCT PRICING & REVENUE ENGIN'!I58 * ASSUMPTIONS!$H$33 * $H$10, IF(I$15=$I$4, 'PRODUCT PRICING & REVENUE ENGIN'!I58 * ASSUMPTIONS!$H$33 * $I$10, 0 ))))) -> 167091.72 | J36: =IF(J$15=$E$4, 'PRODUCT PRICING & REVENUE ENGIN'!J58 * ASSUMPTIONS!$H$33 * $E$10, IF(J$15=$F$4, 'PRODUCT PRICING & REVENUE ENGIN'!J58 * ASSUMPTIONS!$H$33 * $F$10, IF(J$15=$G$4, 'PRODUCT PRICING & REVENUE ENGIN'!J58 * ASSUMPTIONS!$H$33 * $G$10, IF(J$15=$H$4, 'PRODUCT PRICING & REVENUE ENGIN'!J58 * ASSUMPTIONS!$H$33 * $H$10, IF(J$15=$I$4, 'PRODUCT PRICING & REVENUE ENGIN'!J58 * ASSUMPTIONS!$H$33 * $I$10, 0 ))))) -> 334183.45 | K36: =IF(K$15=$E$4, 'PRODUCT PRICING & REVENUE ENGIN'!K58 * ASSUMPTIONS!$H$33 * $E$10, IF(K$15=$F$4, 'PRODUCT PRICING & REVENUE ENGIN'!K58 * ASSUMPTIONS!$H$33 * $F$10, IF(K$15=$G$4, 'PRODUCT PRICING & REVENUE ENGIN'!K58 * ASSUMPTIONS!$H$33 * $G$10, IF(K$15=$H$4, 'PRODUCT PRICING & REVENUE ENGIN'!K58 * ASSUMPTIONS!$H$33 * $H$10, IF(K$15=$I$4, 'PRODUCT PRICING & REVENUE ENGIN'!K58 * ASSUMPTIONS!$H$33 * $I$10, 0 ))))) -> 1368251.2 | L36: =IF(L$15=$E$4, 'PRODUCT PRICING & REVENUE ENGIN'!L58 * ASSUMPTIONS!$H$33 * $E$10, IF(L$15=$F$4, 'PRODUCT PRICING & REVENUE ENGIN'!L58 * ASSUMPTIONS!$H$33 * $F$10, IF(L$15=$G$4, 'PRODUCT PRICING & REVENUE ENGIN'!L58 * ASSUMPTIONS!$H$33 * $G$10, IF(L$15=$H$4, 'PRODUCT PRICING & REVENUE ENGIN'!L58 * ASSUMPTIONS!$H$33 * $H$10, IF(L$15=$I$4, 'PRODUCT PRICING & REVENUE ENGIN'!L58 * ASSUMPTIONS!$H$33 * $I$10, 0 ))))) -> 1535343 | ... BL36: =IF(BL$15=$E$4, 'PRODUCT PRICING & REVENUE ENGIN'!BL58 * ASSUMPTIONS!$H$33 * $E$10, IF(BL$15=$F$4, 'PRODUCT PRICING & REVENUE ENGIN'!BL58 * ASSUMPTIONS!$H$33 * $F$10, IF(BL$15=$G$4, 'PRODUCT PRICING & REVENUE ENGIN'!BL58 * ASSUMPTIONS!$H$33 * $G$10, IF(BL$15=$H$4, 'PRODUCT PRICING & REVENUE ENGIN'!BL58 * ASSUMPTIONS!$H$33 * $H$10, IF(BL$15=$I$4, 'PRODUCT PRICING & REVENUE ENGIN'!BL58 * ASSUMPTIONS!$H$33 * $I$10, 0 ))))) -> 23848173
D37: Section E – Processing Cost | E37: =E22 * ASSUMPTIONS!$H$34 -> 0 | F37: =F22 * ASSUMPTIONS!$H$34 -> 0 | G37: =G22 * ASSUMPTIONS!$H$34 -> 0 | H37: =H22 * ASSUMPTIONS!$H$34 -> 0 | I37: =I22 * ASSUMPTIONS!$H$34 -> 0 | J37: =J22 * ASSUMPTIONS!$H$34 -> 0 | K37: =K22 * ASSUMPTIONS!$H$34 -> 375000 | L37: =L22 * ASSUMPTIONS!$H$34 -> 375000 | ... BL37: =BL22 * ASSUMPTIONS!$H$34 -> 2250000
D38: Section F – Utilities | E38: ='PRODUCT PRICING & REVENUE ENGIN'!E58 * ASSUMPTIONS!$H$57 -> 0 | F38: ='PRODUCT PRICING & REVENUE ENGIN'!F58 * ASSUMPTIONS!$H$57 -> 0 | G38: ='PRODUCT PRICING & REVENUE ENGIN'!G58 * ASSUMPTIONS!$H$57 -> 0 | H38: ='PRODUCT PRICING & REVENUE ENGIN'!H58 * ASSUMPTIONS!$H$57 -> 0 | I38: ='PRODUCT PRICING & REVENUE ENGIN'!I58 * ASSUMPTIONS!$H$57 -> 23870.246 | J38: ='PRODUCT PRICING & REVENUE ENGIN'!J58 * ASSUMPTIONS!$H$57 -> 47740.493 | K38: ='PRODUCT PRICING & REVENUE ENGIN'!K58 * ASSUMPTIONS!$H$57 -> 195464.46 | L38: ='PRODUCT PRICING & REVENUE ENGIN'!L58 * ASSUMPTIONS!$H$57 -> 219334.71 | ... BL38: ='PRODUCT PRICING & REVENUE ENGIN'!BL58 * ASSUMPTIONS!$H$57 -> 2802850.2
D39: Section G – Total COGS | E39: =E21 + E24 +E26 +E27 +E28 +E29 +E30 +E31 +E32 +E33 +E34 + E35 + E36 + E37 + E38 -> 0 | F39: =F21 + F24 +F26 +F27 +F28 +F29 +F30 +F31 +F32 +F33 +F34 + F35 + F36 + F37 + F38 -> 0 | G39: =G21 + G24 +G26 +G27 +G28 +G29 +G30 +G31 +G32 +G33 +G34 + G35 + G36 + G37 + G38 -> 0 | H39: =H21 + H24 +H26 +H27 +H28 +H29 +H30 +H31 +H32 +H33 +H34 + H35 + H36 + H37 + H38 -> 0 | I39: =I21 + I24 +I26 +I27 +I28 +I29 +I30 +I31 +I32 +I33 +I34 + I35 + I36 + I37 + I38 -> 1892443 | J39: =J21 + J24 +J26 +J27 +J28 +J29 +J30 +J31 +J32 +J33 +J34 + J35 + J36 + J37 + J38 -> 3784885.9 | K39: =K21 + K24 +K26 +K27 +K28 +K29 +K30 +K31 +K32 +K33 +K34 + K35 + K36 + K37 + K38 -> 15294868 | L39: =L21 + L24 +L26 +L27 +L28 +L29 +L30 +L31 +L32 +L33 +L34 + L35 + L36 + L37 + L38 -> 17187311 | ... BL39: =BL21 + BL24 +BL26 +BL27 +BL28 +BL29 +BL30 +BL31 +BL32 +BL33 +BL34 + BL35 + BL36 + BL37 + BL38 -> 2.0855088e+08
D40: Section H – Gross Profit | E40: ='PRODUCT PRICING & REVENUE ENGIN'!E58 - E39 -> 0 | F40: ='PRODUCT PRICING & REVENUE ENGIN'!F58 - F39 -> 0 | G40: ='PRODUCT PRICING & REVENUE ENGIN'!G58 - G39 -> 0 | H40: ='PRODUCT PRICING & REVENUE ENGIN'!H58 - H39 -> 0 | I40: ='PRODUCT PRICING & REVENUE ENGIN'!I58 - I39 -> 494581.68 | J40: ='PRODUCT PRICING & REVENUE ENGIN'!J58 - J39 -> 989163.37 | K40: ='PRODUCT PRICING & REVENUE ENGIN'!K58 - K39 -> 4251578 | L40: ='PRODUCT PRICING & REVENUE ENGIN'!L58 - L39 -> 4746159.7 | ... BL40: ='PRODUCT PRICING & REVENUE ENGIN'!BL58 - BL39 -> 71734135
D41: Section I – Gross Margin % | E41: =IF( E40 = 0, 0, E40 / 'PRODUCT PRICING & REVENUE ENGIN'!E58) -> 0 | F41: =IF( F40 = 0, 0, F40 / 'PRODUCT PRICING & REVENUE ENGIN'!F58) -> 0 | G41: =IF( G40 = 0, 0, G40 / 'PRODUCT PRICING & REVENUE ENGIN'!G58) -> 0 | H41: =IF( H40 = 0, 0, H40 / 'PRODUCT PRICING & REVENUE ENGIN'!H58) -> 0 | I41: =IF( I40 = 0, 0, I40 / 'PRODUCT PRICING & REVENUE ENGIN'!I58) -> 0.20719589 | J41: =IF( J40 = 0, 0, J40 / 'PRODUCT PRICING & REVENUE ENGIN'!J58) -> 0.20719589 | K41: =IF( K40 = 0, 0, K40 / 'PRODUCT PRICING & REVENUE ENGIN'!K58) -> 0.21751156 | L41: =IF( L40 = 0, 0, L40 / 'PRODUCT PRICING & REVENUE ENGIN'!L58) -> 0.2163889 | ... BL41: =IF( BL40 = 0, 0, BL40 / 'PRODUCT PRICING & REVENUE ENGIN'!BL58) -> 0.25593282

Sheet HR & OPERATING EXPENSES
A1: =COVER!$B$12 -> Narayan Dairy Project
A2: HR & Operating Expenses
D4: Expense | E4: Role | F4: Headcount | G4: Avg Monthly Salary | H4: Monthly Cost | I4: Start Month
D7: Section A – HR Cost
D8: Land | E8: Lease | G8: 100000 | H8: =G8 -> 100000 | I8: 30
D9: Management | E9: General Manager | F9: 1 | G9: 60000 | H9: =F9 * G9 -> 60000 | I9: 1
D10: Plant Operations | E10: Shift Manager | F10: 3 | G10: 30000 | H10: =F10 * G10 -> 90000 | I10: 5
D11: Quality Control | E11: Chemist | F11: 4 | G11: 30000 | H11: =F11 * G11 -> 120000 | I11: 6
D12: Quality Control | E12: Microbiologist | F12: 2 | G12: 40000 | H12: =F12 * G12 -> 80000 | I12: 6
D13: Plant Operations | E13: Process Operator | F13: 4 | G13: 30000 | H13: =F13 * G13 -> 120000 | I13: 6
D14: Plant Operations | E14: Powder Plant Operator | F14: 4 | G14: 35000 | H14: =F14 * G14 -> 140000 | I14: 7
D15: Plant Operations | E15: Poly Pack Operator | F15: 2 | G15: 25000 | H15: =F15 * G15 -> 50000 | I15: 7
D16: Plant Operations | E16: Ghee & Butter Operator | F16: 2 | G16: 30000 | H16: =F16 * G16 -> 60000 | I16: 8
D17: Admin | E17: Reception Supervisor | F17: 2 | G17: 25000 | H17: =F17 * G17 -> 50000 | I17: 1
D18: Logistics | E18: Dispatch | F18: 3 | G18: 25000 | H18: =F18 * G18 -> 75000 | I18: 7
D19: Support Staff | E19: Unskilled Labour | F19: 100 | G19: =50 * 30 -> 1500 | H19: =F19 * G19 -> 150000 | I19: 6
D20: Maintenance | E20: Fitter/Welder/Electrician | F20: 3 | G20: 20000 | H20: =F20 * G20 -> 60000 | I20: 5
D21: Support Staff | E21: Sweeper | F21: 2 | G21: 15000 | H21: =F21 * G21 -> 30000 | I21: 5
D22: Security | E22: Security Staff | F22: 4 | G22: 15000 | H22: =F22 * G22 -> 60000 | I22: 1
D23: Admin | E23: Accounts | F23: 2 | G23: 30000 | H23: =F23 * G23 -> 60000 | I23: 1
D24: Farm Operations | E24: Veterinary Doctor | F24: 2 | G24: =50 * 30 -> 1500 | H24: =F24 * G24 -> 3000 | I24: 1
D25: Farm Operations | E25: Skilled Farm Supervisor | F25: 6 | G25: =50 * 30 -> 1500 | H25: =F25 * G25 -> 9000 | I25: 1
D27: Product / Year | E27: 1 | F27: 2 | G27: 3 | H27: 4 | I27: 5
D30: Section B – Salary Escalation Factor Schedule
D31: Salary Inflation | E31: =1 -> 1 | F31: =E31 * (1 + ASSUMPTIONS!$H$39) -> 1.08 | G31: =F31 * (1 + ASSUMPTIONS!$H$39) -> 1.1664 | H31: =G31 * (1 + ASSUMPTIONS!$H$39) -> 1.259712 | I31: =H31 * (1 + ASSUMPTIONS!$H$39) -> 1.360489
D33: Product / Month / Year | E33: 1 | F33: =E33+1 -> 2 | G33: =F33+1 -> 3 | H33: =G33+1 -> 4 | I33: =H33+1 -> 5 | J33: =I33+1 -> 6 | K33: =J33+1 -> 7 | L33: =K33+1 -> 8 | M33: =L33+1 -> 9 | ... BL33: =BK33+1 -> 60
E36: =INT((E33 - 1) / 12) +1 -> 1 | F36: =INT((F33 - 1) / 12) +1 -> 1 | G36: =INT((G33 - 1) / 12) +1 -> 1 | H36: =INT((H33 - 1) / 12) +1 -> 1 | I36: =INT((I33 - 1) / 12) +1 -> 1 | J36: =INT((J33 - 1) / 12) +1 -> 1 | K36: =INT((K33 - 1) / 12) +1 -> 1 | L36: =INT((L33 - 1) / 12) +1 -> 1 | ... BL36: =INT((BL33 - 1) / 12) +1 -> 5
D38: ='MILK FLOW ENGINE'!D8 -> Own Livestock (units) | E38: ='MILK FLOW ENGINE'!E8 -> 0 | F38: ='MILK FLOW ENGINE'!F8 -> 0 | G38: ='MILK FLOW ENGINE'!G8 -> 0 | H38: ='MILK FLOW ENGINE'!H8 -> 0 | I38: ='MILK FLOW ENGINE'!I8 -> 50 | J38: ='MILK FLOW ENGINE'!J8 -> 100 | K38: ='MILK FLOW ENGINE'!K8 -> 150 | ... BL38: ='MILK FLOW ENGINE'!BL8 -> 2800
D39: =E19 -> Unskilled Labour | E39: =ROUNDUP((E38 * 4)/50,0) -> 0 | F39: =ROUNDUP((F38 * 4)/50,0) -> 0 | G39: =ROUNDUP((G38 * 4)/50,0) -> 0 | H39: =ROUNDUP((H38 * 4)/50,0) -> 0 | I39: =ROUNDUP((I38 * 4)/50,0) -> 4 | J39: =ROUNDUP((J38 * 4)/50,0) -> 8 | K39: =ROUNDUP((K38 * 4)/50,0) -> 12 | L39: =ROUNDUP((L38 * 4)/50,0) -> 16 | ... BL39: =ROUNDUP((BL38 * 4)/50,0) -> 224
D40: =E25 -> Skilled Farm Supervisor | E40: =ROUNDUP((E38 * 2)/50,0) -> 0 | F40: =ROUNDUP((F38 * 2)/50,0) -> 0 | G40: =ROUNDUP((G38 * 2)/50,0) -> 0 | H40: =ROUNDUP((H38 * 2)/50,0) -> 0 | I40: =ROUNDUP((I38 * 2)/50,0) -> 2 | J40: =ROUNDUP((J38 * 2)/50,0) -> 4 | K40: =ROUNDUP((K38 * 2)/50,0) -> 6 | L40: =ROUNDUP((L38 * 2)/50,0) -> 8 | ... BL40: =ROUNDUP((BL38 * 2)/50,0) -> 112
D41: Section B – HR & Operating Schedule
D42: =E8 -> Lease | E42: {=IFS(AND(E$36=$E$27,E$33>=$I8),$H8*$E$31, AND(E$36=$F$27,E$33>=$I8),$H8*$F$31, AND(E$36=$G$27,E$33>=$I8),$H8*$G$31, AND(E$36=$H$27,E$33>=$I8),$H8*$H$31, AND(E$36=$I$27,E$33>=$I8),$H8*$I$31, TRUE, 0 )} -> 0 | F42: {=IFS(AND(F$36=$E$27,F$33>=$I8),$H8*$E$31, AND(F$36=$F$27,F$33>=$I8),$H8*$F$31, AND(F$36=$G$27,F$33>=$I8),$H8*$G$31, AND(F$36=$H$27,F$33>=$I8),$H8*$H$31, AND(F$36=$I$27,F$33>=$I8),$H8*$I$31, TRUE, 0 )} -> 0 | G42: {=IFS(AND(G$36=$E$27,G$33>=$I8),$H8*$E$31, AND(G$36=$F$27,G$33>=$I8),$H8*$F$31, AND(G$36=$G$27,G$33>=$I8),$H8*$G$31, AND(G$36=$H$27,G$33>=$I8),$H8*$H$31, AND(G$36=$I$27,G$33>=$I8),$H8*$I$31, TRUE, 0 )} -> 0 | H42: {=IFS(AND(H$36=$E$27,H$33>=$I8),$H8*$E$31, AND(H$36=$F$27,H$33>=$I8),$H8*$F$31, AND(H$36=$G$27,H$33>=$I8),$H8*$G$31, AND(H$36=$H$27,H$33>=$I8),$H8*$H$31, AND(H$36=$I$27,H$33>=$I8),$H8*$I$31, TRUE, 0 )} -> 0 | I42: {=IFS(AND(I$36=$E$27,I$33>=$I8),$H8*$E$31, AND(I$36=$F$27,I$33>=$I8),$H8*$F$31, AND(I$36=$G$27,I$33>=$I8),$H8*$G$31, AND(I$36=$H$27,I$33>=$I8),$H8*$H$31, AND(I$36=$I$27,I$33>=$I8),$H8*$I$31, TRUE, 0 )} -> 0 | J42: {=IFS(AND(J$36=$E$27,J$33>=$I8),$H8*$E$31, AND(J$36=$F$27,J$33>=$I8),$H8*$F$31, AND(J$36=$G$27,J$33>=$I8),$H8*$G$31, AND(J$36=$H$27,J$33>=$I8),$H8*$H$31, AND(J$36=$I$27,J$33>=$I8),$H8*$I$31, TRUE, 0 )} -> 0 | K42: {=IFS(AND(K$36=$E$27,K$33>=$I8),$H8*$E$31, AND(K$36=$F$27,K$33>=$I8),$H8*$F$31, AND(K$36=$G$27,K$33>=$I8),$H8*$G$31, AND(K$36=$H$27,K$33>=$I8),$H8*$H$31, AND(K$36=$I$27,K$33>=$I8),$H8*$I$31, TRUE, 0 )} -> 0 | L42: {=IFS(AND(L$36=$E$27,L$33>=$I8),$H8*$E$31, AND(L$36=$F$27,L$33>=$I8),$H8*$F$31, AND(L$36=$G$27,L$33>=$I8),$H8*$G$31, AND(L$36=$H$27,L$33>=$I8),$H8*$H$31, AND(L$36=$I$27,L$33>=$I8),$H8*$I$31, TRUE, 0 )} -> 0 | ... BL42: {=IFS(AND(BL$36=$E$27,BL$33>=$I8),$H8*$E$31, AND(BL$36=$F$27,BL$33>=$I8),$H8*$F$31, AND(BL$36=$G$27,BL$33>=$I8),$H8*$G$31, AND(BL$36=$H$27,BL$33>=$I8),$H8*$H$31, AND(BL$36=$I$27,BL$33>=$I8),$H8*$I$31, TRUE, 0 )} -> 136048.9
D43: General Manager | E43: {=IFS(AND(E$36=$E$27,E$33>=$I9),$H9*$E$31, AND(E$36=$F$27,E$33>=$I9),$H9*$F$31, AND(E$36=$G$27,E$33>=$I9),$H9*$G$31, AND(E$36=$H$27,E$33>=$I9),$H9*$H$31, AND(E$36=$I$27,E$33>=$I9),$H9*$I$31, TRUE, 0 )} -> 60000 | F43: {=IFS(AND(F$36=$E$27,F$33>=$I9),$H9*$E$31, AND(F$36=$F$27,F$33>=$I9),$H9*$F$31, AND(F$36=$G$27,F$33>=$I9),$H9*$G$31, AND(F$36=$H$27,F$33>=$I9),$H9*$H$31, AND(F$36=$I$27,F$33>=$I9),$H9*$I$31, TRUE, 0 )} -> 60000 | G43: {=IFS(AND(G$36=$E$27,G$33>=$I9),$H9*$E$31, AND(G$36=$F$27,G$33>=$I9),$H9*$F$31, AND(G$36=$G$27,G$33>=$I9),$H9*$G$31, AND(G$36=$H$27,G$33>=$I9),$H9*$H$31, AND(G$36=$I$27,G$33>=$I9),$H9*$I$31, TRUE, 0 )} -> 60000 | H43: {=IFS(AND(H$36=$E$27,H$33>=$I9),$H9*$E$31, AND(H$36=$F$27,H$33>=$I9),$H9*$F$31, AND(H$36=$G$27,H$33>=$I9),$H9*$G$31, AND(H$36=$H$27,H$33>=$I9),$H9*$H$31, AND(H$36=$I$27,H$33>=$I9),$H9*$I$31, TRUE, 0 )} -> 60000 | I43: {=IFS(AND(I$36=$E$27,I$33>=$I9),$H9*$E$31, AND(I$36=$F$27,I$33>=$I9),$H9*$F$31, AND(I$36=$G$27,I$33>=$I9),$H9*$G$31, AND(I$36=$H$27,I$33>=$I9),$H9*$H$31, AND(I$36=$I$27,I$33>=$I9),$H9*$I$31, TRUE, 0 )} -> 60000 | J43: {=IFS(AND(J$36=$E$27,J$33>=$I9),$H9*$E$31, AND(J$36=$F$27,J$33>=$I9),$H9*$F$31, AND(J$36=$G$27,J$33>=$I9),$H9*$G$31, AND(J$36=$H$27,J$33>=$I9),$H9*$H$31, AND(J$36=$I$27,J$33>=$I9),$H9*$I$31, TRUE, 0 )} -> 60000 | K43: {=IFS(AND(K$36=$E$27,K$33>=$I9),$H9*$E$31, AND(K$36=$F$27,K$33>=$I9),$H9*$F$31, AND(K$36=$G$27,K$33>=$I9),$H9*$G$31, AND(K$36=$H$27,K$33>=$I9),$H9*$H$31, AND(K$36=$I$27,K$33>=$I9),$H9*$I$31, TRUE, 0 )} -> 60000 | L43: {=IFS(AND(L$36=$E$27,L$33>=$I9),$H9*$E$31, AND(L$36=$F$27,L$33>=$I9),$H9*$F$31, AND(L$36=$G$27,L$33>=$I9),$H9*$G$31, AND(L$36=$H$27,L$33>=$I9),$H9*$H$31, AND(L$36=$I$27,L$33>=$I9),$H9*$I$31, TRUE, 0 )} -> 60000 | ... BL43: {=IFS(AND(BL$36=$E$27,BL$33>=$I9),$H9*$E$31, AND(BL$36=$F$27,BL$33>=$I9),$H9*$F$31, AND(BL$36=$G$27,BL$33>=$I9),$H9*$G$31, AND(BL$36=$H$27,BL$33>=$I9),$H9*$H$31, AND(BL$36=$I$27,BL$33>=$I9),$H9*$I$31, TRUE, 0 )} -> 81629.338
D44: Shift Manager | E44: =IFS( AND(E$36=$E$27,E$33>=$I10),$H10*$E$31, AND(E$36=$F$27,E$33>=$I10),$H10*$F$31, AND(E$36=$G$27,E$33>=$I10),$H10*$G$31, AND(E$36=$H$27,E$33>=$I10),$H10*$H$31, AND(E$36=$I$27,E$33>=$I10),$H10*$I$31, TRUE, 0 ) -> 0 | F44: =IFS( AND(F$36=$E$27,F$33>=$I10),$H10*$E$31, AND(F$36=$F$27,F$33>=$I10),$H10*$F$31, AND(F$36=$G$27,F$33>=$I10),$H10*$G$31, AND(F$36=$H$27,F$33>=$I10),$H10*$H$31, AND(F$36=$I$27,F$33>=$I10),$H10*$I$31, TRUE, 0 ) -> 0 | G44: =IFS( AND(G$36=$E$27,G$33>=$I10),$H10*$E$31, AND(G$36=$F$27,G$33>=$I10),$H10*$F$31, AND(G$36=$G$27,G$33>=$I10),$H10*$G$31, AND(G$36=$H$27,G$33>=$I10),$H10*$H$31, AND(G$36=$I$27,G$33>=$I10),$H10*$I$31, TRUE, 0 ) -> 0 | H44: =IFS( AND(H$36=$E$27,H$33>=$I10),$H10*$E$31, AND(H$36=$F$27,H$33>=$I10),$H10*$F$31, AND(H$36=$G$27,H$33>=$I10),$H10*$G$31, AND(H$36=$H$27,H$33>=$I10),$H10*$H$31, AND(H$36=$I$27,H$33>=$I10),$H10*$I$31, TRUE, 0 ) -> 0 | I44: =IFS( AND(I$36=$E$27,I$33>=$I10),$H10*$E$31, AND(I$36=$F$27,I$33>=$I10),$H10*$F$31, AND(I$36=$G$27,I$33>=$I10),$H10*$G$31, AND(I$36=$H$27,I$33>=$I10),$H10*$H$31, AND(I$36=$I$27,I$33>=$I10),$H10*$I$31, TRUE, 0 ) -> 90000 | J44: =IFS( AND(J$36=$E$27,J$33>=$I10),$H10*$E$31, AND(J$36=$F$27,J$33>=$I10),$H10*$F$31, AND(J$36=$G$27,J$33>=$I10),$H10*$G$31, AND(J$36=$H$27,J$33>=$I10),$H10*$H$31, AND(J$36=$I$27,J$33>=$I10),$H10*$I$31, TRUE, 0 ) -> 90000 | K44: =IFS( AND(K$36=$E$27,K$33>=$I10),$H10*$E$31, AND(K$36=$F$27,K$33>=$I10),$H10*$F$31, AND(K$36=$G$27,K$33>=$I10),$H10*$G$31, AND(K$36=$H$27,K$33>=$I10),$H10*$H$31, AND(K$36=$I$27,K$33>=$I10),$H10*$I$31, TRUE, 0 ) -> 90000 | L44: =IFS( AND(L$36=$E$27,L$33>=$I10),$H10*$E$31, AND(L$36=$F$27,L$33>=$I10),$H10*$F$31, AND(L$36=$G$27,L$33>=$I10),$H10*$G$31, AND(L$36=$H$27,L$33>=$I10),$H10*$H$31, AND(L$36=$I$27,L$33>=$I10),$H10*$I$31, TRUE, 0 ) -> 90000 | ... BL44: =IFS( AND(BL$36=$E$27,BL$33>=$I10),$H10*$E$31, AND(BL$36=$F$27,BL$33>=$I10),$H10*$F$31, AND(BL$36=$G$27,BL$33>=$I10),$H10*$G$31, AND(BL$36=$H$27,BL$33>=$I10),$H10*$H$31, AND(BL$36=$I$27,BL$33>=$I10),$H10*$I$31, TRUE, 0 ) -> 122444.01
D45: Chemist | E45: =IFS( AND(E$36=$E$27,E$33>=$I11),$H11*$E$31, AND(E$36=$F$27,E$33>=$I11),$H11*$F$31, AND(E$36=$G$27,E$33>=$I11),$H11*$G$31, AND(E$36=$H$27,E$33>=$I11),$H11*$H$31, AND(E$36=$I$27,E$33>=$I11),$H11*$I$31, TRUE, 0 ) -> 0 | F45: =IFS( AND(F$36=$E$27,F$33>=$I11),$H11*$E$31, AND(F$36=$F$27,F$33>=$I11),$H11*$F$31, AND(F$36=$G$27,F$33>=$I11),$H11*$G$31, AND(F$36=$H$27,F$33>=$I11),$H11*$H$31, AND(F$36=$I$27,F$33>=$I11),$H11*$I$31, TRUE, 0 ) -> 0 | G45: =IFS( AND(G$36=$E$27,G$33>=$I11),$H11*$E$31, AND(G$36=$F$27,G$33>=$I11),$H11*$F$31, AND(G$36=$G$27,G$33>=$I11),$H11*$G$31, AND(G$36=$H$27,G$33>=$I11),$H11*$H$31, AND(G$36=$I$27,G$33>=$I11),$H11*$I$31, TRUE, 0 ) -> 0 | H45: =IFS( AND(H$36=$E$27,H$33>=$I11),$H11*$E$31, AND(H$36=$F$27,H$33>=$I11),$H11*$F$31, AND(H$36=$G$27,H$33>=$I11),$H11*$G$31, AND(H$36=$H$27,H$33>=$I11),$H11*$H$31, AND(H$36=$I$27,H$33>=$I11),$H11*$I$31, TRUE, 0 ) -> 0 | I45: =IFS( AND(I$36=$E$27,I$33>=$I11),$H11*$E$31, AND(I$36=$F$27,I$33>=$I11),$H11*$F$31, AND(I$36=$G$27,I$33>=$I11),$H11*$G$31, AND(I$36=$H$27,I$33>=$I11),$H11*$H$31, AND(I$36=$I$27,I$33>=$I11),$H11*$I$31, TRUE, 0 ) -> 0 | J45: =IFS( AND(J$36=$E$27,J$33>=$I11),$H11*$E$31, AND(J$36=$F$27,J$33>=$I11),$H11*$F$31, AND(J$36=$G$27,J$33>=$I11),$H11*$G$31, AND(J$36=$H$27,J$33>=$I11),$H11*$H$31, AND(J$36=$I$27,J$33>=$I11),$H11*$I$31, TRUE, 0 ) -> 120000 | K45: =IFS( AND(K$36=$E$27,K$33>=$I11),$H11*$E$31, AND(K$36=$F$27,K$33>=$I11),$H11*$F$31, AND(K$36=$G$27,K$33>=$I11),$H11*$G$31, AND(K$36=$H$27,K$33>=$I11),$H11*$H$31, AND(K$36=$I$27,K$33>=$I11),$H11*$I$31, TRUE, 0 ) -> 120000 | L45: =IFS( AND(L$36=$E$27,L$33>=$I11),$H11*$E$31, AND(L$36=$F$27,L$33>=$I11),$H11*$F$31, AND(L$36=$G$27,L$33>=$I11),$H11*$G$31, AND(L$36=$H$27,L$33>=$I11),$H11*$H$31, AND(L$36=$I$27,L$33>=$I11),$H11*$I$31, TRUE, 0 ) -> 120000 | ... BL45: =IFS( AND(BL$36=$E$27,BL$33>=$I11),$H11*$E$31, AND(BL$36=$F$27,BL$33>=$I11),$H11*$F$31, AND(BL$36=$G$27,BL$33>=$I11),$H11*$G$31, AND(BL$36=$H$27,BL$33>=$I11),$H11*$H$31, AND(BL$36=$I$27,BL$33>=$I11),$H11*$I$31, TRUE, 0 ) -> 163258.68
D46: Microbiologist | E46: =IFS( AND(E$36=$E$27,E$33>=$I12),$H12*$E$31, AND(E$36=$F$27,E$33>=$I12),$H12*$F$31, AND(E$36=$G$27,E$33>=$I12),$H12*$G$31, AND(E$36=$H$27,E$33>=$I12),$H12*$H$31, AND(E$36=$I$27,E$33>=$I12),$H12*$I$31, TRUE, 0 ) -> 0 | F46: =IFS( AND(F$36=$E$27,F$33>=$I12),$H12*$E$31, AND(F$36=$F$27,F$33>=$I12),$H12*$F$31, AND(F$36=$G$27,F$33>=$I12),$H12*$G$31, AND(F$36=$H$27,F$33>=$I12),$H12*$H$31, AND(F$36=$I$27,F$33>=$I12),$H12*$I$31, TRUE, 0 ) -> 0 | G46: =IFS( AND(G$36=$E$27,G$33>=$I12),$H12*$E$31, AND(G$36=$F$27,G$33>=$I12),$H12*$F$31, AND(G$36=$G$27,G$33>=$I12),$H12*$G$31, AND(G$36=$H$27,G$33>=$I12),$H12*$H$31, AND(G$36=$I$27,G$33>=$I12),$H12*$I$31, TRUE, 0 ) -> 0 | H46: =IFS( AND(H$36=$E$27,H$33>=$I12),$H12*$E$31, AND(H$36=$F$27,H$33>=$I12),$H12*$F$31, AND(H$36=$G$27,H$33>=$I12),$H12*$G$31, AND(H$36=$H$27,H$33>=$I12),$H12*$H$31, AND(H$36=$I$27,H$33>=$I12),$H12*$I$31, TRUE, 0 ) -> 0 | I46: =IFS( AND(I$36=$E$27,I$33>=$I12),$H12*$E$31, AND(I$36=$F$27,I$33>=$I12),$H12*$F$31, AND(I$36=$G$27,I$33>=$I12),$H12*$G$31, AND(I$36=$H$27,I$33>=$I12),$H12*$H$31, AND(I$36=$I$27,I$33>=$I12),$H12*$I$31, TRUE, 0 ) -> 0 | J46: =IFS( AND(J$36=$E$27,J$33>=$I12),$H12*$E$31, AND(J$36=$F$27,J$33>=$I12),$H12*$F$31, AND(J$36=$G$27,J$33>=$I12),$H12*$G$31, AND(J$36=$H$27,J$33>=$I12),$H12*$H$31, AND(J$36=$I$27,J$33>=$I12),$H12*$I$31, TRUE, 0 ) -> 80000 | K46: =IFS( AND(K$36=$E$27,K$33>=$I12),$H12*$E$31, AND(K$36=$F$27,K$33>=$I12),$H12*$F$31, AND(K$36=$G$27,K$33>=$I12),$H12*$G$31, AND(K$36=$H$27,K$33>=$I12),$H12*$H$31, AND(K$36=$I$27,K$33>=$I12),$H12*$I$31, TRUE, 0 ) -> 80000 | L46: =IFS( AND(L$36=$E$27,L$33>=$I12),$H12*$E$31, AND(L$36=$F$27,L$33>=$I12),$H12*$F$31, AND(L$36=$G$27,L$33>=$I12),$H12*$G$31, AND(L$36=$H$27,L$33>=$I12),$H12*$H$31, AND(L$36=$I$27,L$33>=$I12),$H12*$I$31, TRUE, 0 ) -> 80000 | ... BL46: =IFS( AND(BL$36=$E$27,BL$33>=$I12),$H12*$E$31, AND(BL$36=$F$27,BL$33>=$I12),$H12*$F$31, AND(BL$36=$G$27,BL$33>=$I12),$H12*$G$31, AND(BL$36=$H$27,BL$33>=$I12),$H12*$H$31, AND(BL$36=$I$27,BL$33>=$I12),$H12*$I$31, TRUE, 0 ) -> 108839.12
D47: Process Operator | E47: =IFS( AND(E$36=$E$27,E$33>=$I13),$H13*$E$31, AND(E$36=$F$27,E$33>=$I13),$H13*$F$31, AND(E$36=$G$27,E$33>=$I13),$H13*$G$31, AND(E$36=$H$27,E$33>=$I13),$H13*$H$31, AND(E$36=$I$27,E$33>=$I13),$H13*$I$31, TRUE, 0 ) -> 0 | F47: =IFS( AND(F$36=$E$27,F$33>=$I13),$H13*$E$31, AND(F$36=$F$27,F$33>=$I13),$H13*$F$31, AND(F$36=$G$27,F$33>=$I13),$H13*$G$31, AND(F$36=$H$27,F$33>=$I13),$H13*$H$31, AND(F$36=$I$27,F$33>=$I13),$H13*$I$31, TRUE, 0 ) -> 0 | G47: =IFS( AND(G$36=$E$27,G$33>=$I13),$H13*$E$31, AND(G$36=$F$27,G$33>=$I13),$H13*$F$31, AND(G$36=$G$27,G$33>=$I13),$H13*$G$31, AND(G$36=$H$27,G$33>=$I13),$H13*$H$31, AND(G$36=$I$27,G$33>=$I13),$H13*$I$31, TRUE, 0 ) -> 0 | H47: =IFS( AND(H$36=$E$27,H$33>=$I13),$H13*$E$31, AND(H$36=$F$27,H$33>=$I13),$H13*$F$31, AND(H$36=$G$27,H$33>=$I13),$H13*$G$31, AND(H$36=$H$27,H$33>=$I13),$H13*$H$31, AND(H$36=$I$27,H$33>=$I13),$H13*$I$31, TRUE, 0 ) -> 0 | I47: =IFS( AND(I$36=$E$27,I$33>=$I13),$H13*$E$31, AND(I$36=$F$27,I$33>=$I13),$H13*$F$31, AND(I$36=$G$27,I$33>=$I13),$H13*$G$31, AND(I$36=$H$27,I$33>=$I13),$H13*$H$31, AND(I$36=$I$27,I$33>=$I13),$H13*$I$31, TRUE, 0 ) -> 0 | J47: =IFS( AND(J$36=$E$27,J$33>=$I13),$H13*$E$31, AND(J$36=$F$27,J$33>=$I13),$H13*$F$31, AND(J$36=$G$27,J$33>=$I13),$H13*$G$31, AND(J$36=$H$27,J$33>=$I13),$H13*$H$31, AND(J$36=$I$27,J$33>=$I13),$H13*$I$31, TRUE, 0 ) -> 120000 | K47: =IFS( AND(K$36=$E$27,K$33>=$I13),$H13*$E$31, AND(K$36=$F$27,K$33>=$I13),$H13*$F$31, AND(K$36=$G$27,K$33>=$I13),$H13*$G$31, AND(K$36=$H$27,K$33>=$I13),$H13*$H$31, AND(K$36=$I$27,K$33>=$I13),$H13*$I$31, TRUE, 0 ) -> 120000 | L47: =IFS( AND(L$36=$E$27,L$33>=$I13),$H13*$E$31, AND(L$36=$F$27,L$33>=$I13),$H13*$F$31, AND(L$36=$G$27,L$33>=$I13),$H13*$G$31, AND(L$36=$H$27,L$33>=$I13),$H13*$H$31, AND(L$36=$I$27,L$33>=$I13),$H13*$I$31, TRUE, 0 ) -> 120000 | ... BL47: =IFS( AND(BL$36=$E$27,BL$33>=$I13),$H13*$E$31, AND(BL$36=$F$27,BL$33>=$I13),$H13*$F$31, AND(BL$36=$G$27,BL$33>=$I13),$H13*$G$31, AND(BL$36=$H$27,BL$33>=$I13),$H13*$H$31, AND(BL$36=$I$27,BL$33>=$I13),$H13*$I$31, TRUE, 0 ) -> 163258.68
D48: Powder Plant Operator | E48: =IFS( AND(E$36=$E$27,E$33>=$I14),$H14*$E$31, AND(E$36=$F$27,E$33>=$I14),$H14*$F$31, AND(E$36=$G$27,E$33>=$I14),$H14*$G$31, AND(E$36=$H$27,E$33>=$I14),$H14*$H$31, AND(E$36=$I$27,E$33>=$I14),$H14*$I$31, TRUE, 0 ) -> 0 | F48: =IFS( AND(F$36=$E$27,F$33>=$I14),$H14*$E$31, AND(F$36=$F$27,F$33>=$I14),$H14*$F$31, AND(F$36=$G$27,F$33>=$I14),$H14*$G$31, AND(F$36=$H$27,F$33>=$I14),$H14*$H$31, AND(F$36=$I$27,F$33>=$I14),$H14*$I$31, TRUE, 0 ) -> 0 | G48: =IFS( AND(G$36=$E$27,G$33>=$I14),$H14*$E$31, AND(G$36=$F$27,G$33>=$I14),$H14*$F$31, AND(G$36=$G$27,G$33>=$I14),$H14*$G$31, AND(G$36=$H$27,G$33>=$I14),$H14*$H$31, AND(G$36=$I$27,G$33>=$I14),$H14*$I$31, TRUE, 0 ) -> 0 | H48: =IFS( AND(H$36=$E$27,H$33>=$I14),$H14*$E$31, AND(H$36=$F$27,H$33>=$I14),$H14*$F$31, AND(H$36=$G$27,H$33>=$I14),$H14*$G$31, AND(H$36=$H$27,H$33>=$I14),$H14*$H$31, AND(H$36=$I$27,H$33>=$I14),$H14*$I$31, TRUE, 0 ) -> 0 | I48: =IFS( AND(I$36=$E$27,I$33>=$I14),$H14*$E$31, AND(I$36=$F$27,I$33>=$I14),$H14*$F$31, AND(I$36=$G$27,I$33>=$I14),$H14*$G$31, AND(I$36=$H$27,I$33>=$I14),$H14*$H$31, AND(I$36=$I$27,I$33>=$I14),$H14*$I$31, TRUE, 0 ) -> 0 | J48: =IFS( AND(J$36=$E$27,J$33>=$I14),$H14*$E$31, AND(J$36=$F$27,J$33>=$I14),$H14*$F$31, AND(J$36=$G$27,J$33>=$I14),$H14*$G$31, AND(J$36=$H$27,J$33>=$I14),$H14*$H$31, AND(J$36=$I$27,J$33>=$I14),$H14*$I$31, TRUE, 0 ) -> 0 | K48: =IFS( AND(K$36=$E$27,K$33>=$I14),$H14*$E$31, AND(K$36=$F$27,K$33>=$I14),$H14*$F$31, AND(K$36=$G$27,K$33>=$I14),$H14*$G$31, AND(K$36=$H$27,K$33>=$I14),$H14*$H$31, AND(K$36=$I$27,K$33>=$I14),$H14*$I$31, TRUE, 0 ) -> 140000 | L48: =IFS( AND(L$36=$E$27,L$33>=$I14),$H14*$E$31, AND(L$36=$F$27,L$33>=$I14),$H14*$F$31, AND(L$36=$G$27,L$33>=$I14),$H14*$G$31, AND(L$36=$H$27,L$33>=$I14),$H14*$H$31, AND(L$36=$I$27,L$33>=$I14),$H14*$I$31, TRUE, 0 ) -> 140000 | ... BL48: =IFS( AND(BL$36=$E$27,BL$33>=$I14),$H14*$E$31, AND(BL$36=$F$27,BL$33>=$I14),$H14*$F$31, AND(BL$36=$G$27,BL$33>=$I14),$H14*$G$31, AND(BL$36=$H$27,BL$33>=$I14),$H14*$H$31, AND(BL$36=$I$27,BL$33>=$I14),$H14*$I$31, TRUE, 0 ) -> 190468.45
D49: Poly Pack Operator | E49: =IFS( AND(E$36=$E$27,E$33>=$I15),$H15*$E$31, AND(E$36=$F$27,E$33>=$I15),$H15*$F$31, AND(E$36=$G$27,E$33>=$I15),$H15*$G$31, AND(E$36=$H$27,E$33>=$I15),$H15*$H$31, AND(E$36=$I$27,E$33>=$I15),$H15*$I$31, TRUE, 0 ) -> 0 | F49: =IFS( AND(F$36=$E$27,F$33>=$I15),$H15*$E$31, AND(F$36=$F$27,F$33>=$I15),$H15*$F$31, AND(F$36=$G$27,F$33>=$I15),$H15*$G$31, AND(F$36=$H$27,F$33>=$I15),$H15*$H$31, AND(F$36=$I$27,F$33>=$I15),$H15*$I$31, TRUE, 0 ) -> 0 | G49: =IFS( AND(G$36=$E$27,G$33>=$I15),$H15*$E$31, AND(G$36=$F$27,G$33>=$I15),$H15*$F$31, AND(G$36=$G$27,G$33>=$I15),$H15*$G$31, AND(G$36=$H$27,G$33>=$I15),$H15*$H$31, AND(G$36=$I$27,G$33>=$I15),$H15*$I$31, TRUE, 0 ) -> 0 | H49: =IFS( AND(H$36=$E$27,H$33>=$I15),$H15*$E$31, AND(H$36=$F$27,H$33>=$I15),$H15*$F$31, AND(H$36=$G$27,H$33>=$I15),$H15*$G$31, AND(H$36=$H$27,H$33>=$I15),$H15*$H$31, AND(H$36=$I$27,H$33>=$I15),$H15*$I$31, TRUE, 0 ) -> 0 | I49: =IFS( AND(I$36=$E$27,I$33>=$I15),$H15*$E$31, AND(I$36=$F$27,I$33>=$I15),$H15*$F$31, AND(I$36=$G$27,I$33>=$I15),$H15*$G$31, AND(I$36=$H$27,I$33>=$I15),$H15*$H$31, AND(I$36=$I$27,I$33>=$I15),$H15*$I$31, TRUE, 0 ) -> 0 | J49: =IFS( AND(J$36=$E$27,J$33>=$I15),$H15*$E$31, AND(J$36=$F$27,J$33>=$I15),$H15*$F$31, AND(J$36=$G$27,J$33>=$I15),$H15*$G$31, AND(J$36=$H$27,J$33>=$I15),$H15*$H$31, AND(J$36=$I$27,J$33>=$I15),$H15*$I$31, TRUE, 0 ) -> 0 | K49: =IFS( AND(K$36=$E$27,K$33>=$I15),$H15*$E$31, AND(K$36=$F$27,K$33>=$I15),$H15*$F$31, AND(K$36=$G$27,K$33>=$I15),$H15*$G$31, AND(K$36=$H$27,K$33>=$I15),$H15*$H$31, AND(K$36=$I$27,K$33>=$I15),$H15*$I$31, TRUE, 0 ) -> 50000 | L49: =IFS( AND(L$36=$E$27,L$33>=$I15),$H15*$E$31, AND(L$36=$F$27,L$33>=$I15),$H15*$F$31, AND(L$36=$G$27,L$33>=$I15),$H15*$G$31, AND(L$36=$H$27,L$33>=$I15),$H15*$H$31, AND(L$36=$I$27,L$33>=$I15),$H15*$I$31, TRUE, 0 ) -> 50000 | ... BL49: =IFS( AND(BL$36=$E$27,BL$33>=$I15),$H15*$E$31, AND(BL$36=$F$27,BL$33>=$I15),$H15*$F$31, AND(BL$36=$G$27,BL$33>=$I15),$H15*$G$31, AND(BL$36=$H$27,BL$33>=$I15),$H15*$H$31, AND(BL$36=$I$27,BL$33>=$I15),$H15*$I$31, TRUE, 0 ) -> 68024.448
D50: Ghee & Butter Operator | E50: =IFS( AND(E$36=$E$27,E$33>=$I16),$H16*$E$31, AND(E$36=$F$27,E$33>=$I16),$H16*$F$31, AND(E$36=$G$27,E$33>=$I16),$H16*$G$31, AND(E$36=$H$27,E$33>=$I16),$H16*$H$31, AND(E$36=$I$27,E$33>=$I16),$H16*$I$31, TRUE, 0 ) -> 0 | F50: =IFS( AND(F$36=$E$27,F$33>=$I16),$H16*$E$31, AND(F$36=$F$27,F$33>=$I16),$H16*$F$31, AND(F$36=$G$27,F$33>=$I16),$H16*$G$31, AND(F$36=$H$27,F$33>=$I16),$H16*$H$31, AND(F$36=$I$27,F$33>=$I16),$H16*$I$31, TRUE, 0 ) -> 0 | G50: =IFS( AND(G$36=$E$27,G$33>=$I16),$H16*$E$31, AND(G$36=$F$27,G$33>=$I16),$H16*$F$31, AND(G$36=$G$27,G$33>=$I16),$H16*$G$31, AND(G$36=$H$27,G$33>=$I16),$H16*$H$31, AND(G$36=$I$27,G$33>=$I16),$H16*$I$31, TRUE, 0 ) -> 0 | H50: =IFS( AND(H$36=$E$27,H$33>=$I16),$H16*$E$31, AND(H$36=$F$27,H$33>=$I16),$H16*$F$31, AND(H$36=$G$27,H$33>=$I16),$H16*$G$31, AND(H$36=$H$27,H$33>=$I16),$H16*$H$31, AND(H$36=$I$27,H$33>=$I16),$H16*$I$31, TRUE, 0 ) -> 0 | I50: =IFS( AND(I$36=$E$27,I$33>=$I16),$H16*$E$31, AND(I$36=$F$27,I$33>=$I16),$H16*$F$31, AND(I$36=$G$27,I$33>=$I16),$H16*$G$31, AND(I$36=$H$27,I$33>=$I16),$H16*$H$31, AND(I$36=$I$27,I$33>=$I16),$H16*$I$31, TRUE, 0 ) -> 0 | J50: =IFS( AND(J$36=$E$27,J$33>=$I16),$H16*$E$31, AND(J$36=$F$27,J$33>=$I16),$H16*$F$31, AND(J$36=$G$27,J$33>=$I16),$H16*$G$31, AND(J$36=$H$27,J$33>=$I16),$H16*$H$31, AND(J$36=$I$27,J$33>=$I16),$H16*$I$31, TRUE, 0 ) -> 0 | K50: =IFS( AND(K$36=$E$27,K$33>=$I16),$H16*$E$31, AND(K$36=$F$27,K$33>=$I16),$H16*$F$31, AND(K$36=$G$27,K$33>=$I16),$H16*$G$31, AND(K$36=$H$27,K$33>=$I16),$H16*$H$31, AND(K$36=$I$27,K$33>=$I16),$H16*$I$31, TRUE, 0 ) -> 0 | L50: =IFS( AND(L$36=$E$27,L$33>=$I16),$H16*$E$31, AND(L$36=$F$27,L$33>=$I16),$H16*$F$31, AND(L$36=$G$27,L$33>=$I16),$H16*$G$31, AND(L$36=$H$27,L$33>=$I16),$H16*$H$31, AND(L$36=$I$27,L$33>=$I16),$H16*$I$31, TRUE, 0 ) -> 60000 | ... BL50: =IFS( AND(BL$36=$E$27,BL$33>=$I16),$H16*$E$31, AND(BL$36=$F$27,BL$33>=$I16),$H16*$F$31, AND(BL$36=$G$27,BL$33>=$I16),$H16*$G$31, AND(BL$36=$H$27,BL$33>=$I16),$H16*$H$31, AND(BL$36=$I$27,BL$33>=$I16),$H16*$I$31, TRUE, 0 ) -> 81629.338
D51: Reception Supervisor | E51: =IFS( AND(E$36=$E$27,E$33>=$I17),$H17*$E$31, AND(E$36=$F$27,E$33>=$I17),$H17*$F$31, AND(E$36=$G$27,E$33>=$I17),$H17*$G$31, AND(E$36=$H$27,E$33>=$I17),$H17*$H$31, AND(E$36=$I$27,E$33>=$I17),$H17*$I$31, TRUE, 0 ) -> 50000 | F51: =IFS( AND(F$36=$E$27,F$33>=$I17),$H17*$E$31, AND(F$36=$F$27,F$33>=$I17),$H17*$F$31, AND(F$36=$G$27,F$33>=$I17),$H17*$G$31, AND(F$36=$H$27,F$33>=$I17),$H17*$H$31, AND(F$36=$I$27,F$33>=$I17),$H17*$I$31, TRUE, 0 ) -> 50000 | G51: =IFS( AND(G$36=$E$27,G$33>=$I17),$H17*$E$31, AND(G$36=$F$27,G$33>=$I17),$H17*$F$31, AND(G$36=$G$27,G$33>=$I17),$H17*$G$31, AND(G$36=$H$27,G$33>=$I17),$H17*$H$31, AND(G$36=$I$27,G$33>=$I17),$H17*$I$31, TRUE, 0 ) -> 50000 | H51: =IFS( AND(H$36=$E$27,H$33>=$I17),$H17*$E$31, AND(H$36=$F$27,H$33>=$I17),$H17*$F$31, AND(H$36=$G$27,H$33>=$I17),$H17*$G$31, AND(H$36=$H$27,H$33>=$I17),$H17*$H$31, AND(H$36=$I$27,H$33>=$I17),$H17*$I$31, TRUE, 0 ) -> 50000 | I51: =IFS( AND(I$36=$E$27,I$33>=$I17),$H17*$E$31, AND(I$36=$F$27,I$33>=$I17),$H17*$F$31, AND(I$36=$G$27,I$33>=$I17),$H17*$G$31, AND(I$36=$H$27,I$33>=$I17),$H17*$H$31, AND(I$36=$I$27,I$33>=$I17),$H17*$I$31, TRUE, 0 ) -> 50000 | J51: =IFS( AND(J$36=$E$27,J$33>=$I17),$H17*$E$31, AND(J$36=$F$27,J$33>=$I17),$H17*$F$31, AND(J$36=$G$27,J$33>=$I17),$H17*$G$31, AND(J$36=$H$27,J$33>=$I17),$H17*$H$31, AND(J$36=$I$27,J$33>=$I17),$H17*$I$31, TRUE, 0 ) -> 50000 | K51: =IFS( AND(K$36=$E$27,K$33>=$I17),$H17*$E$31, AND(K$36=$F$27,K$33>=$I17),$H17*$F$31, AND(K$36=$G$27,K$33>=$I17),$H17*$G$31, AND(K$36=$H$27,K$33>=$I17),$H17*$H$31, AND(K$36=$I$27,K$33>=$I17),$H17*$I$31, TRUE, 0 ) -> 50000 | L51: =IFS( AND(L$36=$E$27,L$33>=$I17),$H17*$E$31, AND(L$36=$F$27,L$33>=$I17),$H17*$F$31, AND(L$36=$G$27,L$33>=$I17),$H17*$G$31, AND(L$36=$H$27,L$33>=$I17),$H17*$H$31, AND(L$36=$I$27,L$33>=$I17),$H17*$I$31, TRUE, 0 ) -> 50000 | ... BL51: =IFS( AND(BL$36=$E$27,BL$33>=$I17),$H17*$E$31, AND(BL$36=$F$27,BL$33>=$I17),$H17*$F$31, AND(BL$36=$G$27,BL$33>=$I17),$H17*$G$31, AND(BL$36=$H$27,BL$33>=$I17),$H17*$H$31, AND(BL$36=$I$27,BL$33>=$I17),$H17*$I$31, TRUE, 0 ) -> 68024.448
D52: Dispatch | E52: =IFS( AND(E$36=$E$27,E$33>=$I18),$H18*$E$31, AND(E$36=$F$27,E$33>=$I18),$H18*$F$31, AND(E$36=$G$27,E$33>=$I18),$H18*$G$31, AND(E$36=$H$27,E$33>=$I18),$H18*$H$31, AND(E$36=$I$27,E$33>=$I18),$H18*$I$31, TRUE, 0 ) -> 0 | F52: =IFS( AND(F$36=$E$27,F$33>=$I18),$H18*$E$31, AND(F$36=$F$27,F$33>=$I18),$H18*$F$31, AND(F$36=$G$27,F$33>=$I18),$H18*$G$31, AND(F$36=$H$27,F$33>=$I18),$H18*$H$31, AND(F$36=$I$27,F$33>=$I18),$H18*$I$31, TRUE, 0 ) -> 0 | G52: =IFS( AND(G$36=$E$27,G$33>=$I18),$H18*$E$31, AND(G$36=$F$27,G$33>=$I18),$H18*$F$31, AND(G$36=$G$27,G$33>=$I18),$H18*$G$31, AND(G$36=$H$27,G$33>=$I18),$H18*$H$31, AND(G$36=$I$27,G$33>=$I18),$H18*$I$31, TRUE, 0 ) -> 0 | H52: =IFS( AND(H$36=$E$27,H$33>=$I18),$H18*$E$31, AND(H$36=$F$27,H$33>=$I18),$H18*$F$31, AND(H$36=$G$27,H$33>=$I18),$H18*$G$31, AND(H$36=$H$27,H$33>=$I18),$H18*$H$31, AND(H$36=$I$27,H$33>=$I18),$H18*$I$31, TRUE, 0 ) -> 0 | I52: =IFS( AND(I$36=$E$27,I$33>=$I18),$H18*$E$31, AND(I$36=$F$27,I$33>=$I18),$H18*$F$31, AND(I$36=$G$27,I$33>=$I18),$H18*$G$31, AND(I$36=$H$27,I$33>=$I18),$H18*$H$31, AND(I$36=$I$27,I$33>=$I18),$H18*$I$31, TRUE, 0 ) -> 0 | J52: =IFS( AND(J$36=$E$27,J$33>=$I18),$H18*$E$31, AND(J$36=$F$27,J$33>=$I18),$H18*$F$31, AND(J$36=$G$27,J$33>=$I18),$H18*$G$31, AND(J$36=$H$27,J$33>=$I18),$H18*$H$31, AND(J$36=$I$27,J$33>=$I18),$H18*$I$31, TRUE, 0 ) -> 0 | K52: =IFS( AND(K$36=$E$27,K$33>=$I18),$H18*$E$31, AND(K$36=$F$27,K$33>=$I18),$H18*$F$31, AND(K$36=$G$27,K$33>=$I18),$H18*$G$31, AND(K$36=$H$27,K$33>=$I18),$H18*$H$31, AND(K$36=$I$27,K$33>=$I18),$H18*$I$31, TRUE, 0 ) -> 75000 | L52: =IFS( AND(L$36=$E$27,L$33>=$I18),$H18*$E$31, AND(L$36=$F$27,L$33>=$I18),$H18*$F$31, AND(L$36=$G$27,L$33>=$I18),$H18*$G$31, AND(L$36=$H$27,L$33>=$I18),$H18*$H$31, AND(L$36=$I$27,L$33>=$I18),$H18*$I$31, TRUE, 0 ) -> 75000 | ... BL52: =IFS( AND(BL$36=$E$27,BL$33>=$I18),$H18*$E$31, AND(BL$36=$F$27,BL$33>=$I18),$H18*$F$31, AND(BL$36=$G$27,BL$33>=$I18),$H18*$G$31, AND(BL$36=$H$27,BL$33>=$I18),$H18*$H$31, AND(BL$36=$I$27,BL$33>=$I18),$H18*$I$31, TRUE, 0 ) -> 102036.67
D53: Unskilled Labour | E53: =IFS( AND(E$36=$E$27,E$33>=$I19),$G19* E$39 * $E$31, AND(E$36=$F$27,E$33>=$I19),$G19* E$39 * $F$31, AND(E$36=$G$27,E$33>=$I19),$G19* E$39 * $G$31, AND(E$36=$H$27,E$33>=$I19),$G19* E$39 * $H$31, AND(E$36=$I$27,E$33>=$I19),$G19* E$39 * $I$31, TRUE, 0 ) -> 0 | F53: =IFS( AND(F$36=$E$27,F$33>=$I19),$G19* F$39 * $E$31, AND(F$36=$F$27,F$33>=$I19),$G19* F$39 * $F$31, AND(F$36=$G$27,F$33>=$I19),$G19* F$39 * $G$31, AND(F$36=$H$27,F$33>=$I19),$G19* F$39 * $H$31, AND(F$36=$I$27,F$33>=$I19),$G19* F$39 * $I$31, TRUE, 0 ) -> 0 | G53: =IFS( AND(G$36=$E$27,G$33>=$I19),$G19* G$39 * $E$31, AND(G$36=$F$27,G$33>=$I19),$G19* G$39 * $F$31, AND(G$36=$G$27,G$33>=$I19),$G19* G$39 * $G$31, AND(G$36=$H$27,G$33>=$I19),$G19* G$39 * $H$31, AND(G$36=$I$27,G$33>=$I19),$G19* G$39 * $I$31, TRUE, 0 ) -> 0 | H53: =IFS( AND(H$36=$E$27,H$33>=$I19),$G19* H$39 * $E$31, AND(H$36=$F$27,H$33>=$I19),$G19* H$39 * $F$31, AND(H$36=$G$27,H$33>=$I19),$G19* H$39 * $G$31, AND(H$36=$H$27,H$33>=$I19),$G19* H$39 * $H$31, AND(H$36=$I$27,H$33>=$I19),$G19* H$39 * $I$31, TRUE, 0 ) -> 0 | I53: =IFS( AND(I$36=$E$27,I$33>=$I19),$G19* I$39 * $E$31, AND(I$36=$F$27,I$33>=$I19),$G19* I$39 * $F$31, AND(I$36=$G$27,I$33>=$I19),$G19* I$39 * $G$31, AND(I$36=$H$27,I$33>=$I19),$G19* I$39 * $H$31, AND(I$36=$I$27,I$33>=$I19),$G19* I$39 * $I$31, TRUE, 0 ) -> 0 | J53: =IFS( AND(J$36=$E$27,J$33>=$I19),$G19* J$39 * $E$31, AND(J$36=$F$27,J$33>=$I19),$G19* J$39 * $F$31, AND(J$36=$G$27,J$33>=$I19),$G19* J$39 * $G$31, AND(J$36=$H$27,J$33>=$I19),$G19* J$39 * $H$31, AND(J$36=$I$27,J$33>=$I19),$G19* J$39 * $I$31, TRUE, 0 ) -> 12000 | K53: =IFS( AND(K$36=$E$27,K$33>=$I19),$G19* K$39 * $E$31, AND(K$36=$F$27,K$33>=$I19),$G19* K$39 * $F$31, AND(K$36=$G$27,K$33>=$I19),$G19* K$39 * $G$31, AND(K$36=$H$27,K$33>=$I19),$G19* K$39 * $H$31, AND(K$36=$I$27,K$33>=$I19),$G19* K$39 * $I$31, TRUE, 0 ) -> 18000 | L53: =IFS( AND(L$36=$E$27,L$33>=$I19),$G19* L$39 * $E$31, AND(L$36=$F$27,L$33>=$I19),$G19* L$39 * $F$31, AND(L$36=$G$27,L$33>=$I19),$G19* L$39 * $G$31, AND(L$36=$H$27,L$33>=$I19),$G19* L$39 * $H$31, AND(L$36=$I$27,L$33>=$I19),$G19* L$39 * $I$31, TRUE, 0 ) -> 24000 | ... BL53: =IFS( AND(BL$36=$E$27,BL$33>=$I19),$G19* BL$39 * $E$31, AND(BL$36=$F$27,BL$33>=$I19),$G19* BL$39 * $F$31, AND(BL$36=$G$27,BL$33>=$I19),$G19* BL$39 * $G$31, AND(BL$36=$H$27,BL$33>=$I19),$G19* BL$39 * $H$31, AND(BL$36=$I$27,BL$33>=$I19),$G19* BL$39 * $I$31, TRUE, 0 ) -> 457124.29
D54: Fitter/Welder/Electrician | E54: =IFS( AND(E$36=$E$27,E$33>=$I20),$H20*$E$31, AND(E$36=$F$27,E$33>=$I20),$H20*$F$31, AND(E$36=$G$27,E$33>=$I20),$H20*$G$31, AND(E$36=$H$27,E$33>=$I20),$H20*$H$31, AND(E$36=$I$27,E$33>=$I20),$H20*$I$31, TRUE, 0 ) -> 0 | F54: =IFS( AND(F$36=$E$27,F$33>=$I20),$H20*$E$31, AND(F$36=$F$27,F$33>=$I20),$H20*$F$31, AND(F$36=$G$27,F$33>=$I20),$H20*$G$31, AND(F$36=$H$27,F$33>=$I20),$H20*$H$31, AND(F$36=$I$27,F$33>=$I20),$H20*$I$31, TRUE, 0 ) -> 0 | G54: =IFS( AND(G$36=$E$27,G$33>=$I20),$H20*$E$31, AND(G$36=$F$27,G$33>=$I20),$H20*$F$31, AND(G$36=$G$27,G$33>=$I20),$H20*$G$31, AND(G$36=$H$27,G$33>=$I20),$H20*$H$31, AND(G$36=$I$27,G$33>=$I20),$H20*$I$31, TRUE, 0 ) -> 0 | H54: =IFS( AND(H$36=$E$27,H$33>=$I20),$H20*$E$31, AND(H$36=$F$27,H$33>=$I20),$H20*$F$31, AND(H$36=$G$27,H$33>=$I20),$H20*$G$31, AND(H$36=$H$27,H$33>=$I20),$H20*$H$31, AND(H$36=$I$27,H$33>=$I20),$H20*$I$31, TRUE, 0 ) -> 0 | I54: =IFS( AND(I$36=$E$27,I$33>=$I20),$H20*$E$31, AND(I$36=$F$27,I$33>=$I20),$H20*$F$31, AND(I$36=$G$27,I$33>=$I20),$H20*$G$31, AND(I$36=$H$27,I$33>=$I20),$H20*$H$31, AND(I$36=$I$27,I$33>=$I20),$H20*$I$31, TRUE, 0 ) -> 60000 | J54: =IFS( AND(J$36=$E$27,J$33>=$I20),$H20*$E$31, AND(J$36=$F$27,J$33>=$I20),$H20*$F$31, AND(J$36=$G$27,J$33>=$I20),$H20*$G$31, AND(J$36=$H$27,J$33>=$I20),$H20*$H$31, AND(J$36=$I$27,J$33>=$I20),$H20*$I$31, TRUE, 0 ) -> 60000 | K54: =IFS( AND(K$36=$E$27,K$33>=$I20),$H20*$E$31, AND(K$36=$F$27,K$33>=$I20),$H20*$F$31, AND(K$36=$G$27,K$33>=$I20),$H20*$G$31, AND(K$36=$H$27,K$33>=$I20),$H20*$H$31, AND(K$36=$I$27,K$33>=$I20),$H20*$I$31, TRUE, 0 ) -> 60000 | L54: =IFS( AND(L$36=$E$27,L$33>=$I20),$H20*$E$31, AND(L$36=$F$27,L$33>=$I20),$H20*$F$31, AND(L$36=$G$27,L$33>=$I20),$H20*$G$31, AND(L$36=$H$27,L$33>=$I20),$H20*$H$31, AND(L$36=$I$27,L$33>=$I20),$H20*$I$31, TRUE, 0 ) -> 60000 | ... BL54: =IFS( AND(BL$36=$E$27,BL$33>=$I20),$H20*$E$31, AND(BL$36=$F$27,BL$33>=$I20),$H20*$F$31, AND(BL$36=$G$27,BL$33>=$I20),$H20*$G$31, AND(BL$36=$H$27,BL$33>=$I20),$H20*$H$31, AND(BL$36=$I$27,BL$33>=$I20),$H20*$I$31, TRUE, 0 ) -> 81629.338
D55: Sweeper | E55: =IFS( AND(E$36=$E$27,E$33>=$I21),$H21*$E$31, AND(E$36=$F$27,E$33>=$I21),$H21*$F$31, AND(E$36=$G$27,E$33>=$I21),$H21*$G$31, AND(E$36=$H$27,E$33>=$I21),$H21*$H$31, AND(E$36=$I$27,E$33>=$I21),$H21*$I$31, TRUE, 0 ) -> 0 | F55: =IFS( AND(F$36=$E$27,F$33>=$I21),$H21*$E$31, AND(F$36=$F$27,F$33>=$I21),$H21*$F$31, AND(F$36=$G$27,F$33>=$I21),$H21*$G$31, AND(F$36=$H$27,F$33>=$I21),$H21*$H$31, AND(F$36=$I$27,F$33>=$I21),$H21*$I$31, TRUE, 0 ) -> 0 | G55: =IFS( AND(G$36=$E$27,G$33>=$I21),$H21*$E$31, AND(G$36=$F$27,G$33>=$I21),$H21*$F$31, AND(G$36=$G$27,G$33>=$I21),$H21*$G$31, AND(G$36=$H$27,G$33>=$I21),$H21*$H$31, AND(G$36=$I$27,G$33>=$I21),$H21*$I$31, TRUE, 0 ) -> 0 | H55: =IFS( AND(H$36=$E$27,H$33>=$I21),$H21*$E$31, AND(H$36=$F$27,H$33>=$I21),$H21*$F$31, AND(H$36=$G$27,H$33>=$I21),$H21*$G$31, AND(H$36=$H$27,H$33>=$I21),$H21*$H$31, AND(H$36=$I$27,H$33>=$I21),$H21*$I$31, TRUE, 0 ) -> 0 | I55: =IFS( AND(I$36=$E$27,I$33>=$I21),$H21*$E$31, AND(I$36=$F$27,I$33>=$I21),$H21*$F$31, AND(I$36=$G$27,I$33>=$I21),$H21*$G$31, AND(I$36=$H$27,I$33>=$I21),$H21*$H$31, AND(I$36=$I$27,I$33>=$I21),$H21*$I$31, TRUE, 0 ) -> 30000 | J55: =IFS( AND(J$36=$E$27,J$33>=$I21),$H21*$E$31, AND(J$36=$F$27,J$33>=$I21),$H21*$F$31, AND(J$36=$G$27,J$33>=$I21),$H21*$G$31, AND(J$36=$H$27,J$33>=$I21),$H21*$H$31, AND(J$36=$I$27,J$33>=$I21),$H21*$I$31, TRUE, 0 ) -> 30000 | K55: =IFS( AND(K$36=$E$27,K$33>=$I21),$H21*$E$31, AND(K$36=$F$27,K$33>=$I21),$H21*$F$31, AND(K$36=$G$27,K$33>=$I21),$H21*$G$31, AND(K$36=$H$27,K$33>=$I21),$H21*$H$31, AND(K$36=$I$27,K$33>=$I21),$H21*$I$31, TRUE, 0 ) -> 30000 | L55: =IFS( AND(L$36=$E$27,L$33>=$I21),$H21*$E$31, AND(L$36=$F$27,L$33>=$I21),$H21*$F$31, AND(L$36=$G$27,L$33>=$I21),$H21*$G$31, AND(L$36=$H$27,L$33>=$I21),$H21*$H$31, AND(L$36=$I$27,L$33>=$I21),$H21*$I$31, TRUE, 0 ) -> 30000 | ... BL55: =IFS( AND(BL$36=$E$27,BL$33>=$I21),$H21*$E$31, AND(BL$36=$F$27,BL$33>=$I21),$H21*$F$31, AND(BL$36=$G$27,BL$33>=$I21),$H21*$G$31, AND(BL$36=$H$27,BL$33>=$I21),$H21*$H$31, AND(BL$36=$I$27,BL$33>=$I21),$H21*$I$31, TRUE, 0 ) -> 40814.669
D56: Security Staff | E56: =IFS( AND(E$36=$E$27,E$33>=$I22),$H22*$E$31, AND(E$36=$F$27,E$33>=$I22),$H22*$F$31, AND(E$36=$G$27,E$33>=$I22),$H22*$G$31, AND(E$36=$H$27,E$33>=$I22),$H22*$H$31, AND(E$36=$I$27,E$33>=$I22),$H22*$I$31, TRUE, 0 ) -> 60000 | F56: =IFS( AND(F$36=$E$27,F$33>=$I22),$H22*$E$31, AND(F$36=$F$27,F$33>=$I22),$H22*$F$31, AND(F$36=$G$27,F$33>=$I22),$H22*$G$31, AND(F$36=$H$27,F$33>=$I22),$H22*$H$31, AND(F$36=$I$27,F$33>=$I22),$H22*$I$31, TRUE, 0 ) -> 60000 | G56: =IFS( AND(G$36=$E$27,G$33>=$I22),$H22*$E$31, AND(G$36=$F$27,G$33>=$I22),$H22*$F$31, AND(G$36=$G$27,G$33>=$I22),$H22*$G$31, AND(G$36=$H$27,G$33>=$I22),$H22*$H$31, AND(G$36=$I$27,G$33>=$I22),$H22*$I$31, TRUE, 0 ) -> 60000 | H56: =IFS( AND(H$36=$E$27,H$33>=$I22),$H22*$E$31, AND(H$36=$F$27,H$33>=$I22),$H22*$F$31, AND(H$36=$G$27,H$33>=$I22),$H22*$G$31, AND(H$36=$H$27,H$33>=$I22),$H22*$H$31, AND(H$36=$I$27,H$33>=$I22),$H22*$I$31, TRUE, 0 ) -> 60000 | I56: =IFS( AND(I$36=$E$27,I$33>=$I22),$H22*$E$31, AND(I$36=$F$27,I$33>=$I22),$H22*$F$31, AND(I$36=$G$27,I$33>=$I22),$H22*$G$31, AND(I$36=$H$27,I$33>=$I22),$H22*$H$31, AND(I$36=$I$27,I$33>=$I22),$H22*$I$31, TRUE, 0 ) -> 60000 | J56: =IFS( AND(J$36=$E$27,J$33>=$I22),$H22*$E$31, AND(J$36=$F$27,J$33>=$I22),$H22*$F$31, AND(J$36=$G$27,J$33>=$I22),$H22*$G$31, AND(J$36=$H$27,J$33>=$I22),$H22*$H$31, AND(J$36=$I$27,J$33>=$I22),$H22*$I$31, TRUE, 0 ) -> 60000 | K56: =IFS( AND(K$36=$E$27,K$33>=$I22),$H22*$E$31, AND(K$36=$F$27,K$33>=$I22),$H22*$F$31, AND(K$36=$G$27,K$33>=$I22),$H22*$G$31, AND(K$36=$H$27,K$33>=$I22),$H22*$H$31, AND(K$36=$I$27,K$33>=$I22),$H22*$I$31, TRUE, 0 ) -> 60000 | L56: =IFS( AND(L$36=$E$27,L$33>=$I22),$H22*$E$31, AND(L$36=$F$27,L$33>=$I22),$H22*$F$31, AND(L$36=$G$27,L$33>=$I22),$H22*$G$31, AND(L$36=$H$27,L$33>=$I22),$H22*$H$31, AND(L$36=$I$27,L$33>=$I22),$H22*$I$31, TRUE, 0 ) -> 60000 | ... BL56: =IFS( AND(BL$36=$E$27,BL$33>=$I22),$H22*$E$31, AND(BL$36=$F$27,BL$33>=$I22),$H22*$F$31, AND(BL$36=$G$27,BL$33>=$I22),$H22*$G$31, AND(BL$36=$H$27,BL$33>=$I22),$H22*$H$31, AND(BL$36=$I$27,BL$33>=$I22),$H22*$I$31, TRUE, 0 ) -> 81629.338
D57: Accounts | E57: =IFS( AND(E$36=$E$27,E$33>=$I23),$H23*$E$31, AND(E$36=$F$27,E$33>=$I23),$H23*$F$31, AND(E$36=$G$27,E$33>=$I23),$H23*$G$31, AND(E$36=$H$27,E$33>=$I23),$H23*$H$31, AND(E$36=$I$27,E$33>=$I23),$H23*$I$31, TRUE, 0 ) -> 60000 | F57: =IFS( AND(F$36=$E$27,F$33>=$I23),$H23*$E$31, AND(F$36=$F$27,F$33>=$I23),$H23*$F$31, AND(F$36=$G$27,F$33>=$I23),$H23*$G$31, AND(F$36=$H$27,F$33>=$I23),$H23*$H$31, AND(F$36=$I$27,F$33>=$I23),$H23*$I$31, TRUE, 0 ) -> 60000 | G57: =IFS( AND(G$36=$E$27,G$33>=$I23),$H23*$E$31, AND(G$36=$F$27,G$33>=$I23),$H23*$F$31, AND(G$36=$G$27,G$33>=$I23),$H23*$G$31, AND(G$36=$H$27,G$33>=$I23),$H23*$H$31, AND(G$36=$I$27,G$33>=$I23),$H23*$I$31, TRUE, 0 ) -> 60000 | H57: =IFS( AND(H$36=$E$27,H$33>=$I23),$H23*$E$31, AND(H$36=$F$27,H$33>=$I23),$H23*$F$31, AND(H$36=$G$27,H$33>=$I23),$H23*$G$31, AND(H$36=$H$27,H$33>=$I23),$H23*$H$31, AND(H$36=$I$27,H$33>=$I23),$H23*$I$31, TRUE, 0 ) -> 60000 | I57: =IFS( AND(I$36=$E$27,I$33>=$I23),$H23*$E$31, AND(I$36=$F$27,I$33>=$I23),$H23*$F$31, AND(I$36=$G$27,I$33>=$I23),$H23*$G$31, AND(I$36=$H$27,I$33>=$I23),$H23*$H$31, AND(I$36=$I$27,I$33>=$I23),$H23*$I$31, TRUE, 0 ) -> 60000 | J57: =IFS( AND(J$36=$E$27,J$33>=$I23),$H23*$E$31, AND(J$36=$F$27,J$33>=$I23),$H23*$F$31, AND(J$36=$G$27,J$33>=$I23),$H23*$G$31, AND(J$36=$H$27,J$33>=$I23),$H23*$H$31, AND(J$36=$I$27,J$33>=$I23),$H23*$I$31, TRUE, 0 ) -> 60000 | K57: =IFS( AND(K$36=$E$27,K$33>=$I23),$H23*$E$31, AND(K$36=$F$27,K$33>=$I23),$H23*$F$31, AND(K$36=$G$27,K$33>=$I23),$H23*$G$31, AND(K$36=$H$27,K$33>=$I23),$H23*$H$31, AND(K$36=$I$27,K$33>=$I23),$H23*$I$31, TRUE, 0 ) -> 60000 | L57: =IFS( AND(L$36=$E$27,L$33>=$I23),$H23*$E$31, AND(L$36=$F$27,L$33>=$I23),$H23*$F$31, AND(L$36=$G$27,L$33>=$I23),$H23*$G$31, AND(L$36=$H$27,L$33>=$I23),$H23*$H$31, AND(L$36=$I$27,L$33>=$I23),$H23*$I$31, TRUE, 0 ) -> 60000 | ... BL57: =IFS( AND(BL$36=$E$27,BL$33>=$I23),$H23*$E$31, AND(BL$36=$F$27,BL$33>=$I23),$H23*$F$31, AND(BL$36=$G$27,BL$33>=$I23),$H23*$G$31, AND(BL$36=$H$27,BL$33>=$I23),$H23*$H$31, AND(BL$36=$I$27,BL$33>=$I23),$H23*$I$31, TRUE, 0 ) -> 81629.338
D58: Veterinary Doctor | E58: =IFS( AND(E$36=$E$27,E$33>=$I24),$G24 * E$38 * $E$31, AND(E$36=$F$27,E$33>=$I24),$G24 * E$38 * $F$31, AND(E$36=$G$27,E$33>=$I24),$G24 * E$38 * $G$31, AND(E$36=$H$27,E$33>=$I24),$G24 * E$38 * $H$31, AND(E$36=$I$27,E$33>=$I24),$G24 * E$38 * $I$31, TRUE, 0 ) -> 0 | F58: =IFS( AND(F$36=$E$27,F$33>=$I24),$G24 * F$38 * $E$31, AND(F$36=$F$27,F$33>=$I24),$G24 * F$38 * $F$31, AND(F$36=$G$27,F$33>=$I24),$G24 * F$38 * $G$31, AND(F$36=$H$27,F$33>=$I24),$G24 * F$38 * $H$31, AND(F$36=$I$27,F$33>=$I24),$G24 * F$38 * $I$31, TRUE, 0 ) -> 0 | G58: =IFS( AND(G$36=$E$27,G$33>=$I24),$G24 * G$38 * $E$31, AND(G$36=$F$27,G$33>=$I24),$G24 * G$38 * $F$31, AND(G$36=$G$27,G$33>=$I24),$G24 * G$38 * $G$31, AND(G$36=$H$27,G$33>=$I24),$G24 * G$38 * $H$31, AND(G$36=$I$27,G$33>=$I24),$G24 * G$38 * $I$31, TRUE, 0 ) -> 0 | H58: =IFS( AND(H$36=$E$27,H$33>=$I24),$G24 * H$38 * $E$31, AND(H$36=$F$27,H$33>=$I24),$G24 * H$38 * $F$31, AND(H$36=$G$27,H$33>=$I24),$G24 * H$38 * $G$31, AND(H$36=$H$27,H$33>=$I24),$G24 * H$38 * $H$31, AND(H$36=$I$27,H$33>=$I24),$G24 * H$38 * $I$31, TRUE, 0 ) -> 0 | I58: =IFS( AND(I$36=$E$27,I$33>=$I24),$G24 * I$38 * $E$31, AND(I$36=$F$27,I$33>=$I24),$G24 * I$38 * $F$31, AND(I$36=$G$27,I$33>=$I24),$G24 * I$38 * $G$31, AND(I$36=$H$27,I$33>=$I24),$G24 * I$38 * $H$31, AND(I$36=$I$27,I$33>=$I24),$G24 * I$38 * $I$31, TRUE, 0 ) -> 75000 | J58: =IFS( AND(J$36=$E$27,J$33>=$I24),$G24 * J$38 * $E$31, AND(J$36=$F$27,J$33>=$I24),$G24 * J$38 * $F$31, AND(J$36=$G$27,J$33>=$I24),$G24 * J$38 * $G$31, AND(J$36=$H$27,J$33>=$I24),$G24 * J$38 * $H$31, AND(J$36=$I$27,J$33>=$I24),$G24 * J$38 * $I$31, TRUE, 0 ) -> 150000 | K58: =IFS( AND(K$36=$E$27,K$33>=$I24),$G24 * K$38 * $E$31, AND(K$36=$F$27,K$33>=$I24),$G24 * K$38 * $F$31, AND(K$36=$G$27,K$33>=$I24),$G24 * K$38 * $G$31, AND(K$36=$H$27,K$33>=$I24),$G24 * K$38 * $H$31, AND(K$36=$I$27,K$33>=$I24),$G24 * K$38 * $I$31, TRUE, 0 ) -> 225000 | L58: =IFS( AND(L$36=$E$27,L$33>=$I24),$G24 * L$38 * $E$31, AND(L$36=$F$27,L$33>=$I24),$G24 * L$38 * $F$31, AND(L$36=$G$27,L$33>=$I24),$G24 * L$38 * $G$31, AND(L$36=$H$27,L$33>=$I24),$G24 * L$38 * $H$31, AND(L$36=$I$27,L$33>=$I24),$G24 * L$38 * $I$31, TRUE, 0 ) -> 300000 | ... BL58: =IFS( AND(BL$36=$E$27,BL$33>=$I24),$G24 * BL$38 * $E$31, AND(BL$36=$F$27,BL$33>=$I24),$G24 * BL$38 * $F$31, AND(BL$36=$G$27,BL$33>=$I24),$G24 * BL$38 * $G$31, AND(BL$36=$H$27,BL$33>=$I24),$G24 * BL$38 * $H$31, AND(BL$36=$I$27,BL$33>=$I24),$G24 * BL$38 * $I$31, TRUE, 0 ) -> 5714053.6
D59: Skilled Farm Supervisor | E59: =IFS( AND(E$36=$E$27,E$33>=$I25),$G25 * E$40 * $E$31, AND(E$36=$F$27,E$33>=$I25),$G25* E$40 * $F$31, AND(E$36=$G$27,E$33>=$I25),$G25* E$40 * $G$31, AND(E$36=$H$27,E$33>=$I25),$G25* E$40 * $H$31, AND(E$36=$I$27,E$33>=$I25),$G25* E$40 * $I$31, TRUE, 0 ) -> 0 | F59: =IFS( AND(F$36=$E$27,F$33>=$I25),$G25 * F$40 * $E$31, AND(F$36=$F$27,F$33>=$I25),$G25* F$40 * $F$31, AND(F$36=$G$27,F$33>=$I25),$G25* F$40 * $G$31, AND(F$36=$H$27,F$33>=$I25),$G25* F$40 * $H$31, AND(F$36=$I$27,F$33>=$I25),$G25* F$40 * $I$31, TRUE, 0 ) -> 0 | G59: =IFS( AND(G$36=$E$27,G$33>=$I25),$G25 * G$40 * $E$31, AND(G$36=$F$27,G$33>=$I25),$G25* G$40 * $F$31, AND(G$36=$G$27,G$33>=$I25),$G25* G$40 * $G$31, AND(G$36=$H$27,G$33>=$I25),$G25* G$40 * $H$31, AND(G$36=$I$27,G$33>=$I25),$G25* G$40 * $I$31, TRUE, 0 ) -> 0 | H59: =IFS( AND(H$36=$E$27,H$33>=$I25),$G25 * H$40 * $E$31, AND(H$36=$F$27,H$33>=$I25),$G25* H$40 * $F$31, AND(H$36=$G$27,H$33>=$I25),$G25* H$40 * $G$31, AND(H$36=$H$27,H$33>=$I25),$G25* H$40 * $H$31, AND(H$36=$I$27,H$33>=$I25),$G25* H$40 * $I$31, TRUE, 0 ) -> 0 | I59: =IFS( AND(I$36=$E$27,I$33>=$I25),$G25 * I$40 * $E$31, AND(I$36=$F$27,I$33>=$I25),$G25* I$40 * $F$31, AND(I$36=$G$27,I$33>=$I25),$G25* I$40 * $G$31, AND(I$36=$H$27,I$33>=$I25),$G25* I$40 * $H$31, AND(I$36=$I$27,I$33>=$I25),$G25* I$40 * $I$31, TRUE, 0 ) -> 3000 | J59: =IFS( AND(J$36=$E$27,J$33>=$I25),$G25 * J$40 * $E$31, AND(J$36=$F$27,J$33>=$I25),$G25* J$40 * $F$31, AND(J$36=$G$27,J$33>=$I25),$G25* J$40 * $G$31, AND(J$36=$H$27,J$33>=$I25),$G25* J$40 * $H$31, AND(J$36=$I$27,J$33>=$I25),$G25* J$40 * $I$31, TRUE, 0 ) -> 6000 | K59: =IFS( AND(K$36=$E$27,K$33>=$I25),$G25 * K$40 * $E$31, AND(K$36=$F$27,K$33>=$I25),$G25* K$40 * $F$31, AND(K$36=$G$27,K$33>=$I25),$G25* K$40 * $G$31, AND(K$36=$H$27,K$33>=$I25),$G25* K$40 * $H$31, AND(K$36=$I$27,K$33>=$I25),$G25* K$40 * $I$31, TRUE, 0 ) -> 9000 | L59: =IFS( AND(L$36=$E$27,L$33>=$I25),$G25 * L$40 * $E$31, AND(L$36=$F$27,L$33>=$I25),$G25* L$40 * $F$31, AND(L$36=$G$27,L$33>=$I25),$G25* L$40 * $G$31, AND(L$36=$H$27,L$33>=$I25),$G25* L$40 * $H$31, AND(L$36=$I$27,L$33>=$I25),$G25* L$40 * $I$31, TRUE, 0 ) -> 12000 | ... BL59: =IFS( AND(BL$36=$E$27,BL$33>=$I25),$G25 * BL$40 * $E$31, AND(BL$36=$F$27,BL$33>=$I25),$G25* BL$40 * $F$31, AND(BL$36=$G$27,BL$33>=$I25),$G25* BL$40 * $G$31, AND(BL$36=$H$27,BL$33>=$I25),$G25* BL$40 * $H$31, AND(BL$36=$I$27,BL$33>=$I25),$G25* BL$40 * $I$31, TRUE, 0 ) -> 228562.15
D60: Total HR Cost | E60: =SUM(E42:E59) -> 230000 | F60: =SUM(F42:F59) -> 230000 | G60: =SUM(G42:G59) -> 230000 | H60: =SUM(H42:H59) -> 230000 | I60: =SUM(I42:I59) -> 488000 | J60: =SUM(J42:J59) -> 898000 | K60: =SUM(K42:K59) -> 1247000 | L60: =SUM(L42:L59) -> 1391000 | ... BL60: =SUM(BL42:BL59) -> 7971104.8

Sheet CAPEX & DEPRECIATION
A1: =COVER!$B$12 -> Narayan Dairy Project
A2: Capex & Depreciation
D4: Asset Category | E4: Amount | F4: Phase | G4: Start Month | H4: Useful Life | I4: Depreciation
D7: Land | E7: ='FUNDING REQUIREMENT'!E8 -> 50000000 | F7: Phase 1 | G7: 1 | H7: 0 | I7: =IF($H7 = 0, 0, $E7/($H7 * 12)) -> 0
D8: Boundary Wall | E8: ='FUNDING REQUIREMENT'!E9 -> 11264000 | F8: Phase 1 | G8: 2 | H8: 15 | I8: =IF($H8 = 0, 0, $E8/($H8 * 12)) -> 62577.778
D9: Borewell & Water Testing | E9: ='FUNDING REQUIREMENT'!E10 -> 500000 | F9: Phase 1 | G9: 2 | H9: 10 | I9: =IF($H9 = 0, 0, $E9/($H9 * 12)) -> 4166.6667
D10: Shed Construction 1 | E10: ='FUNDING REQUIREMENT'!E11 -> 20000000 | F10: Phase 1 | G10: 3 | H10: 20 | I10: =IF($H10 = 0, 0, $E10/($H10 * 12)) -> 83333.333
D11: Stamp Duty & Legal | E11: ='FUNDING REQUIREMENT'!E12 -> 5000000 | F11: Phase 1 | G11: 1 | H11: 5 | I11: =IF($H11 = 0, 0, $E11/($H11 * 12)) -> 83333.333
D12: Bank Deposit | E12: ='FUNDING REQUIREMENT'!E13 -> 2500000 | F12: Phase 1 | G12: 1 | H12: 0 | I12: =IF($H12 = 0, 0, $E12/($H12 * 12)) -> 0
D13: Land Levelling | E13: ='FUNDING REQUIREMENT'!E14 -> 5000000 | F13: Phase 1 | G13: 2 | H13: 10 | I13: =IF($H13 = 0, 0, $E13/($H13 * 12)) -> 41666.667
D14: Plant & Civil Work | E14: ='FUNDING REQUIREMENT'!E17 -> 28736000 | F14: Phase 2 | G14: 5 | H14: 15 | I14: =IF($H14 = 0, 0, $E14/($H14 * 12)) -> 159644.44
D15: Machinery Advance | E15: ='FUNDING REQUIREMENT'!E18 -> 30000000 | F15: Phase 2 | G15: 5 | H15: 10 | I15: =IF($H15 = 0, 0, $E15/($H15 * 12)) -> 250000
D16: Cow Mats | E16: ='FUNDING REQUIREMENT'!E19 -> 2500000 | F16: Phase 2 | G16: 6 | H16: 5 | I16: =IF($H16 = 0, 0, $E16/($H16 * 12)) -> 41666.667
D17: Livestock Batch 1 | E17: =('FUNDING REQUIREMENT'!E20 / 250) * 200 -> 18000000 | F17: Phase 2 | G17: 5 | H17: 8 | I17: =IF($H17 = 0, 0, $E17/($H17 * 12)) -> 187500
D18: Solar System | E18: ='FUNDING REQUIREMENT'!E21 -> 13000000 | F18: Phase 2 | G18: 6 | H18: 15 | I18: =IF($H18 = 0, 0, $E18/($H18 * 12)) -> 72222.222
D19: Transport Vehicles | E19: ='FUNDING REQUIREMENT'!E22 -> 5000000 | F19: Phase 2 | G19: 6 | H19: 8 | I19: =IF($H19 = 0, 0, $E19/($H19 * 12)) -> 52083.333
D20: Plant & Machinery Final | E20: ='FUNDING REQUIREMENT'!E27 -> 70000000 | F20: Phase 3 | G20: 7 | H20: 10 | I20: =IF($H20 = 0, 0, $E20/($H20 * 12)) -> 583333.33
D21: Apartment Cart | E21: ='FUNDING REQUIREMENT'!E28 -> 500000 | F21: Phase 3 | G21: 7 | H21: 5 | I21: =IF($H21 = 0, 0, $E21/($H21 * 12)) -> 8333.3333
D22: Livestock Batch 2 | E22: =SUM('FUNDING REQUIREMENT'!E20/250 * 50 + 'FUNDING REQUIREMENT'!E29) -> 27000000 | F22: Phase 3 | G22: 25 | H22: 8 | I22: =IF($H22 = 0, 0, $E22/($H22 * 12)) -> 281250
D23: Transport Vehicles Batch 2 | E23: ='FUNDING REQUIREMENT'!E30 -> 5000000 | F23: Phase 3 | G23: 12 | H23: 8 | I23: =IF($H23 = 0, 0, $E23/($H23 * 12)) -> 52083.333
D24: Shed Construction 2 | E24: 5000000 | G24: 30 | H24: 20 | I24: =IF($H24 = 0, 0, $E24/($H24 * 12)) -> 20833.333
D26: Asset | E26: 1 | F26: =E26+1 -> 2 | G26: =F26+1 -> 3 | H26: =G26+1 -> 4 | I26: =H26+1 -> 5 | J26: =I26+1 -> 6 | K26: =J26+1 -> 7 | L26: =K26+1 -> 8 | M26: =L26+1 -> 9 | ... BL26: =BK26+1 -> 60
D29: Section A – Monthly Depreciation Schedule
D30: =D7 -> Land | E30: =IF(E$26 >= $G7, $I7, 0) -> 0 | F30: =IF(F$26 >= $G7, $I7, 0) -> 0 | G30: =IF(G$26 >= $G7, $I7, 0) -> 0 | H30: =IF(H$26 >= $G7, $I7, 0) -> 0 | I30: =IF(I$26 >= $G7, $I7, 0) -> 0 | J30: =IF(J$26 >= $G7, $I7, 0) -> 0 | K30: =IF(K$26 >= $G7, $I7, 0) -> 0 | L30: =IF(L$26 >= $G7, $I7, 0) -> 0 | ... BL30: =IF(BL$26 >= $G7, $I7, 0) -> 0
D31: =D8 -> Boundary Wall | E31: =IF(E$26 >= $G8, $I8, 0) -> 0 | F31: =IF(F$26 >= $G8, $I8, 0) -> 62577.778 | G31: =IF(G$26 >= $G8, $I8, 0) -> 62577.778 | H31: =IF(H$26 >= $G8, $I8, 0) -> 62577.778 | I31: =IF(I$26 >= $G8, $I8, 0) -> 62577.778 | J31: =IF(J$26 >= $G8, $I8, 0) -> 62577.778 | K31: =IF(K$26 >= $G8, $I8, 0) -> 62577.778 | L31: =IF(L$26 >= $G8, $I8, 0) -> 62577.778 | ... BL31: =IF(BL$26 >= $G8, $I8, 0) -> 62577.778
D32: =D9 -> Borewell & Water Testing | E32: =IF(E$26 >= $G9, $I9, 0) -> 0 | F32: =IF(F$26 >= $G9, $I9, 0) -> 4166.6667 | G32: =IF(G$26 >= $G9, $I9, 0) -> 4166.6667 | H32: =IF(H$26 >= $G9, $I9, 0) -> 4166.6667 | I32: =IF(I$26 >= $G9, $I9, 0) -> 4166.6667 | J32: =IF(J$26 >= $G9, $I9, 0) -> 4166.6667 | K32: =IF(K$26 >= $G9, $I9, 0) -> 4166.6667 | L32: =IF(L$26 >= $G9, $I9, 0) -> 4166.6667 | ... BL32: =IF(BL$26 >= $G9, $I9, 0) -> 4166.6667
D33: =D10 -> Shed Construction 1 | E33: =IF(E$26 >= $G10, $I10, 0) -> 0 | F33: =IF(F$26 >= $G10, $I10, 0) -> 0 | G33: =IF(G$26 >= $G10, $I10, 0) -> 83333.333 | H33: =IF(H$26 >= $G10, $I10, 0) -> 83333.333 | I33: =IF(I$26 >= $G10, $I10, 0) -> 83333.333 | J33: =IF(J$26 >= $G10, $I10, 0) -> 83333.333 | K33: =IF(K$26 >= $G10, $I10, 0) -> 83333.333 | L33: =IF(L$26 >= $G10, $I10, 0) -> 83333.333 | ... BL33: =IF(BL$26 >= $G10, $I10, 0) -> 83333.333
D34: =D11 -> Stamp Duty & Legal | E34: =IF(E$26 >= $G11, $I11, 0) -> 83333.333 | F34: =IF(F$26 >= $G11, $I11, 0) -> 83333.333 | G34: =IF(G$26 >= $G11, $I11, 0) -> 83333.333 | H34: =IF(H$26 >= $G11, $I11, 0) -> 83333.333 | I34: =IF(I$26 >= $G11, $I11, 0) -> 83333.333 | J34: =IF(J$26 >= $G11, $I11, 0) -> 83333.333 | K34: =IF(K$26 >= $G11, $I11, 0) -> 83333.333 | L34: =IF(L$26 >= $G11, $I11, 0) -> 83333.333 | ... BL34: =IF(BL$26 >= $G11, $I11, 0) -> 83333.333
D35: =D12 -> Bank Deposit | E35: =IF(E$26 >= $G12, $I12, 0) -> 0 | F35: =IF(F$26 >= $G12, $I12, 0) -> 0 | G35: =IF(G$26 >= $G12, $I12, 0) -> 0 | H35: =IF(H$26 >= $G12, $I12, 0) -> 0 | I35: =IF(I$26 >= $G12, $I12, 0) -> 0 | J35: =IF(J$26 >= $G12, $I12, 0) -> 0 | K35: =IF(K$26 >= $G12, $I12, 0) -> 0 | L35: =IF(L$26 >= $G12, $I12, 0) -> 0 | ... BL35: =IF(BL$26 >= $G12, $I12, 0) -> 0
D36: =D13 -> Land Levelling | E36: =IF(E$26 >= $G13, $I13, 0) -> 0 | F36: =IF(F$26 >= $G13, $I13, 0) -> 41666.667 | G36: =IF(G$26 >= $G13, $I13, 0) -> 41666.667 | H36: =IF(H$26 >= $G13, $I13, 0) -> 41666.667 | I36: =IF(I$26 >= $G13, $I13, 0) -> 41666.667 | J36: =IF(J$26 >= $G13, $I13, 0) -> 41666.667 | K36: =IF(K$26 >= $G13, $I13, 0) -> 41666.667 | L36: =IF(L$26 >= $G13, $I13, 0) -> 41666.667 | ... BL36: =IF(BL$26 >= $G13, $I13, 0) -> 41666.667
D37: =D14 -> Plant & Civil Work | E37: =IF(E$26 >= $G14, $I14, 0) -> 0 | F37: =IF(F$26 >= $G14, $I14, 0) -> 0 | G37: =IF(G$26 >= $G14, $I14, 0) -> 0 | H37: =IF(H$26 >= $G14, $I14, 0) -> 0 | I37: =IF(I$26 >= $G14, $I14, 0) -> 159644.44 | J37: =IF(J$26 >= $G14, $I14, 0) -> 159644.44 | K37: =IF(K$26 >= $G14, $I14, 0) -> 159644.44 | L37: =IF(L$26 >= $G14, $I14, 0) -> 159644.44 | ... BL37: =IF(BL$26 >= $G14, $I14, 0) -> 159644.44
D38: =D15 -> Machinery Advance | E38: =IF(E$26 >= $G15, $I15, 0) -> 0 | F38: =IF(F$26 >= $G15, $I15, 0) -> 0 | G38: =IF(G$26 >= $G15, $I15, 0) -> 0 | H38: =IF(H$26 >= $G15, $I15, 0) -> 0 | I38: =IF(I$26 >= $G15, $I15, 0) -> 250000 | J38: =IF(J$26 >= $G15, $I15, 0) -> 250000 | K38: =IF(K$26 >= $G15, $I15, 0) -> 250000 | L38: =IF(L$26 >= $G15, $I15, 0) -> 250000 | ... BL38: =IF(BL$26 >= $G15, $I15, 0) -> 250000
D39: =D16 -> Cow Mats | E39: =IF(E$26 >= $G16, $I16, 0) -> 0 | F39: =IF(F$26 >= $G16, $I16, 0) -> 0 | G39: =IF(G$26 >= $G16, $I16, 0) -> 0 | H39: =IF(H$26 >= $G16, $I16, 0) -> 0 | I39: =IF(I$26 >= $G16, $I16, 0) -> 0 | J39: =IF(J$26 >= $G16, $I16, 0) -> 41666.667 | K39: =IF(K$26 >= $G16, $I16, 0) -> 41666.667 | L39: =IF(L$26 >= $G16, $I16, 0) -> 41666.667 | ... BL39: =IF(BL$26 >= $G16, $I16, 0) -> 41666.667
D40: =D17 -> Livestock Batch 1 | E40: =IF(E$26 >= $G17, $I17, 0) -> 0 | F40: =IF(F$26 >= $G17, $I17, 0) -> 0 | G40: =IF(G$26 >= $G17, $I17, 0) -> 0 | H40: =IF(H$26 >= $G17, $I17, 0) -> 0 | I40: =IF(I$26 >= $G17, $I17, 0) -> 187500 | J40: =IF(J$26 >= $G17, $I17, 0) -> 187500 | K40: =IF(K$26 >= $G17, $I17, 0) -> 187500 | L40: =IF(L$26 >= $G17, $I17, 0) -> 187500 | ... BL40: =IF(BL$26 >= $G17, $I17, 0) -> 187500
D41: =D18 -> Solar System | E41: =IF(E$26 >= $G18, $I18, 0) -> 0 | F41: =IF(F$26 >= $G18, $I18, 0) -> 0 | G41: =IF(G$26 >= $G18, $I18, 0) -> 0 | H41: =IF(H$26 >= $G18, $I18, 0) -> 0 | I41: =IF(I$26 >= $G18, $I18, 0) -> 0 | J41: =IF(J$26 >= $G18, $I18, 0) -> 72222.222 | K41: =IF(K$26 >= $G18, $I18, 0) -> 72222.222 | L41: =IF(L$26 >= $G18, $I18, 0) -> 72222.222 | ... BL41: =IF(BL$26 >= $G18, $I18, 0) -> 72222.222
... D47: =D24 -> Shed Construction 2 | E47: =IF(E$26 >= $G24, $I24, 0) -> 0 | F47: =IF(F$26 >= $G24, $I24, 0) -> 0 | G47: =IF(G$26 >= $G24, $I24, 0) -> 0 | H47: =IF(H$26 >= $G24, $I24, 0) -> 0 | I47: =IF(I$26 >= $G24, $I24, 0) -> 0 | J47: =IF(J$26 >= $G24, $I24, 0) -> 0 | K47: =IF(K$26 >= $G24, $I24, 0) -> 0 | L47: =IF(L$26 >= $G24, $I24, 0) -> 0 | ... BL47: =IF(BL$26 >= $G24, $I24, 0) -> 20833.333
D48: Total Depreciation | E48: =SUM(E30:E47) -> 83333.333 | F48: =SUM(F30:F47) -> 191744.44 | G48: =SUM(G30:G47) -> 275077.78 | H48: =SUM(H30:H47) -> 275077.78 | I48: =SUM(I30:I47) -> 872222.22 | J48: =SUM(J30:J47) -> 1038194.4 | K48: =SUM(K30:K47) -> 1629861.1 | L48: =SUM(L30:L47) -> 1629861.1 | ... BL48: =SUM(BL30:BL47) -> 1984027.8
D49: Section B – Monthly Capex Schedule
D50: =D7 -> Land | E50: =IF(E$26 = $G7, $E7, 0) -> 50000000 | F50: =IF(F$26 = $G7, $E7, 0) -> 0 | G50: =IF(G$26 = $G7, $E7, 0) -> 0 | H50: =IF(H$26 = $G7, $E7, 0) -> 0 | I50: =IF(I$26 = $G7, $E7, 0) -> 0 | J50: =IF(J$26 = $G7, $E7, 0) -> 0 | K50: =IF(K$26 = $G7, $E7, 0) -> 0 | L50: =IF(L$26 = $G7, $E7, 0) -> 0 | ... BL50: =IF(BL$26 = $G7, $E7, 0) -> 0
D51: =D8 -> Boundary Wall | E51: =IF(E$26 = $G8, $E8, 0) -> 0 | F51: =IF(F$26 = $G8, $E8, 0) -> 11264000 | G51: =IF(G$26 = $G8, $E8, 0) -> 0 | H51: =IF(H$26 = $G8, $E8, 0) -> 0 | I51: =IF(I$26 = $G8, $E8, 0) -> 0 | J51: =IF(J$26 = $G8, $E8, 0) -> 0 | K51: =IF(K$26 = $G8, $E8, 0) -> 0 | L51: =IF(L$26 = $G8, $E8, 0) -> 0 | ... BL51: =IF(BL$26 = $G8, $E8, 0) -> 0
D52: =D9 -> Borewell & Water Testing | E52: =IF(E$26 = $G9, $E9, 0) -> 0 | F52: =IF(F$26 = $G9, $E9, 0) -> 500000 | G52: =IF(G$26 = $G9, $E9, 0) -> 0 | H52: =IF(H$26 = $G9, $E9, 0) -> 0 | I52: =IF(I$26 = $G9, $E9, 0) -> 0 | J52: =IF(J$26 = $G9, $E9, 0) -> 0 | K52: =IF(K$26 = $G9, $E9, 0) -> 0 | L52: =IF(L$26 = $G9, $E9, 0) -> 0 | ... BL52: =IF(BL$26 = $G9, $E9, 0) -> 0
D53: =D10 -> Shed Construction 1 | E53: =IF(E$26 = $G10, $E10, 0) -> 0 | F53: =IF(F$26 = $G10, $E10, 0) -> 0 | G53: =IF(G$26 = $G10, $E10, 0) -> 20000000 | H53: =IF(H$26 = $G10, $E10, 0) -> 0 | I53: =IF(I$26 = $G10, $E10, 0) -> 0 | J53: =IF(J$26 = $G10, $E10, 0) -> 0 | K53: =IF(K$26 = $G10, $E10, 0) -> 0 | L53: =IF(L$26 = $G10, $E10, 0) -> 0 | ... BL53: =IF(BL$26 = $G10, $E10, 0) -> 0
D54: =D11 -> Stamp Duty & Legal | E54: =IF(E$26 = $G11, $E11, 0) -> 5000000 | F54: =IF(F$26 = $G11, $E11, 0) -> 0 | G54: =IF(G$26 = $G11, $E11, 0) -> 0 | H54: =IF(H$26 = $G11, $E11, 0) -> 0 | I54: =IF(I$26 = $G11, $E11, 0) -> 0 | J54: =IF(J$26 = $G11, $E11, 0) -> 0 | K54: =IF(K$26 = $G11, $E11, 0) -> 0 | L54: =IF(L$26 = $G11, $E11, 0) -> 0 | ... BL54: =IF(BL$26 = $G11, $E11, 0) -> 0
D55: =D12 -> Bank Deposit | E55: =IF(E$26 = $G12, $E12, 0) -> 2500000 | F55: =IF(F$26 = $G12, $E12, 0) -> 0 | G55: =IF(G$26 = $G12, $E12, 0) -> 0 | H55: =IF(H$26 = $G12, $E12, 0) -> 0 | I55: =IF(I$26 = $G12, $E12, 0) -> 0 | J55: =IF(J$26 = $G12, $E12, 0) -> 0 | K55: =IF(K$26 = $G12, $E12, 0) -> 0 | L55: =IF(L$26 = $G12, $E12, 0) -> 0 | ... BL55: =IF(BL$26 = $G12, $E12, 0) -> 0
D56: =D13 -> Land Levelling | E56: =IF(E$26 = $G13, $E13, 0) -> 0 | F56: =IF(F$26 = $G13, $E13, 0) -> 5000000 | G56: =IF(G$26 = $G13, $E13, 0) -> 0 | H56: =IF(H$26 = $G13, $E13, 0) -> 0 | I56: =IF(I$26 = $G13, $E13, 0) -> 0 | J56: =IF(J$26 = $G13, $E13, 0) -> 0 | K56: =IF(K$26 = $G13, $E13, 0) -> 0 | L56: =IF(L$26 = $G13, $E13, 0) -> 0 | ... BL56: =IF(BL$26 = $G13, $E13, 0) -> 0
D57: =D14 -> Plant & Civil Work | E57: =IF(E$26 = $G14, $E14, 0) -> 0 | F57: =IF(F$26 = $G14, $E14, 0) -> 0 | G57: =IF(G$26 = $G14, $E14, 0) -> 0 | H57: =IF(H$26 = $G14, $E14, 0) -> 0 | I57: =IF(I$26 = $G14, $E14, 0) -> 28736000 | J57: =IF(J$26 = $G14, $E14, 0) -> 0 | K57: =IF(K$26 = $G14, $E14, 0) -> 0 | L57: =IF(L$26 = $G14, $E14, 0) -> 0 | ... BL57: =IF(BL$26 = $G14, $E14, 0) -> 0
D58: =D15 -> Machinery Advance | E58: =IF(E$26 = $G15, $E15, 0) -> 0 | F58: =IF(F$26 = $G15, $E15, 0) -> 0 | G58: =IF(G$26 = $G15, $E15, 0) -> 0 | H58: =IF(H$26 = $G15, $E15, 0) -> 0 | I58: =IF(I$26 = $G15, $E15, 0) -> 30000000 | J58: =IF(J$26 = $G15, $E15, 0) -> 0 | K58: =IF(K$26 = $G15, $E15, 0) -> 0 | L58: =IF(L$26 = $G15, $E15, 0) -> 0 | ... BL58: =IF(BL$26 = $G15, $E15, 0) -> 0
D59: =D16 -> Cow Mats | E59: =IF(E$26 = $G16, $E16, 0) -> 0 | F59: =IF(F$26 = $G16, $E16, 0) -> 0 | G59: =IF(G$26 = $G16, $E16, 0) -> 0 | H59: =IF(H$26 = $G16, $E16, 0) -> 0 | I59: =IF(I$26 = $G16, $E16, 0) -> 0 | J59: =IF(J$26 = $G16, $E16, 0) -> 2500000 | K59: =IF(K$26 = $G16, $E16, 0) -> 0 | L59: =IF(L$26 = $G16, $E16, 0) -> 0 | ... BL59: =IF(BL$26 = $G16, $E16, 0) -> 0
D60: =D17 -> Livestock Batch 1 | E60: =IF(E$26 = $G17, $E17, 0) -> 0 | F60: =IF(F$26 = $G17, $E17, 0) -> 0 | G60: =IF(G$26 = $G17, $E17, 0) -> 0 | H60: =IF(H$26 = $G17, $E17, 0) -> 0 | I60: =IF(I$26 = $G17, $E17, 0) -> 18000000 | J60: =IF(J$26 = $G17, $E17, 0) -> 0 | K60: =IF(K$26 = $G17, $E17, 0) -> 0 | L60: =IF(L$26 = $G17, $E17, 0) -> 0 | ... BL60: =IF(BL$26 = $G17, $E17, 0) -> 0
D61: =D18 -> Solar System | E61: =IF(E$26 = $G18, $E18, 0) -> 0 | F61: =IF(F$26 = $G18, $E18, 0) -> 0 | G61: =IF(G$26 = $G18, $E18, 0) -> 0 | H61: =IF(H$26 = $G18, $E18, 0) -> 0 | I61: =IF(I$26 = $G18, $E18, 0) -> 0 | J61: =IF(J$26 = $G18, $E18, 0) -> 13000000 | K61: =IF(K$26 = $G18, $E18, 0) -> 0 | L61: =IF(L$26 = $G18, $E18, 0) -> 0 | ... BL61: =IF(BL$26 = $G18, $E18, 0) -> 0
... D67: =D24 -> Shed Construction 2 | E67: =IF(E$26 = $G24, $E24, 0) -> 0 | F67: =IF(F$26 = $G24, $E24, 0) -> 0 | G67: =IF(G$26 = $G24, $E24, 0) -> 0 | H67: =IF(H$26 = $G24, $E24, 0) -> 0 | I67: =IF(I$26 = $G24, $E24, 0) -> 0 | J67: =IF(J$26 = $G24, $E24, 0) -> 0 | K67: =IF(K$26 = $G24, $E24, 0) -> 0 | L67: =IF(L$26 = $G24, $E24, 0) -> 0 | ... BL67: =IF(BL$26 = $G24, $E24, 0) -> 0
D68: Total Capex | E68: =SUM(E50:E67) -> 57500000 | F68: =SUM(F50:F67) -> 16764000 | G68: =SUM(G50:G67) -> 20000000 | H68: =SUM(H50:H67) -> 0 | I68: =SUM(I50:I67) -> 76736000 | J68: =SUM(J50:J67) -> 20500000 | K68: =SUM(K50:K67) -> 70500000 | L68: =SUM(L50:L67) -> 0 | ... BL68: =SUM(BL50:BL67) -> 0

Sheet WORKING CAPITAL SCHEDULE
A1: =COVER!$B$12 -> Narayan Dairy Project
A2: Working Capital Schedule
D4: Particulars / Month | E4: 1 | F4: =E4+1 -> 2 | G4: =F4+1 -> 3 | H4: =G4+1 -> 4 | I4: =H4+1 -> 5 | J4: =I4+1 -> 6 | K4: =J4+1 -> 7 | L4: =K4+1 -> 8 | M4: =L4+1 -> 9 | ... BL4: =BK4+1 -> 60
D7: Total Revenue | E7: ='PRODUCT PRICING & REVENUE ENGIN'!E58 -> 0 | F7: ='PRODUCT PRICING & REVENUE ENGIN'!F58 -> 0 | G7: ='PRODUCT PRICING & REVENUE ENGIN'!G58 -> 0 | H7: ='PRODUCT PRICING & REVENUE ENGIN'!H58 -> 0 | I7: ='PRODUCT PRICING & REVENUE ENGIN'!I58 -> 2387024.6 | J7: ='PRODUCT PRICING & REVENUE ENGIN'!J58 -> 4774049.3 | K7: ='PRODUCT PRICING & REVENUE ENGIN'!K58 -> 19546446 | L7: ='PRODUCT PRICING & REVENUE ENGIN'!L58 -> 21933471 | ... BL7: ='PRODUCT PRICING & REVENUE ENGIN'!BL58 -> 2.8028502e+08
D8: Receivable Days | E8: =ASSUMPTIONS!$H$46 -> 1 | F8: =ASSUMPTIONS!$H$46 -> 1 | G8: =ASSUMPTIONS!$H$46 -> 1 | H8: =ASSUMPTIONS!$H$46 -> 1 | I8: =ASSUMPTIONS!$H$46 -> 1 | J8: =ASSUMPTIONS!$H$46 -> 1 | K8: =ASSUMPTIONS!$H$46 -> 1 | L8: =ASSUMPTIONS!$H$46 -> 1 | ... BL8: =ASSUMPTIONS!$H$46 -> 1
D9: Receivables Formula | E9: =(E7 / 30) * E8 -> 0 | F9: =(F7 / 30) * F8 -> 0 | G9: =(G7 / 30) * G8 -> 0 | H9: =(H7 / 30) * H8 -> 0 | I9: =(I7 / 30) * I8 -> 79567.488 | J9: =(J7 / 30) * J8 -> 159134.98 | K9: =(K7 / 30) * K8 -> 651548.21 | L9: =(L7 / 30) * L8 -> 731115.7 | ... BL9: =(BL7 / 30) * BL8 -> 9342833.9
D10: Inventory Days | E10: =ASSUMPTIONS!$H$47 -> 5 | F10: =ASSUMPTIONS!$H$47 -> 5 | G10: =ASSUMPTIONS!$H$47 -> 5 | H10: =ASSUMPTIONS!$H$47 -> 5 | I10: =ASSUMPTIONS!$H$47 -> 5 | J10: =ASSUMPTIONS!$H$47 -> 5 | K10: =ASSUMPTIONS!$H$47 -> 5 | L10: =ASSUMPTIONS!$H$47 -> 5 | ... BL10: =ASSUMPTIONS!$H$47 -> 5
D11: Total COGS | E11: ='COGS ENGINE'!E39 -> 0 | F11: ='COGS ENGINE'!F39 -> 0 | G11: ='COGS ENGINE'!G39 -> 0 | H11: ='COGS ENGINE'!H39 -> 0 | I11: ='COGS ENGINE'!I39 -> 1892443 | J11: ='COGS ENGINE'!J39 -> 3784885.9 | K11: ='COGS ENGINE'!K39 -> 15294868 | L11: ='COGS ENGINE'!L39 -> 17187311 | ... BL11: ='COGS ENGINE'!BL39 -> 2.0855088e+08
D12: Inventory Formula | E12: =(E11 / 30) * E10 -> 0 | F12: =(F11 / 30) * F10 -> 0 | G12: =(G11 / 30) * G10 -> 0 | H12: =(H11 / 30) * H10 -> 0 | I12: =(I11 / 30) * I10 -> 315407.16 | J12: =(J11 / 30) * J10 -> 630814.32 | K12: =(K11 / 30) * K10 -> 2549144.7 | L12: =(L11 / 30) * L10 -> 2864551.9 | ... BL12: =(BL11 / 30) * BL10 -> 34758480
D13: Payables Days | E13: =ASSUMPTIONS!$H$48 -> 2 | F13: =ASSUMPTIONS!$H$48 -> 2 | G13: =ASSUMPTIONS!$H$48 -> 2 | H13: =ASSUMPTIONS!$H$48 -> 2 | I13: =ASSUMPTIONS!$H$48 -> 2 | J13: =ASSUMPTIONS!$H$48 -> 2 | K13: =ASSUMPTIONS!$H$48 -> 2 | L13: =ASSUMPTIONS!$H$48 -> 2 | ... BL13: =ASSUMPTIONS!$H$48 -> 2
D14: Payables Formula | E14: =(E11 / 30) *E13 -> 0 | F14: =(F11 / 30) *F13 -> 0 | G14: =(G11 / 30) *G13 -> 0 | H14: =(H11 / 30) *H13 -> 0 | I14: =(I11 / 30) *I13 -> 126162.86 | J14: =(J11 / 30) *J13 -> 252325.73 | K14: =(K11 / 30) *K13 -> 1019657.9 | L14: =(L11 / 30) *L13 -> 1145820.7 | ... BL14: =(BL11 / 30) *BL13 -> 13903392
D15: Net Working Capital | E15: =E9 + E12 - E14 -> 0 | F15: =F9 + F12 - F14 -> 0 | G15: =G9 + G12 - G14 -> 0 | H15: =H9 + H12 - H14 -> 0 | I15: =I9 + I12 - I14 -> 268811.78 | J15: =J9 + J12 - J14 -> 537623.57 | K15: =K9 + K12 - K14 -> 2181035 | L15: =L9 + L12 - L14 -> 2449846.8 | ... BL15: =BL9 + BL12 - BL14 -> 30197922
D16: Change in Working Capital | E16: =E15 -> 0 | F16: =F15 - E15 -> 0 | G16: =G15 - F15 -> 0 | H16: =H15 - G15 -> 0 | I16: =I15 - H15 -> 268811.78 | J16: =J15 - I15 -> 268811.78 | K16: =K15 - J15 -> 1643411.5 | L16: =L15 - K15 -> 268811.78 | M16: =M15 - L15 -> 268811.78 | ... BL16: =BL15 - BK15 -> 0

Sheet P&L
A1: =COVER!$B$12 -> Narayan Dairy Project
A2: Profit & Loss Statement
D4: Month | E4: 1 | F4: =E4+1 -> 2 | G4: =F4+1 -> 3 | H4: =G4+1 -> 4 | I4: =H4+1 -> 5 | J4: =I4+1 -> 6 | K4: =J4+1 -> 7 | L4: =K4+1 -> 8 | M4: =L4+1 -> 9 | ... BL4: =BK4+1 -> 60
C7: 1. | D7: Total Revenue | E7: ='PRODUCT PRICING & REVENUE ENGIN'!E58 -> 0 | F7: ='PRODUCT PRICING & REVENUE ENGIN'!F58 -> 0 | G7: ='PRODUCT PRICING & REVENUE ENGIN'!G58 -> 0 | H7: ='PRODUCT PRICING & REVENUE ENGIN'!H58 -> 0 | I7: ='PRODUCT PRICING & REVENUE ENGIN'!I58 -> 2387024.6 | J7: ='PRODUCT PRICING & REVENUE ENGIN'!J58 -> 4774049.3 | K7: ='PRODUCT PRICING & REVENUE ENGIN'!K58 -> 19546446 | L7: ='PRODUCT PRICING & REVENUE ENGIN'!L58 -> 21933471 | ... BL7: ='PRODUCT PRICING & REVENUE ENGIN'!BL58 -> 2.8028502e+08
C8: 2. | D8: Total COGS | E8: ='COGS ENGINE'!E39 -> 0 | F8: ='COGS ENGINE'!F39 -> 0 | G8: ='COGS ENGINE'!G39 -> 0 | H8: ='COGS ENGINE'!H39 -> 0 | I8: ='COGS ENGINE'!I39 -> 1892443 | J8: ='COGS ENGINE'!J39 -> 3784885.9 | K8: ='COGS ENGINE'!K39 -> 15294868 | L8: ='COGS ENGINE'!L39 -> 17187311 | ... BL8: ='COGS ENGINE'!BL39 -> 2.0855088e+08
C9: 3. | D9: Gross Profit | E9: =E7 - E8 -> 0 | F9: =F7 - F8 -> 0 | G9: =G7 - G8 -> 0 | H9: =H7 - H8 -> 0 | I9: =I7 - I8 -> 494581.68 | J9: =J7 - J8 -> 989163.37 | K9: =K7 - K8 -> 4251578 | L9: =L7 - L8 -> 4746159.7 | ... BL9: =BL7 - BL8 -> 71734135
C10: A. | D10: Gross Margin % | E10: =IF(E9 = 0, 0, E9 / E7) -> 0 | F10: =IF(F9 = 0, 0, F9 / F7) -> 0 | G10: =IF(G9 = 0, 0, G9 / G7) -> 0 | H10: =IF(H9 = 0, 0, H9 / H7) -> 0 | I10: =IF(I9 = 0, 0, I9 / I7) -> 0.20719589 | J10: =IF(J9 = 0, 0, J9 / J7) -> 0.20719589 | K10: =IF(K9 = 0, 0, K9 / K7) -> 0.21751156 | L10: =IF(L9 = 0, 0, L9 / L7) -> 0.2163889 | ... BL10: =IF(BL9 = 0, 0, BL9 / BL7) -> 0.25593282
C11: 4. | D11: Total Operating Expenses | E11: ='HR & OPERATING EXPENSES'!E60 -> 230000 | F11: ='HR & OPERATING EXPENSES'!F60 -> 230000 | G11: ='HR & OPERATING EXPENSES'!G60 -> 230000 | H11: ='HR & OPERATING EXPENSES'!H60 -> 230000 | I11: ='HR & OPERATING EXPENSES'!I60 -> 488000 | J11: ='HR & OPERATING EXPENSES'!J60 -> 898000 | K11: ='HR & OPERATING EXPENSES'!K60 -> 1247000 | L11: ='HR & OPERATING EXPENSES'!L60 -> 1391000 | ... BL11: ='HR & OPERATING EXPENSES'!BL60 -> 7971104.8
C12: 5. | D12: EBITDA | E12: =E9 - E11 -> -230000 | F12: =F9 - F11 -> -230000 | G12: =G9 - G11 -> -230000 | H12: =H9 - H11 -> -230000 | I12: =I9 - I11 -> 6581.6832 | J12: =J9 - J11 -> 91163.366 | K12: =K9 - K11 -> 3004578 | L12: =L9 - L11 -> 3355159.7 | ... BL12: =BL9 - BL11 -> 63763030
C13: B. | D13: EBITDA % | E13: =IF( E7 = 0, 0, E12 / E7) -> 0 | F13: =IF( F7 = 0, 0, F12 / F7) -> 0 | G13: =IF( G7 = 0, 0, G12 / G7) -> 0 | H13: =IF( H7 = 0, 0, H12 / H7) -> 0 | I13: =IF( I7 = 0, 0, I12 / I7) -> 0.0027572749 | J13: =IF( J7 = 0, 0, J12 / J7) -> 0.019095606 | K13: =IF( K7 = 0, 0, K12 / K7) -> 0.1537148 | L13: =IF( L7 = 0, 0, L12 / L7) -> 0.15296985 | ... BL13: =IF( BL7 = 0, 0, BL12 / BL7) -> 0.22749354
C14: 6. | D14: Depreciation & Amortisation | E14: ='CAPEX & DEPRECIATION'!E48 -> 83333.333 | F14: ='CAPEX & DEPRECIATION'!F48 -> 191744.44 | G14: ='CAPEX & DEPRECIATION'!G48 -> 275077.78 | H14: ='CAPEX & DEPRECIATION'!H48 -> 275077.78 | I14: ='CAPEX & DEPRECIATION'!I48 -> 872222.22 | J14: ='CAPEX & DEPRECIATION'!J48 -> 1038194.4 | K14: ='CAPEX & DEPRECIATION'!K48 -> 1629861.1 | L14: ='CAPEX & DEPRECIATION'!L48 -> 1629861.1 | ... BL14: ='CAPEX & DEPRECIATION'!BL48 -> 1984027.8
C15: 7. | D15: EBIT | E15: =E12 - E14 -> -313333.33 | F15: =F12 - F14 -> -421744.44 | G15: =G12 - G14 -> -505077.78 | H15: =H12 - H14 -> -505077.78 | I15: =I12 - I14 -> -865640.54 | J15: =J12 - J14 -> -947031.08 | K15: =K12 - K14 -> 1374716.9 | L15: =L12 - L14 -> 1725298.6 | ... BL15: =BL12 - BL14 -> 61779002
C16: 8. | D16: Interest | E16: 0 | F16: 0 | G16: 0 | H16: 0 | I16: 0 | J16: 0 | K16: 0 | L16: 0 | M16: 0 | N16: 0 | O16: 0 | P16: 0 | Q16: 0 | R16: 0 | S16: 0 | T16: 0 | U16: 0 | V16: 0 | W16: 0 | X16: 0 | Y16: 0 | Z16: 0 | AA16: 0 | AB16: 0 | AC16: 0 | AD16: 0 | AE16: 0 | AF16: 0 | AG16: 0 | AH16: 0 | AI16: 0 | AJ16: 0 | AK16: 0 | AL16: 0 | AM16: 0 | AN16: 0 | AO16: 0 | AP16: 0 | AQ16: 0 | AR16: 0 | AS16: 0 | AT16: 0 | AU16: 0 | AV16: 0 | AW16: 0 | AX16: 0 | AY16: 0 | AZ16: 0 | BA16: 0 | BB16: 0 | BC16: 0 | BD16: 0 | BE16: 0 | BF16: 0 | BG16: 0 | BH16: 0 | BI16: 0 | BJ16: 0 | BK16: 0 | BL16: 0
C17: 9. | D17: PBT | E17: =E15 - E16 -> -313333.33 | F17: =F15 - F16 -> -421744.44 | G17: =G15 - G16 -> -505077.78 | H17: =H15 - H16 -> -505077.78 | I17: =I15 - I16 -> -865640.54 | J17: =J15 - J16 -> -947031.08 | K17: =K15 - K16 -> 1374716.9 | L17: =L15 - L16 -> 1725298.6 | ... BL17: =BL15 - BL16 -> 61779002
C18: 10. | D18: Taxes | E18: =IF(E17 > 0, E17 * ASSUMPTIONS!$H$58, 0) -> 0 | F18: =IF(F17 > 0, F17 * ASSUMPTIONS!$H$58, 0) -> 0 | G18: =IF(G17 > 0, G17 * ASSUMPTIONS!$H$58, 0) -> 0 | H18: =IF(H17 > 0, H17 * ASSUMPTIONS!$H$58, 0) -> 0 | I18: =IF(I17 > 0, I17 * ASSUMPTIONS!$H$58, 0) -> 0 | J18: =IF(J17 > 0, J17 * ASSUMPTIONS!$H$58, 0) -> 0 | K18: =IF(K17 > 0, K17 * ASSUMPTIONS!$H$58, 0) -> 343679.22 | L18: =IF(L17 > 0, L17 * ASSUMPTIONS!$H$58, 0) -> 431324.64 | ... BL18: =IF(BL17 > 0, BL17 * ASSUMPTIONS!$H$58, 0) -> 15444751
C19: 11. | D19: PAT | E19: =E17 - E18 -> -313333.33 | F19: =F17 - F18 -> -421744.44 | G19: =G17 - G18 -> -505077.78 | H19: =H17 - H18 -> -505077.78 | I19: =I17 - I18 -> -865640.54 | J19: =J17 - J18 -> -947031.08 | K19: =K17 - K18 -> 1031037.7 | L19: =L17 - L18 -> 1293973.9 | ... BL19: =BL17 - BL18 -> 46334252
C20: C. | D20: PAT % | E20: =IF(E7 = 0, 0, E19 / E7) -> 0 | F20: =IF(F7 = 0, 0, F19 / F7) -> 0 | G20: =IF(G7 = 0, 0, G19 / G7) -> 0 | H20: =IF(H7 = 0, 0, H19 / H7) -> 0 | I20: =IF(I7 = 0, 0, I19 / I7) -> -0.36264416 | J20: =IF(J7 = 0, 0, J19 / J7) -> -0.19837061 | K20: =IF(K7 = 0, 0, K19 / K7) -> 0.052748088 | L20: =IF(L7 = 0, 0, L19 / L7) -> 0.058995402 | ... BL20: =IF(BL7 = 0, 0, BL19 / BL7) -> 0.1653112
C22: * Taxes assumed at a blended effective rate; final liability subject to juristiction and incentives.

Sheet CASH_FLOW
A1: =COVER!$B$12 -> Narayan Dairy Project
A2: Cash Flow Statement
D4: Month | E4: 1 | F4: =E4+1 -> 2 | G4: =F4+1 -> 3 | H4: =G4+1 -> 4 | I4: =H4+1 -> 5 | J4: =I4+1 -> 6 | K4: =J4+1 -> 7 | L4: =K4+1 -> 8 | M4: =L4+1 -> 9 | ... BL4: =BK4+1 -> 60
C7: A. | D7: Operating Cash Flow
C8: 1. | D8: Net Profit / (Loss) | E8: ='P&L'!E19 -> -313333.33 | F8: ='P&L'!F19 -> -421744.44 | G8: ='P&L'!G19 -> -505077.78 | H8: ='P&L'!H19 -> -505077.78 | I8: ='P&L'!I19 -> -865640.54 | J8: ='P&L'!J19 -> -947031.08 | K8: ='P&L'!K19 -> 1031037.7 | L8: ='P&L'!L19 -> 1293973.9 | ... BL8: ='P&L'!BL19 -> 46334252
C9: 2. | D9: Add: Depreciation | E9: ='P&L'!E14 -> 83333.333 | F9: ='P&L'!F14 -> 191744.44 | G9: ='P&L'!G14 -> 275077.78 | H9: ='P&L'!H14 -> 275077.78 | I9: ='P&L'!I14 -> 872222.22 | J9: ='P&L'!J14 -> 1038194.4 | K9: ='P&L'!K14 -> 1629861.1 | L9: ='P&L'!L14 -> 1629861.1 | ... BL9: ='P&L'!BL14 -> 1984027.8
C10: 3. | D10: Add / Less: Change in Working Capital | E10: ='WORKING CAPITAL SCHEDULE'!E16 -> 0 | F10: ='WORKING CAPITAL SCHEDULE'!F16 -> 0 | G10: ='WORKING CAPITAL SCHEDULE'!G16 -> 0 | H10: ='WORKING CAPITAL SCHEDULE'!H16 -> 0 | I10: ='WORKING CAPITAL SCHEDULE'!I16 -> 268811.78 | J10: ='WORKING CAPITAL SCHEDULE'!J16 -> 268811.78 | K10: ='WORKING CAPITAL SCHEDULE'!K16 -> 1643411.5 | L10: ='WORKING CAPITAL SCHEDULE'!L16 -> 268811.78 | ... BL10: ='WORKING CAPITAL SCHEDULE'!BL16 -> 0
C11: 3. | D11: Net Operating Cash Flow | E11: =E8 + E9 - E10 -> -230000 | F11: =F8 + F9 - F10 -> -230000 | G11: =G8 + G9 - G10 -> -230000 | H11: =H8 + H9 - H10 -> -230000 | I11: =I8 + I9 - I10 -> -262230.1 | J11: =J8 + J9 - J10 -> -177648.42 | K11: =K8 + K9 - K10 -> 1017487.3 | L11: =L8 + L9 - L10 -> 2655023.3 | ... BL11: =BL8 + BL9 - BL10 -> 48318280
C12: B. | D12: Investing Cash Flow
C13: 4. | D13: Capital Expenditure (Capex) | E13: =-'CAPEX & DEPRECIATION'!E68 -> -57500000 | F13: =-'CAPEX & DEPRECIATION'!F68 -> -16764000 | G13: =-'CAPEX & DEPRECIATION'!G68 -> -20000000 | H13: =-'CAPEX & DEPRECIATION'!H68 -> 0 | I13: =-'CAPEX & DEPRECIATION'!I68 -> -76736000 | J13: =-'CAPEX & DEPRECIATION'!J68 -> -20500000 | K13: =-'CAPEX & DEPRECIATION'!K68 -> -70500000 | L13: =-'CAPEX & DEPRECIATION'!L68 -> 0 | ... BL13: =-'CAPEX & DEPRECIATION'!BL68 -> 0
C14: 5. | D14: Net Investing Cash Flow | E14: =E13 -> -57500000 | F14: =F13 -> -16764000 | G14: =G13 -> -20000000 | H14: =H13 -> 0 | I14: =I13 -> -76736000 | J14: =J13 -> -20500000 | K14: =K13 -> -70500000 | L14: =L13 -> 0 | ... BL14: =BL13 -> 0
C15: C. | D15: Financing Cash Flow
C16: 6. | D16: Equity Funding Received | E16: =IF(E4 = 1, 'FUNDING REQUIREMENT'!$E$15, IF(E4 = 5, 'FUNDING REQUIREMENT'!$E$25, IF(E4 = 7, 'FUNDING REQUIREMENT'!$E$31, 0))) -> 94264000 | F16: =IF(F4 = 1, 'FUNDING REQUIREMENT'!$E$15, IF(F4 = 5, 'FUNDING REQUIREMENT'!$E$25, IF(F4 = 7, 'FUNDING REQUIREMENT'!$E$31, 0))) -> 0 | G16: =IF(G4 = 1, 'FUNDING REQUIREMENT'!$E$15, IF(G4 = 5, 'FUNDING REQUIREMENT'!$E$25, IF(G4 = 7, 'FUNDING REQUIREMENT'!$E$31, 0))) -> 0 | H16: =IF(H4 = 1, 'FUNDING REQUIREMENT'!$E$15, IF(H4 = 5, 'FUNDING REQUIREMENT'!$E$25, IF(H4 = 7, 'FUNDING REQUIREMENT'!$E$31, 0))) -> 0 | I16: =IF(I4 = 1, 'FUNDING REQUIREMENT'!$E$15, IF(I4 = 5, 'FUNDING REQUIREMENT'!$E$25, IF(I4 = 7, 'FUNDING REQUIREMENT'!$E$31, 0))) -> 107736000 | J16: =IF(J4 = 1, 'FUNDING REQUIREMENT'!$E$15, IF(J4 = 5, 'FUNDING REQUIREMENT'!$E$25, IF(J4 = 7, 'FUNDING REQUIREMENT'!$E$31, 0))) -> 0 | K16: =IF(K4 = 1, 'FUNDING REQUIREMENT'!$E$15, IF(K4 = 5, 'FUNDING REQUIREMENT'!$E$25, IF(K4 = 7, 'FUNDING REQUIREMENT'!$E$31, 0))) -> 98000000 | L16: =IF(L4 = 1, 'FUNDING REQUIREMENT'!$E$15, IF(L4 = 5, 'FUNDING REQUIREMENT'!$E$25, IF(L4 = 7, 'FUNDING REQUIREMENT'!$E$31, 0))) -> 0 | ... BL16: =IF(BL4 = 1, 'FUNDING REQUIREMENT'!$E$15, IF(BL4 = 5, 'FUNDING REQUIREMENT'!$E$25, IF(BL4 = 7, 'FUNDING REQUIREMENT'!$E$31, 0))) -> 0
C17: 7. | D17: Net Financing Cash Flow | E17: =E16 -> 94264000 | F17: =F16 -> 0 | G17: =G16 -> 0 | H17: =H16 -> 0 | I17: =I16 -> 107736000 | J17: =J16 -> 0 | K17: =K16 -> 98000000 | L17: =L16 -> 0 | ... BL17: =BL16 -> 0
C18: D. | D18: Cash Position
C19: 8. | D19: Net Cash Movement | E19: =E11 + E14 + E17 -> 36534000 | F19: =F11 + F14 + F17 -> -16994000 | G19: =G11 + G14 + G17 -> -20230000 | H19: =H11 + H14 + H17 -> -230000 | I19: =I11 + I14 + I17 -> 30737770 | J19: =J11 + J14 + J17 -> -20677648 | K19: =K11 + K14 + K17 -> 28517487 | L19: =L11 + L14 + L17 -> 2655023.3 | ... BL19: =BL11 + BL14 + BL17 -> 48318280
C20: 9. | D20: Opening Cash Balance | E20: ='FUNDING REQUIREMENT'!E13 -> 2500000 | F20: =E21 -> 39034000 | G20: =F21 -> 22040000 | H20: =G21 -> 1810000 | I20: =H21 -> 1580000 | J20: =I21 -> 32317770 | K20: =J21 -> 11640121 | L20: =K21 -> 40157609 | M20: =L21 -> 42812632 | ... BL20: =BK21 -> 1181391478
C21: 10. | D21: Closing Cash Balance | E21: =E19 + E20 -> 39034000 | F21: =F19 + F20 -> 22040000 | G21: =G19 + G20 -> 1810000 | H21: =H19 + H20 -> 1580000 | I21: =I19 + I20 -> 32317770 | J21: =J19 + J20 -> 11640121 | K21: =K19 + K20 -> 40157609 | L21: =L19 + L20 -> 42812632 | ... BL21: =BL19 + BL20 -> 1229709757

Sheet YEARLY_SUMMARY
A1: =COVER!$B$12 -> Narayan Dairy Project
A2: Annual Summary
D4: Month | E4: Year 1 | F4: Year 2 | G4: Year 3 | H4: Year 4 | I4: Year 5
C7: 1. | D7: Total Revenue | E7: =SUM('P&L'!E7:P7) -> 160245121 | F7: =SUM('P&L'!Q7:AB7) -> 5.9346277e+08 | G7: =SUM('P&L'!AC7:AN7) -> 1188290397 | H7: =SUM('P&L'!AO7:AZ7) -> 2781598958 | I7: =SUM('P&L'!BA7:BL7) -> 3363420208
C8: 2. | D8: Total COGS | E8: =SUM('P&L'!E8:P8) -> 1.2583318e+08 | F8: =SUM('P&L'!Q8:AB8) -> 4.7090414e+08 | G8: =SUM('P&L'!AC8:AN8) -> 9.3585327e+08 | H8: =SUM('P&L'!AO8:AZ8) -> 2147231804 | I8: =SUM('P&L'!BA8:BL8) -> 2502610589
C9: 3. | D9: Gross Profit | E9: =SUM('P&L'!E9:P9) -> 34411938 | F9: =SUM('P&L'!Q9:AB9) -> 1.2255864e+08 | G9: =SUM('P&L'!AC9:AN9) -> 2.5243713e+08 | H9: =SUM('P&L'!AO9:AZ9) -> 6.3436715e+08 | I9: =SUM('P&L'!BA9:BL9) -> 8.6080962e+08
C10: A. | D10: Gross Margin % | E10: =E9 / E7 -> 0.21474562 | F10: =F9 / F7 -> 0.20651445 | G10: =G9 / G7 -> 0.21243723 | H10: =H9 / H7 -> 0.22805845 | I10: =I9 / I7 -> 0.25593282
C11: 4. | D11: Total Operating Expenses | E11: =SUM('P&L'!E11:P11) -> 11348000 | F11: =SUM('P&L'!Q11:AB11) -> 29458080 | G11: =SUM('P&L'!AC11:AN11) -> 46739981 | H11: =SUM('P&L'!AO11:AZ11) -> 79679303 | I11: =SUM('P&L'!BA11:BL11) -> 95653258
C12: 5. | D12: EBITDA | E12: =SUM('P&L'!E12:P12) -> 23063938 | F12: =SUM('P&L'!Q12:AB12) -> 93100557 | G12: =SUM('P&L'!AC12:AN12) -> 2.0569714e+08 | H12: =SUM('P&L'!AO12:AZ12) -> 5.5468785e+08 | I12: =SUM('P&L'!BA12:BL12) -> 7.6515636e+08
C13: B. | D13: EBITDA % | E13: =E12 / E7 -> 0.14392911 | F13: =F12 / F7 -> 0.15687683 | G13: =G12 / G7 -> 0.17310343 | H13: =H12 / H7 -> 0.19941331 | I13: =I12 / I7 -> 0.22749354
C14: 6. | D14: Depreciation & Amortisation | E14: =SUM('P&L'!E14:P14) -> 12566900 | F14: =SUM('P&L'!Q14:AB14) -> 20183333 | G14: =SUM('P&L'!AC14:AN14) -> 23704167 | H14: =SUM('P&L'!AO14:AZ14) -> 23808333 | I14: =SUM('P&L'!BA14:BL14) -> 23808333
C15: 7. | D15: EBIT | E15: =SUM('P&L'!E15:P15) -> 10497038 | F15: =SUM('P&L'!Q15:AB15) -> 72917224 | G15: =SUM('P&L'!AC15:AN15) -> 1.8199298e+08 | H15: =SUM('P&L'!AO15:AZ15) -> 5.3087952e+08 | I15: =SUM('P&L'!BA15:BL15) -> 7.4134803e+08
C16: 8. | D16: Interest | E16: =SUM('P&L'!E16:P16) -> 0 | F16: =SUM('P&L'!Q16:AB16) -> 0 | G16: =SUM('P&L'!AC16:AN16) -> 0 | H16: =SUM('P&L'!AO16:AZ16) -> 0 | I16: =SUM('P&L'!BA16:BL16) -> 0
C17: 9. | D17: PBT | E17: =SUM('P&L'!E17:P17) -> 10497038 | F17: =SUM('P&L'!Q17:AB17) -> 72917224 | G17: =SUM('P&L'!AC17:AN17) -> 1.8199298e+08 | H17: =SUM('P&L'!AO17:AZ17) -> 5.3087952e+08 | I17: =SUM('P&L'!BA17:BL17) -> 7.4134803e+08
C18: 10. | D18: Taxes | E18: =E$17 * ASSUMPTIONS!$H$58 -> 2624259.6 | F18: =F$17 * ASSUMPTIONS!$H$58 -> 18229306 | G18: =G$17 * ASSUMPTIONS!$H$58 -> 45498245 | H18: =H$17 * ASSUMPTIONS!$H$58 -> 1.3271988e+08 | I18: =I$17 * ASSUMPTIONS!$H$58 -> 185337007
C19: 11. | D19: PAT | E19: =E17 - E18 -> 7872778.8 | F19: =F17 - F18 -> 54687918 | G19: =G17 - G18 -> 1.3649473e+08 | H19: =H17 - H18 -> 3.9815964e+08 | I19: =I17 - I18 -> 5.5601102e+08
C20: C. | D20: PAT % | E20: =E19 / E7 -> 0.0491296 | F20: =F19 / F7 -> 0.092150545 | G20: =G19 / G7 -> 0.11486648 | H20: =H19 / H7 -> 0.14314056 | I20: =I19 / I7 -> 0.1653112
